Workbook
Name ___APC1: [1]Report!$F$13
Name ___ARR1: [1]Report!$G$8
Name ___INDEX_SHEET___: #REF!
Name ___INDEX_SHEET___: #REF!
Name ___INDEX_SHEET___: #REF!
Name ___INDEX_SHEET___: #REF!
Name ___INDEX_SHEET___: #REF!
Name ___INDEX_SHEET___: #REF!
Name ___INDEX_SHEET___: #REF!
Name ___INDEX_SHEET___: #REF!
Name ___INDEX_SHEET___: #REF!
Name ___INDEX_SHEET___: #REF!
Name __APC1: [1]Report!$F$13
Name __ARR1: [1]Report!$G$8
Name __Mth1: #REF!
Name __Mth1: #REF!
Name __Mth1: #REF!
Name __Mth1: #REF!
Name __Mth1: #REF!
Name __Mth1: #REF!
Name __Mth1: #REF!
Name __Mth1: #REF!
Name __Mth1: #REF!
Name __Mth1: #REF!
Name __Mth2: #REF!
Name __Mth2: #REF!
Name __Mth2: #REF!
Name __Mth2: #REF!
Name __Mth2: #REF!
Name __Mth2: #REF!
Name __Mth2: #REF!
Name __Mth4: #REF!
Name __Mth4: #REF!
Name __Mth4: #REF!
Name __Mth4: #REF!
Name __Mth4: #REF!
Name __Mth4: #REF!
Name __Mth4: #REF!
Name _APC1: [2]Report!$F$13
Name _ARR1: [2]Report!$G$8
Name _Mth5: #REF!
Name _Mth5: #REF!
Name _Mth5: #REF!
Name _Mth5: #REF!
Name _Mth5: #REF!
Name _Mth5: #REF!
Name _Mth5: #REF!
Name _Mth5: #REF!
Name _Mth5: #REF!
Name _Mth5: #REF!
Name _Mth6: #REF!
Name _Mth6: #REF!
Name _Mth6: #REF!
Name _Mth6: #REF!
Name _Mth6: #REF!
Name _Mth6: #REF!
Name _Mth6: #REF!
Name ABSENTISM: [3]MANPOWER!#REF!
Name ABSENTISM: [3]MANPOWER!#REF!
Name ABSENTISM: [3]MANPOWER!#REF!

Sheet INDEX
A1: CAM CALCULATION SHEET
A2: INDEX
A3: Area Summary
A4: Area Breakup - Mall
A5: Aarea Breakup- Office
A6: Area Breakup- Common Area
A7: Comm. Services
A8: CAM Variables
A9: CAM Charge Summary
A10: CAM Charge Calculation Sheet
A11: AMC Cost
A12: Common Electrical Load
... A19: Sinking Fund Calculation

Sheet Area Summary
A1: AREA STATEMENT | F1: INDEX
A2: BUILT-UP AREA STATEMENT
A4: PLOT AREA = 8082.16 Sq.m
B5: Actual areas
A7: Sr No. | B7: Description | C7: Built Up Area | D7: Leasable Area | E7: Air conditioned Area
A9: A | B9: Parking/Services
A10: 1 | B10: 2nd Basement | C10: 70796.981
A11: 2 | B11: 3rd Basement | C11: 70796.981
A12: 3 | B12: 4th Basement | C12: 70796.981
A13: 4 | B13: 1st Basement (MEP) | C13: 66168.891 | D13: =C13 -> 66168.891
C14: =SUM(C10:C13) -> 278559.83
A15: B | B15: Mall
A16: 2 | B16: Ground (Retail) | C16: ='Area-Mall'!F17 -> 35978.67 | D16: ='Area-Mall'!I17 -> 44426.57
A17: 3 | B17: L1(Retail) | C17: ='Area-Mall'!F28 -> 34642.858 | D17: ='Area-Mall'!I28 -> 46313.445
A18: 4 | B18: L2(Retail) | C18: ='Area-Mall'!F41 -> 36523.328 | D18: ='Area-Mall'!I41 -> 51865.354
A19: 5 | B19: L3(Food Court) | C19: 48631.752 | D19: ='Area-Mall'!I49 -> 44518
B20: Total Mall Area | C20: =SUM(C16:C19) -> 155776.61 | D20: =SUM(D16:D19) -> 187123.37 | E20: =D20*50%*90% -> 84205.516
A22: C | B22: Office
A24: 1 | B24: Office-L4 | C24: ='Area-Office'!F11 -> 46058.08 | D24: ='Area-Office'!I11 -> 58033.18
B25: Office-L5 | C25: ='Area-Office'!F20 -> 44248.651 | D25: ='Area-Office'!I20 -> 55753.301
B26: Office-L6 | C26: ='Area-Office'!F29 -> 46058.08 | D26: ='Area-Office'!I29 -> 58033.18
B27: Office-L7 | C27: ='Area-Office'!F37 -> 46058.08 | D27: ='Area-Office'!I37 -> 58033.18
B28: Office-L8 | C28: ='Area-Office'!F45 -> 46058.08 | D28: ='Area-Office'!I45 -> 58033.18
B29: Total Office Area | C29: =SUM(C25:C28) -> 182422.89 | D29: =SUM(D24:D28) -> 287886.02 | E29: =D29*70% -> 201520.22
B32: TOTAL B+C+D | D32: =D20+D29 -> 475009.39

Sheet Area-Mall
A1: AREA STATEMENT
A2: Sl. No. | B2: Description | C2: Carpet area | E2: Built up area | G2: Loading in % | H2: Super BUA/Saleable area | J2: efficiency | K2: f/d
C3: Sq m | D3: Sq ft | E3: Sq m | F3: Sq ft | G3: % | H3: Sq m | I3: Sq ft | J3: super / carpet
B4: Ground Floor Area
A5: 1 | B5: LG - 01 | C5: 107.3 | D5: 1154.9772 | E5: 115.9 | F5: 1247.5476 | G5: 0.62 | H5: 187.758 | I5: 2021.0271 | J5: =D5/I5 -> 0.57148031 | K5: =F5/D5 -> 1.0801491
A6: 2 | B6: LG – 02 | C6: 36.4 | D6: 391.8096 | E6: 40.3 | F6: 433.7892 | G6: 0.67 | H6: 67.301 | I6: 724.42796 | J6: =D6/I6 -> 0.54085378 | K6: =F6/D6 -> 1.1071429
A7: 3 | B7: LG - 03 | C7: 37.5 | D7: 403.65 | E7: 41.7 | F7: 448.8588 | G7: 0.67 | H7: 69.639 | I7: 749.5942 | J7: =D7/I7 -> 0.53849136 | K7: =F7/D7 -> 1.112
A8: 4 | B8: LG – 04- Anchor 01 | C8: 2244 | D8: 24154.416 | E8: 2285.9 | F8: 24605.428 | G8: 0.24 | H8: 2834.516 | I8: 30510.73 | J8: =D8/I8 -> 0.79166955 | K8: =F8/D8 -> 1.018672
A9: 5 | B9: LG - 05 | C9: 35.9 | D9: 386.4276 | E9: 39.2 | F9: 421.9488 | G9: 0.67 | H9: 65.464 | I9: 704.6545 | J9: =D9/I9 -> 0.54839301 | K9: =F9/D9 -> 1.091922
A10: 6 | B10: LG - 06 | C10: 61.8 | D10: 665.2152 | E10: 69 | F10: 742.716 | G10: 0.65 | H10: 113.85 | I10: 1225.4814 | J10: =D10/I10 -> 0.5428195 | K10: =F10/D10 -> 1.1165049
A11: 7 | B11: LG - 07 | C11: 63.1 | D11: 679.2084 | E11: 70.2 | F11: 755.6328 | G11: 0.65 | H11: 115.83 | I11: 1246.7941 | J11: =D11/I11 -> 0.54476388 | K11: =F11/D11 -> 1.1125198
A12: 8 | B12: LG - 08 | C12: 58.4 | D12: 628.6176 | E12: 63 | F12: 678.132 | G12: 0.65 | H12: 103.95 | I12: 1118.9178 | J12: =D12/I12 -> 0.56180856 | K12: =F12/D12 -> 1.0787671
A13: 9 | B13: LG - 09 | C13: 20.8 | D13: 223.8912 | E13: 23.3 | F13: 250.8012 | G13: 0.67 | H13: 38.911 | I13: 418.838 | J13: =D13/I13 -> 0.53455321 | K13: =F13/D13 -> 1.1201923
A14: 10 | B14: LG - 10 | C14: 58.7 | D14: 631.8468 | E14: 64.6 | F14: 695.3544 | G14: 0.65 | H14: 106.59 | I14: 1147.3348 | J14: =D14/I14 -> 0.55070832 | K14: =F14/D14 -> 1.1005111
A15: 11 | B15: LG - 11-1 | C15: 252.5 | D15: 2717.91 | E15: 264.7 | F15: 2849.2308 | G15: 0.6 | H15: 221.94352 | I15: 2389 | L15: Actual area sold (loading not done)
A16: 12 | B16: LG - 11-2 | C16: 252.5 | D16: 2717.91 | E16: 264.7 | F16: 2849.2308 | G16: 0.6 | H16: 201.57655 | I16: 2169.77 | J16: =D16/I16 -> 1.2526259 | K16: =F16/D16 -> 1.0483168 | L16: Actual area sold (loading not done)
B17: TOTAL | F17: =SUM(F5:F16) -> 35978.67 | H17: 4127.3291 | I17: 44426.57
B19: First Floor Area
A20: 1 | B20: L1 - 01 | C20: 146.4 | D20: 1575.8496 | E20: 155 | F20: 1668.42 | G20: 0.6 | H20: 248 | I20: 2669.472 | J20: =D20/I20 -> 0.59032258 | K20: =F20/D20 -> 1.0587432
A21: 2 | B21: L1 - 02 | C21: 58.7 | D21: 631.8468 | E21: 63.6 | F21: 684.5904 | G21: 0.65 | H21: 104.94 | I21: 1129.5742 | J21: =D21/I21 -> 0.55936726 | K21: =F21/D21 -> 1.0834753
A22: 3 | B22: L1 - 03 | C22: 28.8 | D22: 310.0032 | E22: 30.7 | F22: 330.4548 | G22: 0.67 | H22: 51.269 | I22: 551.85952 | J22: =D22/I22 -> 0.56174296 | K22: =F22/D22 -> 1.0659722
A23: 4 | B23: L1 - 04-Anchor 01 | C23: 2352 | D23: 25316.928 | E23: 2400 | F23: 25833.6 | G23: 0.24 | H23: 2976 | I23: 32033.664 | J23: =D23/I23 -> 0.79032258 | K23: =F23/D23 -> 1.0204082
A24: 5 | B24: L1 - 05 | C24: 80.3 | D24: 864.3492 | E24: 84.5 | F24: 909.558 | G24: 0.65 | H24: 139.425 | I24: 1500.7707 | J24: =D24/I24 -> 0.57593688 | K24: =F24/D24 -> 1.0523039
A25: 6 | B25: L1 - 06 | C25: 89.8 | D25: 966.6072 | E25: 96 | F25: 1033.344 | G25: 0.65 | H25: 158.4 | I25: 1705.0176 | J25: =D25/I25 -> 0.56691919 | K25: =F25/D25 -> 1.0690423
A26: 7 | B26: L1 - 07 | C26: 52.2 | D26: 561.8808 | E26: 56.6 | F26: 609.2424 | G26: 0.65 | H26: 93.39 | I26: 1005.25 | J26: =D26/I26 -> 0.55894635 | K26: =F26/D26 -> 1.0842912
A27: 8 | B27: L1 - 08 | C27: 316.3 | D27: 3404.6532 | E27: 332 | F27: 3573.648 | G27: 0.6 | H27: 531.2 | I27: 5717.8368 | J27: =D27/I27 -> 0.59544428 | K27: =F27/D27 -> 1.0496364
B28: TOTAL | F28: =SUM(F20:F27) -> 34642.858 | H28: 4302.624 | I28: 46313.445
B30: Second Floor Area
A31: 1 | B31: L2 - 01 | C31: 66.2 | D31: 712.5768 | E31: 72.6 | F31: 781.4664 | G31: 0.65 | H31: 119.79 | I31: 1289.4196 | J31: =D31/I31 -> 0.55263378 | K31: =F31/D31 -> 1.0966767
A32: 2 | B32: L2 - 02 | C32: 66.8 | D32: 719.0352 | E32: 72.3 | F32: 778.2372 | G32: 0.65 | H32: 119.295 | I32: 1284.0914 | J32: =D32/I32 -> 0.55995641 | K32: =F32/D32 -> 1.0823353
A33: 3 | B33: L2 - 03 | C33: 33.3 | D33: 358.4412 | E33: 37 | F33: 398.268 | G33: 0.67 | H33: 61.79 | I33: 665.10756 | J33: =D33/I33 -> 0.53892216 | K33: =F33/D33 -> 1.1111111
A34: 4 | B34: L2 - 04- Anchor 01 | C34: 1800.8 | D34: 19383.811 | E34: 1832.6 | F34: 19726.106 | G34: 0.28 | H34: 2345.728 | I34: 25249.416 | J34: =D34/I34 -> 0.76769344 | K34: =F34/D34 -> 1.0176588
A35: 5 | B35: L2 - 05 (kiosk) | C35: 16 | D35: 172.224 | E35: 19 | F35: 204.516 | G35: 0.67 | H35: 31.73 | I35: 341.54172 | J35: =D35/I35 -> 0.50425465 | K35: =F35/D35 -> 1.1875
A36: 6 | B36: L2 - 06 | C36: 96.7 | D36: 1040.8788 | E36: 102.6 | F36: 1104.3864 | G36: 0.65 | H36: 169.29 | I36: 1822.2376 | J36: =D36/I36 -> 0.57120917 | K36: =F36/D36 -> 1.0610134
A37: 7 | B37: L2- 07 | C37: 220.3 | D37: 2371.3092 | E37: 226.8 | F37: 2441.2752 | G37: 0.6 | H37: 362.88 | I37: 3906.0403 | J37: =D37/I37 -> 0.60708774 | K37: =F37/D37 -> 1.0295052
A38: 8 | B38: L2 - 08 | C38: 61.3 | D38: 659.8332 | E38: 66.2 | F38: 712.5768 | G38: 0.65 | H38: 109.23 | I38: 1175.7517 | J38: =D38/I38 -> 0.56120114 | K38: =F38/D38 -> 1.0799347
A39: 9 | B39: L2 – 09 | C39: 898.5 | D39: 9671.454 | E39: 926.7 | F39: 9974.9988 | G39: 0.55 | H39: 1436.385 | I39: 15461.248 | J39: =D39/I39 -> 0.62552867 | K39: =F39/D39 -> 1.0313856
A40: 10 | B40: L2 – 10 (kiosk) | C40: 34 | D40: 365.976 | E40: 37.3 | F40: 401.4972 | G40: 0.67 | H40: 62.291 | I40: 670.50032 | J40: =D40/I40 -> 0.54582524 | K40: =F40/D40 -> 1.0970588
B41: TOTAL | F41: =SUM(F31:F40) -> 36523.328 | H41: 4818.409 | I41: 51865.354
B43: Third Floor Area
A44: 1 | B44: Edutainemnt Centre/ Restaurant- 01 | I44: 20148
A45: 2 | B45: Restaurant - 02 | I45: 4693
A46: 3 | B46: Restaurant - 03 | I46: 8219
A47: 4 | B47: Restaurant - 04 | I47: 3923
A48: 5 | B48: Restaurant - 05 | I48: 7535
H49: TOTAL | I49: =I44+I45+I46+I47+I48 -> 44518
F52: Complete area/ SBU of mall | I52: =I49+I41+I28+I17 -> 187123.37
D55: Complete area/ SBU of mall exculding LG and L1 achor stores | I55: =I52-I23-I8 -> 124578.98
D56: Total cam for mall exculding LG and L1 anchor stores. | I56: =I55*15 -> 1868684.6
D57: Cam for LG L1 anchor stores | I57: =(D8+D23)*6 -> 296828.06
D58: Total CAM collection for mall | I58: =I56+I57 -> 2165512.7

Sheet Area-Office
A1: AREA STATEMENT- OFFICE
A2: Sl. No. | B2: Description | C2: Carpet area | E2: Built up area | G2: Loading in % | H2: Super BUA/Saleable area | J2: efficiency | K2: f/d
C3: Sq m | D3: Sq ft | E3: Sq m | F3: Sq ft | G3: % | H3: Sq m | I3: Sq ft | J3: super / carpet
B4: Fourth Floor
A5: 1 | B5: OFFICE-01 | C5: 1086.5 | D5: 11695.086 | E5: 1114.45 | F5: 11995.94 | G5: 0.26 | H5: 1404.207 | I5: 15114.884 | J5: =F5/I5 -> 0.79365079 | K5: =F5/D5 -> 1.0257248
A6: 2 | B6: OFFICE-02 | C6: 718.45 | D6: 7733.3958 | E6: 739.95 | F6: 7964.8218 | G6: 0.26 | H6: 932.337 | I6: 10035.675 | J6: =F6/I6 -> 0.79365079 | K6: =F6/D6 -> 1.0299255
A7: 3 | B7: OFFICE-03 | C7: 518.1 | D7: 5576.8284 | E7: 530.3 | F7: 5708.1492 | G7: 0.26 | H7: 668.178 | I7: 7192.268 | J7: =F7/I7 -> 0.79365079 | K7: =F7/D7 -> 1.0235476
A8: 4 | B8: OFFICE-04 | C8: 755 | D8: 8126.82 | E8: 778.3 | F8: 8377.6212 | G8: 0.26 | H8: 980.658 | I8: 10555.803 | J8: =F8/I8 -> 0.79365079 | K8: =F8/D8 -> 1.0308609
A9: 5 | B9: OFFICE-05 | C9: 589.35 | D9: 6343.7634 | E9: 604.5 | F9: 6506.838 | G9: 0.26 | H9: 761.67 | I9: 8198.6159 | J9: =F9/I9 -> 0.79365079 | K9: =F9/D9 -> 1.0257063
A10: 6 | B10: OFFICE-06 | C10: 492.52 | D10: 5301.4853 | E10: 511.4 | F10: 5504.7096 | G10: 0.26 | H10: 644.364 | I10: 6935.9341 | J10: =F10/I10 -> 0.79365079 | K10: =F10/D10 -> 1.0383335
B11: TOTAL | F11: =SUM(F5:F10) -> 46058.08 | H11: 5391.414 | I11: 58033.18
B13: Fifth Floor
A14: 1 | B14: OFFICE-01 | C14: 1086.5 | D14: 11695.086 | E14: 1114.45 | F14: 11995.94 | G14: 0.26 | H14: 1404.207 | I14: 15114.884 | J14: =F14/I14 -> 0.79365079 | K14: =F14/D14 -> 1.0257248
A15: 2 | B15: OFFICE-02 | C15: 706.45 | D15: 7604.2278 | E15: 735.45 | F15: 7916.3838 | G15: 0.26 | H15: 926.667 | I15: 9974.6436 | J15: =F15/I15 -> 0.79365079 | K15: =F15/D15 -> 1.0410503 | L15: Refuge area Reduction
A16: 3 | B16: OFFICE-03 | C16: 353.35 | D16: 3803.4594 | E16: 366.7 | F16: 3947.1588 | G16: 0.26 | H16: 462.042 | I16: 4973.4201 | J16: =F16/I16 -> 0.79365079 | K16: =F16/D16 -> 1.0377812 | L16: Refuge area Reduction
A17: 4 | B17: OFFICE-04 | C17: 755 | D17: 8126.82 | E17: 778.3 | F17: 8377.6212 | G17: 0.26 | H17: 980.658 | I17: 10555.803 | J17: =F17/I17 -> 0.79365079 | K17: =F17/D17 -> 1.0308609
A18: 5 | B18: OFFICE-05 | C18: 589.35 | D18: 6343.7634 | E18: 604.5 | F18: 6506.838 | G18: 0.26 | H18: 761.67 | I18: 8198.6159 | J18: =F18/I18 -> 0.79365079 | K18: =F18/D18 -> 1.0257063
A19: 6 | B19: OFFICE-06 | C19: 492.52 | D19: 5301.4853 | E19: 511.4 | F19: 5504.7096 | G19: 0.26 | H19: 644.364 | I19: 6935.9341 | J19: =F19/I19 -> 0.79365079 | K19: =F19/D19 -> 1.0383335
B20: TOTAL | F20: =SUM(F14:F19) -> 44248.651 | H20: 5179.608 | I20: 55753.301
B21: Sixth Floor
A22: 1 | B22: OFFICE-01 | C22: 1086.5 | D22: 11695.086 | E22: 1114.45 | F22: 11995.94 | G22: 0.26 | H22: 1404.207 | I22: 15114.884 | J22: =F22/I22 -> 0.79365079 | K22: =F22/D22 -> 1.0257248
A23: 2 | B23: OFFICE-02 | C23: 718.45 | D23: 7733.3958 | E23: 739.95 | F23: 7964.8218 | G23: 0.26 | H23: 932.337 | I23: 10035.675 | J23: =F23/I23 -> 0.79365079 | K23: =F23/D23 -> 1.0299255
A24: 3 | B24: OFFICE-03-1 | C24: 125.36 | D24: 1349.375 | E24: 128.3 | F24: 1381.0212 | G24: 0.26 | H24: 161.658 | I24: 1740.0867 | J24: =F24/I24 -> 0.79365079 | K24: =F24/D24 -> 1.0234525
A25: 4 | B25: OFFICE-03-2 | C25: 392.74 | D25: 4227.4534 | E25: 402 | F25: 4327.128 | G25: 0.26 | H25: 506.52 | I25: 5452.1813 | J25: =F25/I25 -> 0.79365079 | K25: =F25/D25 -> 1.0235779
A26: 5 | B26: OFFICE-04 | C26: 755 | D26: 8126.82 | E26: 778.3 | F26: 8377.6212 | G26: 0.26 | H26: 980.658 | I26: 10555.803 | J26: =F26/I26 -> 0.79365079 | K26: =F26/D26 -> 1.0308609
A27: 6 | B27: OFFICE-05 | C27: 589.35 | D27: 6343.7634 | E27: 604.5 | F27: 6506.838 | G27: 0.26 | H27: 761.67 | I27: 8198.6159 | J27: =F27/I27 -> 0.79365079 | K27: =F27/D27 -> 1.0257063
A28: 7 | B28: OFFICE-06 | C28: 492.52 | D28: 5301.4853 | E28: 511.4 | F28: 5504.7096 | G28: 0.26 | H28: 644.364 | I28: 6935.9341 | J28: =F28/I28 -> 0.79365079 | K28: =F28/D28 -> 1.0383335
B29: TOTAL | F29: =SUM(F22:F28) -> 46058.08 | H29: 5391.414 | I29: 58033.18
B30: Seventh Floor
A31: 1 | B31: OFFICE-01 | C31: 1086.5 | D31: 11695.086 | E31: 1114.45 | F31: 11995.94 | G31: 0.26 | H31: 1404.207 | I31: 15114.884 | J31: =F31/I31 -> 0.79365079 | K31: =F31/D31 -> 1.0257248
A32: 2 | B32: OFFICE-02 | C32: 718.45 | D32: 7733.3958 | E32: 739.95 | F32: 7964.8218 | G32: 0.26 | H32: 932.337 | I32: 10035.675 | J32: =F32/I32 -> 0.79365079 | K32: =F32/D32 -> 1.0299255
A33: 3 | B33: OFFICE-03 | C33: 518.1 | D33: 5576.8284 | E33: 530.3 | F33: 5708.1492 | G33: 0.26 | H33: 668.178 | I33: 7192.268 | J33: =F33/I33 -> 0.79365079 | K33: =F33/D33 -> 1.0235476
A34: 4 | B34: OFFICE-04 | C34: 755 | D34: 8126.82 | E34: 778.3 | F34: 8377.6212 | G34: 0.26 | H34: 980.658 | I34: 10555.803 | J34: =F34/I34 -> 0.79365079 | K34: =F34/D34 -> 1.0308609
A35: 5 | B35: OFFICE-05 | C35: 589.35 | D35: 6343.7634 | E35: 604.5 | F35: 6506.838 | G35: 0.26 | H35: 761.67 | I35: 8198.6159 | J35: =F35/I35 -> 0.79365079 | K35: =F35/D35 -> 1.0257063
A36: 6 | B36: OFFICE-06 | C36: 492.52 | D36: 5301.4853 | E36: 511.4 | F36: 5504.7096 | G36: 0.26 | H36: 644.364 | I36: 6935.9341 | J36: =F36/I36 -> 0.79365079 | K36: =F36/D36 -> 1.0383335
B37: TOTAL | F37: =SUM(F31:F36) -> 46058.08 | H37: 5391.414 | I37: 58033.18
B38: Eighth Floor
A39: 1 | B39: OFFICE-01 | C39: 1086.5 | D39: 11695.086 | E39: 1114.45 | F39: 11995.94 | G39: 0.26 | H39: 1404.207 | I39: 15114.884 | J39: =F39/I39 -> 0.79365079 | K39: =F39/D39 -> 1.0257248
A40: 2 | B40: OFFICE-02 | C40: 718.45 | D40: 7733.3958 | E40: 739.95 | F40: 7964.8218 | G40: 0.26 | H40: 932.337 | I40: 10035.675 | J40: =F40/I40 -> 0.79365079 | K40: =F40/D40 -> 1.0299255
A41: 3 | B41: OFFICE-03 | C41: 518.1 | D41: 5576.8284 | E41: 530.3 | F41: 5708.1492 | G41: 0.26 | H41: 668.178 | I41: 7192.268 | J41: =F41/I41 -> 0.79365079 | K41: =F41/D41 -> 1.0235476
A42: 4 | B42: OFFICE-04 | C42: 755 | D42: 8126.82 | E42: 778.3 | F42: 8377.6212 | G42: 0.26 | H42: 980.658 | I42: 10555.803 | J42: =F42/I42 -> 0.79365079 | K42: =F42/D42 -> 1.0308609
A43: 5 | B43: OFFICE-05 | C43: 589.35 | D43: 6343.7634 | E43: 604.5 | F43: 6506.838 | G43: 0.26 | H43: 761.67 | I43: 8198.6159 | J43: =F43/I43 -> 0.79365079 | K43: =F43/D43 -> 1.0257063
A44: 6 | B44: OFFICE-06 | C44: 492.52 | D44: 5301.4853 | E44: 511.4 | F44: 5504.7096 | G44: 0.26 | H44: 644.364 | I44: 6935.9341 | J44: =F44/I44 -> 0.79365079 | K44: =F44/D44 -> 1.0383335
B45: TOTAL | F45: =SUM(F39:F44) -> 46058.08 | H45: 5391.414 | I45: 58033.18
B46: Total | C46: 20622.85 | D46: 221984.36 | E46: 21226.4 | F46: 228480.97 | G46: 26% Average | H46: 26745.264 | I46: 287886.02

Sheet Area-Comm
B1: AREA BREAKUP FOR COMMON AREA | R1: INDEX
B2: Common area components for each floor | C2: B4 | D2: B3 | E2: B2 | F2: B1 | G2: LG | H2: L1 | I2: L2 | J2: L3 | K2: L4 | L2: L5 | M2: L6 | N2: L7 | O2: L8 | P2: Total Sq Mtr | Q2: Total Sq ft
A4: Non AC | B4: Comm. Area | C4: =SUM(C5:C21) -> 745.8 | D4: =SUM(D5:D21) -> 451.17 | E4: =SUM(E5:E21) -> 451.7 | F4: =SUM(F5:F21) -> 2938 | G4: =SUM(G5:G21) -> 219.3 | H4: =SUM(H5:H21) -> 225.5 | I4: =SUM(I5:I21) -> 362.1 | J4: =SUM(J5:J21) -> 297.3 | ... P4: =SUM(P5:P21) -> 6551.53 | Q4: =P4*10.764 -> 70520.669
A5: Non AC | B5: Common Toilet | D5: 47 | F5: 70 | I5: 84.2 | J5: 80.4 | P5: =SUM(C5:O5) -> 281.6
A6: Non AC | B6: Services Area | C6: 276.7 | D6: 260.47 | E6: 308 | F6: 319 | G6: 73.5 | H6: 102 | I6: 157 | J6: 97 | K6: 57.5 | L6: 57.5 | M6: 57.5 | N6: 57.5 | O6: 57.5 | P6: =SUM(C6:O6) -> 1881.17
A7: Non AC | B7: Service Yard | F7: 554.6 | P7: =SUM(C7:O7) -> 554.6
A8: Non AC | B8: Electrical (HT/LT/Transformer/Panel) | F8: 619.1 | P8: =SUM(C8:O8) -> 619.1
A9: Non AC | B9: DG | F9: 264.4 | P9: =SUM(C9:O9) -> 264.4
A10: Non AC | B10: Plumbing and Fire fighting | F10: 197.3 | P10: =SUM(C10:O10) -> 197.3
A11: Non AC | B11: Fire fighting and CCTV control | F11: 48.4 | P11: =SUM(C11:O11) -> 48.4
A12: Non AC | B12: STP | C12: 325.4 | P12: =SUM(C12:O12) -> 325.4
A13: Non AC | B13: WTP | P13: =SUM(C13:O13) -> 0
A14: Non AC | B14: HVAC | F14: 692.3 | P14: =SUM(C14:O14) -> 692.3
A15: Non AC | B15: UPS and Battery | F15: 31.7 | P15: =SUM(C15:O15) -> 31.7
A16: Non AC | B16: ST-01 | C16: 28.8 | D16: 28.8 | E16: 28.8 | F16: 28.8 | G16: 24 | H16: 34.3 | I16: 29.3 | J16: 27 | K16: 28.14 | L16: 29.1 | M16: 28.14 | N16: 28.14 | O16: 28.14 | P16: =SUM(C16:O16) -> 371.46
A17: Non AC | B17: ST-02 | P17: =SUM(C17:O17) -> 0
A18: Non AC | B18: ST-03 | C18: 29.5 | D18: 29.5 | E18: 29.5 | F18: 27 | G18: 61 | H18: 28.4 | I18: 29.2 | J18: 29.2 | K18: 44.8 | L18: 26.5 | M18: 26.5 | N18: 26.5 | O18: 26.5 | P18: =SUM(C18:O18) -> 414.1
A19: Non AC | B19: ST-04 | C19: 30.4 | D19: 30.4 | E19: 30.4 | F19: 30.4 | G19: 30.4 | H19: 30.4 | I19: 30.4 | J19: 33.3 | K19: 25.74 | L19: 25.74 | M19: 25.74 | N19: 25.74 | O19: 25.74 | P19: =SUM(C19:O19) -> 374.8
A20: Non AC | B20: ST-05 | C20: 30.4 | D20: 30.4 | E20: 30.4 | F20: 30.4 | G20: 30.4 | H20: 30.4 | I20: 32 | J20: 30.4 | K20: 30.4 | L20: 30.4 | M20: 30.4 | N20: 30.4 | O20: 30.4 | P20: =SUM(C20:O20) -> 396.8
A21: Non AC | B21: ST-06 | C21: 24.6 | D21: 24.6 | E21: 24.6 | F21: 24.6 | P21: =SUM(C21:O21) -> 98.4
A23: Non AC | B23: Mall- Non AC | C23: =SUM(C24:C26) -> 45.8 | D23: =SUM(D24:D26) -> 45.8 | E23: =SUM(E24:E26) -> 45.8 | F23: =SUM(F24:F26) -> 56 | G23: =SUM(G24:G26) -> 56 | H23: =SUM(H24:H26) -> 56 | I23: =SUM(I24:I26) -> 56 | J23: =SUM(J24:J26) -> 33.6 | ... P23: =SUM(P24:P26) -> 395 | Q23: =P23*10.764 -> 4251.78
A24: Non AC | B24: Mall GE | C24: 16.8 | D24: 16.8 | E24: 16.8 | F24: 16.8 | G24: 16.8 | H24: 16.8 | I24: 16.8 | J24: 16.8 | P24: =SUM(C24:O24) -> 134.4
A25: Non AC | B25: Mall SE | C25: 16.8 | D25: 16.8 | E25: 16.8 | F25: 16.8 | G25: 16.8 | H25: 16.8 | I25: 16.8 | J25: 16.8 | P25: =SUM(C25:O25) -> 134.4
A26: Non AC | B26: Freight elevator | C26: 12.2 | D26: 12.2 | E26: 12.2 | F26: 22.4 | G26: 22.4 | H26: 22.4 | I26: 22.4 | P26: =SUM(C26:O26) -> 126.2
A27: Non AC | B27: Service lobby-Mall | G27: 104.3 | H27: 54.17 | I27: 56.14 | J27: 276.2 | P27: =SUM(C27:O27) -> 490.81
B28: Common Toilet-Mall | D28: 47 | F28: 70 | I28: 84.2 | J28: 80.4 | P28: =SUM(C28:O28) -> 281.6
A30: AC | B30: Mall- AC | C30: =SUM(C31:C33) -> 17 | D30: =SUM(D31:D33) -> 17 | E30: =SUM(E31:E33) -> 17 | F30: =SUM(F31:F33) -> 707.8 | G30: =SUM(G31:G33) -> 476 | H30: =SUM(H31:H33) -> 302 | I30: =SUM(I31:I33) -> 771.48 | J30: =SUM(J31:J33) -> 907.4 | ... P30: =SUM(P31:P33) -> 3215.68 | Q30: =P30*10.764 -> 34613.58
A31: AC | B31: Mall BOH | F31: 677.7 | P31: =SUM(C31:O31) -> 677.7
A32: AC | B32: Mall lobby | C32: 17 | D32: 17 | E32: 17 | F32: 30.1 | P32: =SUM(C32:O32) -> 81.1
A33: AC | B33: Corridor-Mall | G33: 476 | H33: 302 | I33: 771.48 | J33: 907.4 | P33: =SUM(C33:O33) -> 2456.88
A35: Non AC | B35: Office | C35: =SUM(C36:C39) -> 34.8 | D35: =SUM(D36:D39) -> 34.8 | E35: =SUM(E36:E39) -> 34.8 | F35: =SUM(F36:F39) -> 80.1 | G35: =SUM(G36:G39) -> 34.8 | H35: =SUM(H36:H39) -> 34.8 | I35: =SUM(I36:I39) -> 34.8 | J35: =SUM(J36:J39) -> 34.8 | ... O35: =SUM(O36:O39) -> 64.3 | P35: =SUM(P36:P38) -> 603.4 | Q35: =P35*10.764 -> 6494.9976 | S35: =Q35+Q41 -> 8982.0198
A36: Non AC | B36: Office GE | C36: 26.1 | D36: 26.1 | E36: 26.1 | F36: 26.1 | G36: 26.1 | H36: 26.1 | I36: 26.1 | J36: 26.1 | K36: 26.1 | L36: 26.1 | M36: 26.1 | N36: 26.1 | O36: 26.1 | P36: =SUM(C36:O36) -> 339.3
A37: Non AC | B37: Office SE | C37: 8.7 | D37: 8.7 | E37: 8.7 | F37: 8.7 | G37: 8.7 | H37: 8.7 | I37: 8.7 | J37: 8.7 | K37: 8.7 | L37: 8.7 | M37: 8.7 | N37: 8.7 | O37: 8.7 | P37: =SUM(C37:O37) -> 113.1
A38: Non AC | B38: Refuge Area | L38: 151 | P38: =SUM(C38:O38) -> 151
A39: Non AC | B39: Service lobby-Office | F39: 45.3 | K39: 29.5 | L39: 29.5 | M39: 29.5 | N39: 29.5 | O39: 29.5
A41: AC | B41: Office lobby | C41: =SUM(C42:C43) -> 24.35 | D41: =SUM(D42:D43) -> 24.35 | E41: =SUM(E42:E43) -> 24.35 | F41: =SUM(F42:F43) -> 42 | G41: =SUM(G42:G43) -> 116 | H41: =SUM(H42:H43) -> 0 | I41: =SUM(I42:I43) -> 0 | J41: =SUM(J42:J43) -> 0 | ... P41: =SUM(P42:P43) -> 231.05 | Q41: =P41*10.764 -> 2487.0222
A42: AC | B42: Office lobby | C42: 24.35 | D42: 24.35 | E42: 24.35 | F42: 42 | G42: 116 | P42: =SUM(C42:O42) -> 231.05
A43: AC | B43: Corridor-Office | K43: 228 | L43: 271.8 | M43: 228 | N43: 228 | O43: 228
P45: =SUM(P4,P23,P30,P35,P41) -> 10996.66 | Q45: =SUM(Q4,Q23,Q30,Q35,Q41) -> 118368.05

Sheet Common Services
A1: MAJOR COST HEADS FOR COMMON AREA CHARGES | E1: INDEX
A2: 1 | B2: Property Managenent Charges | C2: Property Management Company Servcies Charges
C3: Management Establishment Cost
A4: 2 | B4: Engineering Services / Spares and Consumables / AMC | C4: Engineering Manpower
C5: Spares and Consumables
C6: General Maintenance tools ( Amortized Cost)
C7: AMC Charges
A8: 3 | B8: Utility Cost ( Electricity , Air conditioning and Water) | C8: Common Area Equipments / Lighting etc
C9: Common Area Airconditioning Cost
C10: Cost of water
A11: 5 | B11: Janitorial / Gardening / Pest Control/ Security | C11: Housekeeping Manpower
C12: Housekeeping Equipments
C13: Housekeeping Cleaning Consumables and Toiletries
C14: Housekeeping Toiletries
C15: Horticulture Manpower
C16: Horticulture Tools and Consumables
C17: Pest Control Services
C18: Waste Management System
C19: Façade Cleaning Services
C20: Security Manpower Costing
A21: 6 | B21: Liosaning, Licenses and Audit Cost | C21: Electrical and DG License renewal
C22: Lift License Renewal
C23: Fire NOC
C24: STP CTO
C25: Labour license and registration
C26: Liosaning & Licenses Cost
C27: Environmental and Pollution Control Inspections
A28: 7 | B28: Miscellaneous Costs | C28: Rental Equipment (Pumps / Ladders etc)
C29: Travel / Conveyance / Hire Charges Of taxi / cabs
C30: Office Stationary and Printed Stationary
C31: Site Team Communication Charges-Mobile
C32: Mangzine, Journals and Newspapers
C33: TV Cable Connection
C34: Staff Welfare for deployed manpower ( CW & Sub Contractor)
C35: Events and Festivel Expenses ( Decoration, Sweets, Consumables)
C36: Courier Charges
C37: Staff Uniforms
C38: C&W administration cost for misc. expenses
A39: 8 | B39: Audits | C39: Energy Audit / Thermography and Harmonic Test
C40: Financial Audit
C41: Fire, Health & Safety Audits
C42: Indoor Air Quality and DG emmission testing
C43: Legal and professional servcies
C44: Security Audit
C45: Statutory compliances (PF, ESIC, Ptax, Lab.Welfare, Licenses, Returns, Audit etc.)
C46: Water Testing Charges
A47: 9 | B47: Insurance & Funds | C47: Sinking Fund
C48: Contigency Funds
C49: Insurance Structural & Electro mechanical equipments
C50: Group Accidential Insurance
C51: Insurance for Thrid Party liability

Sheet CAM Variables
A1: CAM Variables-
A2: Variable 1 | F2: Mall Leasablke Area in sq ft | G2: ='Area Summary'!D20 -> 187123.37 | I2: INDEX
F3: Office Space leasable area in sq ft | G3: ='Area Summary'!D29 -> 287886.02 | J3: =G2+G3 -> 475009.39
A5: Variable 2 | B5: Power Supply Details
D6: DG Set Supply | F6: EB Supply
B7: Rates estimated for FY 14-15 | D7: Rate | E7: 64 | F7: Fixed Charges ( KVA) | G7: 350
D8: Unit per Ltrs. | E8: 3.5 | F8: Unit Rate ( KVAH) | G8: 6.5
D9: Cost per Unit | E9: =ROUND(E7/E8,2) -> 18.29 | F9: Power Breakdown in hrs | G9: 1.5
D10: Operation % | E10: =G9/24 -> 0.0625 | F10: Operation % | G10: =(24-G9)/24 -> 0.9375
A12: Variable 3 | B12: Minimum Wages Category | F12: Basic | G12: VDA
B13: Current Minimum wages rates | E13: Skilled | F13: 8079 | G13: 1739
E14: Semiskilled | F14: 6579 | G14: 1419
E15: Unskilled | F15: 5579 | G15: 1199

Sheet CAM Charges Summary
A1: CAM CHARGE CALCULATION BASED ON BUILT UP AREA | D1: 1st Year | H1: 2nd Year | L1: 3rd Year | O1: INDEX
D2: Mall | F2: Office | H2: Mall | J2: Office | L2: Mall | N2: Office
B3: AREA IN SQ. FT | D3: CAM / sq ft | F3: CAM / sq ft | H3: CAM / sq ft | J3: CAM / sq ft | L3: CAM / sq ft | N3: CAM / sq ft
B4: CAM COST PER MONTH PER SQ FT IN INR | D4: =SUM(D6,D8,D10,D12,D14,D16,D18,D20,D22) -> 13.32221 | F4: =SUM(F6,F8,F10,F12,F14,F16,F18,F20,F22) -> 9.9673078 | H4: =SUM(H6,H8,H10,H12,H14,H16,H18,H20,H22) -> 14.723316 | J4: =SUM(J6,J8,J10,J12,J14,J16,J18,J20,J22) -> 11.773246 | L4: =SUM(L6,L8,L10,L12,L14,L16,L18,L20,L22) -> 16.834874 | N4: =SUM(N6,N8,N10,N12,N14,N16,N18,N20,N22) -> 13.285133
A6: 1 | B6: Manpower Cost | D6: ='CAM Charges'!I8 -> 7.538619 | F6: ='CAM Charges'!M8 -> 5.2125856 | H6: ='CAM Charges'!T8 -> 8.2924809 | J6: ='CAM Charges'!X8 -> 5.7338442 | L6: ='CAM Charges'!AE8 -> 9.121729 | N6: ='CAM Charges'!AI8 -> 6.3072286
A8: 2 | B8: Spares and Consumables ( Engineering & Building Services) | D8: ='CAM Charges'!I19 -> 0.89448424 | F8: ='CAM Charges'!M19 -> 0.75263651 | H8: ='CAM Charges'!T19 -> 0.95074193 | J8: ='CAM Charges'!X19 -> 0.80180182 | L8: ='CAM Charges'!AE19 -> 0.98748713 | N8: ='CAM Charges'!AI19 -> 0.83110002
A10: 3 | B10: AMC Charges | D10: ='CAM Charges'!I26 -> 0 | F10: ='CAM Charges'!M26 -> 0 | H10: ='CAM Charges'!T26 -> 0.26961572 | J10: ='CAM Charges'!X26 -> 0.90644183 | L10: ='CAM Charges'!AE26 -> 1.1752477 | N10: ='CAM Charges'!AI26 -> 1.515923
A12: 4 | B12: Electricity Cost ( Utility & Common Area HVAC) | D12: ='CAM Charges'!I28 -> 1.6797 | F12: ='CAM Charges'!M28 -> 1.2593082 | H12: ='CAM Charges'!T28 -> 1.763685 | J12: ='CAM Charges'!X28 -> 1.3222736 | L12: ='CAM Charges'!AE28 -> 1.8518693 | N12: ='CAM Charges'!AI28 -> 1.3883873
A14: 5 | B14: Audits | D14: ='CAM Charges'!I32 -> 0.091226267 | F14: ='CAM Charges'!M32 -> 0.091226267 | H14: ='CAM Charges'!T32 -> 0.12806764 | J14: ='CAM Charges'!X32 -> 0.12806764 | L14: ='CAM Charges'!AE32 -> 0.12806764 | N14: ='CAM Charges'!AI32 -> 0.12806764
A16: 6 | B16: Liosaning & Licenses Cost | D16: ='CAM Charges'!I40 -> 0.079770353 | F16: ='CAM Charges'!M40 -> 0.079770353 | H16: ='CAM Charges'!T40 -> 0.078717742 | J16: ='CAM Charges'!X40 -> 0.078717742 | L16: ='CAM Charges'!AE40 -> 0.078717742 | N16: ='CAM Charges'!AI32 -> 0.12806764
A18: 7 | B18: Administrative Expenses | D18: ='CAM Charges'!I51 -> 0.14799707 | F18: ='CAM Charges'!M51 -> 0.14799707 | H18: ='CAM Charges'!T51 -> 0.16483885 | J18: ='CAM Charges'!X51 -> 0.16483885 | L18: ='CAM Charges'!AE51 -> 0.16483885 | N18: ='CAM Charges'!AI51 -> 0.16483885
A20: 8 | B20: Insurance, Sinking Fund | D20: ='CAM Charges'!I62 -> 1.4569431 | F20: ='CAM Charges'!M62 -> 1.4569431 | H20: ='CAM Charges'!T62 -> 1.5032069 | J20: ='CAM Charges'!X62 -> 1.5032069 | L20: ='CAM Charges'!AE62 -> 1.5513213 | N20: ='CAM Charges'!AI62 -> 1.5513213
A22: 9 | B22: Profit Margin 10% on Actual Expense | D22: ='CAM Charges'!I68 -> 1.4334702 | F22: ='CAM Charges'!M68 -> 0.96684071 | H22: ='CAM Charges'!T68 -> 1.5719615 | J22: ='CAM Charges'!X68 -> 1.134053 | L22: ='CAM Charges'!AE68 -> 1.7755951 | N22: ='CAM Charges'!AI68 -> 1.2701988

Sheet CAM Charges
A1: PROPOSED CAM CHARGES
A2: CAM CHARGE CALCULATION BASED ON BUILT UP AREA OF | D2: 1st Year | O2: 2nd Year | Z2: 3rd Year | AK2: INDEX
D3: Combined Services | G3: Mall | K3: Office Area | O3: Combined Services | R3: Mall | V3: Office Area | Z3: Combined Services | AC3: Mall | AG3: Office Area
B4: AREA IN SQ. FT | D4: Area sft | E4: ='CAM Variables'!J3 -> 475009.39 | G4: Area sft | H4: ='CAM Variables'!G2 -> 187123.37 | I4: CAM rate | K4: Area sft | L4: ='CAM Variables'!G3 -> 287886.02 | M4: CAM rate | O4: Area sft | P4: =E4 -> 475009.39 | R4: Area sft | S4: =H4 -> 187123.37 | T4: CAM rate | V4: Area sft | W4: =L4 -> 287886.02 | X4: CAM rate | Z4: Area sft | AA4: =P4 -> 475009.39 | AC4: Area sft | AD4: =S4 -> 187123.37 | AE4: CAM rate | AG4: Area sft | AH4: =W4 -> 287886.02 | AI4: CAM rate
B5: CAM COST PER MONTH IN INR | D5: Monthly Cost | E5: =SUM(D8,D19,D26,D28,D32,D40,D51,D62,D68) -> 3888670.3 | G5: Monthly Cost | H5: =SUM(G8,G19,G26,G28,G32,G40,G51,G62,G68) -> 1418705.7 | I5: =SUM(I8,I19,I26,I28,I32,I40,I51,I62,I68) -> 13.32221 | K5: Monthly Cost | L5: =SUM(K8,K19,K26,K28,K32,K40,K51,K62,K68) -> 704956.7 | M5: =SUM(M8,M19,M26,M28,M32,M40,M51,M62,M68) -> 9.9673078 | O5: Monthly Cost | P5: =SUM(O8,O19,O26,O28,O32,O40,O51,O62,O68) -> 4357603.3 | R5: Monthly Cost | S5: =SUM(R8,R19,R26,R28,R32,R40,R51,R62,R68) -> 1519040.5 | T5: =SUM(T8,T19,T26,T28,T32,T40,T51,T62,T68) -> 14.723316 | V5: Monthly Cost | W5: =SUM(V8,V19,V26,V28,V32,V40,V51,V62,V68) -> 950272.09 | X5: =SUM(X8,X19,X26,X28,X32,X40,X51,X62,X68) -> 11.773246 | Z5: Monthly Cost | AA5: =SUM(Z8,Z19,Z26,Z28,Z32,Z40,Z51,Z62,Z68) -> 4976847.4 | AC5: Monthly Cost | AD5: =SUM(AC8,AC19,AC26,AC28,AC32,AC40,AC51,AC62,AC68) -> 1694248.7 | AE5: =SUM(AE8,AE19,AE26,AE28,AE32,AE40,AE51,AE62,AE68) -> 16.834874 | AG5: Monthly Cost | AH5: =SUM(AG8,AG19,AG26,AG28,AG32,AG40,AG51,AG62,AG68) -> 1006110 | AI5: =SUM(AI8,AI19,AI26,AI28,AI32,AI40,AI51,AI62,AI68) -> 13.235783
A6: CAM Charges INR/ Per sq ft / month | D6: per sq. ft cost | E6: =SUM(E8,E19,E26,E28,E32,E40,E51,E62,E68) -> 8.1903459 | G6: per sq. ft cost | H6: =SUM(H8,H19,H26,H28,H32,H40,H51,H62,H68) -> 5.1356979 | K6: per sq. ft cost | L6: =SUM(L8,L19,L26,L28,L32,L40,L51,L62,L68) -> 1.7807954 | O6: per sq. ft cost | P6: =SUM(P8,P19,P26,P28,P32,P40,P51,P62,P68) -> 9.1676069 | R6: per sq. ft cost | S6: =SUM(S8,S19,S26,S28,S32,S40,S51,S62,S68) -> 5.5495959 | V6: per sq. ft cost | W6: =SUM(W8,W19,W26,W28,W32,W40,W51,W62,W68) -> 2.5995252 | Z6: per sq. ft cost | AA6: =SUM(AA8,AA19,AA26,AA28,AA32,AA40,AA51,AA62,AA68) -> 10.473139 | AC6: per sq. ft cost | AD6: =SUM(AD8,AD19,AD26,AD28,AD32,AD40,AD51,AD62,AD68) -> 6.3575074 | AG6: per sq. ft cost | AH6: =SUM(AH8,AH19,AH26,AH28,AH32,AH40,AH51,AH62,AH68) -> 2.7584168
A8: 1 | B8: Manpower Cost | D8: =SUM(D9:D17) -> 2224001.8 | E8: =SUM(E9:E17) -> 4.6820165 | G8: =SUM(G10:G17) -> 534537.1 | H8: =SUM(H10:H17) -> 2.8566026 | I8: =SUM(I9:I17) -> 7.538619 | K8: =SUM(K10:K17) -> 152743.45 | L8: =SUM(L10:L17) -> 0.53056918 | M8: =SUM(M9:M17) -> 5.2125856 | O8: =SUM(O9:O17) -> 2446402 | P8: =SUM(P9:P17) -> 5.1502181 | R8: =SUM(R10:R17) -> 587990.81 | S8: =SUM(S10:S17) -> 3.1422628 | T8: =SUM(T9:T17) -> 8.2924809 | V8: =SUM(V10:V17) -> 168017.8 | W8: =SUM(W10:W17) -> 0.5836261 | X8: =SUM(X9:X17) -> 5.7338442 | Z8: =SUM(Z9:Z17) -> 2691042.2 | AA8: =SUM(AA9:AA17) -> 5.6652399 | AC8: =SUM(AC10:AC17) -> 646789.89 | AD8: =SUM(AD10:AD17) -> 3.4564891 | AE8: =SUM(AE9:AE17) -> 9.121729 | AG8: =SUM(AG10:AG17) -> 184819.57 | AH8: =SUM(AH10:AH17) -> 0.64198871 | AI8: =SUM(AI9:AI17) -> 6.3072286
A9: a | B9: Manpower Cost | D9: =Manpower!M8 -> 180000 | E9: =D9/$E$4 -> 0.37893988 | G9: 0 | H9: =G9/$H$4 -> 0 | I9: =E9+H9 -> 0.37893988 | L9: =K9/$L$4 -> 0 | M9: =E9+L9 -> 0.37893988 | O9: =D9*110% -> 198000 | P9: =O9/$E$4 -> 0.41683386 | R9: =G9*110% -> 0 | S9: =R9/$H$4 -> 0 | T9: =P9+S9 -> 0.41683386 | V9: =K9*110% -> 0 | W9: =V9/$L$4 -> 0 | X9: =P9+W9 -> 0.41683386 | Z9: =O9*110% -> 217800 | AA9: =Z9/$E$4 -> 0.45851725 | AC9: =R9*110% -> 0 | AD9: =AC9/$H$4 -> 0 | AE9: =AA9+AD9 -> 0.45851725 | AG9: =V9*110% -> 0 | AH9: =AG9/$L$4 -> 0 | AI9: =AA9+AH9 -> 0.45851725
A10: b | B10: Management Staff | D10: =Manpower!M20 -> 495833.33 | E10: =D10/$E$4 -> 1.043839 | G10: 0 | H10: =G10/$H$4 -> 0 | I10: =E10+H10 -> 1.043839 | K10: =G10*110% -> 0 | L10: =K10/$L$4 -> 0 | M10: =E10+L10 -> 1.043839 | O10: =D10*110% -> 545416.67 | P10: =O10/$E$4 -> 1.1482229 | R10: =G10*110% -> 0 | S10: =R10/$H$4 -> 0 | T10: =P10+S10 -> 1.1482229 | V10: =K10*110% -> 0 | W10: =V10/$L$4 -> 0 | X10: =P10+W10 -> 1.1482229 | Z10: =O10*110% -> 599958.33 | AA10: =Z10/$E$4 -> 1.2630452 | AC10: =R10*110% -> 0 | AD10: =AC10/$H$4 -> 0 | AE10: =AA10+AD10 -> 1.2630452 | AG10: =V10*110% -> 0 | AH10: =AG10/$L$4 -> 0 | AI10: =AA10+AH10 -> 1.2630452
A11: c | B11: Property Management Fee- IPC | D11: 225000 | E11: =D11/$E$4 -> 0.47367485 | G11: 0 | H11: =G11/$H$4 -> 0 | I11: =E11+H11 -> 0.47367485 | K11: =G11*110% -> 0 | L11: =K11/$L$4 -> 0 | M11: =E11+L11 -> 0.47367485 | O11: =D11*110% -> 247500 | P11: =O11/$E$4 -> 0.52104233 | R11: =G11*110% -> 0 | S11: =R11/$H$4 -> 0 | T11: =P11+S11 -> 0.52104233 | V11: =K11*110% -> 0 | W11: =V11/$L$4 -> 0 | X11: =P11+W11 -> 0.52104233 | Z11: =O11*110% -> 272250 | AA11: =Z11/$E$4 -> 0.57314656 | AC11: =R11*110% -> 0 | AD11: =AC11/$H$4 -> 0 | AE11: =AA11+AD11 -> 0.57314656 | AG11: =V11*110% -> 0 | AH11: =AG11/$L$4 -> 0 | AI11: =AA11+AH11 -> 0.57314656
A12: d | B12: Engineering Manpower | D12: =Manpower!M33 -> 572810 | E12: =D12/$E$4 -> 1.2058919 | G12: 0 | H12: =G12/$H$4 -> 0 | I12: =E12+H12 -> 1.2058919 | K12: =G12*110% -> 0 | L12: =K12/$L$4 -> 0 | M12: =E12+L12 -> 1.2058919 | O12: =D12*110% -> 630091 | P12: =O12/$E$4 -> 1.3264811 | R12: =G12*110% -> 0 | S12: =R12/$H$4 -> 0 | T12: =P12+S12 -> 1.3264811 | V12: =K12*110% -> 0 | W12: =V12/$L$4 -> 0 | X12: =P12+W12 -> 1.3264811 | Z12: =O12*110% -> 693100.1 | AA12: =Z12/$E$4 -> 1.4591293 | AC12: =R12*110% -> 0 | AD12: =AC12/$H$4 -> 0 | AE12: =AA12+AD12 -> 1.4591293 | AG12: =V12*110% -> 0 | AH12: =AG12/$L$4 -> 0 | AI12: =AA12+AH12 -> 1.4591293
A13: e | B13: Custodial Services Manpower | D13: =Manpower!M40 -> 132704.45 | E13: =D13/$E$4 -> 0.27937227 | G13: =Manpower!M45 -> 303957.1 | H13: =G13/$H$4 -> 1.6243674 | I13: =E13+H13 -> 1.9037397 | K13: =Manpower!M49 -> 95098.45 | L13: =K13/$L$4 -> 0.33033368 | M13: =E13+L13 -> 0.60970595 | O13: =D13*110% -> 145974.9 | P13: =O13/$E$4 -> 0.30730949 | R13: =G13*110% -> 334352.81 | S13: =R13/$H$4 -> 1.7868041 | T13: =P13+S13 -> 2.0941136 | V13: =K13*110% -> 104608.29 | W13: =V13/$L$4 -> 0.36336705 | X13: =P13+W13 -> 0.67067654 | Z13: =O13*110% -> 160572.38 | AA13: =Z13/$E$4 -> 0.33804044 | AC13: =R13*110% -> 367788.09 | AD13: =AC13/$H$4 -> 1.9654845 | AE13: =AA13+AD13 -> 2.303525 | AG13: =V13*110% -> 115069.12 | AH13: =AG13/$L$4 -> 0.39970376 | AI13: =AA13+AH13 -> 0.7377442
A14: f | B14: Horticulture Manpower | D14: =Manpower!M53 -> 45648 | E14: =D14/$E$4 -> 0.096099153 | G14: 0 | H14: =G14/$H$4 -> 0 | I14: =E14+H14 -> 0.096099153 | K14: 0 | L14: =K14/$L$4 -> 0 | M14: =E14+L14 -> 0.096099153 | O14: =D14*110% -> 50212.8 | P14: =O14/$E$4 -> 0.10570907 | R14: =G14*110% -> 0 | S14: =R14/$H$4 -> 0 | T14: =P14+S14 -> 0.10570907 | V14: =K14*110% -> 0 | W14: =V14/$L$4 -> 0 | X14: =P14+W14 -> 0.10570907 | Z14: =O14*110% -> 55234.08 | AA14: =Z14/$E$4 -> 0.11627997 | AC14: =R14*110% -> 0 | AD14: =AC14/$H$4 -> 0 | AE14: =AA14+AD14 -> 0.11627997 | AG14: =V14*110% -> 0 | AH14: =AG14/$L$4 -> 0 | AI14: =AA14+AH14 -> 0.11627997
A15: g | B15: Pest Control Services | D15: =100000*20/100 -> 20000 | E15: =D15/$E$4 -> 0.042104431 | G15: 0 | H15: =G15/$H$4 -> 0 | I15: =E15+H15 -> 0.042104431 | K15: 0 | L15: =K15/$L$4 -> 0 | M15: =E15+L15 -> 0.042104431 | O15: =D15*110% -> 22000 | P15: =O15/$E$4 -> 0.046314874 | R15: =G15*110% -> 0 | S15: =R15/$H$4 -> 0 | T15: =P15+S15 -> 0.046314874 | V15: =K15*110% -> 0 | W15: =V15/$L$4 -> 0 | X15: =P15+W15 -> 0.046314874 | Z15: =O15*110% -> 24200 | AA15: =Z15/$E$4 -> 0.050946361 | AC15: =R15*110% -> 0 | AD15: =AC15/$H$4 -> 0 | AE15: =AA15+AD15 -> 0.050946361 | AG15: =V15*110% -> 0 | AH15: =AG15/$L$4 -> 0 | AI15: =AA15+AH15 -> 0.050946361
A16: h | B16: Façade Cleaning Services | D16: =Manpower!M84 -> 84952 | E16: =D16/$E$4 -> 0.17884278 | H16: =G16/$H$4 -> 0 | I16: =E16+H16 -> 0.17884278 | L16: =K16/$L$4 -> 0 | M16: =E16+L16 -> 0.17884278 | O16: =D16*110% -> 93447.2 | P16: =O16/$E$4 -> 0.19672706 | S16: =R16/$H$4 -> 0 | T16: =P16+S16 -> 0.19672706 | W16: =V16/$L$4 -> 0 | X16: =P16+W16 -> 0.19672706 | Z16: =O16*110% -> 102791.92 | AA16: =Z16/$E$4 -> 0.21639976 | AD16: =AC16/$H$4 -> 0 | AE16: =AA16+AD16 -> 0.21639976 | AH16: =AG16/$L$4 -> 0 | AI16: =AA16+AH16 -> 0.21639976
A17: i | B17: Security Services-manpower | D17: =Manpower!M68 -> 467054 | E17: =D17/$E$4 -> 0.98325214 | G17: =Manpower!M73 -> 230580 | H17: =G17/$H$4 -> 1.2322352 | I17: =E17+H17 -> 2.2154873 | K17: =Manpower!M76 -> 57645 | L17: =K17/$L$4 -> 0.20023549 | M17: =E17+L17 -> 1.1834876 | O17: =D17*110% -> 513759.4 | P17: =O17/$E$4 -> 1.0815774 | R17: =G17*110% -> 253638 | S17: =R17/$H$4 -> 1.3554587 | T17: =P17+S17 -> 2.4370361 | V17: =K17*110% -> 63409.5 | W17: =V17/$L$4 -> 0.22025904 | X17: =P17+W17 -> 1.3018364 | Z17: =O17*110% -> 565135.34 | AA17: =Z17/$E$4 -> 1.1897351 | AC17: =R17*110% -> 279001.8 | AD17: =AC17/$H$4 -> 1.4910046 | AE17: =AA17+AD17 -> 2.6807397 | AG17: =V17*110% -> 69750.45 | AH17: =AG17/$L$4 -> 0.24228495 | AI17: =AA17+AH17 -> 1.43202
A19: 2 | B19: Spares and Consumables ( Engineering & Building Services) | D19: =SUM(D20:D24) -> 324620.2 | E19: =SUM(E20:E24) -> 0.68339744 | G19: =SUM(G20:G24) -> 100268.21 | H19: =SUM(H20:H24) -> 0.2110868 | I19: =SUM(I20:I24) -> 0.89448424 | K19: =SUM(K20:K24) -> 32889.212 | L19: =SUM(L20:L24) -> 0.069239077 | M19: =SUM(M20:M24) -> 0.75263651 | O19: =SUM(O20:O24) -> 346329.72 | P19: =SUM(P20:P24) -> 0.72910079 | R19: =SUM(R20:R24) -> 105281.62 | S19: =SUM(S20:S24) -> 0.22164114 | T19: =SUM(T20:T24) -> 0.95074193 | V19: =SUM(V20:V24) -> 34533.672 | W19: =SUM(W20:W24) -> 0.072701031 | X19: =SUM(X20:X24) -> 0.80180182 | Z19: =SUM(Z20:Z24) -> 358519.96 | AA19: =SUM(AA20:AA24) -> 0.75476393 | AC19: =SUM(AC20:AC24) -> 110545.7 | AD19: =SUM(AD20:AD24) -> 0.2327232 | AE19: =SUM(AE20:AE24) -> 0.98748713 | AG19: =SUM(AG20:AG24) -> 36260.356 | AH19: =SUM(AH20:AH24) -> 0.076336083 | AI19: =SUM(AI20:AI24) -> 0.83110002
A20: a | B20: Engineering Spares and Consumables | D20: =265119*80% -> 212095.2 | E20: =D20/$E$4 -> 0.44650738 | G20: 80768.212 | H20: =G20/$E$4 -> 0.17003498 | I20: =E20+H20 -> 0.61654236 | K20: 23389.212 | L20: =K20/$E$4 -> 0.049239473 | M20: =E20+L20 -> 0.49574686 | O20: =D20*110% -> 233304.72 | P20: =O20/$E$4 -> 0.49115812 | R20: =G20*105% -> 84806.623 | S20: =R20/$E$4 -> 0.17853673 | T20: =P20+S20 -> 0.66969485 | V20: =K20*105% -> 24558.672 | W20: =V20/$E$4 -> 0.051701446 | X20: =P20+W20 -> 0.54285957 | Z20: =O20*105% -> 244969.96 | AA20: =Z20/$E$4 -> 0.51571603 | AC20: =R20*105% -> 89046.954 | AD20: =AC20/$E$4 -> 0.18746357 | AE20: =AA20+AD20 -> 0.70317959 | AG20: =V20*105% -> 25786.606 | AH20: =AG20/$E$4 -> 0.054286519 | AI20: =AA20+AH20 -> 0.57000255
A21: b | B21: Housekeeping Equipments | D21: ='HK - Secr Equipments'!J14 -> 30525 | E21: =D21/$E$4 -> 0.064261887 | H21: =G21/$E$4 -> 0 | I21: =E21+H21 -> 0.064261887 | L21: =K21/$E$4 -> 0 | M21: =E21+L21 -> 0.064261887 | O21: =D21 -> 30525 | P21: =O21/$E$4 -> 0.064261887 | R21: =G21 -> 0 | S21: =R21/$E$4 -> 0 | T21: =P21+S21 -> 0.064261887 | V21: =K21 -> 0 | W21: =V21/$E$4 -> 0 | X21: =P21+W21 -> 0.064261887 | Z21: =O21 -> 30525 | AA21: =Z21/$E$4 -> 0.064261887 | AC21: =R21 -> 0 | AD21: =AC21/$E$4 -> 0 | AE21: =AA21+AD21 -> 0.064261887 | AG21: =V21 -> 0 | AH21: =AG21/$E$4 -> 0 | AI21: =AA21+AH21 -> 0.064261887
A22: c | B22: Housekeeping Consumables and Toiletries | D22: 10000 | E22: =D22/$E$4 -> 0.021052215 | G22: 19500 | H22: =G22/$E$4 -> 0.04105182 | I22: =E22+H22 -> 0.062104035 | K22: 9500 | L22: =K22/$E$4 -> 0.019999605 | M22: =E22+L22 -> 0.04105182 | O22: =D22*105% -> 10500 | P22: =O22/$E$4 -> 0.022104826 | R22: =G22*105% -> 20475 | S22: =R22/$E$4 -> 0.043104411 | T22: =P22+S22 -> 0.065209237 | V22: =K22*105% -> 9975 | W22: =V22/$E$4 -> 0.020999585 | X22: =P22+W22 -> 0.043104411 | Z22: =O22*105% -> 11025 | AA22: =Z22/$E$4 -> 0.023210067 | AC22: =R22*105% -> 21498.75 | AD22: =AC22/$E$4 -> 0.045259632 | AE22: =AA22+AD22 -> 0.068469699 | AG22: =V22*105% -> 10473.75 | AH22: =AG22/$E$4 -> 0.022049564 | AI22: =AA22+AH22 -> 0.045259632
A23: f | B23: Horticulture Tools and Consumables | D23: =Manpower!M58 -> 29000 | E23: =D23/$E$4 -> 0.061051425 | H23: =G23/$E$4 -> 0 | I23: =E23+H23 -> 0.061051425 | L23: =K23/$E$4 -> 0 | M23: =E23+L23 -> 0.061051425 | O23: =D23 -> 29000 | P23: =O23/$E$4 -> 0.061051425 | R23: =G23 -> 0 | S23: =R23/$E$4 -> 0 | T23: =P23+S23 -> 0.061051425 | V23: =K23 -> 0 | W23: =V23/$E$4 -> 0 | X23: =P23+W23 -> 0.061051425 | Z23: =O23 -> 29000 | AA23: =Z23/$E$4 -> 0.061051425 | AC23: =R23 -> 0 | AD23: =AC23/$E$4 -> 0 | AE23: =AA23+AD23 -> 0.061051425 | AG23: =V23 -> 0 | AH23: =AG23/$E$4 -> 0 | AI23: =AA23+AH23 -> 0.061051425
A24: g | B24: Security Equipments | D24: ='HK - Secr Equipments'!H22 -> 43000 | E24: =D24/$E$4 -> 0.090524526 | H24: =G24/$E$4 -> 0 | I24: =E24+H24 -> 0.090524526 | L24: =K24/$E$4 -> 0 | M24: =E24+L24 -> 0.090524526 | O24: =D24 -> 43000 | P24: =O24/$E$4 -> 0.090524526 | R24: =G24 -> 0 | S24: =R24/$E$4 -> 0 | T24: =P24+S24 -> 0.090524526 | V24: =K24 -> 0 | W24: =V24/$E$4 -> 0 | X24: =P24+W24 -> 0.090524526 | Z24: =O24 -> 43000 | AA24: =Z24/$E$4 -> 0.090524526 | AC24: =R24 -> 0 | AD24: =AC24/$E$4 -> 0 | AE24: =AA24+AD24 -> 0.090524526 | AG24: =V24 -> 0 | AH24: =AG24/$E$4 -> 0 | AI24: =AA24+AH24 -> 0.090524526
A26: 3 | B26: AMC Charges | D26: ='AMC Cost'!D13 -> 0 | E26: =D26/$E$4 -> 0 | G26: ='AMC Cost'!D18 -> 0 | H26: =G26/$H$4 -> 0 | I26: =E26+H26 -> 0 | K26: ='AMC Cost'!D23 -> 0 | L26: =K26/$L$4 -> 0 | M26: =E26+L26 -> 0 | O26: ='AMC Cost'!E13 -> 128070 | P26: =O26/$E$4 -> 0.26961572 | R26: ='AMC Cost'!E23 -> 0 | S26: =R26/$H$4 -> 0 | T26: =P26+S26 -> 0.26961572 | V26: ='AMC Cost'!E18 -> 183333.33 | W26: =V26/$L$4 -> 0.6368261 | X26: =P26+W26 -> 0.90644183 | Z26: ='AMC Cost'!F13 -> 403829.34 | AA26: =Z26/$E$4 -> 0.85015023 | AC26: ='AMC Cost'!F23 -> 60833.333 | AD26: =AC26/$H$4 -> 0.32509747 | AE26: =AA26+AD26 -> 1.1752477 | AG26: ='AMC Cost'!F18 -> 191666.67 | AH26: =AG26/$L$4 -> 0.66577274 | AI26: =AA26+AH26 -> 1.515923
A28: 4 | B28: Electricity Cost ( Utility & Common Area HVAC) | D28: =SUM(D29:D30) -> 142946.15 | E28: =SUM(E29:E30) -> 0.30093331 | G28: =SUM(G29:G30) -> 654927.13 | H28: =SUM(H29:H30) -> 1.3787667 | I28: =SUM(I29:I30) -> 1.6797 | K28: =SUM(K29:K30) -> 455237.06 | L28: =SUM(L29:L30) -> 0.95837487 | M28: =SUM(M29:M30) -> 1.2593082 | O28: =SUM(O29:O30) -> 150093.45 | P28: =SUM(P29:P30) -> 0.31597997 | R28: =SUM(R29:R30) -> 687673.49 | S28: =SUM(S29:S30) -> 1.447705 | T28: =SUM(T29:T30) -> 1.763685 | V28: =SUM(V29:V30) -> 477998.92 | W28: =SUM(W29:W30) -> 1.0062936 | X28: =SUM(X29:X30) -> 1.3222736 | Z28: =SUM(Z29:Z30) -> 157598.13 | AA28: =SUM(AA29:AA30) -> 0.33177897 | AC28: =SUM(AC29:AC30) -> 722057.16 | AD28: =SUM(AD29:AD30) -> 1.5200903 | AE28: =SUM(AE29:AE30) -> 1.8518693 | AG28: =SUM(AG29:AG30) -> 501898.86 | AH28: =SUM(AH29:AH30) -> 1.0566083 | AI28: =SUM(AI29:AI30) -> 1.3883873
A29: a | B29: Common Area Electricity Expense | D29: ='Comm Electrical load'!D9 -> 142946.15 | E29: =D29/$E$4 -> 0.30093331 | G29: ='Comm Electrical load'!D19 -> 98607.656 | H29: =G29/$E$4 -> 0.20759096 | I29: =E29+H29 -> 0.50852427 | K29: ='Comm Electrical load'!D29 -> 40071.331 | L29: =K29/$E$4 -> 0.084359029 | M29: =E29+L29 -> 0.38529233 | O29: =D29*105% -> 150093.45 | P29: =O29/$E$4 -> 0.31597997 | R29: =G29*105% -> 103538.04 | S29: =R29/$E$4 -> 0.21797051 | T29: =P29+S29 -> 0.53395048 | V29: =K29*105% -> 42074.898 | W29: =V29/$E$4 -> 0.08857698 | X29: =P29+W29 -> 0.40455695 | Z29: =O29*105% -> 157598.13 | AA29: =Z29/$E$4 -> 0.33177897 | AC29: =R29*105% -> 108714.94 | AD29: =AC29/$E$4 -> 0.22886903 | AE29: =AA29+AD29 -> 0.560648 | AG29: =V29*105% -> 44178.642 | AH29: =AG29/$E$4 -> 0.093005829 | AI29: =AA29+AH29 -> 0.4247848
A30: b | B30: HVAC Expense for common area | E30: =D30/$E$4 -> 0 | G30: ='HVAC-Mall'!C26 -> 556319.48 | H30: =G30/$E$4 -> 1.1711757 | I30: =E30+H30 -> 1.1711757 | K30: ='Load Breakup'!I265 -> 415165.73 | L30: =K30/$E$4 -> 0.87401584 | M30: =E30+L30 -> 0.87401584 | O30: =D30*105% -> 0 | P30: =O30/$E$4 -> 0 | R30: =G30*105% -> 584135.45 | S30: =R30/$E$4 -> 1.2297345 | T30: =P30+S30 -> 1.2297345 | V30: =K30*105% -> 435924.02 | W30: =V30/$E$4 -> 0.91771663 | X30: =P30+W30 -> 0.91771663 | Z30: =O30*105% -> 0 | AA30: =Z30/$E$4 -> 0 | AC30: =R30*105% -> 613342.22 | AD30: =AC30/$E$4 -> 1.2912213 | AE30: =AA30+AD30 -> 1.2912213 | AG30: =V30*105% -> 457720.22 | AH30: =AG30/$E$4 -> 0.96360247 | AI30: =AA30+AH30 -> 0.96360247
A32: 5 | B32: Audits | D32: =SUM(D33:D38) -> 43333.333 | E32: =ROUND(SUM(E33:E38),2) -> 0.09 | G32: =SUM(G33:G38) -> 0 | H32: =ROUND(SUM(H33:H38),2) -> 0 | I32: =SUM(I33:I38) -> 0.091226267 | K32: =SUM(K33:K38) -> 0 | L32: =ROUND(SUM(L33:L38),2) -> 0 | M32: =SUM(M33:M38) -> 0.091226267 | O32: =SUM(O33:O38) -> 60833.333 | P32: =ROUND(SUM(P33:P38),2) -> 0.13 | R32: =SUM(R33:R38) -> 0 | S32: =ROUND(SUM(S33:S38),2) -> 0 | T32: =SUM(T33:T38) -> 0.12806764 | V32: =SUM(V33:V38) -> 0 | W32: =ROUND(SUM(W33:W38),2) -> 0 | X32: =SUM(X33:X38) -> 0.12806764 | Z32: =SUM(Z33:Z38) -> 60833.333 | AA32: =ROUND(SUM(AA33:AA38),2) -> 0.13 | AC32: =SUM(AC33:AC38) -> 0 | AD32: =ROUND(SUM(AD33:AD38),2) -> 0 | AE32: =SUM(AE33:AE38) -> 0.12806764 | AG32: =SUM(AG33:AG38) -> 0 | AH32: =ROUND(SUM(AH33:AH38),2) -> 0 | AI32: =SUM(AI33:AI38) -> 0.12806764
A33: a | B33: Energy Audit / Thermography and Harmonic Test | D33: 8333.3333 | E33: =D33/$E$4 -> 0.017543513 | H33: =G33/$E$4 -> 0 | I33: =E33+H33 -> 0.017543513 | L33: =K33/$E$4 -> 0 | M33: =E33+L33 -> 0.017543513 | O33: 8333.3333 | P33: =O33/$E$4 -> 0.017543513 | S33: =R33/$E$4 -> 0 | T33: =P33+S33 -> 0.017543513 | W33: =V33/$E$4 -> 0 | X33: =P33+W33 -> 0.017543513 | Z33: 8333.3333 | AA33: =Z33/$E$4 -> 0.017543513 | AD33: =AC33/$E$4 -> 0 | AE33: =AA33+AD33 -> 0.017543513 | AH33: =AG33/$E$4 -> 0 | AI33: =AA33+AH33 -> 0.017543513
A34: b | B34: Fire, Health & Safety Audits | D34: 8333.3333 | E34: =D34/$E$4 -> 0.017543513 | H34: =G34/$E$4 -> 0 | I34: =E34+H34 -> 0.017543513 | L34: =K34/$E$4 -> 0 | M34: =E34+L34 -> 0.017543513 | O34: 8333.3333 | P34: =O34/$E$4 -> 0.017543513 | S34: =R34/$E$4 -> 0 | T34: =P34+S34 -> 0.017543513 | W34: =V34/$E$4 -> 0 | X34: =P34+W34 -> 0.017543513 | Z34: 8333.3333 | AA34: =Z34/$E$4 -> 0.017543513 | AD34: =AC34/$E$4 -> 0 | AE34: =AA34+AD34 -> 0.017543513 | AH34: =AG34/$E$4 -> 0 | AI34: =AA34+AH34 -> 0.017543513
A35: c | B35: Indoor Air Quality and DG emmission testing | D35: 8333.3333 | E35: =D35/$E$4 -> 0.017543513 | H35: =G35/$E$4 -> 0 | I35: =E35+H35 -> 0.017543513 | L35: =K35/$E$4 -> 0 | M35: =E35+L35 -> 0.017543513 | O35: 8333.3333 | P35: =O35/$E$4 -> 0.017543513 | S35: =R35/$E$4 -> 0 | T35: =P35+S35 -> 0.017543513 | W35: =V35/$E$4 -> 0 | X35: =P35+W35 -> 0.017543513 | Z35: 8333.3333 | AA35: =Z35/$E$4 -> 0.017543513 | AD35: =AC35/$E$4 -> 0 | AE35: =AA35+AD35 -> 0.017543513 | AH35: =AG35/$E$4 -> 0 | AI35: =AA35+AH35 -> 0.017543513
A36: d | B36: Legal and professional servcies | D36: 8333.3333 | E36: =D36/$E$4 -> 0.017543513 | H36: =G36/$E$4 -> 0 | I36: =E36+H36 -> 0.017543513 | L36: =K36/$E$4 -> 0 | M36: =E36+L36 -> 0.017543513 | O36: 20833.333 | P36: =O36/$E$4 -> 0.043858782 | S36: =R36/$E$4 -> 0 | T36: =P36+S36 -> 0.043858782 | W36: =V36/$E$4 -> 0 | X36: =P36+W36 -> 0.043858782 | Z36: 20833.333 | AA36: =Z36/$E$4 -> 0.043858782 | AD36: =AC36/$E$4 -> 0 | AE36: =AA36+AD36 -> 0.043858782 | AH36: =AG36/$E$4 -> 0 | AI36: =AA36+AH36 -> 0.043858782
A37: e | B37: Statutory compliances (PF, ESIC, Ptax, Lab.Welfare, Licenses, Returns, Audit etc.) | D37: 5000 | E37: =D37/$E$4 -> 0.010526108 | H37: =G37/$E$4 -> 0 | I37: =E37+H37 -> 0.010526108 | L37: =K37/$E$4 -> 0 | M37: =E37+L37 -> 0.010526108 | O37: 10000 | P37: =O37/$E$4 -> 0.021052215 | S37: =R37/$E$4 -> 0 | T37: =P37+S37 -> 0.021052215 | W37: =V37/$E$4 -> 0 | X37: =P37+W37 -> 0.021052215 | Z37: 10000 | AA37: =Z37/$E$4 -> 0.021052215 | AD37: =AC37/$E$4 -> 0 | AE37: =AA37+AD37 -> 0.021052215 | AH37: =AG37/$E$4 -> 0 | AI37: =AA37+AH37 -> 0.021052215
A38: f | B38: Water Testing Charges | D38: 5000 | E38: =D38/$E$4 -> 0.010526108 | H38: =G38/$E$4 -> 0 | I38: =E38+H38 -> 0.010526108 | L38: =K38/$E$4 -> 0 | M38: =E38+L38 -> 0.010526108 | O38: 5000 | P38: =O38/$E$4 -> 0.010526108 | S38: =R38/$E$4 -> 0 | T38: =P38+S38 -> 0.010526108 | W38: =V38/$E$4 -> 0 | X38: =P38+W38 -> 0.010526108 | Z38: 5000 | AA38: =Z38/$E$4 -> 0.010526108 | AD38: =AC38/$E$4 -> 0 | AE38: =AA38+AD38 -> 0.010526108 | AH38: =AG38/$E$4 -> 0 | AI38: =AA38+AH38 -> 0.010526108
A40: 6 | B40: Liosaning & Licenses Cost | D40: =SUM(D41:D49) -> 37891.667 | E40: =SUM(E41:E49) -> 0.079770353 | G40: =SUM(G41:G49) -> 0 | H40: =SUM(H41:H49) -> 0 | I40: =SUM(I41:I49) -> 0.079770353 | K40: =SUM(K41:K49) -> 0 | L40: =SUM(L41:L49) -> 0 | M40: =SUM(M41:M49) -> 0.079770353 | O40: =SUM(O41:O49) -> 37391.667 | P40: =SUM(P41:P49) -> 0.078717742 | R40: =SUM(R41:R49) -> 0 | S40: =SUM(S41:S49) -> 0 | T40: =SUM(T41:T49) -> 0.078717742 | V40: =SUM(V41:V49) -> 0 | W40: =SUM(W41:W49) -> 0 | X40: =SUM(X41:X49) -> 0.078717742 | Z40: =SUM(Z41:Z49) -> 37391.667 | AA40: =SUM(AA41:AA49) -> 0.078717742 | AC40: =SUM(AC41:AC49) -> 0 | AD40: =SUM(AD41:AD49) -> 0 | AE40: =SUM(AE41:AE49) -> 0.078717742 | AG40: =SUM(AG41:AG49) -> 0 | AH40: =SUM(AH41:AH49) -> 0 | AI40: =SUM(AI41:AI49) -> 0.078717742
A41: a | B41: Electrical and DG License renewal | D41: 208.33333 | E41: =D41/$E$4 -> 0.00043858782 | H41: =G41/$E$4 -> 0 | I41: =E41+H41 -> 0.00043858782 | L41: =K41/$E$4 -> 0 | M41: =E41+L41 -> 0.00043858782 | O41: 208.33333 | P41: =O41/$E$4 -> 0.00043858782 | S41: =R41/$E$4 -> 0 | T41: =P41+S41 -> 0.00043858782 | W41: =V41/$E$4 -> 0 | X41: =P41+W41 -> 0.00043858782 | Z41: 208.33333 | AA41: =Z41/$E$4 -> 0.00043858782 | AD41: =AC41/$E$4 -> 0 | AE41: =AA41+AD41 -> 0.00043858782 | AH41: =AG41/$E$4 -> 0 | AI41: =AA41+AH41 -> 0.00043858782
A42: b | B42: Lift License Renewal | D42: 2500 | E42: =D42/$E$4 -> 0.0052630538 | H42: =G42/$E$4 -> 0 | I42: =E42+H42 -> 0.0052630538 | L42: =K42/$E$4 -> 0 | M42: =E42+L42 -> 0.0052630538 | O42: 2000 | P42: =O42/$E$4 -> 0.0042104431 | S42: =R42/$E$4 -> 0 | T42: =P42+S42 -> 0.0042104431 | W42: =V42/$E$4 -> 0 | X42: =P42+W42 -> 0.0042104431 | Z42: 2000 | AA42: =Z42/$E$4 -> 0.0042104431 | AD42: =AC42/$E$4 -> 0 | AE42: =AA42+AD42 -> 0.0042104431 | AH42: =AG42/$E$4 -> 0 | AI42: =AA42+AH42 -> 0.0042104431
A43: c | B43: Fire NOC | D43: 83.333333 | E43: =D43/$E$4 -> 0.00017543513 | H43: =G43/$E$4 -> 0 | I43: =E43+H43 -> 0.00017543513 | L43: =K43/$E$4 -> 0 | M43: =E43+L43 -> 0.00017543513 | O43: 83.333333 | P43: =O43/$E$4 -> 0.00017543513 | S43: =R43/$E$4 -> 0 | T43: =P43+S43 -> 0.00017543513 | W43: =V43/$E$4 -> 0 | X43: =P43+W43 -> 0.00017543513 | Z43: 83.333333 | AA43: =Z43/$E$4 -> 0.00017543513 | AD43: =AC43/$E$4 -> 0 | AE43: =AA43+AD43 -> 0.00017543513 | AH43: =AG43/$E$4 -> 0 | AI43: =AA43+AH43 -> 0.00017543513
A44: d | B44: Labour license and registration | D44: 4166.6667 | E44: =D44/$E$4 -> 0.0087717564 | H44: =G44/$E$4 -> 0 | I44: =E44+H44 -> 0.0087717564 | L44: =K44/$E$4 -> 0 | M44: =E44+L44 -> 0.0087717564 | O44: 4166.6667 | P44: =O44/$E$4 -> 0.0087717564 | S44: =R44/$E$4 -> 0 | T44: =P44+S44 -> 0.0087717564 | W44: =V44/$E$4 -> 0 | X44: =P44+W44 -> 0.0087717564 | Z44: 4166.6667 | AA44: =Z44/$E$4 -> 0.0087717564 | AD44: =AC44/$E$4 -> 0 | AE44: =AA44+AD44 -> 0.0087717564 | AH44: =AG44/$E$4 -> 0 | AI44: =AA44+AH44 -> 0.0087717564
A45: e | B45: Liosaning & Licenses Cost | D45: 25000 | E45: =D45/$E$4 -> 0.052630538 | H45: =G45/$E$4 -> 0 | I45: =E45+H45 -> 0.052630538 | L45: =K45/$E$4 -> 0 | M45: =E45+L45 -> 0.052630538 | O45: 25000 | P45: =O45/$E$4 -> 0.052630538 | S45: =R45/$E$4 -> 0 | T45: =P45+S45 -> 0.052630538 | W45: =V45/$E$4 -> 0 | X45: =P45+W45 -> 0.052630538 | Z45: 25000 | AA45: =Z45/$E$4 -> 0.052630538 | AD45: =AC45/$E$4 -> 0 | AE45: =AA45+AD45 -> 0.052630538 | AH45: =AG45/$E$4 -> 0 | AI45: =AA45+AH45 -> 0.052630538
A46: f | B46: Environmental and Pollution Control Inspections | D46: 4166.6667 | E46: =D46/$E$4 -> 0.0087717564 | H46: =G46/$E$4 -> 0 | I46: =E46+H46 -> 0.0087717564 | L46: =K46/$E$4 -> 0 | M46: =E46+L46 -> 0.0087717564 | O46: 4166.6667 | P46: =O46/$E$4 -> 0.0087717564 | S46: =R46/$E$4 -> 0 | T46: =P46+S46 -> 0.0087717564 | W46: =V46/$E$4 -> 0 | X46: =P46+W46 -> 0.0087717564 | Z46: 4166.6667 | AA46: =Z46/$E$4 -> 0.0087717564 | AD46: =AC46/$E$4 -> 0 | AE46: =AA46+AD46 -> 0.0087717564 | AH46: =AG46/$E$4 -> 0 | AI46: =AA46+AH46 -> 0.0087717564
A47: g | B47: Water Cess | D47: 1250 | E47: =D47/$E$4 -> 0.0026315269 | H47: =G47/$E$4 -> 0 | I47: =E47+H47 -> 0.0026315269 | L47: =K47/$E$4 -> 0 | M47: =E47+L47 -> 0.0026315269 | O47: 1250 | P47: =O47/$E$4 -> 0.0026315269 | S47: =R47/$E$4 -> 0 | T47: =P47+S47 -> 0.0026315269 | W47: =V47/$E$4 -> 0 | X47: =P47+W47 -> 0.0026315269 | Z47: 1250 | AA47: =Z47/$E$4 -> 0.0026315269 | AD47: =AC47/$E$4 -> 0 | AE47: =AA47+AD47 -> 0.0026315269 | AH47: =AG47/$E$4 -> 0 | AI47: =AA47+AH47 -> 0.0026315269
A48: h | B48: Shop & Etablishment ( 5years) | D48: 100 | E48: =D48/$E$4 -> 0.00021052215 | H48: =G48/$E$4 -> 0 | I48: =E48+H48 -> 0.00021052215 | L48: =K48/$E$4 -> 0 | M48: =E48+L48 -> 0.00021052215 | O48: 100 | P48: =O48/$E$4 -> 0.00021052215 | S48: =R48/$E$4 -> 0 | T48: =P48+S48 -> 0.00021052215 | W48: =V48/$E$4 -> 0 | X48: =P48+W48 -> 0.00021052215 | Z48: 100 | AA48: =Z48/$E$4 -> 0.00021052215 | AD48: =AC48/$E$4 -> 0 | AE48: =AA48+AD48 -> 0.00021052215 | AH48: =AG48/$E$4 -> 0 | AI48: =AA48+AH48 -> 0.00021052215
A49: i | B49: Licesnse for storing Pertrolium | D49: 416.66667 | E49: =D49/$E$4 -> 0.00087717564 | H49: =G49/$E$4 -> 0 | I49: =E49+H49 -> 0.00087717564 | L49: =K49/$E$4 -> 0 | M49: =E49+L49 -> 0.00087717564 | O49: 416.66667 | P49: =O49/$E$4 -> 0.00087717564 | S49: =R49/$E$4 -> 0 | T49: =P49+S49 -> 0.00087717564 | W49: =V49/$E$4 -> 0 | X49: =P49+W49 -> 0.00087717564 | Z49: 416.66667 | AA49: =Z49/$E$4 -> 0.00087717564 | AD49: =AC49/$E$4 -> 0 | AE49: =AA49+AD49 -> 0.00087717564 | AH49: =AG49/$E$4 -> 0 | AI49: =AA49+AH49 -> 0.00087717564
A51: 7 | B51: Administrative Expenses | D51: =SUM(D52:D60) -> 70300 | E51: =ROUND(SUM(E52:E60),2) -> 0.15 | G51: =SUM(G52:G60) -> 0 | H51: =ROUND(SUM(H52:H60),2) -> 0 | I51: =SUM(I52:I60) -> 0.14799707 | K51: =SUM(K52:K60) -> 0 | L51: =ROUND(SUM(L52:L60),2) -> 0 | M51: =SUM(M52:M60) -> 0.14799707 | O51: =SUM(O52:O60) -> 78300 | P51: =ROUND(SUM(P52:P60),2) -> 0.16 | R51: =SUM(R52:R60) -> 0 | S51: =ROUND(SUM(S52:S60),2) -> 0 | T51: =SUM(T52:T60) -> 0.16483885 | V51: =SUM(V52:V60) -> 0 | W51: =ROUND(SUM(W52:W60),2) -> 0 | X51: =SUM(X52:X60) -> 0.16483885 | Z51: =SUM(Z52:Z60) -> 78300 | AA51: =ROUND(SUM(AA52:AA60),2) -> 0.16 | AC51: =SUM(AC52:AC60) -> 0 | AD51: =ROUND(SUM(AD52:AD60),2) -> 0 | AE51: =SUM(AE52:AE60) -> 0.16483885 | AG51: =SUM(AG52:AG60) -> 0 | AH51: =ROUND(SUM(AH52:AH60),2) -> 0 | AI51: =SUM(AI52:AI60) -> 0.16483885
A52: a | B52: Rental Equipment (Photocopier, PC, Pumps etc) | D52: 7000 | E52: =D52/$E$4 -> 0.014736551 | H52: =G52/$E$4 -> 0 | I52: =E52+H52 -> 0.014736551 | L52: =K52/$E$4 -> 0 | M52: =E52+L52 -> 0.014736551 | O52: 7000 | P52: =O52/$E$4 -> 0.014736551 | S52: =R52/$E$4 -> 0 | T52: =P52+S52 -> 0.014736551 | W52: =V52/$E$4 -> 0 | X52: =P52+W52 -> 0.014736551 | Z52: 7000 | AA52: =Z52/$E$4 -> 0.014736551 | AD52: =AC52/$E$4 -> 0 | AE52: =AA52+AD52 -> 0.014736551 | AH52: =AG52/$E$4 -> 0 | AI52: =AA52+AH52 -> 0.014736551
A53: b | B53: Travel / Conveyance | D53: 5000 | E53: =D53/$E$4 -> 0.010526108 | H53: =G53/$E$4 -> 0 | I53: =E53+H53 -> 0.010526108 | L53: =K53/$E$4 -> 0 | M53: =E53+L53 -> 0.010526108 | O53: 5000 | P53: =O53/$E$4 -> 0.010526108 | S53: =R53/$E$4 -> 0 | T53: =P53+S53 -> 0.010526108 | W53: =V53/$E$4 -> 0 | X53: =P53+W53 -> 0.010526108 | Z53: 5000 | AA53: =Z53/$E$4 -> 0.010526108 | AD53: =AC53/$E$4 -> 0 | AE53: =AA53+AD53 -> 0.010526108 | AH53: =AG53/$E$4 -> 0 | AI53: =AA53+AH53 -> 0.010526108
A54: c | B54: Office Stationary and Printed Stationary | D54: 10000 | E54: =D54/$E$4 -> 0.021052215 | H54: =G54/$E$4 -> 0 | I54: =E54+H54 -> 0.021052215 | L54: =K54/$E$4 -> 0 | M54: =E54+L54 -> 0.021052215 | O54: 18000 | P54: =O54/$E$4 -> 0.037893988 | S54: =R54/$E$4 -> 0 | T54: =P54+S54 -> 0.037893988 | W54: =V54/$E$4 -> 0 | X54: =P54+W54 -> 0.037893988 | Z54: 18000 | AA54: =Z54/$E$4 -> 0.037893988 | AD54: =AC54/$E$4 -> 0 | AE54: =AA54+AD54 -> 0.037893988 | AH54: =AG54/$E$4 -> 0 | AI54: =AA54+AH54 -> 0.037893988
A55: d | B55: Site Team Communication Charges-Mobile | D55: =(Manpower!L8+Manpower!L20)*500*70% -> 7000 | E55: =D55/$E$4 -> 0.014736551 | H55: =G55/$E$4 -> 0 | I55: =E55+H55 -> 0.014736551 | L55: =K55/$E$4 -> 0 | M55: =E55+L55 -> 0.014736551 | O55: =D55 -> 7000 | P55: =O55/$E$4 -> 0.014736551 | S55: =R55/$E$4 -> 0 | T55: =P55+S55 -> 0.014736551 | W55: =V55/$E$4 -> 0 | X55: =P55+W55 -> 0.014736551 | Z55: =O55 -> 7000 | AA55: =Z55/$E$4 -> 0.014736551 | AD55: =AC55/$E$4 -> 0 | AE55: =AA55+AD55 -> 0.014736551 | AH55: =AG55/$E$4 -> 0 | AI55: =AA55+AH55 -> 0.014736551
A56: e | B56: Magzine, Journals and Newspapers | D56: =150*2+(250*10) -> 2800 | E56: =D56/$E$4 -> 0.0058946203 | H56: =G56/$E$4 -> 0 | I56: =E56+H56 -> 0.0058946203 | L56: =K56/$E$4 -> 0 | M56: =E56+L56 -> 0.0058946203 | O56: =150*2+(250*10) -> 2800 | P56: =O56/$E$4 -> 0.0058946203 | S56: =R56/$E$4 -> 0 | T56: =P56+S56 -> 0.0058946203 | W56: =V56/$E$4 -> 0 | X56: =P56+W56 -> 0.0058946203 | Z56: =150*2+(250*10) -> 2800 | AA56: =Z56/$E$4 -> 0.0058946203 | AD56: =AC56/$E$4 -> 0 | AE56: =AA56+AD56 -> 0.0058946203 | AH56: =AG56/$E$4 -> 0 | AI56: =AA56+AH56 -> 0.0058946203
A57: f | B57: Internet Broadband Connection | D57: 5000 | E57: =D57/$E$4 -> 0.010526108 | H57: =G57/$E$4 -> 0 | I57: =E57+H57 -> 0.010526108 | L57: =K57/$E$4 -> 0 | M57: =E57+L57 -> 0.010526108 | O57: 5000 | P57: =O57/$E$4 -> 0.010526108 | S57: =R57/$E$4 -> 0 | T57: =P57+S57 -> 0.010526108 | W57: =V57/$E$4 -> 0 | X57: =P57+W57 -> 0.010526108 | Z57: 5000 | AA57: =Z57/$E$4 -> 0.010526108 | AD57: =AC57/$E$4 -> 0 | AE57: =AA57+AD57 -> 0.010526108 | AH57: =AG57/$E$4 -> 0 | AI57: =AA57+AH57 -> 0.010526108
A58: g | B58: Landline phone connection | D58: 5000 | E58: =D58/$E$4 -> 0.010526108 | H58: =G58/$E$4 -> 0 | I58: =E58+H58 -> 0.010526108 | L58: =K58/$E$4 -> 0 | M58: =E58+L58 -> 0.010526108 | O58: 5000 | P58: =O58/$E$4 -> 0.010526108 | S58: =R58/$E$4 -> 0 | T58: =P58+S58 -> 0.010526108 | W58: =V58/$E$4 -> 0 | X58: =P58+W58 -> 0.010526108 | Z58: 5000 | AA58: =Z58/$E$4 -> 0.010526108 | AD58: =AC58/$E$4 -> 0 | AE58: =AA58+AD58 -> 0.010526108 | AH58: =AG58/$E$4 -> 0 | AI58: =AA58+AH58 -> 0.010526108
A59: h | B59: Staff Welfare for deployed manpower | D59: =200*5*26 -> 26000 | E59: =D59/$E$4 -> 0.05473576 | H59: =G59/$E$4 -> 0 | I59: =E59+H59 -> 0.05473576 | L59: =K59/$E$4 -> 0 | M59: =E59+L59 -> 0.05473576 | O59: =200*5*26 -> 26000 | P59: =O59/$E$4 -> 0.05473576 | S59: =R59/$E$4 -> 0 | T59: =P59+S59 -> 0.05473576 | W59: =V59/$E$4 -> 0 | X59: =P59+W59 -> 0.05473576 | Z59: =200*5*26 -> 26000 | AA59: =Z59/$E$4 -> 0.05473576 | AD59: =AC59/$E$4 -> 0 | AE59: =AA59+AD59 -> 0.05473576 | AH59: =AG59/$E$4 -> 0 | AI59: =AA59+AH59 -> 0.05473576
A60: i | B60: Courier Charges | D60: 2500 | E60: =D60/$E$4 -> 0.0052630538 | H60: =G60/$E$4 -> 0 | I60: =E60+H60 -> 0.0052630538 | L60: =K60/$E$4 -> 0 | M60: =E60+L60 -> 0.0052630538 | O60: 2500 | P60: =O60/$E$4 -> 0.0052630538 | S60: =R60/$E$4 -> 0 | T60: =P60+S60 -> 0.0052630538 | W60: =V60/$E$4 -> 0 | X60: =P60+W60 -> 0.0052630538 | Z60: 2500 | AA60: =Z60/$E$4 -> 0.0052630538 | AD60: =AC60/$E$4 -> 0 | AE60: =AA60+AD60 -> 0.0052630538 | AH60: =AG60/$E$4 -> 0 | AI60: =AA60+AH60 -> 0.0052630538
A62: 8 | B62: Insurance, Sinking Fund | D62: =SUM(D63:D66) -> 692061.66 | E62: =ROUND(D62/$E$4,2) -> 1.46 | G62: =SUM(G63:G66) -> 0 | H62: =ROUND(G62/$E$4,2) -> 0 | I62: =SUM(I63:I66) -> 1.4569431 | K62: =SUM(K63:K66) -> 0 | L62: =ROUND(K62/$E$4,2) -> 0 | M62: =SUM(M63:M66) -> 1.4569431 | O62: =SUM(O63:O66) -> 714037.4 | P62: =ROUND(O62/$E$4,2) -> 1.5 | R62: =SUM(R63:R66) -> 0 | S62: =ROUND(R62/$E$4,2) -> 0 | T62: =SUM(T63:T66) -> 1.5032069 | V62: =SUM(V63:V66) -> 0 | W62: =ROUND(V62/$E$4,2) -> 0 | X62: =SUM(X63:X66) -> 1.5032069 | Z62: =SUM(Z63:Z66) -> 736892.17 | AA62: =ROUND(Z62/$E$4,2) -> 1.55 | AC62: =SUM(AC63:AC66) -> 0 | AD62: =ROUND(AC62/$E$4,2) -> 0 | AE62: =SUM(AE63:AE66) -> 1.5513213 | AG62: =SUM(AG63:AG66) -> 0 | AH62: =ROUND(AG62/$E$4,2) -> 0 | AI62: =SUM(AI63:AI66) -> 1.5513213
A63: a | B63: Insurance Fund ( Equipment & Structure) | D63: =E63*E4 -> 76001.503 | E63: 0.16 | H63: =G63/H4 -> 0 | I63: =E63+H63 -> 0.16 | L63: =K63/L4 -> 0 | M63: =E63+L63 -> 0.16 | O63: =P63*P4 -> 76001.503 | P63: 0.16 | S63: =R63/S4 -> 0 | T63: =P63+S63 -> 0.16 | W63: =V63/W4 -> 0 | X63: =P63+W63 -> 0.16 | Z63: =AA63*AA4 -> 76001.503 | AA63: 0.16 | AD63: =AC63/AD4 -> 0 | AE63: =AA63+AD63 -> 0.16 | AH63: =AG63/AH4 -> 0 | AI63: =AA63+AH63 -> 0.16
A64: b | B64: Sinking Fund | D64: =E64*E4 -> 549393.49 | E64: =SinkingFundEstimation!B27 -> 1.156595 | H64: 0 | I64: =E64+H64 -> 1.156595 | L64: 0 | M64: =E64+L64 -> 1.156595 | O64: =P64*P4 -> 571369.23 | P64: =SinkingFundEstimation!C27 -> 1.2028588 | S64: 0 | T64: =P64+S64 -> 1.2028588 | W64: 0 | X64: =P64+W64 -> 1.2028588 | Z64: =AA64*AA4 -> 594224 | AA64: =SinkingFundEstimation!D27 -> 1.2509732 | AD64: 0 | AE64: =AA64+AD64 -> 1.2509732 | AH64: 0 | AI64: =AA64+AH64 -> 1.2509732
A65: c | B65: Contigency Funds | D65: 50000 | E65: =D65/$E$4 -> 0.10526108 | H65: =G65/$E$4 -> 0 | I65: =E65+H65 -> 0.10526108 | L65: =K65/$E$4 -> 0 | M65: =E65+L65 -> 0.10526108 | O65: 50000 | P65: =O65/$E$4 -> 0.10526108 | S65: =R65/$E$4 -> 0 | T65: =P65+S65 -> 0.10526108 | W65: =V65/$E$4 -> 0 | X65: =P65+W65 -> 0.10526108 | Z65: 50000 | AA65: =Z65/$E$4 -> 0.10526108 | AD65: =AC65/$E$4 -> 0 | AE65: =AA65+AD65 -> 0.10526108 | AH65: =AG65/$E$4 -> 0 | AI65: =AA65+AH65 -> 0.10526108
A66: d | B66: Insurance for Thrid Party liability | D66: =5*40000/12 -> 16666.667 | E66: =D66/$E$4 -> 0.035087026 | H66: =G66/$E$4 -> 0 | I66: =E66+H66 -> 0.035087026 | L66: =K66/$E$4 -> 0 | M66: =E66+L66 -> 0.035087026 | O66: =5*40000/12 -> 16666.667 | P66: =O66/$E$4 -> 0.035087026 | S66: =R66/$E$4 -> 0 | T66: =P66+S66 -> 0.035087026 | W66: =V66/$E$4 -> 0 | X66: =P66+W66 -> 0.035087026 | Z66: =5*40000/12 -> 16666.667 | AA66: =Z66/$E$4 -> 0.035087026 | AD66: =AC66/$E$4 -> 0 | AE66: =AA66+AD66 -> 0.035087026 | AH66: =AG66/$E$4 -> 0 | AI66: =AA66+AH66 -> 0.035087026
A68: 9 | B68: Profit Margin 10% on Actual Expense | D68: =SUM(D8,D19,D26,D28,D32,D40,D51,D62)*10% -> 353515.48 | E68: =D68/E4 -> 0.7442284 | G68: =SUM(G8,G19,G26,G28,G32,G40,G51,G62)*10% -> 128973.24 | H68: =G68/H4 -> 0.68924178 | I68: =E68+H68 -> 1.4334702 | K68: =SUM(K8,K19,K26,K28,K32,K40,K51,K62)*10% -> 64086.973 | L68: =K68/L4 -> 0.22261231 | M68: =E68+L68 -> 0.96684071 | O68: =SUM(O8,O19,O26,O28,O32,O40,O51,O62)*10% -> 396145.75 | P68: =O68/P4 -> 0.83397457 | R68: =SUM(R8,R19,R26,R28,R32,R40,R51,R62)*10% -> 138094.59 | S68: =R68/S4 -> 0.73798688 | T68: =P68+S68 -> 1.5719615 | V68: =SUM(V8,V19,V26,V28,V32,V40,V51,V62)*10% -> 86388.372 | W68: =V68/W4 -> 0.30007838 | X68: =P68+W68 -> 1.134053 | Z68: =SUM(Z8,Z19,Z26,Z28,Z32,Z40,Z51,Z62)*10% -> 452440.68 | AA68: =Z68/AA4 -> 0.95248785 | AC68: =SUM(AC8,AC19,AC26,AC28,AC32,AC40,AC51,AC62)*10% -> 154022.61 | AD68: =AC68/AD4 -> 0.82310729 | AE68: =AA68+AD68 -> 1.7755951 | AG68: =SUM(AG8,AG19,AG26,AG28,AG32,AG40,AG51,AG62)*10% -> 91464.546 | AH68: =AG68/AH4 -> 0.31771097 | AI68: =AA68+AH68 -> 1.2701988

Sheet AMC Cost
A1: ANNUAL MAINTENANCE CHARGE ESTIMATION- | I1: INDEX
A2: S.No. as per Budget | B2: Package No. | C2: Package Name | D2: DLP | E2: 2nd Year | F2: 3rd Year | G2: 4th Year | H2: 5th Year
A3: 1 | B3: TIIPL/MEP-003(PART-1) | C3: Fire Fighting | E3: =482405+76630 -> 559035 | F3: =E3*107% -> 598167.45 | G3: =F3*107% -> 640039.17 | H3: =G3*107% -> 684841.91
A4: 2 | B4: TIIPL/MEP-009 | C4: FAS | E4: 263130 | F4: =E4*107% -> 281549.1 | G4: =F4*107% -> 301257.54 | H4: =G4*107% -> 322345.56
C5: CCTV | E5: 166000 | F5: =E5*107% -> 177620 | G5: =F5*107% -> 190053.4 | H5: =G5*107% -> 203357.14
C6: IBMS&PAS | E6: 208675 | F6: =E6*107% -> 223282.25 | G6: =F6*107% -> 238912.01 | H6: =G6*107% -> 255635.85
A7: 4 | B7: TIIPL/MEP - 002 | C7: Electrical Panels ( HT / LT) | E7: =5*6000+(10*3500)*2 -> 100000 | F7: =E7*105% -> 105000 | G7: =F7*105% -> 110250 | H7: =G7*105% -> 115762.5
A8: 5 | B8: TIIPL/MEP - 11 Part 1 | C8: Fire Fighting Pumps | D8: 0
A9: 6 | B9: TIIPL/INT - 002 | C9: Elevators | D9: 0 | E9: 0 | F9: 3008333.3 | G9: =F9*107% -> 3218916.7 | H9: =G9*107% -> 3444240.8
A10: 7 | B10: TIIPL/MEP-005 | C10: Diesel Generators | D10: 0 | E10: 0 | F10: 200000 | G10: =+F10+F10*10% -> 220000 | H10: =+G10+G10*10% -> 242000
C11: IT Infrastructure- Computers | E11: =20*6000*2 -> 240000 | F11: =E11*105% -> 252000 | G11: =F11*105% -> 264600 | H11: =G11*105% -> 277830
C12: Annual Cost | D12: =SUM(D3:D11) -> 0 | E12: =SUM(E3:E11) -> 1536840 | F12: =SUM(F3:F11) -> 4845952.1 | G12: =SUM(G3:G11) -> 5184028.8 | H12: =SUM(H3:H11) -> 5546013.8
C13: Monthly Cost | D13: =D12/12 -> 0 | E13: =E12/12 -> 128070 | F13: =F12/12 -> 403829.34 | G13: =G12/12 -> 432002.4 | H13: =H12/12 -> 462167.82
C14: Per sq ft Cost | D14: =D12/12/'CAM Variables'!$J$3 -> 0 | E14: =E12/12/'CAM Variables'!$J$3 -> 0.26961572 | F14: =F12/12/'CAM Variables'!$J$3 -> 0.85015023 | G14: =G12/12/'CAM Variables'!$J$3 -> 0.90946075 | H14: =H12/12/'CAM Variables'!$J$3 -> 0.97296564
A16: Office
B17: TIIPL/MEP -7(PART-2) | C17: Package Units | E17: 2200000 | F17: 2300000 | G17: 2400000 | H17: 2600000
B18: Office Total | C18: Monthly Cost | D18: =D17/12 -> 0 | E18: =E17/12 -> 183333.33 | F18: =F17/12 -> 191666.67 | G18: =G17/12 -> 200000 | H18: =H17/12 -> 216666.67
A21: Mall
B22: TIIPL/MEP-007 | C22: Chillers | D22: 0 | E22: 0 | F22: 730000 | G22: 730000 | H22: 730000
B23: Mall Total | C23: Monthly Cost | D23: =D22/12 -> 0 | E23: =E22/12 -> 0 | F23: =F22/12 -> 60833.333 | G23: =G22/12 -> 60833.333 | H23: =H22/12 -> 60833.333

Sheet Comm Electrical load
A1: ELECTRICAL EXPENSE CALCULATION | E1: INDEX
A2: COMM. UTILITIES
A4: Common Area Electrcity Consumption
A5: Total Unit Consumed per month | B5: ='Load Breakup'!I190 -> 19752.469
A6: Source | B6: Rate per unit | C6: Units Comsumed | D6: Cost
A7: DG Set | B7: ='CAM Variables'!$E$9 -> 18.29 | C7: =B5*'CAM Variables'!$E$10 -> 1234.5293 | D7: =C7*B7 -> 22579.541
A8: UPPCL | B8: ='CAM Variables'!$G$8 -> 6.5 | C8: =B5*'CAM Variables'!$G$10 -> 18517.939 | D8: =C8*B8 -> 120366.61
A9: TOTAL UNIT CHARGES | D9: =SUM(D7:D8) -> 142946.15
A11: ELECTRICAL EXPENSE CALCULATION
A12: MALL ELECTRICITY EXPENSES
A14: Common Area Electrcity Consumption
A15: Total Unit Consumed per month | B15: ='Load Breakup'!I226 -> 13625.723
A16: Source | B16: Rate per unit | C16: Units Comsumed | D16: Cost
A17: DG Set | B17: ='CAM Variables'!$E$9 -> 18.29 | C17: =B15*'CAM Variables'!$E$10 -> 851.6077 | D17: =C17*B17 -> 15575.905
A18: UPPCL | B18: ='CAM Variables'!$G$8 -> 6.5 | C18: =B15*'CAM Variables'!$G$10 -> 12774.116 | D18: =C18*B18 -> 83031.751
A19: TOTAL UNIT CHARGES | D19: =SUM(D17:D18) -> 98607.656
A21: ELECTRICAL EXPENSE CALCULATION
A22: OFFICE ELECTRICITY EXPENSES
A24: Common Area Electrcity Consumption
A25: Total Unit Consumed per month | B25: ='Load Breakup'!I243 -> 5537.1042
A26: Source | B26: Rate per unit | C26: Units Comsumed | D26: Cost
A27: DG Set | B27: ='CAM Variables'!$E$9 -> 18.29 | C27: =B25*'CAM Variables'!$E$10 -> 346.06901 | D27: =C27*B27 -> 6329.6022
A28: UPPCL | B28: ='CAM Variables'!$G$8 -> 6.5 | C28: =B25*'CAM Variables'!$G$10 -> 5191.0352 | D28: =C28*B28 -> 33741.729
A29: TOTAL UNIT CHARGES | D29: =SUM(D27:D28) -> 40071.331

Sheet Load Breakup
A1: COMM. AREA ELECTRAL LOAD DETAIL - ELECTRICITY CONSUMPTION | L1: INDEX
A2: Sl.No | B2: DESCRIPTION OF AREA | C2: EQUIPMENT DETAILS | D2: CAPACITY IN KW | E2: Diversity Factor-Load | F2: Diversity Factor-Seasonal | G2: Daily hrs of operation | H2: Daily Units | I2: Monthly units | J2: Monthly Cost
A4: Comm. Utilities
A5: Lighting Load- Comm | D5: =SUM(D6:D17) -> 69.18 | H5: =SUM(H6:H17) -> 273.44856 | I5: =SUM(I6:I17) -> 8340.1811 | K5: =I5*'HVAC-Mall'!$C$14 -> 66502.519 | L5: =K5*12 -> 798030.23
A6: 1 | B6: STAIRCASE | C6: bulk head (11w) | D6: 1.6 | E6: 0.5 | F6: 0.5 | G6: 18 | H6: =D6*E6*F6*G6 -> 7.2 | I6: =H6*30.5 -> 219.6
A7: 2 | B7: LIFT SHAFT | C7: bulk head (9w) | D7: 1.78 | E7: 0.2 | F7: 0.5 | G7: 1 | H7: =D7*E7*F7*G7 -> 0.178 | I7: =H7*30.5 -> 5.429
A8: 3 | B8: External Lighting | D8: 10 | E8: 0.7 | F8: 0.5 | G8: 10 | H8: =D8*E8*F8*G8 -> 35 | I8: =H8*30.5 -> 1067.5
A9: 4 | B9: Basement-1 | C9: fluroscent lamp (2*28w) | D9: 14.84 | E9: 0.7 | F9: 0.5 | G9: 12 | H9: =D9*E9*F9*G9 -> 62.328 | I9: =H9*30.5 -> 1901.004
C10: fluroscent lamp (1*28w) | D10: 1.008 | E10: 0.7 | F10: 0.3 | G10: 18 | H10: =D10*E10*F10*G10 -> 3.81024 | I10: =H10*30.5 -> 116.21232
C11: fluroscent lamp (1*9w) | D11: 0.108 | E11: 0.7 | F11: 0.5 | G11: 18 | H11: =D11*E11*F11*G11 -> 0.6804 | I11: =H11*30.5 -> 20.7522
A12: 5 | B12: Basement-2 | C12: fluroscent lamp (2*28w) | D12: 8.288 | E12: 0.7 | F12: 0.5 | G12: 12 | H12: =D12*E12*F12*G12 -> 34.8096 | I12: =H12*30.5 -> 1061.6928
C13: fluroscent lamp (1*28w) | D13: 4.9 | E13: 0.7 | F13: 0.3 | G13: 18 | H13: =D13*E13*F13*G13 -> 18.522 | I13: =H13*30.5 -> 564.921
A14: 6 | B14: Basement-3 | C14: fluroscent lamp (2*28w) | D14: 12.152 | E14: 0.7 | F14: 0.5 | G14: 12 | H14: =D14*E14*F14*G14 -> 51.0384 | I14: =H14*30.5 -> 1556.6712
C15: fluroscent lamp (1*28w) | D15: 1.372 | E15: 0.7 | F15: 0.3 | G15: 18 | H15: =D15*E15*F15*G15 -> 5.18616 | I15: =H15*30.5 -> 158.17788
A16: 7 | B16: Basement-4 | C16: fluroscent lamp (2*28w) | D16: 12.04 | E16: 0.7 | F16: 0.5 | G16: 12 | H16: =D16*E16*F16*G16 -> 50.568 | I16: =H16*30.5 -> 1542.324
C17: fluroscent lamp (1*28w) | D17: 1.092 | E17: 0.7 | F17: 0.3 | G17: 18 | H17: =D17*E17*F17*G17 -> 4.12776 | I17: =H17*30.5 -> 125.89668
A19: Ventilation and Exhaust- Comm | D19: =SUM(D20:D125) -> 1057.8 | H19: =SUM(H20:H125) -> 112.3051 | I19: =SUM(I20:I125) -> 3425.3056 | K19: =6000000*70% -> 4200000
A20: 119 | B20: DG- EXAUST AIR | C20: AXIAL FAN | D20: 15 | E20: 0.5 | F20: 0.7 | G20: =0.1*12/12 -> 0.1 | H20: =D20*E20*F20*G20 -> 0.525 | I20: =H20*30.5 -> 16.0125
A21: 120 | B21: DG- EXAUST AIR | C21: AXIAL FAN | D21: 15 | E21: 0.5 | F21: 0.7 | G21: =0.1*12/12 -> 0.1 | H21: =D21*E21*F21*G21 -> 0.525 | I21: =H21*30.5 -> 16.0125
A22: 121 | B22: DG- EXAUST AIR | C22: AXIAL FAN | D22: 15 | E22: 0.5 | F22: 0.7 | G22: =0.1*12/12 -> 0.1 | H22: =D22*E22*F22*G22 -> 0.525 | I22: =H22*30.5 -> 16.0125
A23: 122 | B23: DG- EXAUST AIR | C23: AXIAL FAN | D23: 15 | E23: 0.5 | F23: 0.7 | G23: =0.1*12/12 -> 0.1 | H23: =D23*E23*F23*G23 -> 0.525 | I23: =H23*30.5 -> 16.0125
A24: 123 | B24: DG-FRESH AIR | C24: AXIAL FAN | D24: 15 | E24: 0.5 | F24: 0.7 | G24: =0.1*12/12 -> 0.1 | H24: =D24*E24*F24*G24 -> 0.525 | I24: =H24*30.5 -> 16.0125
A25: 124 | B25: DG-FRESH AIR | C25: AXIAL FAN | D25: 15 | E25: 0.5 | F25: 0.7 | G25: =0.1*12/12 -> 0.1 | H25: =D25*E25*F25*G25 -> 0.525 | I25: =H25*30.5 -> 16.0125
A26: 125 | B26: DG-FRESH AIR | C26: AXIAL FAN | D26: 15 | E26: 0.5 | F26: 0.7 | G26: =0.1*12/12 -> 0.1 | H26: =D26*E26*F26*G26 -> 0.525 | I26: =H26*30.5 -> 16.0125
A27: 126 | B27: DG-FRESH AIR | C27: AXIAL FAN | D27: 15 | E27: 0.5 | F27: 0.7 | G27: =0.1*12/12 -> 0.1 | H27: =D27*E27*F27*G27 -> 0.525 | I27: =H27*30.5 -> 16.0125
A28: 127 | B28: TRASFORMER ROOM EXAUST AIR | C28: AXIAL FAN | D28: 2.2 | E28: 0.5 | F28: 0.7 | G28: 11 | H28: =D28*E28*F28*G28 -> 8.47 | I28: =H28*30.5 -> 258.335
A29: 128 | B29: TRASFORMER ROOM EXAUST AIR | C29: AXIAL FAN | D29: 2.2 | E29: 0.5 | F29: 0.7 | G29: 11 | H29: =D29*E29*F29*G29 -> 8.47 | I29: =H29*30.5 -> 258.335
A30: 129 | B30: HVAC PLANT ROOM FRESH AIR | C30: AXIAL FAN | D30: 5.5 | E30: 0.25 | F30: 0.7 | G30: 12 | H30: =D30*E30*F30*G30 -> 11.55 | I30: =H30*30.5 -> 352.275
A31: 130 | B31: HVAC PLANT ROOM FRESH AIR | C31: AXIAL FAN | D31: 5.5 | E31: 0.25 | F31: 0.7 | G31: 12 | H31: =D31*E31*F31*G31 -> 11.55 | I31: =H31*30.5 -> 352.275
A32: 131 | B32: HVAC PLANT ROOM EXAUST AIR | C32: AXIAL FAN | D32: 5.5 | E32: 0.25 | F32: 0.7 | G32: 12 | H32: =D32*E32*F32*G32 -> 11.55 | I32: =H32*30.5 -> 352.275
A33: 132 | B33: HVAC PLANT ROOM EXAUST AIR | C33: AXIAL FAN | D33: 5.5 | E33: 0.25 | F33: 0.7 | G33: 12 | H33: =D33*E33*F33*G33 -> 11.55 | I33: =H33*30.5 -> 352.275
A34: 133 | B34: PARKING EXHAUST | C34: AXIAL FAN | D34: 7.5 | E34: 0.2 | F34: 0.7 | G34: 0.25 | H34: =D34*E34*F34*G34 -> 0.2625 | I34: =H34*30.5 -> 8.00625
A35: 134 | B35: PARKING EXHAUST | C35: AXIAL FAN | D35: 7.5 | E35: 0.2 | F35: 0.7 | G35: 0.25 | H35: =D35*E35*F35*G35 -> 0.2625 | I35: =H35*30.5 -> 8.00625
A36: 135 | B36: PARKING EXHAUST | C36: AXIAL FAN | D36: 7.5 | E36: 0.2 | F36: 0.7 | G36: 0.25 | H36: =D36*E36*F36*G36 -> 0.2625 | I36: =H36*30.5 -> 8.00625
A37: 136 | B37: PARKING FRESH AIR | C37: AXIAL FAN | D37: 7.5 | E37: 0.2 | F37: 0.7 | G37: 0.25 | H37: =D37*E37*F37*G37 -> 0.2625 | I37: =H37*30.5 -> 8.00625
A38: 137 | B38: PARKING FRESH AIR | C38: AXIAL FAN | D38: 7.5 | E38: 0.2 | F38: 0.7 | G38: 0.25 | H38: =D38*E38*F38*G38 -> 0.2625 | I38: =H38*30.5 -> 8.00625
A39: 143 | B39: BASEMENT-2 | C39: AXIAL FAN | D39: 9.3 | E39: 0.2 | F39: 0.7 | G39: =0.1*12/12 -> 0.1 | H39: =D39*E39*F39*G39 -> 0.1302 | I39: =H39*30.5 -> 3.9711
A40: 144 | B40: BASEMENT-2 | C40: AXIAL FAN | D40: 9.3 | E40: 0.2 | F40: 0.7 | G40: =0.1*12/12 -> 0.1 | H40: =D40*E40*F40*G40 -> 0.1302 | I40: =H40*30.5 -> 3.9711
A41: 145 | B41: BASEMENT-2 | C41: AXIAL FAN | D41: 9.3 | E41: 0.2 | F41: 0.7 | G41: =0.1*12/12 -> 0.1 | H41: =D41*E41*F41*G41 -> 0.1302 | I41: =H41*30.5 -> 3.9711
A42: 146 | B42: BASEMENT-2 | C42: AXIAL FAN | D42: 9.3 | E42: 0.2 | F42: 0.7 | G42: =0.1*12/12 -> 0.1 | H42: =D42*E42*F42*G42 -> 0.1302 | I42: =H42*30.5 -> 3.9711
A43: 147 | B43: BASEMENT-2 | C43: AXIAL FAN | D43: 9.3 | E43: 0.2 | F43: 0.7 | G43: =0.1*12/12 -> 0.1 | H43: =D43*E43*F43*G43 -> 0.1302 | I43: =H43*30.5 -> 3.9711
A44: 148 | B44: BASEMENT-2 | C44: AXIAL FAN | D44: 9.3 | E44: 0.2 | F44: 0.7 | G44: =0.1*12/12 -> 0.1 | H44: =D44*E44*F44*G44 -> 0.1302 | I44: =H44*30.5 -> 3.9711
A45: 149 | B45: BASEMENT-2 | C45: AXIAL FAN | D45: 9.3 | E45: 0.2 | F45: 0.7 | G45: =0.1*12/12 -> 0.1 | H45: =D45*E45*F45*G45 -> 0.1302 | I45: =H45*30.5 -> 3.9711
A46: 150 | B46: BASEMENT-2 | C46: AXIAL FAN | D46: 9.3 | E46: 0.2 | F46: 0.7 | G46: =0.1*12/12 -> 0.1 | H46: =D46*E46*F46*G46 -> 0.1302 | I46: =H46*30.5 -> 3.9711
A47: 151 | B47: BASEMENT-2 | C47: AXIAL FAN | D47: 9.3 | E47: 0.2 | F47: 0.7 | G47: =0.1*12/12 -> 0.1 | H47: =D47*E47*F47*G47 -> 0.1302 | I47: =H47*30.5 -> 3.9711
A48: 152 | B48: BASEMENT-2 | C48: AXIAL FAN | D48: 9.3 | E48: 0.2 | F48: 0.7 | G48: =0.1*12/12 -> 0.1 | H48: =D48*E48*F48*G48 -> 0.1302 | I48: =H48*30.5 -> 3.9711
A49: 153 | B49: BASEMENT-2 | C49: AXIAL FAN | D49: 9.3 | E49: 0.2 | F49: 0.7 | G49: =0.1*12/12 -> 0.1 | H49: =D49*E49*F49*G49 -> 0.1302 | I49: =H49*30.5 -> 3.9711
A50: 154 | B50: BASEMENT-2 | C50: AXIAL FAN | D50: 9.3 | E50: 0.2 | F50: 0.7 | G50: =0.1*12/12 -> 0.1 | H50: =D50*E50*F50*G50 -> 0.1302 | I50: =H50*30.5 -> 3.9711
... A118: 222 | B118: BASEMENT-4 | C118: AXIAL FAN | D118: 15 | E118: 0.2 | F118: 0.7 | G118: =0.1*12/12 -> 0.1 | H118: =D118*E118*F118*G118 -> 0.21 | I118: =H118*30.5 -> 6.405
A119: 324 | B119: STAIR PRESSURISATON-3 | C119: AXIAL FAN | D119: 4 | E119: 0.2 | F119: 1 | G119: 0.2 | H119: =D119*E119*F119*G119 -> 0.16 | I119: =H119*30.5 -> 4.88
A120: 325 | B120: STAIR PRESSURISATON-4 | C120: AXIAL FAN | D120: 4 | E120: 0.2 | F120: 1 | G120: 0.2 | H120: =D120*E120*F120*G120 -> 0.16 | I120: =H120*30.5 -> 4.88
A121: 326 | B121: STAIR PRESSURISATON-5 | C121: AXIAL FAN | D121: 4 | E121: 0.2 | F121: 1 | G121: 0.2 | H121: =D121*E121*F121*G121 -> 0.16 | I121: =H121*30.5 -> 4.88
A122: 327 | B122: STAIR PRESSURISATON-1 | C122: AXIAL FAN | D122: 4 | E122: 0.2 | F122: 1 | G122: 0.2 | H122: =D122*E122*F122*G122 -> 0.16 | I122: =H122*30.5 -> 4.88
A123: 138 | B123: ST-6 STAIRCASE PRESSURIZATION | C123: AXIAL FAN | D123: 7.5 | E123: 0.2 | F123: 1 | G123: 0.2 | H123: =D123*E123*F123*G123 -> 0.3 | I123: =H123*30.5 -> 9.15
A124: 142 | B124: ST-3 STAIRCASE PRESSURIZATION | C124: AXIAL FAN | D124: 5.5 | E124: 0.2 | F124: 1 | G124: 0.2 | H124: =D124*E124*F124*G124 -> 0.22 | I124: =H124*30.5 -> 6.71
A125: 328 | B125: STP EXAUST | C125: AXIAL FAN | D125: 4 | E125: 0.8 | F125: 0.8 | G125: 12 | H125: =D125*E125*F125*G125 -> 30.72 | I125: =H125*30.5 -> 936.96
K126: =K19/K5 -> 63.155503
A127: Sump Pumps- Comm | D127: =SUM(D128:D137) -> 50 | H127: =SUM(H128:H137) -> 3.125 | I127: =SUM(I128:I137) -> 95.3125 | K127: =K126/12 -> 5.2629585
A128: 13 | B128: Basement 4 | C128: Catch Basin pump 1 | D128: 5 | E128: 0.5 | F128: 0.5 | G128: 0.25 | H128: =D128*E128*F128*G128 -> 0.3125 | I128: =H128*30.5 -> 9.53125
A129: 14 | B129: Basement 4 | C129: Catch Basin pump 2 | D129: 5 | E129: 0.5 | F129: 0.5 | G129: 0.25 | H129: =D129*E129*F129*G129 -> 0.3125 | I129: =H129*30.5 -> 9.53125
A130: 15 | B130: Basement 4 | C130: Catch Basin pump 3 | D130: 5 | E130: 0.5 | F130: 0.5 | G130: 0.25 | H130: =D130*E130*F130*G130 -> 0.3125 | I130: =H130*30.5 -> 9.53125
A131: 16 | B131: Basement 4 | C131: Catch Basin pump 4 | D131: 5 | E131: 0.5 | F131: 0.5 | G131: 0.25 | H131: =D131*E131*F131*G131 -> 0.3125 | I131: =H131*30.5 -> 9.53125
A132: 17 | B132: Basement 4 | C132: Catch Basin pump 5 | D132: 5 | E132: 0.5 | F132: 0.5 | G132: 0.25 | H132: =D132*E132*F132*G132 -> 0.3125 | I132: =H132*30.5 -> 9.53125
A133: 18 | B133: Basement 4 | C133: Catch Basin pump 6 | D133: 5 | E133: 0.5 | F133: 0.5 | G133: 0.25 | H133: =D133*E133*F133*G133 -> 0.3125 | I133: =H133*30.5 -> 9.53125
A134: 19 | B134: Basement 4 | C134: Catch Basin pump 7 | D134: 5 | E134: 0.5 | F134: 0.5 | G134: 0.25 | H134: =D134*E134*F134*G134 -> 0.3125 | I134: =H134*30.5 -> 9.53125
A135: 20 | B135: Basement 4 | C135: Catch Basin pump 8 | D135: 5 | E135: 0.5 | F135: 0.5 | G135: 0.25 | H135: =D135*E135*F135*G135 -> 0.3125 | I135: =H135*30.5 -> 9.53125
A136: 21 | B136: Basement 4 | C136: Catch Basin pump 9 | D136: 5 | E136: 0.5 | F136: 0.5 | G136: 0.25 | H136: =D136*E136*F136*G136 -> 0.3125 | I136: =H136*30.5 -> 9.53125
A137: 22 | B137: Basement 4 | C137: Catch Basin pump 10 | D137: 5 | E137: 0.5 | F137: 0.5 | G137: 0.25 | H137: =D137*E137*F137*G137 -> 0.3125 | I137: =H137*30.5 -> 9.53125
A139: Fire Pumps | D139: =SUM(D140:D146) -> 239 | H139: =SUM(H140:H146) -> 1.2047619 | I139: =SUM(I140:I146) -> 36.745238
A140: 1 | B140: Basement 1 | C140: Fire PUMP | D140: 75 | E140: 0.8 | F140: 1 | G140: =1/(24*7) -> 0.005952381 | H140: =D140*E140*F140*G140 -> 0.35714286 | I140: =H140*30.5 -> 10.892857
A141: 2 | B141: Basement 1 | C141: Fire PUMP | D141: 75 | E141: 0.8 | F141: 1 | G141: =1/(24*7) -> 0.005952381 | H141: =D141*E141*F141*G141 -> 0.35714286 | I141: =H141*30.5 -> 10.892857
A142: 3 | B142: Basement 1 | C142: Fire PUMP | D142: 75 | E142: 0.8 | F142: 1 | G142: =1/(24*7) -> 0.005952381 | H142: =D142*E142*F142*G142 -> 0.35714286 | I142: =H142*30.5 -> 10.892857
A143: 4 | B143: Basement 1 | C143: Fire PUMP | D143: 4 | E143: 0.8 | F143: 1 | G143: =2/(24*7) -> 0.011904762 | H143: =D143*E143*F143*G143 -> 0.038095238 | I143: =H143*30.5 -> 1.1619048
A144: 5 | B144: Basement 1 | C144: Fire PUMP | D144: 4 | E144: 0.8 | F144: 1 | G144: =2/(24*7) -> 0.011904762 | H144: =D144*E144*F144*G144 -> 0.038095238 | I144: =H144*30.5 -> 1.1619048
A145: 6 | B145: Basement 1 | C145: Fire PUMP | D145: 3 | E145: 0.8 | F145: 1 | G145: =2/(24*7) -> 0.011904762 | H145: =D145*E145*F145*G145 -> 0.028571429 | I145: =H145*30.5 -> 0.87142857
A146: 7 | B146: Terrace | C146: Fire PUMP | D146: 3 | E146: 0.8 | F146: 1 | G146: =2/(24*7) -> 0.011904762 | H146: =D146*E146*F146*G146 -> 0.028571429 | I146: =H146*30.5 -> 0.87142857
A148: WTP | D148: =SUM(D149:D158) -> 73 | H148: =SUM(H149:H158) -> 118.86 | I148: =SUM(I149:I158) -> 3625.23
A149: 1 | B149: Basement 1 | C149: Hydro pnematic pump 1 | D149: 11 | E149: 0.25 | F149: 0.7 | G149: 6 | H149: =D149*E149*F149*G149 -> 11.55 | I149: =H149*30.5 -> 352.275
A150: 2 | B150: Basement 1 | C150: Hydro pnematic pump 2 | D150: 11 | E150: 0.25 | F150: 0.7 | G150: 6 | H150: =D150*E150*F150*G150 -> 11.55 | I150: =H150*30.5 -> 352.275
A151: 3 | B151: Basement 1 | C151: Hydro pnematic pump 3 | D151: 11 | E151: 0.25 | F151: 0.7 | G151: 6 | H151: =D151*E151*F151*G151 -> 11.55 | I151: =H151*30.5 -> 352.275
A152: 4 | B152: Basement 1 | C152: Hydro pnematic pump 4 | D152: 11 | E152: 0.25 | F152: 0.7 | G152: 6 | H152: =D152*E152*F152*G152 -> 11.55 | I152: =H152*30.5 -> 352.275
A153: 5 | B153: Basement 1 | C153: Domestic Pump 1 | D153: 7.5 | E153: 0.5 | F153: 0.7 | G153: 6 | H153: =D153*E153*F153*G153 -> 15.75 | I153: =H153*30.5 -> 480.375
A154: 6 | B154: Basement 1 | C154: Domestic Pump 2 | D154: 7.5 | E154: 0.5 | F154: 0.7 | G154: 6 | H154: =D154*E154*F154*G154 -> 15.75 | I154: =H154*30.5 -> 480.375
A155: 14 | B155: Basement 4 | C155: Pump | D155: 4 | E155: 0.7 | F155: 0.7 | G155: 6 | H155: =D155*E155*F155*G155 -> 11.76 | I155: =H155*30.5 -> 358.68
A156: 15 | B156: Basement 4 | C156: Pump | D156: 4 | E156: 0.7 | F156: 0.7 | G156: 6 | H156: =D156*E156*F156*G156 -> 11.76 | I156: =H156*30.5 -> 358.68
A157: 7 | B157: Basement 1 | C157: Raw Water pump 1 | D157: 3 | E157: 0.7 | F157: 0.7 | G157: 6 | H157: =D157*E157*F157*G157 -> 8.82 | I157: =H157*30.5 -> 269.01
A158: 8 | B158: Basement 1 | C158: Raw Water pump 2 | D158: 3 | E158: 0.7 | F158: 0.7 | G158: 6 | H158: =D158*E158*F158*G158 -> 8.82 | I158: =H158*30.5 -> 269.01
K159: =2000000/60 -> 33333.333
A160: Raw Power Load | D160: =SUM(D161:D168) -> 16 | H160: =SUM(H161:H168) -> 2 | I160: =SUM(I161:I168) -> 61 | K160: =K159/'CAM Variables'!J3 -> 0.070174051
A161: 1 | B161: Basement-4 | C161: Mobile chargers,Vaccum cleaners etc. | D161: 2 | E161: 0.5 | F161: 0.25 | G161: 1 | H161: =D161*E161*F161*G161 -> 0.25 | I161: =H161*30.5 -> 7.625
A162: 2 | B162: Basement-3 | C162: Mobile chargers,Vaccum cleaners etc. | D162: 2 | E162: 0.5 | F162: 0.25 | G162: 1 | H162: =D162*E162*F162*G162 -> 0.25 | I162: =H162*30.5 -> 7.625
A163: 3 | B163: Basement-2 | C163: Mobile chargers,Vaccum cleaners etc. | D163: 2 | E163: 0.5 | F163: 0.25 | G163: 1 | H163: =D163*E163*F163*G163 -> 0.25 | I163: =H163*30.5 -> 7.625
A164: 4 | B164: Basement-1 | C164: Mobile chargers,Vaccum cleaners etc. | D164: 2 | E164: 0.5 | F164: 0.25 | G164: 1 | H164: =D164*E164*F164*G164 -> 0.25 | I164: =H164*30.5 -> 7.625
A165: 5 | B165: Ground Floor | C165: Mobile chargers,Vaccum cleaners etc. | D165: 2 | E165: 0.5 | F165: 0.25 | G165: 1 | H165: =D165*E165*F165*G165 -> 0.25 | I165: =H165*30.5 -> 7.625
A166: 6 | B166: Level-1 | C166: Mobile chargers,Vaccum cleaners etc. | D166: 2 | E166: 0.5 | F166: 0.25 | G166: 1 | H166: =D166*E166*F166*G166 -> 0.25 | I166: =H166*30.5 -> 7.625
A167: 7 | B167: Level-2 | C167: Mobile chargers,Vaccum cleaners etc. | D167: 2 | E167: 0.5 | F167: 0.25 | G167: 1 | H167: =D167*E167*F167*G167 -> 0.25 | I167: =H167*30.5 -> 7.625
A168: 8 | B168: Level-3 | C168: Mobile chargers,Vaccum cleaners etc. | D168: 2 | E168: 0.5 | F168: 0.25 | G168: 1 | H168: =D168*E168*F168*G168 -> 0.25 | I168: =H168*30.5 -> 7.625
A170: STP | D170: =SUM(D171:D188) -> 71.11 | H170: =SUM(H171:H188) -> 136.6785 | I170: =SUM(I171:I188) -> 4168.6942
A171: 1 | B171: Basement 4 | C171: Reactor feed Pump | D171: 1.5 | E171: 0.5 | F171: 0.7 | G171: 6 | H171: =D171*E171*F171*G171 -> 3.15 | I171: =H171*30.5 -> 96.075
A172: 2 | B172: Basement 4 | C172: Reactor feed Pump | D172: 1.5 | E172: 0.5 | F172: 0.7 | G172: 6 | H172: =D172*E172*F172*G172 -> 3.15 | I172: =H172*30.5 -> 96.075
...

Sheet HVAC-Mall
A1: HVAC CHARGES CALCULATION
A2: Description | C2: Mall | F2: Aux. Pumps | G2: Mani | I2: Total | J2: Standby | M2: INDEX
A3: Airconditioned Area | B3: Comm. Area | C3: ='Area-Comm'!Q30 -> 34613.58 | F3: PRIMARY | G3: 18.5 | H3: 15 | I3: =SUM(G3:H3) -> 33.5 | J3: 18.5
B4: Leased Area | C4: ='Area Summary'!E20 -> 84205.516 | F4: Secondary- Comm. | G4: 22 | H4: 22 | I4: =SUM(G4:H4) -> 44 | J4: 22
B5: Total Area | C5: =SUM(C3:C4) -> 118819.1 | D5: ='Area Summary'!D20 -> 187123.37 | F5: Condenser | G5: 45 | H5: 22 | I5: =SUM(G5:H5) -> 67 | J5: 44
A6: Chiller Tonage | B6: TOTAL (TR) | C6: =610+350 -> 960 | D6: =C6*B8 -> 587.90059 | E6: 0.5 | F6: Cooling Towers | G6: 22 | H6: 11 | I6: =SUM(G6:H6) -> 33 | J6: 22
A7: Electrical Load-Chiller (IKW / TR) | B7: 0.63 | C7: =C6*B7 -> 604.8 | D7: =C5/D6 -> 202.10746 | G7: =SUM(G3:G6) -> 107.5 | I7: =SUM(I3:I6) -> 177.5
A8: Chiller Loading / unloading factor in 12 hrs operation | B8: 0.61239645 | C8: =C7*B8 -> 370.37737
A9: Auxillary Pump Load | B9: 0.73032158 | C9: =I7*B9 -> 129.63208 | D9: =C9/C8 -> 0.35
A10: Total Connected Load | C10: =SUM(C8:C9) -> 500.00946
A11: Electricity Cost-State Electricity Board | C11: ='CAM Variables'!G8 -> 6.5
A12: Electricity Cost-DG Power | C12: ='CAM Variables'!E9 -> 18.29
A13: Power Cut in Hrs (in 12 hrs) | C13: ='CAM Variables'!G9 -> 1.5
A14: Average Cost for Power unit | C14: =(((12-C13)*C11)+(C13*C12))/12 -> 7.97375
A15: Total Cost per hr | C15: =C10*C14 -> 3986.9504
A16: Total Cost per day (12 hrs operation) | C16: =C15*12 -> 47843.405
A17: Total Cost per month | C17: =C16*30.5 -> 1459223.8
A18: Cost per ton per month | C18: =C17/C6 -> 1520.0248
A19: AC cost per sq. ft per month | C19: =C17/C5 -> 12.281055
A20: Seasonal Diversity Factor | C20: 0.7
A21: Final AC cost per sq. ft per month | B21: INR | C21: =C19*C20 -> 8.5967385
A22: AC Charges for Common Area per month | C22: =C21*C5 -> 1021456.7
A24: Cost for HVAC of Common Area in sq ft- Chiller | B24: ='Area-Comm'!Q30*1.5 -> 51920.369 | C24: =B24*C21 -> 446345.84
A25: Cost of AHU- Comm Area | C25: ='Mall AHU Load'!K29 -> 109973.64
C26: =SUM(C24:C25) -> 556319.48
A28: Cost for HVAC for Tenants inside Mall
A29: Leasable Area inside Mall | B29: Sq ft | C29: ='Area Summary'!D20 -> 187123.37
A30: Cost for Air conditioning excluding Comm. Area cost | B30: INR | C30: =C22-C24 -> 575110.86
C31: =C30/C29 -> 3.0734315

Sheet Mall AHU Load
A1: ELECTRICAL LOAD OF AHU / FCU
A2: Sr. No | B2: LOCATION | C2: TYPE | D2: MAKE | E2: Sr. No | F2: CAPACITY IN KW | G2: Diversity Factor-Load | H2: Diversity Factor-Seasonal | I2: Daily hrs of operation | J2: Daily Units | K2: Monthly units | L2: INDEX
A3: 1 | B3: BOH CSU | C3: CSU | D3: ZECO | E3: 1341110 | F3: 1.5 | G3: 0.7 | H3: 0.5 | I3: 12 | J3: =F3*G3*H3*I3 -> 6.3 | K3: =J3*26 -> 163.8
A4: 2 | B4: BOH CSU | C4: CSU | D4: ZECO | E4: 1341111 | F4: 1.5 | G4: 0.7 | H4: 0.5 | I4: 12 | J4: =F4*G4*H4*I4 -> 6.3 | K4: =J4*26 -> 163.8
A5: 3 | B5: GROUND FLOOR | C5: LG | D5: LTI | E5: 13/055/041 | F5: 5.5 | G5: 0.7 | H5: 0.5 | I5: 12 | J5: =F5*G5*H5*I5 -> 23.1 | K5: =J5*26 -> 600.6
A6: 4 | B6: GROUND FLOOR | C6: LG | D6: LTI | E6: 13/055/042 | F6: 5.5 | G6: 0.7 | H6: 0.5 | I6: 12 | J6: =F6*G6*H6*I6 -> 23.1 | K6: =J6*26 -> 600.6
A7: 5 | B7: GROUND FLOOR | C7: LG | D7: LTI | E7: 13/055/043 | F7: 5.5 | G7: 0.7 | H7: 0.5 | I7: 12 | J7: =F7*G7*H7*I7 -> 23.1 | K7: =J7*26 -> 600.6
A8: 6 | B8: GROUND FLOOR | C8: LG | D8: LTI | E8: 13/055/044 | F8: 5.5 | G8: 0.7 | H8: 0.5 | I8: 12 | J8: =F8*G8*H8*I8 -> 23.1 | K8: =J8*26 -> 600.6
A9: 7 | B9: LEVEL-1 | C9: CORRIDOR | D9: ZECO | E9: 1341106-2 | F9: 3.7 | G9: 0.7 | H9: 0.5 | I9: 12 | J9: =F9*G9*H9*I9 -> 15.54 | K9: =J9*26 -> 404.04
A10: 8 | B10: LEVEL-1 | C10: LI - LVL | D10: ZECO | E10: 1341105-1 | F10: 7.5 | G10: 0.7 | H10: 0.5 | I10: 12 | J10: =F10*G10*H10*I10 -> 31.5 | K10: =J10*26 -> 819
A11: 9 | B11: LEVEL-1 | C11: LI - LVL | D11: ZECO | E11: 1341105-2 | F11: 7.5 | G11: 0.7 | H11: 0.5 | I11: 12 | J11: =F11*G11*H11*I11 -> 31.5 | K11: =J11*26 -> 819
A12: 10 | B12: LEVEL-1 | C12: LI - LVL | D12: ZECO | E12: 1341105-3 | F12: 7.5 | G12: 0.7 | H12: 0.5 | I12: 12 | J12: =F12*G12*H12*I12 -> 31.5 | K12: =J12*26 -> 819
A13: 11 | B13: LEVEL-1 | C13: LI - LVL | D13: ZECO | E13: 1341124 | F13: 7.5 | G13: 0.7 | H13: 0.5 | I13: 12 | J13: =F13*G13*H13*I13 -> 31.5 | K13: =J13*26 -> 819
A14: 12 | B14: LEVEL-2 | C14: CORRIDOR | D14: ZECO | E14: 134110601 | F14: 3.7 | G14: 0.7 | H14: 0.5 | I14: 12 | J14: =F14*G14*H14*I14 -> 15.54 | K14: =J14*26 -> 404.04
A15: 13 | B15: LEVEL-2 | C15: L2 - LVL | D15: LTI | E15: 13/055/013 | F15: 5.5 | G15: 0.7 | H15: 0.5 | I15: 12 | J15: =F15*G15*H15*I15 -> 23.1 | K15: =J15*26 -> 600.6
A16: 14 | B16: LEVEL-2 | C16: L2 - LVL | D16: LTI | E16: 13/055/035 | F16: 5.5 | G16: 0.7 | H16: 0.5 | I16: 12 | J16: =F16*G16*H16*I16 -> 23.1 | K16: =J16*26 -> 600.6
A17: 15 | B17: LEVEL-2 | C17: L2 - LVL | D17: LTI | E17: 13/055/050 | F17: 5.5 | G17: 0.7 | H17: 0.5 | I17: 12 | J17: =F17*G17*H17*I17 -> 23.1 | K17: =J17*26 -> 600.6
A18: 16 | B18: LEVEL-2 | C18: L2 - LVL | D18: LTI | E18: 13/055/036 | F18: 5.5 | G18: 0.7 | H18: 0.5 | I18: 12 | J18: =F18*G18*H18*I18 -> 23.1 | K18: =J18*26 -> 600.6
A19: 17 | B19: LEVEL-2 | C19: LOFT | D19: ZECO | E19: 1341107-28 | F19: 3.7 | G19: 0.7 | H19: 0.5 | I19: 12 | J19: =F19*G19*H19*I19 -> 15.54 | K19: =J19*26 -> 404.04
A20: 18 | B20: LEVEL-3 | C20: CORRIDOR | D20: ZECO | E20: 1341122 | F20: 3.7 | G20: 0.7 | H20: 0.5 | I20: 12 | J20: =F20*G20*H20*I20 -> 15.54 | K20: =J20*26 -> 404.04
A21: 19 | B21: LEVEL-3 | C21: CORRIDOR | D21: ZECO | E21: 1341123 | F21: 5.5 | G21: 0.7 | H21: 0.5 | I21: 12 | J21: =F21*G21*H21*I21 -> 23.1 | K21: =J21*26 -> 600.6
A22: 20 | B22: LEVEL-3 | C22: L3 - LVL | D22: ZECO | E22: 1341108 | F22: 5.5 | G22: 0.7 | H22: 0.5 | I22: 12 | J22: =F22*G22*H22*I22 -> 23.1 | K22: =J22*26 -> 600.6
A23: 21 | B23: LEVEL-3 | C23: L3 - LVL | D23: ZECO | E23: 1341119-5 | F23: 5.5 | G23: 0.7 | H23: 0.5 | I23: 12 | J23: =F23*G23*H23*I23 -> 23.1 | K23: =J23*26 -> 600.6
A24: 22 | B24: LEVEL-3 | C24: L3 - LVL | D24: ZECO | E24: 1341116-3 | F24: 7.5 | G24: 0.7 | H24: 0.5 | I24: 12 | J24: =F24*G24*H24*I24 -> 31.5 | K24: =J24*26 -> 819
A25: 23 | B25: LEVEL-3 | C25: L3 - LVL | D25: ZECO | E25: 13411051 | F25: 7.5 | G25: 0.7 | H25: 0.5 | I25: 12 | J25: =F25*G25*H25*I25 -> 31.5 | K25: =J25*26 -> 819
A26: 24 | B26: PANEL ROOM CSU | C26: CSU | D26: ZECO | E26: 1341118-2 | F26: 3 | G26: 0.7 | H26: 0.5 | I26: 12 | J26: =F26*G26*H26*I26 -> 12.6 | K26: =J26*26 -> 327.6
E27: Total Units consumed | H27: Total Units | K27: =SUM(K3:K26) -> 13791.96
E28: Per unit Cost | H28: Unit Rate | K28: ='HVAC-Mall'!C14 -> 7.97375
E29: Cost per month | H29: Total Cost per Montrh | K29: =K27*K28 -> 109973.64

Sheet Manpower
C1: MANPOWER DEPLOYMENT PLAN AND COSTING | G1: 100% occupancy
A2: Designation | B2: Service Deployment Area | C2: Designation | F2: Monthly Unit Cost | G2: SHIFT | L2: Total | M2: Monthly Cost | N2: INDEX
G3: A | H3: B | I3: C | J3: Gen | K3: Rel
A4: Management Staff | C4: Property Management Staff
A5: GM Operations | C5: =CONCATENATE(A5,B5) -> GM Operations | E5: =720000 -> 720000 | F5: =E5/12 -> 60000 | J5: 1 | L5: =SUM(G5:K5) -> 1 | M5: =L5*F5 -> 60000
A6: Finance Manager | C6: =CONCATENATE(A6,B6) -> Finance Manager | E6: =720000 -> 720000 | F6: =E6/12 -> 60000 | J6: 1 | L6: =SUM(G6:K6) -> 1 | M6: =L6*F6 -> 60000
A7: Manager- Marketing | C7: =CONCATENATE(A7,B7) -> Manager- Marketing | E7: =720000 -> 720000 | F7: =E7/12 -> 60000 | J7: 1 | L7: =SUM(G7:K7) -> 1 | M7: =L7*F7 -> 60000
A8: Sub Total C&W staff Cost (A) | C8: Sub Total C&W staff Cost (A) | G8: =SUM(G5:G7) -> 0 | H8: =SUM(H5:H7) -> 0 | I8: =SUM(I5:I7) -> 0 | J8: =SUM(J5:J7) -> 3 | K8: =SUM(K5:K7) -> 0 | L8: =SUM(L5:L7) -> 3 | M8: =SUM(M5:M7) -> 180000 | N8: =M8/'CAM Variables'!$J$3 -> 0.37893988
A9: C&W Management Staff | C9: Property Management Staff
A10: Property Manager | C10: =CONCATENATE(A10,B10) -> Property Manager | E10: =75000*12 -> 900000 | F10: =E10/12 -> 75000 | J10: 1 | L10: =SUM(G10:K10) -> 1 | M10: =L10*F10 -> 75000
A11: Manager- | B11: Accounts and Finance | C11: =CONCATENATE(A11,B11) -> Manager- Accounts and Finance | E11: 600000 | F11: =E11/12 -> 50000 | L11: =SUM(G11:K11) -> 0 | M11: =L11*F11 -> 0
A12: Executive- | B12: Purchase & Store | C12: =CONCATENATE(A12,B12) -> Executive-Purchase & Store | D12: 360000 | E12: 250000 | F12: =E12/12 -> 20833.333 | J12: 1 | L12: =SUM(G12:K12) -> 1 | M12: =L12*F12 -> 20833.333
A13: Manager- | B13: Engineering Services | C13: =CONCATENATE(A13,B13) -> Manager-Engineering Services | D13: 900000 | E13: 600000 | F13: =E13/12 -> 50000 | J13: 1 | L13: =SUM(G13:K13) -> 1 | M13: =L13*F13 -> 50000
A14: Shift Engineers | B14: Technical Services | C14: =CONCATENATE(A14,B14) -> Shift EngineersTechnical Services | E14: 250000 | F14: =E14/12 -> 20833.333 | G14: 1 | H14: 1 | I14: 1 | L14: =SUM(G14:K14) -> 3 | M14: =L14*F14 -> 62500
A15: Manager- | B15: Custodial Services | C15: =CONCATENATE(A15,B15) -> Manager-Custodial Services | D15: 900000 | E15: 600000 | F15: =E15/12 -> 50000 | J15: 1 | L15: =SUM(G15:K15) -> 1 | M15: =L15*F15 -> 50000
A16: Facility Executive- | B16: General Cleaning & Housekeeping | C16: =CONCATENATE(A16,B16) -> Facility Executive-General Cleaning & Housekeeping | E16: 300000 | F16: =E16/12 -> 25000 | G16: 1 | H16: 1 | L16: =SUM(G16:K16) -> 2 | M16: =L16*F16 -> 50000
A17: Facility Executive- | B17: Help Desk | C17: =CONCATENATE(A17,B17) -> Facility Executive-Help Desk | E17: 250000 | F17: =E17/12 -> 20833.333 | G17: 1 | H17: 1 | I17: 1 | K17: 1 | L17: =SUM(G17:K17) -> 4 | M17: =L17*F17 -> 83333.333
A18: Manager- | B18: Security and Fire Safety | C18: =CONCATENATE(A18,B18) -> Manager-Security and Fire Safety | E18: 500000 | F18: =E18/12 -> 41666.667 | J18: 1 | L18: =SUM(G18:K18) -> 1 | M18: =L18*F18 -> 41666.667
A19: Security & Fire Officer | C19: =CONCATENATE(A19,B19) -> Security & Fire Officer | E19: 250000 | F19: =E19/12 -> 20833.333 | G19: 1 | H19: 1 | I19: 1 | L19: =SUM(G19:K19) -> 3 | M19: =L19*F19 -> 62500
A20: Sub Total C&W staff Cost (A) | C20: Sub Total C&W staff Cost (A) | G20: =SUM(G10:G19) -> 4 | H20: =SUM(H10:H19) -> 4 | I20: =SUM(I10:I19) -> 3 | J20: =SUM(J10:J19) -> 5 | K20: =SUM(K10:K19) -> 1 | L20: =SUM(L10:L19) -> 17 | M20: =SUM(M10:M19) -> 495833.33 | N20: =M20/'CAM Variables'!$J$3 -> 1.043839 | P20: =N20*0.6 -> 0.62630341
A21: Engineering Services (8hrs X 6 days a week) | C21: =A21 -> Engineering Services (8hrs X 6 days a week)
A22: Technical Supervisor | C22: =CONCATENATE(A22," ",B22) -> Technical Supervisor | E22: =F22*12 -> 224952 | F22: =HLOOKUP(A22,'Salary Breakup'!$D$3:$AE$34,32,0) -> 18746 | G22: 1 | H22: 1 | I22: 1 | K22: 1 | L22: =SUM(G22:K22) -> 4 | M22: =L22*F22 -> 74984
A23: Multi skill Technicians | C23: =CONCATENATE(A23," ",B23) -> Multi skill Technicians | E23: =F23*12 -> 196800 | F23: =HLOOKUP(A23,'Salary Breakup'!$D$3:$AE$34,32,0) -> 16400 | G23: 2 | H23: 2 | I23: 1 | K23: 1 | L23: =SUM(G23:K23) -> 6 | M23: =L23*F23 -> 98400
A24: BMS Operator | C24: =CONCATENATE(A24," ",B24) -> BMS Operator | E24: =F24*12 -> 196800 | F24: =HLOOKUP(A24,'Salary Breakup'!$D$3:$AE$34,32,0) -> 16400 | G24: 1 | H24: 1 | I24: 1 | L24: =SUM(G24:K24) -> 3 | M24: =L24*F24 -> 49200
A25: HVAC Technician | C25: =CONCATENATE(A25," ",B25) -> HVAC Technician | E25: =F25*12 -> 196800 | F25: =HLOOKUP(A25,'Salary Breakup'!$D$3:$AE$34,32,0) -> 16400 | G25: 2 | H25: 2 | I25: 1 | K25: 1 | L25: =SUM(G25:K25) -> 6 | M25: =L25*F25 -> 98400
A26: Plumber | C26: =CONCATENATE(A26," ",B26) -> Plumber | E26: =F26*12 -> 196800 | F26: =HLOOKUP(A26,'Salary Breakup'!$D$3:$AE$34,32,0) -> 16400 | G26: 1 | H26: 1 | I26: 1 | K26: 1 | L26: =SUM(G26:K26) -> 4 | M26: =L26*F26 -> 65600
A27: Carpenter | C27: =CONCATENATE(A27," ",B27) -> Carpenter | E27: =F27*12 -> 196800 | F27: =HLOOKUP(A27,'Salary Breakup'!$D$3:$AE$34,32,0) -> 16400 | J27: 1 | L27: =SUM(G27:K27) -> 1 | M27: =L27*F27 -> 16400
A28: Painter | C28: =CONCATENATE(A28," ",B28) -> Painter | E28: =F28*12 -> 196836 | F28: =HLOOKUP(A28,'Salary Breakup'!$D$3:$AE$34,32,0) -> 16403 | J28: 1 | L28: =SUM(G28:K28) -> 1 | M28: =L28*F28 -> 16403
A29: Masson | C29: =CONCATENATE(A29," ",B29) -> Masson | E29: =F29*12 -> 196860 | F29: =HLOOKUP(A29,'Salary Breakup'!$D$3:$AE$34,32,0) -> 16405 | L29: =SUM(G29:K29) -> 0 | M29: =L29*F29 -> 0
A30: Painter | C30: =CONCATENATE(A30," ",B30) -> Painter | E30: =F30*12 -> 196836 | F30: =HLOOKUP(A30,'Salary Breakup'!$D$3:$AE$34,32,0) -> 16403 | J30: 1 | L30: =SUM(G30:K30) -> 1 | M30: =L30*F30 -> 16403
A31: Technical Helper | C31: =CONCATENATE(A31," ",B31) -> Technical Helper | E31: =F31*12 -> 147504 | F31: =HLOOKUP(A31,'Salary Breakup'!$D$3:$AE$34,32,0) -> 12292 | G31: 1 | H31: 1 | I31: 1 | K31: 1 | L31: =SUM(G31:K31) -> 4 | M31: =L31*F31 -> 49168
A32: Valet Driver | C32: =CONCATENATE(A32," ",B32) -> Valet Driver | E32: =F32*12 -> 175704 | F32: =HLOOKUP(A32,'Salary Breakup'!$D$3:$AE$34,32,0) -> 14642 | J32: 6 | L32: =SUM(G32:K32) -> 6 | M32: =L32*F32 -> 87852
A33: Sub Total (B) - Engineering Services | C33: Sub Total (B) - Engineering Services | D33: =F33*12 -> 0 | G33: =SUM(G22:G32) -> 8 | H33: =SUM(H22:H32) -> 8 | I33: =SUM(I22:I32) -> 6 | J33: =SUM(J22:J32) -> 9 | K33: =SUM(K22:K32) -> 5 | L33: =SUM(L22:L32) -> 36 | M33: =SUM(M22:M32) -> 572810 | N33: =M33/'CAM Variables'!$J$3 -> 1.2058919 | P33: =N33*0.8 -> 0.96471356
A34: Custodial Services (HK and General Cleaning Servcies) (8hrs X 6 days a week)- Comm | C34: =A34 -> Custodial Services (HK and General Cleaning Servcies) (8hrs X 6 days a week)- Comm
A35: Runner | C35: =CONCATENATE(A35," ",B35) -> Runner | E35: =F35*12 -> 161412 | F35: =HLOOKUP(A35,'Salary Breakup'!$D$3:$AE$34,32,0) -> 13451 | J35: 1 | L35: =SUM(G35:K35) -> 1 | M35: =L35*F35 -> 13451
A36: Pantry Boy | B36: Back Office | C36: =CONCATENATE(A36," ",B36) -> Pantry Boy Back Office | E36: =F36*12 -> 161412 | F36: =HLOOKUP(A36,'Salary Breakup'!$D$3:$AE$34,32,0) -> 13451 | J36: 1 | L36: =SUM(G36:K36) -> 1 | M36: =L36*F36 -> 13451
A37: Housekeeping Supervisor | C37: =CONCATENATE(A37," ",B37) -> Housekeeping Supervisor | E37: =F37*12 -> 239028 | F37: =HLOOKUP(A37,'Salary Breakup'!$D$3:$AE$34,32,0) -> 19919 | G37: 0.5 | H37: 0.5 | I37: 0.25 | K37: 0.3 | L37: =SUM(G37:K37) -> 1.55 | M37: =L37*F37 -> 30874.45
A38: Janitors | B38: Outer Periphery | C38: =CONCATENATE(A38," ",B38) -> Janitors Outer Periphery | E38: =F38*12 -> 128448 | F38: =HLOOKUP(A38,'Salary Breakup'!$D$3:$AE$34,32,0) -> 10704 | G38: 2 | H38: 2 | I38: 2 | L38: =SUM(G38:K38) -> 6 | M38: =L38*F38 -> 64224
A39: Janitors | B39: B1- B4 & Utilities | C39: =CONCATENATE(A39," ",B39) -> Janitors B1- B4 & Utilities | E39: =F39*12 -> 128448 | F39: =HLOOKUP(A39,'Salary Breakup'!$D$3:$AE$34,32,0) -> 10704 | K39: 1 | L39: =SUM(G39:K39) -> 1 | M39: =L39*F39 -> 10704
A40: Sub Total (C) - Custodial Services | C40: Sub Total (C) - Housekeeping Services | G40: =SUM(G35:G39) -> 2.5 | H40: =SUM(H35:H39) -> 2.5 | I40: =SUM(I35:I39) -> 2.25 | J40: =SUM(J35:J39) -> 2 | K40: =SUM(K35:K39) -> 1.3 | L40: =SUM(L35:L39) -> 10.55 | M40: =SUM(M35:M39) -> 132704.45 | N40: =M40/'CAM Variables'!$J$3 -> 0.27937227 | P40: =N40*0.5 -> 0.13968613
A41: Custodial Services (HK and General Cleaning Servcies) (8hrs X 6 days a week)- Mall | C41: =A41 -> Custodial Services (HK and General Cleaning Servcies) (8hrs X 6 days a week)- Mall
A42: Housekeeping Supervisor | C42: =CONCATENATE(A42," ",B42) -> Housekeeping Supervisor | E42: =F42*12 -> 239028 | F42: =HLOOKUP(A42,'Salary Breakup'!$D$3:$AE$34,32,0) -> 19919 | G42: 1 | H42: 1 | I42: 0.5 | K42: 0.4 | L42: =SUM(G42:K42) -> 2.9 | M42: =L42*F42 -> 57765.1
A43: Janitors | B43: L1- L3 | C43: =CONCATENATE(A43," ",B43) -> Janitors L1- L3 | E43: =F43*12 -> 128448 | F43: =HLOOKUP(A43,'Salary Breakup'!$D$3:$AE$34,32,0) -> 10704 | G43: 6 | H43: 6 | I43: 4 | L43: =SUM(G43:K43) -> 16 | M43: =L43*F43 -> 171264
A44: Janitors | B44: Comm Toilets | C44: =CONCATENATE(A44," ",B44) -> Janitors Comm Toilets | E44: =F44*12 -> 128448 | F44: =HLOOKUP(A44,'Salary Breakup'!$D$3:$AE$34,32,0) -> 10704 | G44: 2 | H44: 2 | K44: =ROUND(SUM(G43:J44)/6,0) -> 3 | L44: =SUM(G44:K44) -> 7 | M44: =L44*F44 -> 74928
A45: Sub Total (C) - Custodial Services | C45: Sub Total (C) - Housekeeping Services | G45: =SUM(G42:G44) -> 9 | H45: =SUM(H42:H44) -> 9 | I45: =SUM(I42:I44) -> 4.5 | J45: =SUM(J42:J44) -> 0 | K45: =SUM(K42:K44) -> 3.4 | L45: =SUM(L42:L44) -> 25.9 | M45: =SUM(M42:M44) -> 303957.1 | N45: =M45/'CAM Variables'!$J$3 -> 0.63989703 | P45: =N45*0.5 -> 0.31994852
A46: Custodial Services (HK and General Cleaning Servcies) (8hrs X 6 days a week)- Office | C46: =A46 -> Custodial Services (HK and General Cleaning Servcies) (8hrs X 6 days a week)- Office
A47: Housekeeping Supervisor | C47: =CONCATENATE(A47," ",B47) -> Housekeeping Supervisor | E47: =F47*12 -> 239028 | F47: =HLOOKUP(A47,'Salary Breakup'!$D$3:$AE$34,32,0) -> 19919 | G47: 0.5 | H47: 0.5 | I47: 0.25 | K47: 0.3 | L47: =SUM(G47:K47) -> 1.55 | M47: =L47*F47 -> 30874.45
A48: Janitors | B48: L4-L8 | C48: =CONCATENATE(A48," ",B48) -> Janitors L4-L8 | E48: =F48*12 -> 128448 | F48: =HLOOKUP(A48,'Salary Breakup'!$D$3:$AE$34,32,0) -> 10704 | G48: 2 | H48: 2 | I48: 2 | L48: =SUM(G48:K48) -> 6 | M48: =L48*F48 -> 64224
A49: Sub Total (C) - Custodial Services | C49: Sub Total (C) - Housekeeping Services | G49: =SUM(G47:G48) -> 2.5 | H49: =SUM(H47:H48) -> 2.5 | I49: =SUM(I47:I48) -> 2.25 | J49: =SUM(J47:J48) -> 0 | K49: =SUM(K47:K48) -> 0.3 | L49: =SUM(L47:L48) -> 7.55 | M49: =SUM(M47:M48) -> 95098.45 | N49: =M49/'CAM Variables'!$J$3 -> 0.20020331
A50: Outsourced Services ( Horticulture Manpower) (8hrs X 6 days a week) | C50: =A50 -> Outsourced Services ( Horticulture Manpower) (8hrs X 6 days a week)
A51: Head Gardner | C51: =CONCATENATE(A51,B51) -> Head Gardner | E51: =F51*12 -> 224952 | F51: =HLOOKUP(A51,'Salary Breakup'!$D$3:$AE$34,32,0) -> 18746 | J51: 1 | L51: =SUM(G51:K51) -> 1 | M51: =L51*F51 -> 18746
A52: Gardner | B52: Common Area | C52: =CONCATENATE(A52,B52) -> GardnerCommon Area | E52: =F52*12 -> 161412 | F52: =HLOOKUP(A52,'Salary Breakup'!$D$3:$AE$34,32,0) -> 13451 | J52: 2 | L52: =SUM(G52:K52) -> 2 | M52: =L52*F52 -> 26902
A53: Sub Total (D) - Horticulture Services | C53: Sub Total (D) - Horticulture Services | L53: =SUM(L51:L52) -> 3 | M53: =SUM(M51:M52) -> 45648 | N53: =M53/'CAM Variables'!$J$3 -> 0.096099153
A54: Outsourced Services ( Horticulture Consumables) (8hrs X 6 days a week) | C54: =A54 -> Outsourced Services ( Horticulture Consumables) (8hrs X 6 days a week)
A55: Tools and Equipments | C55: =CONCATENATE(A55,B55) -> Tools and Equipments | M55: =SUM(L53)*1000 -> 3000
C56: Potted Plants Costing | M56: =60*300 -> 18000
A57: Manure, Chemicals and Saplings | C57: =CONCATENATE(A57,B57) -> Manure, Chemicals and Saplings | M57: 8000
A58: Sub Total (E) - Horticulture Services | C58: Sub Total (E) - Horticulture Services | L58: =SUM(L51:L51) -> 1 | M58: =SUM(M55:M57) -> 29000 | N58: =M58/'CAM Variables'!$J$3 -> 0.061051425
A59: ( Security Servcies) (8hrs X 6 days a week)- Comm | C59: =A59 -> ( Security Servcies) (8hrs X 6 days a week)- Comm
A60: Security Supervisor | B60: Main Entry | C60: =CONCATENATE(A60," ",B60) -> Security Supervisor Main Entry | E60: =F60*12 -> 168216 | F60: =HLOOKUP(A60,'Salary Breakup'!$D$3:$AE$34,32,0) -> 14018 | G60: 1 | H60: 1 | I60: 1 | K60: =ROUND(SUM(G60:J61)/6,0) -> 1 | L60: =SUM(G60:K60) -> 4 | M60: =L60*F60 -> 56072
A61: Head Guard | B61: Control Room | C61: =CONCATENATE(A61," ",B61) -> Head Guard Control Room | E61: =F61*12 -> 168216 | F61: =HLOOKUP(A61,'Salary Breakup'!$D$3:$AE$34,32,0) -> 14018 | G61: 1 | H61: 1 | I61: 1 | L61: =SUM(G61:K61) -> 3 | M61: =L61*F61 -> 42054
A62: Security Guard | B62: Entry & Exit Point | C62: =CONCATENATE(A62," ",B62) -> Security Guard Entry & Exit Point | E62: =F62*12 -> 138348 | F62: =HLOOKUP(A62,'Salary Breakup'!$D$3:$AE$34,32,0) -> 11529 | G62: 1 | H62: 1 | I62: 1 | L62: =SUM(G62:K62) -> 3 | M62: =L62*F62 -> 34587
A63: Security Guard | B63: Campus Perifery & Drive Ways | C63: =CONCATENATE(A63," ",B63) -> Security Guard Campus Perifery & Drive Ways | E63: =F63*12 -> 138348 | F63: =HLOOKUP(A63,'Salary Breakup'!$D$3:$AE$34,32,0) -> 11529 | G63: 2 | H63: 2 | I63: 1 | J63: 2 | L63: =SUM(G63:K63) -> 7 | M63: =L63*F63 -> 80703
A64: Security Guard | B64: Basement 1 ( Lift Lobbies) | C64: =CONCATENATE(A64," ",B64) -> Security Guard Basement 1 ( Lift Lobbies) | E64: =F64*12 -> 138348 | F64: =HLOOKUP(A64,'Salary Breakup'!$D$3:$AE$34,32,0) -> 11529 | G64: 1 | H64: 1 | I64: 1 | J64: 1 | L64: =SUM(G64:K64) -> 4 | M64: =L64*F64 -> 46116
A65: Security Guard | B65: Basement 2 ( Lift Lobbies) | C65: =CONCATENATE(A65," ",B65) -> Security Guard Basement 2 ( Lift Lobbies) | E65: =F65*12 -> 138348 | F65: =HLOOKUP(A65,'Salary Breakup'!$D$3:$AE$34,32,0) -> 11529 | G65: 1 | H65: 1 | I65: 0 | J65: 1 | L65: =SUM(G65:K65) -> 3 | M65: =L65*F65 -> 34587
A66: Security Guard | B66: Basement 3 ( Lift Lobbies) | C66: =CONCATENATE(A66," ",B66) -> Security Guard Basement 3 ( Lift Lobbies) | E66: =F66*12 -> 138348 | F66: =HLOOKUP(A66,'Salary Breakup'!$D$3:$AE$34,32,0) -> 11529 | G66: 1 | H66: 1 | I66: 0 | J66: 3 | L66: =SUM(G66:K66) -> 5 | M66: =L66*F66 -> 57645
A67: Security Guard | B67: Basement 4 ( Lift Lobbies) | C67: =CONCATENATE(A67," ",B67) -> Security Guard Basement 4 ( Lift Lobbies) | E67: =F67*12 -> 138348 | F67: =HLOOKUP(A67,'Salary Breakup'!$D$3:$AE$34,32,0) -> 11529 | G67: 1 | H67: 1 | I67: 0 | J67: 3 | K67: =ROUND(SUM(G62:J67)/6,0) -> 5 | L67: =SUM(G67:K67) -> 10 | M67: =L67*F67 -> 115290
A68: Sub Total (F) - Security Services | C68: Sub Total (F) - Security Services | G68: =SUM(G60:G67) -> 9 | H68: =SUM(H60:H67) -> 9 | I68: =SUM(I60:I67) -> 5 | J68: =SUM(J60:J67) -> 10 | K68: =SUM(K60:K67) -> 6 | L68: =SUM(L60:L67) -> 39 | M68: =SUM(M60:M67) -> 467054 | N68: =M68/'CAM Variables'!$J$3 -> 0.98325214
A69: ( Security Servcies) (8hrs X 6 days a week)- Mall | C69: =A69 -> ( Security Servcies) (8hrs X 6 days a week)- Mall
A70: Security Guard | B70: Grd Floor- Mall Entry Outside | C70: =CONCATENATE(A70," ",B70) -> Security Guard Grd Floor- Mall Entry Outside | E70: =F70*12 -> 138348 | F70: =HLOOKUP(A70,'Salary Breakup'!$D$3:$AE$34,32,0) -> 11529 | I70: 2 | J70: 2 | L70: =SUM(G70:K70) -> 4 | M70: =L70*F70 -> 46116
A71: Security Guard | B71: Mall Atrium Gate | C71: =CONCATENATE(A71," ",B71) -> Security Guard Mall Atrium Gate | E71: =F71*12 -> 138348 | F71: =HLOOKUP(A71,'Salary Breakup'!$D$3:$AE$34,32,0) -> 11529 | G71: 2 | H71: 2 | I71: 1 | J71: 1 | L71: =SUM(G71:K71) -> 6 | M71: =L71*F71 -> 69174
A72: Security Guard | B72: LG-L3- Mall | C72: =CONCATENATE(A72," ",B72) -> Security Guard LG-L3- Mall | E72: =F72*12 -> 138348 | F72: =HLOOKUP(A72,'Salary Breakup'!$D$3:$AE$34,32,0) -> 11529 | G72: 3 | H72: 3 | I72: 1 | K72: =ROUND(SUM(G70:J72)/6,0) -> 3 | L72: =SUM(G72:K72) -> 10 | M72: =L72*F72 -> 115290
A73: Sub Total (G) - Security Services | C73: Sub Total (F) - Security Services | G73: =SUM(G70:G72) -> 5 | I73: =SUM(I70:I72) -> 4 | J73: =SUM(J70:J72) -> 3 | L73: =SUM(L70:L72) -> 20 | M73: =SUM(M70:M72) -> 230580 | N73: =M73/'CAM Variables'!$J$3 -> 0.48542198
A74: ( Security Servcies) (8hrs X 6 days a week)- Office | C74: =A74 -> ( Security Servcies) (8hrs X 6 days a week)- Office
A75: Security Guard | B75: Grd Floor- Office Entry | C75: =CONCATENATE(A75," ",B75) -> Security Guard Grd Floor- Office Entry | E75: =F75*12 -> 138348 | F75: =HLOOKUP(A75,'Salary Breakup'!$D$3:$AE$34,32,0) -> 11529 | G75: 2 | H75: 2 | I75: 1 | L75: =SUM(G75:K75) -> 5 | M75: =L75*F75 -> 57645
A76: Sub Total (H) - Security Services | C76: Sub Total (F) - Security Services | G76: =SUM(G75:G75) -> 2 | I76: =SUM(I75:I75) -> 1 | J76: =SUM(J75:J75) -> 0 | L76: =SUM(L75:L75) -> 5 | M76: =SUM(M75:M75) -> 57645 | N76: =M76/'CAM Variables'!$J$3 -> 0.1213555
A77: ( Façade Cleaning Servcies) (8hrs X 6 days a week) | C77: =A77 -> ( Façade Cleaning Servcies) (8hrs X 6 days a week)
A78: Façade Cleaning Supervisor | C78: =CONCATENATE(A78," ",B78) -> Façade Cleaning Supervisor | E78: =F78*12 -> 168216 | F78: =HLOOKUP(A78,'Salary Breakup'!$D$3:$AE$34,32,0) -> 14018 | K78: 1 | L78: =SUM(G78:K78) -> 1 | M78: =L78*F78 -> 14018
A79: Cradle Operator | C79: =CONCATENATE(A79," ",B79) -> Cradle Operator | E79: =F79*12 -> 168216 | F79: =HLOOKUP(A79,'Salary Breakup'!$D$3:$AE$34,32,0) -> 14018 | K79: 1 | L79: =SUM(G79:K79) -> 1 | M79: =L79*F79 -> 14018
A80: Façade Cleaner | C80: =CONCATENATE(A80," ",B80) -> Façade Cleaner | E80: =F80*12 -> 168216 | F80: =HLOOKUP(A80,'Salary Breakup'!$D$3:$AE$34,32,0) -> 14018 | K80: 2 | L80: =SUM(G80:K80) -> 2 | M80: =L80*F80 -> 28036
A81: Spiderman | C81: =CONCATENATE(A81," ",B81) -> Spiderman | E81: =F81*12 -> 168216 | F81: =HLOOKUP(A81,'Salary Breakup'!$D$3:$AE$34,32,0) -> 14018 | K81: 1 | L81: =SUM(G81:K81) -> 1 | M81: =L81*F81 -> 14018
A82: Helpers | C82: =CONCATENATE(A82," ",B82) -> Helpers | E82: =F82*12 -> 118344 | F82: =HLOOKUP(A82,'Salary Breakup'!$D$3:$AE$34,32,0) -> 9862 | K82: 1 | L82: =SUM(G82:K82) -> 1 | M82: =L82*F82 -> 9862
A83: Spideman Tool Kit | C83: =CONCATENATE(A83," ",B83) -> Spideman Tool Kit | F83: 2500 | L83: 2 | M83: =L83*F83 -> 5000
A84: Sub Total (I) - Façade Cleaning Services | C84: Sub Total (F) - Security Services | G84: =SUM(G78:G83) -> 0 | H84: =SUM(H78:H83) -> 0 | I84: =SUM(I78:I83) -> 0 | J84: =SUM(J78:J83) -> 0 | K84: =SUM(K78:K83) -> 6 | L84: =SUM(L78:L83) -> 8 | M84: =SUM(M78:M83) -> 84952 | N84: =M84/'CAM Variables'!$J$3 -> 0.17884278

Sheet Salary Breakup
A1: Salary Breakup- Hyderabad
A2: SALARY DETAILS | D2: ENGINEERING SERVICES | R2: HK Services | V2: Horticulture | X2: Façade Cleaning | AC2: Security | AG2: INDEX
A3: Designation | D3: Technical Supervisor | E3: Multi skill Technicians | F3: Electrician | G3: DG Operator | H3: BMS Operator | I3: HVAC Technician | J3: HVAC Operators | K3: Plumber | L3: Carpenter | M3: Painter | N3: Masson | O3: Painter | P3: Technical Helper | Q3: Valet Driver | R3: Housekeeping Supervisor | S3: Pantry Boy | T3: Runner | U3: Janitors | V3: Head Gardner | W3: Gardner | X3: Façade Cleaning Supervisor | Y3: Cradle Operator | Z3: Façade Cleaner | AA3: Spiderman | AB3: Helpers | AC3: Security Supervisor | AD3: Head Guard | AE3: Security Guard
A4: Employee Category | D4: Skilled | E4: Skilled | F4: Skilled | G4: Skilled | H4: Skilled | I4: Skilled | J4: Skilled | K4: Skilled | L4: Skilled | M4: Skilled | N4: Skilled | O4: Skilled | P4: SemiSkilled | Q4: SemiSkilled | R4: Skilled | S4: SemiSkilled | T4: SemiSkilled | U4: unskilled | V4: Skilled | W4: SemiSkilled | X4: Skilled | Y4: Skilled | Z4: Skilled | AA4: Skilled | AB4: unskilled | AC4: Skilled | AD4: Skilled | AE4: Semiskilled
A5: GROSS SALARY
A6: Basic | D6: =VLOOKUP(D4,'CAM Variables'!$E$13:$F$15,2,FALSE) -> 8079 | E6: =VLOOKUP(E4,'CAM Variables'!$E$13:$F$15,2,FALSE) -> 8079 | F6: =VLOOKUP(F4,'CAM Variables'!$E$13:$F$15,2,FALSE) -> 8079 | G6: =VLOOKUP(G4,'CAM Variables'!$E$13:$F$15,2,FALSE) -> 8079 | H6: =VLOOKUP(H4,'CAM Variables'!$E$13:$F$15,2,FALSE) -> 8079 | I6: =VLOOKUP(I4,'CAM Variables'!$E$13:$F$15,2,FALSE) -> 8079 | J6: =VLOOKUP(J4,'CAM Variables'!$E$13:$F$15,2,FALSE) -> 8079 | K6: =VLOOKUP(K4,'CAM Variables'!$E$13:$F$15,2,FALSE) -> 8079 | ... AE6: =VLOOKUP(AE4,'CAM Variables'!$E$13:$F$15,2,FALSE) -> 6579
A7: DA | D7: =VLOOKUP(D4,'CAM Variables'!$E$13:$G$15,3,FALSE) -> 1739 | E7: =VLOOKUP(E4,'CAM Variables'!$E$13:$G$15,3,FALSE) -> 1739 | F7: =VLOOKUP(F4,'CAM Variables'!$E$13:$G$15,3,FALSE) -> 1739 | G7: =VLOOKUP(G4,'CAM Variables'!$E$13:$G$15,3,FALSE) -> 1739 | H7: =VLOOKUP(H4,'CAM Variables'!$E$13:$G$15,3,FALSE) -> 1739 | I7: =VLOOKUP(I4,'CAM Variables'!$E$13:$G$15,3,FALSE) -> 1739 | J7: =VLOOKUP(J4,'CAM Variables'!$E$13:$G$15,3,FALSE) -> 1739 | K7: =VLOOKUP(K4,'CAM Variables'!$E$13:$G$15,3,FALSE) -> 1739 | ... AE7: =VLOOKUP(AE4,'CAM Variables'!$E$13:$G$15,3,FALSE) -> 1419
A8: BASIC & DA | D8: =D6+D7 -> 9818 | E8: =E6+E7 -> 9818 | F8: =F6+F7 -> 9818 | G8: =G6+G7 -> 9818 | H8: =H6+H7 -> 9818 | I8: =I6+I7 -> 9818 | J8: =J6+J7 -> 9818 | K8: =K6+K7 -> 9818 | ... AE8: =AE6+AE7 -> 7998
A9: Conv.
A10: HRA
A11: Special Allowance | D11: 4103.0687 | E11: 2067.4453 | F11: 2067.4453 | G11: 2067.4453 | H11: 2067.4453 | I11: 2067.4453 | J11: 2067.4453 | K11: 2067.4453 | L11: 2067.4453 | M11: 2067.4453 | N11: 2067.4453 | O11: 2067.4453 | P11: 650.80407 | Q11: 2686.4275 | R11: 5120.8804 | S11: 1668.6158 | T11: 1668.6158 | U11: 730.85496 | V11: 4103.0687 | W11: 1668.6158
A12: SUB TOTAL | D12: =SUM(D8:D11) -> 13921.069 | E12: =SUM(E8:E11) -> 11885.445 | F12: =SUM(F8:F11) -> 11885.445 | G12: =SUM(G8:G11) -> 11885.445 | H12: =SUM(H8:H11) -> 11885.445 | I12: =SUM(I8:I11) -> 11885.445 | J12: =SUM(J8:J11) -> 11885.445 | K12: =SUM(K8:K11) -> 11885.445 | ... AE12: =SUM(AE8:AE11) -> 7998
A13: COMPLIANCES
A14: Employee | B14: ESI | C14: 0.0175 | D14: =IF(D12<15000,1.75%*D12,0) -> 243.6187 | E14: =IF(E12<15000,1.75%*E12,0) -> 207.99529 | F14: =IF(F12<15000,1.75%*F12,0) -> 207.99529 | G14: =IF(G12<15000,1.75%*G12,0) -> 207.99529 | H14: =IF(H12<15000,1.75%*H12,0) -> 207.99529 | I14: =IF(I12<15000,1.75%*I12,0) -> 207.99529 | J14: =IF(J12<15000,1.75%*J12,0) -> 207.99529 | K14: =IF(K12<15000,1.75%*K12,0) -> 207.99529 | ... AE14: =IF(AE12<15000,1.75%*AE12,0) -> 139.965
B15: EPF | C15: 0.12 | D15: =ROUND(D6*12%,0) -> 969 | E15: =ROUND(E6*12%,0) -> 969 | F15: =ROUND(F6*12%,0) -> 969 | G15: =ROUND(G6*12%,0) -> 969 | H15: =ROUND(H6*12%,0) -> 969 | I15: =ROUND(I6*12%,0) -> 969 | J15: =ROUND(J6*12%,0) -> 969 | K15: =ROUND(K6*12%,0) -> 969 | ... AE15: =ROUND(AE6*12%,0) -> 789
A16: SUB TOTAL | D16: =SUM(D14:D15) -> 1212.6187 | E16: =SUM(E14:E15) -> 1176.9953 | F16: =SUM(F14:F15) -> 1176.9953 | G16: =SUM(G14:G15) -> 1176.9953 | H16: =SUM(H14:H15) -> 1176.9953 | I16: =SUM(I14:I15) -> 1176.9953 | J16: =SUM(J14:J15) -> 1176.9953 | K16: =SUM(K14:K15) -> 1176.9953 | ... AE16: =SUM(AE14:AE15) -> 928.965
A17: Employer | B17: ESI | C17: 0.0475 | D17: =IF(D12<15000,4.75%*D12,0) -> 661.25076 | E17: =IF(E12<15000,4.75%*E12,0) -> 564.55865 | F17: =IF(F12<15000,4.75%*F12,0) -> 564.55865 | G17: =IF(G12<15000,4.75%*G12,0) -> 564.55865 | H17: =IF(H12<15000,4.75%*H12,0) -> 564.55865 | I17: =IF(I12<15000,4.75%*I12,0) -> 564.55865 | J17: =IF(J12<15000,4.75%*J12,0) -> 564.55865 | K17: =IF(K12<15000,4.75%*K12,0) -> 564.55865 | ... AE17: =IF(AE12<15000,4.75%*AE12,0) -> 379.905
B18: EPF | C18: 0.1361 | D18: =ROUND(D6*13.61%,0) -> 1100 | E18: =ROUND(E6*13.61%,0) -> 1100 | F18: =ROUND(F6*13.61%,0) -> 1100 | G18: =ROUND(G6*13.61%,0) -> 1100 | H18: =ROUND(H6*13.61%,0) -> 1100 | I18: =ROUND(I6*13.61%,0) -> 1100 | J18: =ROUND(J6*13.61%,0) -> 1100 | K18: =ROUND(K6*13.61%,0) -> 1100 | ... AE18: =ROUND(AE6*13.61%,0) -> 895
A19: SUB TOTAL | D19: =SUM(D17:D18) -> 1761.2508 | E19: =SUM(E17:E18) -> 1664.5587 | F19: =SUM(F17:F18) -> 1664.5587 | G19: =SUM(G17:G18) -> 1664.5587 | H19: =SUM(H17:H18) -> 1664.5587 | I19: =SUM(I17:I18) -> 1664.5587 | J19: =SUM(J17:J18) -> 1664.5587 | K19: =SUM(K17:K18) -> 1664.5587 | ... AE19: =SUM(AE17:AE18) -> 1274.905
A20: ADMINISTRATION CHARGES
A21: Bonus | C21: 0.0833 | D21: =IF(D8>3500,(3500*$C$21),(D8*$C$21)) -> 291.55 | E21: =IF(E8>3500,(3500*$C$21),(E8*$C$21)) -> 291.55 | F21: =IF(F8>3500,(3500*$C$21),(F8*$C$21)) -> 291.55 | G21: =IF(G8>3500,(3500*$C$21),(G8*$C$21)) -> 291.55 | H21: =IF(H8>3500,(3500*$C$21),(H8*$C$21)) -> 291.55 | I21: =IF(I8>3500,(3500*$C$21),(I8*$C$21)) -> 291.55 | J21: =IF(J8>3500,(3500*$C$21),(J8*$C$21)) -> 291.55 | K21: =IF(K8>3500,(3500*$C$21),(K8*$C$21)) -> 291.55 | ... AE21: =IF(AE8>3500,(3500*$C$21),(AE8*$C$21)) -> 291.55
A22: Leave Component | C22: 0.0833 | D22: =D8*$C$22 -> 817.8394 | E22: =E8*$C$22 -> 817.8394 | F22: =F8*$C$22 -> 817.8394 | G22: =G8*$C$22 -> 817.8394 | H22: =H8*$C$22 -> 817.8394 | I22: =I8*$C$22 -> 817.8394 | J22: =J8*$C$22 -> 817.8394 | K22: =K8*$C$22 -> 817.8394 | ... AE22: =AE8*$C$22 -> 666.2334
A23: Uniform & Tools | C23: (Pro-rata) | D23: 150 | E23: 150 | F23: 150 | G23: 150 | H23: 150 | I23: 150 | J23: 150 | K23: 150 | L23: 150 | M23: 151 | N23: 152 | O23: 155 | P23: 156 | Q23: 158 | R23: 150 | S23: 150 | T23: 150 | U23: 150 | V23: 150 | W23: 150 | X23: 150 | Y23: 150 | Z23: 150 | AA23: 150 | AB23: 150 | AC23: 150 | AD23: 150 | AE23: 150
A24: SUB TOTAL | D24: =SUM(D21:D23) -> 1259.3894 | E24: =SUM(E21:E23) -> 1259.3894 | F24: =SUM(F21:F23) -> 1259.3894 | G24: =SUM(G21:G23) -> 1259.3894 | H24: =SUM(H21:H23) -> 1259.3894 | I24: =SUM(I21:I23) -> 1259.3894 | J24: =SUM(J21:J23) -> 1259.3894 | K24: =SUM(K21:K23) -> 1259.3894 | ... AE24: =SUM(AE21:AE23) -> 1107.7834
A25: INSURANCE
A26: Medical & Accidential Insurance | D26: 100 | E26: 100 | F26: 100 | G26: 100 | H26: 100 | I26: 100 | J26: 100 | K26: 100 | L26: 100 | M26: 101 | N26: 102 | O26: 105 | P26: 106 | Q26: 108 | R26: 100 | S26: 100 | T26: 100 | U26: 100 | V26: 100 | W26: 100 | X26: 100 | Y26: 100 | Z26: 100 | AA26: 100 | AB26: 100 | AC26: 100 | AD26: 100 | AE26: 100
A27: Others
A28: SUB TOTAL | D28: =SUM(D26:D27) -> 100 | E28: =SUM(E26:E27) -> 100 | F28: =SUM(F26:F27) -> 100 | G28: =SUM(G26:G27) -> 100 | H28: =SUM(H26:H27) -> 100 | I28: =SUM(I26:I27) -> 100 | J28: =SUM(J26:J27) -> 100 | K28: =SUM(K26:K27) -> 100 | ... AE28: =SUM(AE26:AE27) -> 100
A29: FINAL
A30: Cash In hand | D30: =D31-D16-D19-D24+D21-D28 -> 13000 | E30: =E31-E16-E19-E24+E21-E28 -> 11000 | F30: =F31-F16-F19-F24+F21-F28 -> 11000 | G30: =G31-G16-G19-G24+G21-G28 -> 11000 | H30: =H31-H16-H19-H24+H21-H28 -> 11000 | I30: =I31-I16-I19-I24+I21-I28 -> 11000 | J30: =J31-J16-J19-J24+J21-J28 -> 11000 | K30: =K31-K16-K19-K24+K21-K28 -> 11000 | ... AE30: =AE31-AE16-AE19-AE24+AE21-AE28 -> 7360.585
A31: CTC | D31: =D12+D19+D24+D28 -> 17041.709 | E31: =E12+E19+E24+E28 -> 14909.393 | F31: =F12+F19+F24+F28 -> 14909.393 | G31: =G12+G19+G24+G28 -> 14909.393 | H31: =H12+H19+H24+H28 -> 14909.393 | I31: =I12+I19+I24+I28 -> 14909.393 | J31: =J12+J19+J24+J28 -> 14909.393 | K31: =K12+K19+K24+K28 -> 14909.393 | ... AE31: =AE12+AE19+AE24+AE28 -> 10480.688
A32: SERVICE PROVIDER CHARGES
A33: Service Charges | C33: 0.1 | D33: =D31*$C$33 -> 1704.1709 | E33: =E31*$C$33 -> 1490.9393 | F33: =F31*$C$33 -> 1490.9393 | G33: =G31*$C$33 -> 1490.9393 | H33: =H31*$C$33 -> 1490.9393 | I33: =I31*$C$33 -> 1490.9393 | J33: =J31*$C$33 -> 1490.9393 | K33: =K31*$C$33 -> 1490.9393 | ... AE33: =AE31*$C$33 -> 1048.0688
A34: BILL TO CLIENT | D34: =ROUND(D31+D33,0) -> 18746 | E34: =ROUND(E31+E33,0) -> 16400 | F34: =ROUND(F31+F33,0) -> 16400 | G34: =ROUND(G31+G33,0) -> 16400 | H34: =ROUND(H31+H33,0) -> 16400 | I34: =ROUND(I31+I33,0) -> 16400 | J34: =ROUND(J31+J33,0) -> 16400 | K34: =ROUND(K31+K33,0) -> 16400 | ... AE34: =ROUND(AE31+AE33,0) -> 11529
D35: 13000 | E35: 11000 | F35: 11000 | G35: 11000 | H35: 11000 | I35: 11000 | J35: 11000 | K35: 11000 | L35: 11000 | M35: 11000 | N35: 11000 | O35: 11000 | P35: 8000 | Q35: 10000 | R35: 12000 | S35: 9000 | T35: 9000 | U35: 7000 | V35: 13000 | W35: 9000 | X35: 13000 | Y35: 10000 | Z35: 10000 | AA35: 12000 | AB35: 8000 | AC35: 12000 | AD35: 11000 | AE35: 10000

Sheet HK - Secr Equipments
A1: HOUSEKEEPING EQUIPMENT COST
A2: Sl.No | B2: Name of Machines | C2: Brand | D2: Cost/ unit | E2: Life in months | F2: Common | G2: Total | H2: Total Cost | J2: Amortized Cost | K2: INDEX
A3: 1 | B3: Walk Behind- Auto Scrubbr/ Dryr | C3: NILFISK | D3: 130000 | E3: 24 | F3: 1 | G3: =SUM(F3:F3) -> 1 | H3: =G3*D3 -> 130000 | I3: =D3/E3 -> 5416.6667 | J3: =H3/E3 -> 5416.6667
A4: 1 | B4: SINGLE DISC MACHINE | C4: NILFISK | D4: 70000 | E4: 24 | F4: 2 | G4: =SUM(F4:F4) -> 2 | H4: =G4*D4 -> 140000 | I4: =D4/E4 -> 2916.6667 | J4: =H4/E4 -> 5833.3333
A5: 2 | B5: MANUAL ROAD SWEEPER | C5: COMAC | D5: 15000 | E5: 24 | F5: 1 | G5: =SUM(F5:F5) -> 1 | H5: =G5*D5 -> 15000 | I5: =D5/E5 -> 625 | J5: =H5/E5 -> 625
A6: 3 | B6: HIGH PRESSURE JET | C6: TASKI | D6: 70000 | E6: 24 | F6: 1 | G6: =SUM(F6:F6) -> 1 | H6: =G6*D6 -> 70000 | I6: =D6/E6 -> 2916.6667 | J6: =H6/E6 -> 2916.6667
A7: 4 | B7: WET/DRY VACUUM | C7: EUREKA | D7: 20000 | E7: 24 | F7: 2 | G7: =SUM(F7:F7) -> 2 | H7: =G7*D7 -> 40000 | I7: =D7/E7 -> 833.33333 | J7: =H7/E7 -> 1666.6667
A8: 5 | B8: WRINGER TROLLEY | C8: UNGER | D8: 5000 | E8: 12 | F8: 10 | G8: =SUM(F8:F8) -> 10 | H8: =G8*D8 -> 50000 | I8: =D8/E8 -> 416.66667 | J8: =H8/E8 -> 4166.6667
A9: 6 | B9: GLASS CLEANING KIT WITH TELESCOPIC POLE | C9: KARAM | D9: 10000 | E9: 12 | F9: 2 | G9: =SUM(F9:F9) -> 2 | H9: =G9*D9 -> 20000 | I9: =D9/E9 -> 833.33333 | J9: =H9/E9 -> 1666.6667
A10: 7 | B10: CADDY & SIGNAGES | C10: CONTA | D10: 1000 | E10: 12 | F10: 10 | G10: =SUM(F10:F10) -> 10 | H10: =G10*D10 -> 10000 | I10: =D10/E10 -> 83.333333 | J10: =H10/E10 -> 833.33333
A11: Sub Total | H11: =SUM(H4:H10) -> 345000 | J11: =SUM(J3:J10) -> 23125
B12: SPARES @ 20% | J12: =J11*20% -> 4625
B13: INTEREST @ 12% | J13: =J11*12% -> 2775
A14: TOTAL cost per month (b) | J14: =SUM(J11:J13) -> 30525
A16: SECURITY EQUIPMENTR C COSTING
A17: Sr.No | B17: Equipment | E17: Monthly Rental | F17: Common | G17: Total | H17: Total Rental
A18: 1 | B18: DFMD | E18: 2000 | G18: =5+5 -> 10 | H18: =G18*E18 -> 20000
A19: 2 | B19: HHMD | E19: 800 | G19: =G18 -> 10 | H19: =G19*E19 -> 8000
A20: 3 | B20: Wireless Set | E20: 1000 | G20: 15 | H20: =G20*E20 -> 15000
B21: Under Carrage Mirror | E21: 250 | G21: 2 | H21: =G21*E21 -> 500
B22: GRAND TOTAL | G22: =SUM(G18:G20) -> 35 | H22: =SUM(H18:H20) -> 43000

Sheet SinkingFundEstimation
A1: Sinking Fund Estimation-
A2: Cost of Equipments | J2: Actual Cost of Euipment to be considered | N2: # of years in which replacement will be required | R2: % of Replacement required | V2: INDEX
A3: FAS,CCTV,IBMS&PAS | J3: 2.6742048 | N3: 10 | R3: 0.25
A4: Chillers | J4: 1.5694631 | N4: 15 | R4: 0.5
A5: Package Units | J5: 3.0892182 | N5: 12 | R5: 0.4
A6: 33KV Transformers | J6: 0.888 | N6: 20 | R6: 0.5
A7: Elevators | J7: =6.3404717*60% -> 3.804283 | N7: 12 | R7: 0.3
A8: Diesel Generators | J8: 4.7743408 | N8: 15 | R8: 0.3
A9: Total Cost taken for refurbishment | J9: =SUM(J3:M8) -> 16.79951 | R9: =AVERAGE(R3:U8) -> 0.375
A11: Area in sft | B11: ='[8]Area Details'!E4 -> 211750
A12: Inflation yoy for Equipment Cost | B12: 0.04
A14: Replacement Funds required considering YOY Inflation >> | B14: 1 | C14: 2 | D14: 3 | E14: 4 | F14: 5 | G14: 6 | H14: 7 | I14: 8 | J14: 9 | K14: 10 | L14: 11 | M14: 12 | N14: 13 | O14: 14 | P14: 15 | Q14: 16 | R14: 17 | S14: 18 | T14: 19 | U14: 20
A15: =A3 -> FAS,CCTV,IBMS&PAS | B15: =IF(ISNUMBER(SEARCH(".",B14/$N$3)),"0",($R$3*$J$3*(1+$B$12)^B14)) -> 0 | C15: =IF(ISNUMBER(SEARCH(".",C14/$N$3)),"0",($R$3*$J$3*(1+$B$12)^C14)) -> 0 | D15: =IF(ISNUMBER(SEARCH(".",D14/$N$3)),"0",($R$3*$J$3*(1+$B$12)^D14)) -> 0 | E15: =IF(ISNUMBER(SEARCH(".",E14/$N$3)),"0",($R$3*$J$3*(1+$B$12)^E14)) -> 0 | F15: =IF(ISNUMBER(SEARCH(".",F14/$N$3)),"0",($R$3*$J$3*(1+$B$12)^F14)) -> 0 | G15: =IF(ISNUMBER(SEARCH(".",G14/$N$3)),"0",($R$3*$J$3*(1+$B$12)^G14)) -> 0 | H15: =IF(ISNUMBER(SEARCH(".",H14/$N$3)),"0",($R$3*$J$3*(1+$B$12)^H14)) -> 0 | I15: =IF(ISNUMBER(SEARCH(".",I14/$N$3)),"0",($R$3*$J$3*(1+$B$12)^I14)) -> 0 | ... U15: =IF(ISNUMBER(SEARCH(".",U14/$N$3)),"0",($R$3*$J$3*(1+$B$12)^U14)) -> 1.464878
A16: =A4 -> Chillers | B16: =IF(ISNUMBER(SEARCH(".",B14/$N$4)),"0",($R$4*$J$4*(1+$B$12)^B14)) -> 0 | C16: =IF(ISNUMBER(SEARCH(".",C14/$N$4)),"0",($R$4*$J$4*(1+$B$12)^C14)) -> 0 | D16: =IF(ISNUMBER(SEARCH(".",D14/$N$4)),"0",($R$4*$J$4*(1+$B$12)^D14)) -> 0 | E16: =IF(ISNUMBER(SEARCH(".",E14/$N$4)),"0",($R$4*$J$4*(1+$B$12)^E14)) -> 0 | F16: =IF(ISNUMBER(SEARCH(".",F14/$N$4)),"0",($R$4*$J$4*(1+$B$12)^F14)) -> 0 | G16: =IF(ISNUMBER(SEARCH(".",G14/$N$4)),"0",($R$4*$J$4*(1+$B$12)^G14)) -> 0 | H16: =IF(ISNUMBER(SEARCH(".",H14/$N$4)),"0",($R$4*$J$4*(1+$B$12)^H14)) -> 0 | I16: =IF(ISNUMBER(SEARCH(".",I14/$N$4)),"0",($R$4*$J$4*(1+$B$12)^I14)) -> 0 | ... U16: =IF(ISNUMBER(SEARCH(".",U14/$N$4)),"0",($R$4*$J$4*(1+$B$12)^U14)) -> 0
A17: =A5 -> Package Units | B17: =IF(ISNUMBER(SEARCH(".",B14/$N$5)),"0",($R$5*$J$5*(1+$B$12)^B14)) -> 0 | C17: =IF(ISNUMBER(SEARCH(".",C14/$N$5)),"0",($R$5*$J$5*(1+$B$12)^C14)) -> 0 | D17: =IF(ISNUMBER(SEARCH(".",D14/$N$5)),"0",($R$5*$J$5*(1+$B$12)^D14)) -> 0 | E17: =IF(ISNUMBER(SEARCH(".",E14/$N$5)),"0",($R$5*$J$5*(1+$B$12)^E14)) -> 0 | F17: =IF(ISNUMBER(SEARCH(".",F14/$N$5)),"0",($R$5*$J$5*(1+$B$12)^F14)) -> 0 | G17: =IF(ISNUMBER(SEARCH(".",G14/$N$5)),"0",($R$5*$J$5*(1+$B$12)^G14)) -> 0 | H17: =IF(ISNUMBER(SEARCH(".",H14/$N$5)),"0",($R$5*$J$5*(1+$B$12)^H14)) -> 0 | I17: =IF(ISNUMBER(SEARCH(".",I14/$N$5)),"0",($R$5*$J$5*(1+$B$12)^I14)) -> 0 | ... U17: =IF(ISNUMBER(SEARCH(".",U14/$N$5)),"0",($R$5*$J$5*(1+$B$12)^U14)) -> 0
A18: =A6 -> 33KV Transformers | B18: =IF(ISNUMBER(SEARCH(".",B14/$N$6)),"0",($R$6*$J$6*(1+$B$12)^B14)) -> 0 | C18: =IF(ISNUMBER(SEARCH(".",C14/$N$6)),"0",($R$6*$J$6*(1+$B$12)^C14)) -> 0 | D18: =IF(ISNUMBER(SEARCH(".",D14/$N$6)),"0",($R$6*$J$6*(1+$B$12)^D14)) -> 0 | E18: =IF(ISNUMBER(SEARCH(".",E14/$N$6)),"0",($R$6*$J$6*(1+$B$12)^E14)) -> 0 | F18: =IF(ISNUMBER(SEARCH(".",F14/$N$6)),"0",($R$6*$J$6*(1+$B$12)^F14)) -> 0 | G18: =IF(ISNUMBER(SEARCH(".",G14/$N$6)),"0",($R$6*$J$6*(1+$B$12)^G14)) -> 0 | H18: =IF(ISNUMBER(SEARCH(".",H14/$N$6)),"0",($R$6*$J$6*(1+$B$12)^H14)) -> 0 | I18: =IF(ISNUMBER(SEARCH(".",I14/$N$6)),"0",($R$6*$J$6*(1+$B$12)^I14)) -> 0 | ... U18: =IF(ISNUMBER(SEARCH(".",U14/$N$6)),"0",($R$6*$J$6*(1+$B$12)^U14)) -> 0.97285868
A19: =A7 -> Elevators | B19: =IF(ISNUMBER(SEARCH(".",B14/$N$7)),"0",($R$7*$J$7*(1+$B$12)^B14)) -> 0 | C19: =IF(ISNUMBER(SEARCH(".",C14/$N$7)),"0",($R$7*$J$7*(1+$B$12)^C14)) -> 0 | D19: =IF(ISNUMBER(SEARCH(".",D14/$N$7)),"0",($R$7*$J$7*(1+$B$12)^D14)) -> 0 | E19: =IF(ISNUMBER(SEARCH(".",E14/$N$7)),"0",($R$7*$J$7*(1+$B$12)^E14)) -> 0 | F19: =IF(ISNUMBER(SEARCH(".",F14/$N$7)),"0",($R$7*$J$7*(1+$B$12)^F14)) -> 0 | G19: =IF(ISNUMBER(SEARCH(".",G14/$N$7)),"0",($R$7*$J$7*(1+$B$12)^G14)) -> 0 | H19: =IF(ISNUMBER(SEARCH(".",H14/$N$7)),"0",($R$7*$J$7*(1+$B$12)^H14)) -> 0 | I19: =IF(ISNUMBER(SEARCH(".",I14/$N$7)),"0",($R$7*$J$7*(1+$B$12)^I14)) -> 0 | ... U19: =IF(ISNUMBER(SEARCH(".",U14/$N$7)),"0",($R$7*$J$7*(1+$B$12)^U14)) -> 0
A20: =A8 -> Diesel Generators | B20: =IF(ISNUMBER(SEARCH(".",B14/$N$8)),"0",($R$8*$J$8*(1+$B$12)^B14)) -> 0 | C20: =IF(ISNUMBER(SEARCH(".",C14/$N$8)),"0",($R$8*$J$8*(1+$B$12)^C14)) -> 0 | D20: =IF(ISNUMBER(SEARCH(".",D14/$N$8)),"0",($R$8*$J$8*(1+$B$12)^D14)) -> 0 | E20: =IF(ISNUMBER(SEARCH(".",E14/$N$8)),"0",($R$8*$J$8*(1+$B$12)^E14)) -> 0 | F20: =IF(ISNUMBER(SEARCH(".",F14/$N$8)),"0",($R$8*$J$8*(1+$B$12)^F14)) -> 0 | G20: =IF(ISNUMBER(SEARCH(".",G14/$N$8)),"0",($R$8*$J$8*(1+$B$12)^G14)) -> 0 | H20: =IF(ISNUMBER(SEARCH(".",H14/$N$8)),"0",($R$8*$J$8*(1+$B$12)^H14)) -> 0 | I20: =IF(ISNUMBER(SEARCH(".",I14/$N$8)),"0",($R$8*$J$8*(1+$B$12)^I14)) -> 0 | ... U20: =IF(ISNUMBER(SEARCH(".",U14/$N$8)),"0",($R$8*$J$8*(1+$B$12)^U14)) -> 0
A21: Replacement Funds required >> | B21: =SUM(B15:B20) -> 0 | C21: =SUM(C15:C20) -> 0 | D21: =SUM(D15:D20) -> 0 | E21: =SUM(E15:E20) -> 0 | F21: =SUM(F15:F20) -> 0 | G21: =SUM(G15:G20) -> 0 | H21: =SUM(H15:H20) -> 0 | I21: =SUM(I15:I20) -> 0 | ... U21: =SUM(U15:U20) -> 2.4377367
B23: 2016 | C23: =B23+1 -> 2017 | D23: =C23+1 -> 2018 | E23: =D23+1 -> 2019 | F23: =E23+1 -> 2020 | G23: =F23+1 -> 2021 | H23: =G23+1 -> 2022 | I23: =H23+1 -> 2023 | J23: =I23+1 -> 2024 | ... U23: =T23+1 -> 2035
A24: Sinking Fund Generation Account | B24: =B14 -> 1 | C24: =B24+1 -> 2 | D24: =C24+1 -> 3 | E24: =D24+1 -> 4 | F24: =E24+1 -> 5 | G24: =F24+1 -> 6 | H24: =G24+1 -> 7 | I24: =H24+1 -> 8 | J24: =I24+1 -> 9 | ... U24: =T24+1 -> 20
A25: Interest Rate possible on sinking fund ( post TDS) | B25: 0.07
A26: Inflation yoy | B26: =B12 -> 0.04
A27: Rate Per sqft paid for Sinking Fund | B27: 1.156595 | C27: =B27*(1+$B$26) -> 1.2028588 | D27: =C27*(1+$B$26) -> 1.2509732 | E27: =D27*(1+$B$26) -> 1.3010121 | F27: =E27*(1+$B$26) -> 1.3530526 | G27: =F27*(1+$B$26) -> 1.4071747 | H27: =G27*(1+$B$26) -> 1.4634617 | I27: =H27*(1+$B$26) -> 1.5220001 | J27: =I27*(1+$B$26) -> 1.5828801 | ... U27: =T27*(1+$B$26) -> 2.4367712
A29: Contribution from Annual Sinking Fund | B29: =B27*$B$11*12/10^7 -> 0.29389079 | C29: =C27*$B$11*12/10^7 -> 0.30564642 | D29: =D27*$B$11*12/10^7 -> 0.31787228 | E29: =E27*$B$11*12/10^7 -> 0.33058717 | F29: =F27*$B$11*12/10^7 -> 0.34381066 | G29: =G27*$B$11*12/10^7 -> 0.35756309 | H29: =H27*$B$11*12/10^7 -> 0.37186561 | I29: =I27*$B$11*12/10^7 -> 0.38674023 | ... U29: =U27*$B$11*12/10^7 -> 0.61918357
A30: Carry Forward from previous Year | B30: 0 | C30: =B33-B37 -> 0.31446315 | D30: =C33-C37 -> 0.66351724 | E30: =D33-D37 -> 1.0500868 | F30: =E33-E37 -> 1.4773211 | G30: =F33-F37 -> 1.948611 | H30: =G33-G37 -> 2.4676063 | I30: =H33-H37 -> 3.0382349 | J30: =I33-I37 -> 3.6647234 | ... U30: =T33-T37 -> 2.6605719
A31: Total Amount on which interest is applicable | B31: =SUM(B29:B30) -> 0.29389079 | C31: =SUM(C29:C30) -> 0.62010957 | D31: =SUM(D29:D30) -> 0.98138952 | E31: =SUM(E29:E30) -> 1.380674 | F31: =SUM(F29:F30) -> 1.8211318 | G31: =SUM(G29:G30) -> 2.3061741 | H31: =SUM(H29:H30) -> 2.8394719 | I31: =SUM(I29:I30) -> 3.4249752 | ... U31: =SUM(U29:U30) -> 3.2797555
A32: Interest Generated Annual | B32: =$B$25*B31 -> 0.020572355 | C32: =$B$25*C31 -> 0.04340767 | D32: =$B$25*D31 -> 0.068697267 | E32: =$B$25*E31 -> 0.096647177 | F32: =$B$25*F31 -> 0.12747923 | G32: =$B$25*G31 -> 0.16143219 | H32: =$B$25*H31 -> 0.19876303 | I32: =$B$25*I31 -> 0.23974826 | ... U32: =$B$25*U31 -> 0.22958288
A33: End of Year Amount | B33: =B31+B32 -> 0.31446315 | C33: =C31+C32 -> 0.66351724 | D33: =D31+D32 -> 1.0500868 | E33: =E31+E32 -> 1.4773211 | F33: =F31+F32 -> 1.948611 | G33: =G31+G32 -> 2.4676063 | H33: =H31+H32 -> 3.0382349 | I33: =I31+I32 -> 3.6647234 | ... U33: =U31+U32 -> 3.5093384
A35: Sinking Fund Account Usage | B35: =B24 -> 1 | C35: =C24 -> 2 | D35: =D24 -> 3 | E35: =E24 -> 4 | F35: =F24 -> 5 | G35: =G24 -> 6 | H35: =H24 -> 7 | I35: =I24 -> 8 | ... U35: =U24 -> 20
A36: Starting Balance | B36: =B33 -> 0.31446315 | C36: =C33 -> 0.66351724 | D36: =D33 -> 1.0500868 | E36: =E33 -> 1.4773211 | F36: =F33 -> 1.948611 | G36: =G33 -> 2.4676063 | H36: =H33 -> 3.0382349 | I36: =I33 -> 3.6647234 | ... U36: =U33 -> 3.5093384
A37: Sinking Fund Consumed | B37: =B21 -> 0 | C37: =C21 -> 0 | D37: =D21 -> 0 | E37: =E21 -> 0 | F37: =F21 -> 0 | G37: =G21 -> 0 | H37: =H21 -> 0 | I37: =I21 -> 0 | ... U37: =U21 -> 2.4377367
A38: Ending Balance | B38: =B36-B37 -> 0.31446315 | C38: =C36-C37 -> 0.66351724 | D38: =D36-D37 -> 1.0500868 | E38: =E36-E37 -> 1.4773211 | F38: =F36-F37 -> 1.948611 | G38: =G36-G37 -> 2.4676063 | H38: =H36-H37 -> 3.0382349 | I38: =I36-I37 -> 3.6647234 | ... U38: =U36-U37 -> 1.0716017
A40: Maximum Outage | B40: =MIN(B38:U38) -> 0
