Workbook

Sheet Cummulative Summary
A3: MONTHLY CAM CHARGES CALCULATION SUMMARY - OGM
A4: 490749 | B4: Total Building Saleable area-SFT | C4: 490749
B5: Month | C5: Jun`23 | D5: Jul`23 | E5: Aug`23 | F5: Sep`23 | G5: Oct`23 | H5: Nov`23 | I5: Dec`23 | J5: Jan`24 | M5: Feb`24 | P5: Mar`24 | S5: Apr`24 | V5: May`24 | Y5: Jun`24 | AB5: Jul`24 | AE5: Aug`24 | AH5: Sep`24 | AK5: Oct`24 | AN5: Nov`24 | AQ5: Dec`24 | AT5: Jan`25 | AW5: Feb`25 | AZ5: Mar`25 | BC5: Apr`25 | BF5: May`25 | BI5: Jun`25 | BL5: Jul`25 | BO5: Aug`25 | BR5: Sep`25 | BU5: Oct`25 | BX5: Nov`25
A6: Sl no | B6: Description | J6: Total | K6: MCP | L6: OGM | M6: Total | N6: MCP | O6: OGM | P6: Total | Q6: MCP | R6: OGM | S6: Total | T6: MCP | U6: OGM | V6: Total | W6: MCP | X6: OGM | Y6: Total | Z6: MCP | AA6: OGM | AB6: Total | AC6: MCP | AD6: OGM | AE6: Total | AF6: MCP | AG6: OGM | AH6: Total | AI6: MCP | AJ6: OGM | AK6: Total | AL6: MCP | AM6: OGM | AN6: Total | AO6: MCP | AP6: OGM | AQ6: Total | AR6: MCP | AS6: OGM | AT6: Total | AU6: MCP | AV6: OGM | AW6: Total | AX6: MCP | AY6: OGM | AZ6: Total | BA6: MCP | BB6: OGM | BC6: Total | BD6: MCP | BE6: OGM | BF6: Total | BG6: MCP | BH6: OGM | BI6: Total | BJ6: MCP | BK6: OGM | BL6: Total | BM6: MCP | BN6: OGM | BO6: Total | BP6: MCP | BQ6: OGM | BR6: Total | BS6: MCP | BT6: OGM | BU6: Total | BV6: MCP | BW6: OGM | BX6: Total | BY6: MCP | BZ6: OGM
J7: 490749 | K7: 167554 | L7: 323195 | M7: 490749 | N7: 167554 | O7: 323195 | P7: 490749 | Q7: 167554 | R7: 323195 | S7: 490749 | T7: 167554 | U7: 323195 | V7: 490749 | W7: 167554 | X7: 323195 | Y7: 490749 | Z7: 167554 | AA7: 323195 | AB7: 490749 | AC7: 167554 | AD7: 323195 | AE7: 490749 | AF7: 167554 | AG7: 323195 | AH7: 490749 | AI7: 167554 | AJ7: 323195 | AK7: 490749 | AL7: 167554 | AM7: 323195 | AN7: 490749 | AO7: 167554 | AP7: 323195 | AQ7: 490749 | AR7: 167554 | AS7: 323195 | AT7: 490749 | AU7: 167554 | AV7: 323195 | AW7: 490749 | AX7: 167554 | AY7: 323195 | AZ7: 490749 | BA7: 167554 | BB7: 323195 | BC7: 490749 | BD7: 167554 | BE7: 323195 | BF7: 490749 | BG7: 167554 | BH7: 323195 | BI7: 490749 | BJ7: 167554 | BK7: 323195 | BL7: 490749 | BM7: 167554 | BN7: 323195 | BO7: 490749 | BP7: 167554 | BQ7: 323195 | BR7: 490749 | BS7: 167554 | BT7: 323195 | BU7: 490749 | BV7: 167554 | BW7: 323195 | BX7: 490749 | BY7: 167554 | BZ7: 323195
A8: 1 | B8: Management staff (By Area) | C8: ='CAM-Jun`23'!C6 -> 53038 | D8: ='CAM-Jul`23'!C6 -> 148967 | E8: ='CAM-Aug`23'!C6 -> 140000 | F8: ='CAM-Sep`23'!C6 -> 140000 | G8: ='CAM-Oct`23'!C6 -> 197561 | H8: ='CAM-Nov`23'!C6 -> 234758 | I8: ='CAM-Dec`23'!C6 -> 262200 | J8: ='CAM-Jan`24'!C5 -> 339700 | K8: ='CAM-Jan`24'!G5 -> 115982.09 | L8: ='CAM-Jan`24'!H5 -> 223717.91 | M8: ='CAM-Feb`24'!C5 -> 339700 | N8: ='CAM-Feb`24'!G5 -> 115982.09 | O8: ='CAM-Feb`24'!H5 -> 223717.91 | P8: ='CAM-Mar`24'!C6 -> 339700 | Q8: ='CAM-Mar`24'!G6 -> 115982.09 | R8: ='CAM-Mar`24'!H6 -> 223717.91 | S8: ='CAM-Apr`24'!C6 -> 383033 | T8: ='CAM-Apr`24'!G6 -> 130777.06 | U8: ='CAM-Apr`24'!H6 -> 252255.94 | V8: ='CAM-May`24'!C6 -> 389700 | W8: ='CAM-May`24'!G6 -> 133053.34 | X8: ='CAM-May`24'!H6 -> 256646.66 | Y8: ='CAM-Jun`24'!C6 -> 389700 | Z8: ='CAM-Jun`24'!G6 -> 133053.34 | AA8: ='CAM-Jun`24'!H6 -> 256646.66 | AB8: ='CAM-Jul`24'!C6 -> 389700 | AC8: ='CAM-Jul`24'!G6 -> 133053.34 | AD8: ='CAM-Jul`24'!H6 -> 256646.66 | AE8: ='CAM-Aug`24'!C6 -> 403700 | AF8: ='CAM-Aug`24'!G6 -> 137833.29 | AG8: ='CAM-Aug`24'!H6 -> 265866.71 | AH8: ='CAM-Sep`24'!C6 -> 403700 | AI8: ='CAM-Sep`24'!G6 -> 137833.29 | AJ8: ='CAM-Sep`24'!H6 -> 265866.71 | AK8: ='CAM-Oct`24'!C6 -> 403700 | AL8: ='CAM-Oct`24'!G6 -> 137833.29 | AM8: ='CAM-Oct`24'!H6 -> 265866.71 | AN8: ='CAM-Nov`24'!C6 -> 403700 | AO8: ='CAM-Nov`24'!G6 -> 137833.29 | AP8: ='CAM-Nov`24'!H6 -> 265866.71 | AQ8: ='CAM-Dec2024'!C6 -> 403700 | AR8: ='CAM-Dec2024'!G6 -> 137833.29 | AS8: ='CAM-Dec2024'!H6 -> 265866.71 | AT8: ='CAM-Jan2025'!C6 -> 403700 | AU8: ='CAM-Jan2025'!G6 -> 137833.29 | AV8: ='CAM-Jan2025'!H6 -> 265866.71 | AW8: ='CAM-Feb2025'!C6 -> 403377 | AX8: ='CAM-Feb2025'!G6 -> 137723.01 | AY8: ='CAM-Feb2025'!H6 -> 265653.99 | AZ8: ='CAM-Mar2025'!C6 -> 430000 | BA8: ='CAM-Mar2025'!G6 -> 146812.77 | BB8: ='CAM-Mar2025'!H6 -> 283187.23 | BC8: ='CAM-Apr2025'!C6 -> 430000 | BD8: ='CAM-Apr2025'!G6 -> 146812.77 | BE8: ='CAM-Apr2025'!H6 -> 283187.23 | BF8: ='CAM-May2025'!C6 -> 430000 | BG8: ='CAM-May2025'!G6 -> 146812.77 | BH8: ='CAM-May2025'!H6 -> 283187.23 | BI8: ='CAM-Jun2025'!C6 -> 430000 | BJ8: ='CAM-Jun2025'!G6 -> 146812.77 | BK8: ='CAM-Jun2025'!H6 -> 283187.23 | BL8: ='CAM-Jul2025'!C6 -> 430000 | BM8: ='CAM-Jul2025'!G6 -> 146812.77 | BN8: ='CAM-Jul2025'!H6 -> 283187.23 | BO8: ='CAM-Aug2025'!C6 -> 440000 | BP8: ='CAM-Aug2025'!G6 -> 150227.02 | BQ8: ='CAM-Aug2025'!H6 -> 289772.98 | BR8: ='CAM-Sep2025'!C6 -> 440000 | BS8: ='CAM-Sep2025'!G6 -> 150227.02 | BT8: ='CAM-Sep2025'!H6 -> 289772.98 | BU8: ='CAM-Oct2025'!C6 -> 430065 | BV8: ='CAM-Oct2025'!G6 -> 146834.96 | BW8: ='CAM-Oct2025'!H6 -> 283230.04 | BX8: ='CAM-Nov2025'!C6 -> 429733 | BY8: ='CAM-Nov2025'!G6 -> 146721.61 | BZ8: ='CAM-Nov2025'!H6 -> 283011.39
A9: 2 | B9: Technical manpower (% Share) | C9: ='CAM-Jun`23'!C7 -> 214572.12 | D9: ='CAM-Jul`23'!C7 -> 319159.81 | E9: ='CAM-Aug`23'!C7 -> 336939.16 | F9: ='CAM-Sep`23'!C7 -> 303890.86 | G9: ='CAM-Oct`23'!C7 -> 313903.64 | H9: ='CAM-Nov`23'!C7 -> 315254.99 | I9: ='CAM-Dec`23'!C7 -> 315466 | J9: ='CAM-Jan`24'!C6 -> 354076 | K9: ='CAM-Jan`24'!G6 -> 39190.932 | L9: ='CAM-Jan`24'!H6 -> 314885.07 | M9: ='CAM-Feb`24'!C6 -> 396050.84 | N9: ='CAM-Feb`24'!G6 -> 43836.92 | O9: ='CAM-Feb`24'!H6 -> 352213.92 | P9: ='CAM-Mar`24'!C7 -> 445788.92 | Q9: ='CAM-Mar`24'!G7 -> 49342.184 | R9: ='CAM-Mar`24'!H7 -> 396446.74 | S9: ='CAM-Apr`24'!C7 -> 449526 | T9: ='CAM-Apr`24'!G7 -> 49755.823 | U9: ='CAM-Apr`24'!H7 -> 399770.18 | V9: ='CAM-May`24'!C7 -> 442335.19 | W9: ='CAM-May`24'!G7 -> 48959.908 | X9: ='CAM-May`24'!H7 -> 393375.28 | Y9: ='CAM-Jun`24'!C7 -> 448502.68 | Z9: ='CAM-Jun`24'!G7 -> 49642.557 | AA9: ='CAM-Jun`24'!H7 -> 398860.12 | AB9: ='CAM-Jul`24'!C7 -> 434075 | AC9: ='CAM-Jul`24'!G7 -> 48045.628 | AD9: ='CAM-Jul`24'!H7 -> 386029.37 | AE9: ='CAM-Aug`24'!C7 -> 458568 | AF9: ='CAM-Aug`24'!G7 -> 50756.638 | AG9: ='CAM-Aug`24'!H7 -> 407811.36 | AH9: ='CAM-Sep`24'!C7 -> 454526.61 | AI9: ='CAM-Sep`24'!G7 -> 50309.316 | AJ9: ='CAM-Sep`24'!H7 -> 404217.29 | AK9: ='CAM-Oct`24'!C7 -> 451719.26 | AL9: ='CAM-Oct`24'!G7 -> 49998.584 | AM9: ='CAM-Oct`24'!H7 -> 401720.68 | AN9: ='CAM-Nov`24'!C7 -> 443919 | AO9: ='CAM-Nov`24'!G7 -> 49135.212 | AP9: ='CAM-Nov`24'!H7 -> 394783.79 | AQ9: ='CAM-Dec2024'!C7 -> 515108 | AR9: ='CAM-Dec2024'!G7 -> 57014.772 | AS9: ='CAM-Dec2024'!H7 -> 458093.23 | AT9: ='CAM-Jan2025'!C7 -> 473152 | AU9: ='CAM-Jan2025'!G7 -> 52370.869 | AV9: ='CAM-Jan2025'!H7 -> 420781.13 | AW9: ='CAM-Feb2025'!C7 -> 469303 | AX9: ='CAM-Feb2025'!G7 -> 51944.842 | AY9: ='CAM-Feb2025'!H7 -> 417358.16 | AZ9: ='CAM-Mar2025'!C7 -> 460044 | BA9: ='CAM-Mar2025'!G7 -> 50920.009 | BB9: ='CAM-Mar2025'!H7 -> 409123.99 | BC9: ='CAM-Apr2025'!C7 -> 438967 | BD9: ='CAM-Apr2025'!G7 -> 48587.099 | BE9: ='CAM-Apr2025'!H7 -> 390379.9 | BF9: ='CAM-May2025'!C7 -> 455320 | BG9: ='CAM-May2025'!G7 -> 50397.132 | BH9: ='CAM-May2025'!H7 -> 404922.87 | BI9: ='CAM-Jun2025'!C7 -> 467212 | BJ9: ='CAM-Jun2025'!G7 -> 51713.399 | BK9: ='CAM-Jun2025'!H7 -> 415498.6 | BL9: ='CAM-Jul2025'!C7 -> 513432 | BM9: ='CAM-Jul2025'!G7 -> 56829.264 | BN9: ='CAM-Jul2025'!H7 -> 456602.74 | BO9: ='CAM-Aug2025'!C7 -> 498816 | BP9: ='CAM-Aug2025'!G7 -> 55211.491 | BQ9: ='CAM-Aug2025'!H7 -> 443604.51 | BR9: ='CAM-Sep2025'!C7 -> 500685 | BS9: ='CAM-Sep2025'!G7 -> 55418.361 | BT9: ='CAM-Sep2025'!H7 -> 445266.64 | BU9: ='CAM-Oct2025'!C7 -> 481179 | BV9: ='CAM-Oct2025'!G7 -> 53259.338 | BW9: ='CAM-Oct2025'!H7 -> 427919.66 | BX9: ='CAM-Nov2025'!C7 -> 472384 | BY9: ='CAM-Nov2025'!G7 -> 52285.863 | BZ9: ='CAM-Nov2025'!H7 -> 420098.14
A10: 3 | B10: HK Manpower (% Share) | C10: ='CAM-Jun`23'!C8 -> 83898 | D10: ='CAM-Jul`23'!C8 -> 202650 | E10: ='CAM-Aug`23'!C8 -> 232689 | F10: ='CAM-Sep`23'!C8 -> 200251 | G10: ='CAM-Oct`23'!C8 -> 209224 | H10: ='CAM-Nov`23'!C8 -> 223858 | I10: ='CAM-Dec`23'!C8 -> 214010 | J10: ='CAM-Jan`24'!C7 -> 253952 | K10: ='CAM-Jan`24'!G7 -> 59296.015 | L10: ='CAM-Jan`24'!H7 -> 194655.99 | M10: ='CAM-Feb`24'!C7 -> 295625 | N10: ='CAM-Feb`24'!G7 -> 69026.368 | O10: ='CAM-Feb`24'!H7 -> 226598.63 | P10: ='CAM-Mar`24'!C8 -> 340210 | Q10: ='CAM-Mar`24'!G8 -> 79436.654 | R10: ='CAM-Mar`24'!H8 -> 260773.35 | S10: ='CAM-Apr`24'!C8 -> 310200 | T10: ='CAM-Apr`24'!G8 -> 72429.529 | U10: ='CAM-Apr`24'!H8 -> 237770.47 | V10: ='CAM-May`24'!C8 -> 354052 | W10: ='CAM-May`24'!G8 -> 82668.664 | X10: ='CAM-May`24'!H8 -> 271383.34 | Y10: ='CAM-Jun`24'!C8 -> 414000 | Z10: ='CAM-Jun`24'!G8 -> 96666.102 | AA10: ='CAM-Jun`24'!H8 -> 317333.9 | AB10: ='CAM-Jul`24'!C8 -> 389390 | AC10: ='CAM-Jul`24'!G8 -> 90919.84 | AD10: ='CAM-Jul`24'!H8 -> 298470.16 | AE10: ='CAM-Aug`24'!C8 -> 396600 | AF10: ='CAM-Aug`24'!G8 -> 92603.324 | AG10: ='CAM-Aug`24'!H8 -> 303996.68 | AH10: ='CAM-Sep`24'!C8 -> 380810 | AI10: ='CAM-Sep`24'!G8 -> 88916.47 | AJ10: ='CAM-Sep`24'!H8 -> 291893.53 | AK10: ='CAM-Oct`24'!C8 -> 414000 | AL10: ='CAM-Oct`24'!G8 -> 96666.102 | AM10: ='CAM-Oct`24'!H8 -> 317333.9 | AN10: ='CAM-Nov`24'!C8 -> 414000 | AO10: ='CAM-Nov`24'!G8 -> 96666.102 | AP10: ='CAM-Nov`24'!H8 -> 317333.9 | AQ10: ='CAM-Dec2024'!C8 -> 414000 | AR10: ='CAM-Dec2024'!G8 -> 96666.102 | AS10: ='CAM-Dec2024'!H8 -> 317333.9 | AT10: ='CAM-Jan2025'!C8 -> 524450.25 | AU10: ='CAM-Jan2025'!G8 -> 122455.46 | AV10: ='CAM-Jan2025'!H8 -> 401994.79 | AW10: ='CAM-Feb2025'!C8 -> 620526 | AX10: ='CAM-Feb2025'!G8 -> 144888.48 | AY10: ='CAM-Feb2025'!H8 -> 475637.52 | AZ10: ='CAM-Mar2025'!C8 -> 459584 | BA10: ='CAM-Mar2025'!G8 -> 107309.65 | BB10: ='CAM-Mar2025'!H8 -> 352274.35 | BC10: ='CAM-Apr2025'!C8 -> 612768 | BD10: ='CAM-Apr2025'!G8 -> 143077.04 | BE10: ='CAM-Apr2025'!H8 -> 469690.96 | BF10: ='CAM-May2025'!C8 -> 578143 | BG10: ='CAM-May2025'!G8 -> 134992.34 | BH10: ='CAM-May2025'!H8 -> 443150.66 | BI10: ='CAM-Jun2025'!C8 -> 458301 | BJ10: ='CAM-Jun2025'!G8 -> 107010.08 | BK10: ='CAM-Jun2025'!H8 -> 351290.92 | BL10: ='CAM-Jul2025'!C8 -> 745595 | BM10: ='CAM-Jul2025'!G8 -> 174091.21 | BN10: ='CAM-Jul2025'!H8 -> 571503.79 | BO10: ='CAM-Aug2025'!C8 -> 570028 | BP10: ='CAM-Aug2025'!G8 -> 133097.55 | BQ10: ='CAM-Aug2025'!H8 -> 436930.45 | BR10: ='CAM-Sep2025'!C8 -> 563243 | BS10: ='CAM-Sep2025'!G8 -> 131513.3 | BT10: ='CAM-Sep2025'!H8 -> 431729.7 | BU10: ='CAM-Oct2025'!C8 -> 587396 | BV10: ='CAM-Oct2025'!G8 -> 137152.85 | BW10: ='CAM-Oct2025'!H8 -> 450243.15 | BX10: ='CAM-Nov2025'!C8 -> 659735 | BY10: ='CAM-Nov2025'!G8 -> 154043.51 | BZ10: ='CAM-Nov2025'!H8 -> 505691.49
A11: 4 | B11: LP Manpower -Security Services (By Area) | C11: ='CAM-Jun`23'!C9 -> 158096 | D11: ='CAM-Jul`23'!C9 -> 581771.08 | E11: ='CAM-Aug`23'!C9 -> 605821.08 | F11: ='CAM-Sep`23'!C9 -> 674625.17 | G11: ='CAM-Oct`23'!C9 -> 660344.45 | H11: ='CAM-Nov`23'!C9 -> 637994.44 | I11: ='CAM-Dec`23'!C9 -> 660344 | J11: ='CAM-Jan`24'!C8 -> 751571 | K11: ='CAM-Jan`24'!G8 -> 256605.16 | L11: ='CAM-Jan`24'!H8 -> 494965.84 | M11: ='CAM-Feb`24'!C8 -> 776020.71 | N11: ='CAM-Feb`24'!G8 -> 264952.91 | O11: ='CAM-Feb`24'!H8 -> 511067.8 | P11: ='CAM-Mar`24'!C9 -> 680837.4 | Q11: ='CAM-Mar`24'!G9 -> 232454.94 | R11: ='CAM-Mar`24'!H9 -> 448382.46 | S11: ='CAM-Apr`24'!C9 -> 656106 | T11: ='CAM-Apr`24'!G9 -> 224011.02 | U11: ='CAM-Apr`24'!H9 -> 432094.98 | V11: ='CAM-May`24'!C9 -> 802542.26 | W11: ='CAM-May`24'!G9 -> 274008.03 | X11: ='CAM-May`24'!H9 -> 528534.23 | Y11: ='CAM-Jun`24'!C9 -> 675091 | Z11: ='CAM-Jun`24'!G9 -> 230492.98 | AA11: ='CAM-Jun`24'!H9 -> 444598.02 | AB11: ='CAM-Jul`24'!C9 -> 677635 | AC11: ='CAM-Jul`24'!G9 -> 231361.56 | AD11: ='CAM-Jul`24'!H9 -> 446273.44 | AE11: ='CAM-Aug`24'!C9 -> 729655 | AF11: ='CAM-Aug`24'!G9 -> 249122.49 | AG11: ='CAM-Aug`24'!H9 -> 480532.51 | AH11: ='CAM-Sep`24'!C9 -> 757772.45 | AI11: ='CAM-Sep`24'!G9 -> 258722.49 | AJ11: ='CAM-Sep`24'!H9 -> 499049.96 | AK11: ='CAM-Oct`24'!C9 -> 712510.19 | AL11: ='CAM-Oct`24'!G9 -> 243268.82 | AM11: ='CAM-Oct`24'!H9 -> 469241.37 | AN11: ='CAM-Nov`24'!C9 -> 728782.43 | AO11: ='CAM-Nov`24'!G9 -> 248824.57 | AP11: ='CAM-Nov`24'!H9 -> 479957.86 | AQ11: ='CAM-Dec2024'!C9 -> 760481 | AR11: ='CAM-Dec2024'!G9 -> 259647.26 | AS11: ='CAM-Dec2024'!H9 -> 500833.74 | AT11: ='CAM-Jan2025'!C9 -> 713053 | AU11: ='CAM-Jan2025'!G9 -> 243454.15 | AV11: ='CAM-Jan2025'!H9 -> 469598.85 | AW11: ='CAM-Feb2025'!C9 -> 685071 | AX11: ='CAM-Feb2025'!G9 -> 233900.4 | AY11: ='CAM-Feb2025'!H9 -> 451170.6 | AZ11: ='CAM-Mar2025'!C9 -> 753414 | BA11: ='CAM-Mar2025'!G9 -> 257234.41 | BB11: ='CAM-Mar2025'!H9 -> 496179.59 | BC11: ='CAM-Apr2025'!C9 -> 699771 | BD11: ='CAM-Apr2025'!G9 -> 238919.35 | BE11: ='CAM-Apr2025'!H9 -> 460851.65 | BF11: ='CAM-May2025'!C9 -> 825265 | BG11: ='CAM-May2025'!G9 -> 281766.14 | BH11: ='CAM-May2025'!H9 -> 543498.86 | BI11: ='CAM-Jun2025'!C9 -> 795848 | BJ11: ='CAM-Jun2025'!G9 -> 271722.44 | BK11: ='CAM-Jun2025'!H9 -> 524125.56 | BL11: ='CAM-Jul2025'!C9 -> 805517 | BM11: ='CAM-Jul2025'!G9 -> 275023.68 | BN11: ='CAM-Jul2025'!H9 -> 530493.32 | BO11: ='CAM-Aug2025'!C9 -> 812461 | BP11: ='CAM-Aug2025'!G9 -> 277394.53 | BQ11: ='CAM-Aug2025'!H9 -> 535066.47 | BR11: ='CAM-Sep2025'!C9 -> 816680 | BS11: ='CAM-Sep2025'!G9 -> 278835.01 | BT11: ='CAM-Sep2025'!H9 -> 537844.99 | BU11: ='CAM-Oct2025'!C9 -> 782706 | BV11: ='CAM-Oct2025'!G9 -> 267235.43 | BW11: ='CAM-Oct2025'!H9 -> 515470.57 | BX11: ='CAM-Nov2025'!C9 -> 683583 | BY11: ='CAM-Nov2025'!G9 -> 233392.36 | BZ11: ='CAM-Nov2025'!H9 -> 450190.64
A12: 5 | B12: AMC (By Area) | C12: ='CAM-Jun`23'!C10 -> 0 | D12: ='CAM-Jul`23'!C10 -> 5000 | E12: ='CAM-Aug`23'!C10 -> 50000 | F12: ='CAM-Sep`23'!C10 -> 50000 | G12: ='CAM-Oct`23'!C10 -> 56000 | H12: ='CAM-Nov`23'!C10 -> 56000 | I12: ='CAM-Dec`23'!C10 -> 56000 | J12: ='CAM-Jan`24'!C9 -> 56000 | K12: ='CAM-Jan`24'!G9 -> 19119.803 | L12: ='CAM-Jan`24'!H9 -> 36880.197 | M12: ='CAM-Feb`24'!C9 -> 56000 | N12: ='CAM-Feb`24'!G9 -> 19119.803 | O12: ='CAM-Feb`24'!H9 -> 36880.197 | P12: ='CAM-Mar`24'!C10 -> 56000 | Q12: ='CAM-Mar`24'!G10 -> 19119.803 | R12: ='CAM-Mar`24'!H10 -> 36880.197 | S12: ='CAM-Apr`24'!C10 -> 208000 | T12: ='CAM-Apr`24'!G10 -> 71016.41 | U12: ='CAM-Apr`24'!H10 -> 136983.59 | V12: ='CAM-May`24'!C10 -> 216000 | W12: ='CAM-May`24'!G10 -> 73747.81 | X12: ='CAM-May`24'!H10 -> 142252.19 | Y12: ='CAM-Jun`24'!C10 -> 136000 | Z12: ='CAM-Jun`24'!G10 -> 46433.806 | AA12: ='CAM-Jun`24'!H10 -> 89566.194 | AB12: ='CAM-Jul`24'!C10 -> 212462 | AC12: ='CAM-Jul`24'!G10 -> 72539.848 | AD12: ='CAM-Jul`24'!H10 -> 139922.15 | AE12: ='CAM-Aug`24'!C10 -> 136000 | AF12: ='CAM-Aug`24'!G10 -> 46433.806 | AG12: ='CAM-Aug`24'!H10 -> 89566.194 | AH12: ='CAM-Sep`24'!C10 -> 136000 | AI12: ='CAM-Sep`24'!G10 -> 46433.806 | AJ12: ='CAM-Sep`24'!H10 -> 89566.194 | AK12: ='CAM-Oct`24'!C10 -> 136000 | AL12: ='CAM-Oct`24'!G10 -> 46433.806 | AM12: ='CAM-Oct`24'!H10 -> 89566.194 | AN12: ='CAM-Nov`24'!C10 -> 368050 | AO12: ='CAM-Nov`24'!G10 -> 125661.49 | AP12: ='CAM-Nov`24'!H10 -> 242388.51 | AQ12: ='CAM-Dec2024'!C10 -> 280000 | AR12: ='CAM-Dec2024'!G10 -> 95599.013 | AS12: ='CAM-Dec2024'!H10 -> 184400.99 | AT12: ='CAM-Jan2025'!C10 -> 297850 | AU12: ='CAM-Jan2025'!G10 -> 101693.45 | AV12: ='CAM-Jan2025'!H10 -> 196156.55 | AW12: ='CAM-Feb2025'!C10 -> 161800 | AX12: ='CAM-Feb2025'!G10 -> 55242.572 | AY12: ='CAM-Feb2025'!H10 -> 106557.43 | AZ12: ='CAM-Mar2025'!C10 -> 165348 | BA12: ='CAM-Mar2025'!G10 -> 56453.949 | BB12: ='CAM-Mar2025'!H10 -> 108894.05 | BC12: ='CAM-Apr2025'!C10 -> 166800 | BD12: ='CAM-Apr2025'!G10 -> 56949.698 | BE12: ='CAM-Apr2025'!H10 -> 109850.3 | BF12: ='CAM-May2025'!C10 -> 236800 | BG12: ='CAM-May2025'!G10 -> 80849.451 | BH12: ='CAM-May2025'!H10 -> 155950.55 | BI12: ='CAM-Jun2025'!C10 -> 161497 | BJ12: ='CAM-Jun2025'!G10 -> 55139.121 | BK12: ='CAM-Jun2025'!H10 -> 106357.88 | BL12: ='CAM-Jul2025'!C10 -> 233897 | BM12: ='CAM-Jul2025'!G10 -> 79858.294 | BN12: ='CAM-Jul2025'!H10 -> 154038.71 | BO12: ='CAM-Aug2025'!C10 -> 163897 | BP12: ='CAM-Aug2025'!G10 -> 55958.541 | BQ12: ='CAM-Aug2025'!H10 -> 107938.46 | BR12: ='CAM-Sep2025'!C10 -> 157810 | BS12: ='CAM-Sep2025'!G10 -> 53880.287 | BT12: ='CAM-Sep2025'!H10 -> 103929.71 | BU12: ='CAM-Oct2025'!C10 -> 164040 | BV12: ='CAM-Oct2025'!G10 -> 56007.365 | BW12: ='CAM-Oct2025'!H10 -> 108032.64 | BX12: ='CAM-Nov2025'!C10 -> 207686 | BY12: ='CAM-Nov2025'!G10 -> 70909.202 | BZ12: ='CAM-Nov2025'!H10 -> 136776.8
A13: 6 | B13: AMC Excl. MCP | K13: ='CAM-Jan`24'!G10 -> 0 | L13: ='CAM-Jan`24'!H10 -> 0 | M13: ='CAM-Feb`24'!C10 -> 0 | N13: ='CAM-Feb`24'!G10 -> 0 | O13: ='CAM-Feb`24'!H10 -> 0 | P13: ='CAM-Mar`24'!C11 -> 0 | Q13: ='CAM-Mar`24'!G11 -> 0 | R13: ='CAM-Mar`24'!H11 -> 0 | S13: ='CAM-Apr`24'!C11 -> 0 | T13: ='CAM-Apr`24'!G11 -> 0 | U13: ='CAM-Apr`24'!H11 -> 0 | V13: ='CAM-May`24'!C11 -> 0 | W13: ='CAM-May`24'!G11 -> 0 | X13: ='CAM-May`24'!H11 -> 0 | Y13: ='CAM-Jun`24'!C11 -> 51573 | Z13: ='CAM-Jun`24'!G11 -> 0 | AA13: ='CAM-Jun`24'!H11 -> 51573 | AB13: ='CAM-Jul`24'!C11 -> 55573 | AC13: ='CAM-Jul`24'!G11 -> 0 | AD13: ='CAM-Jul`24'!H11 -> 55573 | AE13: ='CAM-Aug`24'!C11 -> 55573 | AF13: ='CAM-Aug`24'!G11 -> 0 | AG13: ='CAM-Aug`24'!H11 -> 55573 | AH13: ='CAM-Sep`24'!C11 -> 36451.35 | AI13: ='CAM-Sep`24'!G11 -> 0 | AJ13: ='CAM-Sep`24'!H11 -> 36451.35 | AK13: ='CAM-Oct`24'!C11 -> 9917.52 | AL13: ='CAM-Oct`24'!G11 -> 0 | AM13: ='CAM-Oct`24'!H11 -> 9917.52 | AN13: ='CAM-Nov`24'!C11 -> 29341 | AO13: ='CAM-Nov`24'!G11 -> 0 | AP13: ='CAM-Nov`24'!H11 -> 29341 | AQ13: ='CAM-Dec2024'!C11 -> 48384.5 | AR13: ='CAM-Dec2024'!G11 -> 0 | AS13: ='CAM-Dec2024'!H11 -> 48384.5 | AT13: ='CAM-Jan2025'!C11 -> 22850 | AU13: ='CAM-Jan2025'!G11 -> 0 | AV13: ='CAM-Jan2025'!H11 -> 22850 | AW13: ='CAM-Feb2025'!C11 -> 38461.4 | AX13: ='CAM-Feb2025'!G11 -> 0 | AY13: ='CAM-Feb2025'!H11 -> 38461.4 | AZ13: ='CAM-Mar2025'!C11 -> 34898 | BA13: ='CAM-Mar2025'!G11 -> 0 | BB13: ='CAM-Mar2025'!H11 -> 34898 | BC13: ='CAM-Apr2025'!C11 -> 36970 | BD13: ='CAM-Apr2025'!G11 -> 0 | BE13: ='CAM-Apr2025'!H11 -> 36970 | BF13: ='CAM-May2025'!C11 -> 41110 | BG13: ='CAM-May2025'!G11 -> 0 | BH13: ='CAM-May2025'!H11 -> 41110 | BI13: ='CAM-Jun2025'!C11 -> 36970 | BJ13: ='CAM-Jun2025'!G11 -> 0 | BK13: ='CAM-Jun2025'!H11 -> 36970 | BL13: ='CAM-Jul2025'!C11 -> 39169 | BM13: ='CAM-Jul2025'!G11 -> 0 | BN13: ='CAM-Jul2025'!H11 -> 39169 | BO13: ='CAM-Aug2025'!C11 -> 34750 | BP13: ='CAM-Aug2025'!G11 -> 0 | BQ13: ='CAM-Aug2025'!H11 -> 34750 | BR13: ='CAM-Sep2025'!C11 -> 39195 | BS13: ='CAM-Sep2025'!G11 -> 0 | BT13: ='CAM-Sep2025'!H11 -> 39195 | BU13: ='CAM-Oct2025'!C11 -> 39195 | BV13: ='CAM-Oct2025'!G11 -> 0 | BW13: ='CAM-Oct2025'!H11 -> 39195 | BX13: ='CAM-Nov2025'!C11 -> 40490 | BY13: ='CAM-Nov2025'!G11 -> 0 | BZ13: ='CAM-Nov2025'!H11 -> 40490
A14: 7 | B14: Consumables (HK %Share) | C14: ='CAM-Jun`23'!C11 -> 0 | D14: ='CAM-Jul`23'!C11 -> 0 | E14: ='CAM-Aug`23'!C11 -> 10917 | F14: ='CAM-Sep`23'!C11 -> 0 | G14: ='CAM-Oct`23'!C11 -> 12164 | H14: ='CAM-Nov`23'!C11 -> 24951 | I14: ='CAM-Dec`23'!C11 -> 52361 | J14: ='CAM-Jan`24'!C11 -> 0 | K14: ='CAM-Jan`24'!G11 -> 0 | L14: ='CAM-Jan`24'!H11 -> 0 | M14: ='CAM-Feb`24'!C11 -> 22313 | N14: ='CAM-Feb`24'!G11 -> 5209.9293 | O14: ='CAM-Feb`24'!H11 -> 17103.071 | P14: ='CAM-Mar`24'!C12 -> 0 | Q14: ='CAM-Mar`24'!G12 -> 0 | R14: ='CAM-Mar`24'!H12 -> 0 | S14: ='CAM-Apr`24'!C12 -> 0 | T14: ='CAM-Apr`24'!G12 -> 0 | U14: ='CAM-Apr`24'!H12 -> 0 | V14: ='CAM-May`24'!C12 -> 0 | W14: ='CAM-May`24'!G12 -> 0 | X14: ='CAM-May`24'!H12 -> 0 | Y14: ='CAM-Jun`24'!C12 -> 1357 | Z14: ='CAM-Jun`24'!G12 -> 316.85 | AA14: ='CAM-Jun`24'!H12 -> 1040.15 | AB14: ='CAM-Jul`24'!C12 -> 0 | AC14: ='CAM-Jul`24'!G12 -> 0 | AD14: ='CAM-Jul`24'!H12 -> 0 | AE14: ='CAM-Aug`24'!C12 -> 76819 | AF14: ='CAM-Aug`24'!G12 -> 17936.699 | AG14: ='CAM-Aug`24'!H12 -> 58882.301 | AH14: ='CAM-Sep`24'!C12 -> 0 | AI14: ='CAM-Sep`24'!G12 -> 0 | AJ14: ='CAM-Sep`24'!H12 -> 0 | AK14: ='CAM-Oct`24'!C12 -> 40138 | AL14: ='CAM-Oct`24'!G12 -> 9371.9421 | AM14: ='CAM-Oct`24'!H12 -> 30766.058 | AN14: ='CAM-Nov`24'!C12 -> 57124 | AO14: ='CAM-Nov`24'!G12 -> 13338.054 | AP14: ='CAM-Nov`24'!H12 -> 43785.946 | AQ14: ='CAM-Dec2024'!C12 -> 11818 | AR14: ='CAM-Dec2024'!G12 -> 2759.4203 | AS14: ='CAM-Dec2024'!H12 -> 9058.5797 | AT14: ='CAM-Jan2025'!C12 -> 95212 | AU14: ='CAM-Jan2025'!G12 -> 22231.336 | AV14: ='CAM-Jan2025'!H12 -> 72980.664 | AW14: ='CAM-Feb2025'!C12 -> 85319.08 | AX14: ='CAM-Feb2025'!G12 -> 19921.408 | AY14: ='CAM-Feb2025'!H12 -> 65397.672 | AZ14: ='CAM-Mar2025'!C12 -> 250985 | BA14: ='CAM-Mar2025'!G12 -> 58603.241 | BB14: ='CAM-Mar2025'!H12 -> 192381.76 | BC14: ='CAM-Apr2025'!C12 -> 0 | BD14: ='CAM-Apr2025'!G12 -> 0 | BE14: ='CAM-Apr2025'!H12 -> 0 | BF14: ='CAM-May2025'!C12 -> 0 | BG14: ='CAM-May2025'!G12 -> 0 | BH14: ='CAM-May2025'!H12 -> 0 | BI14: ='CAM-Jun2025'!C12 -> 2055 | BJ14: ='CAM-Jun2025'!G12 -> 479.82812 | BK14: ='CAM-Jun2025'!H12 -> 1575.1719 | BL14: ='CAM-Jul2025'!C12 -> 0 | BM14: ='CAM-Jul2025'!G12 -> 0 | BN14: ='CAM-Jul2025'!H12 -> 0 | BO14: ='CAM-Aug2025'!C12 -> 182353 | BP14: ='CAM-Aug2025'!G12 -> 42578.149 | BQ14: ='CAM-Aug2025'!H12 -> 139774.85 | BR14: ='CAM-Sep2025'!C12 -> 0 | BS14: ='CAM-Sep2025'!G12 -> 0 | BT14: ='CAM-Sep2025'!H12 -> 0 | BU14: ='CAM-Oct2025'!C12 -> 0 | BV14: ='CAM-Oct2025'!G12 -> 0 | BW14: ='CAM-Oct2025'!H12 -> 0 | BX14: ='CAM-Nov2025'!C12 -> 92619 | BY14: ='CAM-Nov2025'!G12 -> 21625.888 | BZ14: ='CAM-Nov2025'!H12 -> 70993.112
A15: 8 | B15: Cousumables Excl MCP | K15: ='CAM-Jan`24'!G12 -> 0 | L15: ='CAM-Jan`24'!H12 -> 0 | M15: ='CAM-Feb`24'!C12 -> 0 | N15: ='CAM-Feb`24'!G12 -> 0 | O15: ='CAM-Feb`24'!H12 -> 0 | P15: ='CAM-Mar`24'!C13 -> 0 | Q15: ='CAM-Mar`24'!G13 -> 0 | R15: ='CAM-Mar`24'!H13 -> 0 | S15: ='CAM-Apr`24'!C13 -> 0 | T15: ='CAM-Apr`24'!G13 -> 0 | U15: ='CAM-Apr`24'!H13 -> 0 | V15: ='CAM-May`24'!C13 -> 0 | W15: ='CAM-May`24'!G13 -> 0 | X15: ='CAM-May`24'!H13 -> 0 | Y15: ='CAM-Jun`24'!C13 -> 0 | Z15: ='CAM-Jun`24'!G13 -> 0 | AA15: ='CAM-Jun`24'!H13 -> 0 | AB15: ='CAM-Jul`24'!C13 -> 227385 | AC15: ='CAM-Jul`24'!G13 -> 0 | AD15: ='CAM-Jul`24'!H13 -> 227385 | AE15: ='CAM-Aug`24'!C13 -> 0 | AF15: ='CAM-Aug`24'!G13 -> 0 | AG15: ='CAM-Aug`24'!H13 -> 0 | AH15: ='CAM-Sep`24'!C13 -> 0 | AI15: ='CAM-Sep`24'!G13 -> 0 | AJ15: ='CAM-Sep`24'!H13 -> 0 | AK15: ='CAM-Oct`24'!C13 -> 17600 | AL15: ='CAM-Oct`24'!G13 -> 0 | AM15: ='CAM-Oct`24'!H13 -> 17600 | AN15: ='CAM-Nov`24'!C13 -> 400425 | AO15: ='CAM-Nov`24'!G13 -> 0 | AP15: ='CAM-Nov`24'!H13 -> 400425 | AQ15: ='CAM-Dec2024'!C13 -> 146926 | AR15: ='CAM-Dec2024'!G13 -> 0 | AS15: ='CAM-Dec2024'!H13 -> 146926 | AT15: ='CAM-Jan2025'!C13 -> 0 | AU15: ='CAM-Jan2025'!G13 -> 0 | AV15: ='CAM-Jan2025'!H13 -> 0 | AW15: ='CAM-Feb2025'!C13 -> 0 | AX15: ='CAM-Feb2025'!G13 -> 0 | AY15: ='CAM-Feb2025'!H13 -> 0 | AZ15: ='CAM-Mar2025'!C13 -> 0 | BA15: ='CAM-Mar2025'!G13 -> 0 | BB15: ='CAM-Mar2025'!H13 -> 0 | BC15: ='CAM-Apr2025'!C13 -> 0 | BD15: ='CAM-Apr2025'!G13 -> 0 | BE15: ='CAM-Apr2025'!H13 -> 0 | BF15: ='CAM-May2025'!C13 -> 0 | BG15: ='CAM-May2025'!G13 -> 0 | BH15: ='CAM-May2025'!H13 -> 0 | BI15: ='CAM-Jun2025'!C13 -> 0 | BJ15: ='CAM-Jun2025'!G13 -> 0 | BK15: ='CAM-Jun2025'!H13 -> 0 | BL15: ='CAM-Jul2025'!C13 -> 0 | BM15: ='CAM-Jul2025'!G13 -> 0 | BN15: ='CAM-Jul2025'!H13 -> 0 | BO15: ='CAM-Aug2025'!C13 -> 0 | BP15: ='CAM-Aug2025'!G13 -> 0 | BQ15: ='CAM-Aug2025'!H13 -> 0 | BR15: ='CAM-Sep2025'!C13 -> 0 | BS15: ='CAM-Sep2025'!G13 -> 0 | BT15: ='CAM-Sep2025'!H13 -> 0 | BU15: ='CAM-Oct2025'!C13 -> 0 | BV15: ='CAM-Oct2025'!G13 -> 0 | BW15: ='CAM-Oct2025'!H13 -> 0 | BX15: ='CAM-Nov2025'!C13 -> 0 | BY15: ='CAM-Nov2025'!G13 -> 0 | BZ15: ='CAM-Nov2025'!H13 -> 0
A16: 9 | B16: Common area Electrical & DG Charges (Tech %Share) | C16: ='CAM-Jun`23'!C12 -> 0 | D16: ='CAM-Jul`23'!C12 -> 178245.6 | E16: ='CAM-Aug`23'!C12 -> 168132.03 | F16: ='CAM-Sep`23'!C12 -> 284860.14 | G16: ='CAM-Oct`23'!C12 -> 526913.85 | H16: ='CAM-Nov`23'!C12 -> 789696.42 | I16: ='CAM-Dec`23'!C12 -> 861105.07 | J16: ='CAM-Jan`24'!C13 -> 1057296.1 | K16: ='CAM-Jan`24'!G13 -> 117026.91 | L16: ='CAM-Jan`24'!H13 -> 940269.21 | M16: ='CAM-Feb`24'!C13 -> 711634.4 | N16: ='CAM-Feb`24'!G13 -> 78767.313 | O16: ='CAM-Feb`24'!H13 -> 632867.09 | P16: ='CAM-Mar`24'!C14 -> 717978.53 | Q16: ='CAM-Mar`24'!G14 -> 79469.514 | R16: ='CAM-Mar`24'!H14 -> 638509.02 | S16: ='CAM-Apr`24'!C14 -> 851696.18 | T16: ='CAM-Apr`24'!G14 -> 94270.063 | U16: ='CAM-Apr`24'!H14 -> 757426.12 | V16: ='CAM-May`24'!C14 -> 1003807 | W16: ='CAM-May`24'!G14 -> 111106.46 | X16: ='CAM-May`24'!H14 -> 892700.5 | Y16: ='CAM-Jun`24'!C14 -> 871712.07 | Z16: ='CAM-Jun`24'!G14 -> 96485.524 | AA16: ='CAM-Jun`24'!H14 -> 775226.55 | AB16: ='CAM-Jul`24'!C14 -> 513702.2 | AC16: ='CAM-Jul`24'!G14 -> 56859.172 | AD16: ='CAM-Jul`24'!H14 -> 456843.03 | AE16: ='CAM-Aug`24'!C14 -> 473811.31 | AF16: ='CAM-Aug`24'!G14 -> 52443.844 | AG16: ='CAM-Aug`24'!H14 -> 421367.46 | AH16: ='CAM-Sep`24'!C14 -> 626737.2 | AI16: ='CAM-Sep`24'!G14 -> 69370.459 | AJ16: ='CAM-Sep`24'!H14 -> 557366.74 | AK16: ='CAM-Oct`24'!C14 -> 689066.23 | AL16: ='CAM-Oct`24'!G14 -> 76269.353 | AM16: ='CAM-Oct`24'!H14 -> 612796.87 | AN16: ='CAM-Nov`24'!C14 -> 624688 | AO16: ='CAM-Nov`24'!G14 -> 69143.644 | AP16: ='CAM-Nov`24'!H14 -> 555544.36 | AQ16: ='CAM-Dec2024'!C14 -> 715350 | AR16: ='CAM-Dec2024'!G14 -> 79178.575 | AS16: ='CAM-Dec2024'!H14 -> 636171.43 | AT16: ='CAM-Jan2025'!C14 -> 686502 | AU16: ='CAM-Jan2025'!G14 -> 75985.531 | AV16: ='CAM-Jan2025'!H14 -> 610516.47 | AW16: ='CAM-Feb2025'!C14 -> 672812 | AX16: ='CAM-Feb2025'!G14 -> 74470.253 | AY16: ='CAM-Feb2025'!H14 -> 598341.75 | AZ16: ='CAM-Mar2025'!C14 -> 703950 | BA16: ='CAM-Mar2025'!G14 -> 77916.765 | BB16: ='CAM-Mar2025'!H14 -> 626033.24 | BC16: ='CAM-Apr2025'!C14 -> 1030521.2 | BD16: ='CAM-Apr2025'!G14 -> 114063.32 | BE16: ='CAM-Apr2025'!H14 -> 916457.84 | BF16: ='CAM-May2025'!C14 -> 1355682.9 | BG16: ='CAM-May2025'!G14 -> 150053.88 | BH16: ='CAM-May2025'!H14 -> 1205629.1 | BI16: ='CAM-Jun2025'!C14 -> 1063539.5 | BJ16: ='CAM-Jun2025'!G14 -> 117717.96 | BK16: ='CAM-Jun2025'!H14 -> 945821.52 | BL16: ='CAM-Jul2025'!C14 -> 1117852.3 | BM16: ='CAM-Jul2025'!G14 -> 123729.58 | BN16: ='CAM-Jul2025'!H14 -> 994122.76 | BO16: ='CAM-Aug2025'!C14 -> 1076658.6 | BP16: ='CAM-Aug2025'!G14 -> 119170.05 | BQ16: ='CAM-Aug2025'!H14 -> 957488.59 | BR16: ='CAM-Sep2025'!C14 -> 1020375.7 | BS16: ='CAM-Sep2025'!G14 -> 112940.36 | BT16: ='CAM-Sep2025'!H14 -> 907435.29 | BU16: ='CAM-Oct2025'!C14 -> 1011739.5 | BV16: ='CAM-Oct2025'!G14 -> 111984.47 | BW16: ='CAM-Oct2025'!H14 -> 899754.99 | BX16: ='CAM-Nov2025'!C14 -> 1159983.9 | BY16: ='CAM-Nov2025'!G14 -> 128392.92 | BZ16: ='CAM-Nov2025'!H14 -> 1031591
A17: 10 | B17: Common area Water charges (By Area) | C17: ='CAM-Jun`23'!C13+'CAM-Jun`23'!C14 -> 57300 | D17: ='CAM-Jul`23'!C13+'CAM-Jul`23'!C14 -> 37600 | E17: ='CAM-Aug`23'!C13+'CAM-Aug`23'!C14 -> 45600 | F17: ='CAM-Sep`23'!C13+'CAM-Sep`23'!C14 -> 520150 | G17: ='CAM-Oct`23'!C13 -> 330345.92 | H17: ='CAM-Nov`23'!C13+'CAM-Nov`23'!C14 -> 328579.18 | I17: ='CAM-Dec`23'!C13 -> 259757.67 | J17: ='CAM-Jan`24'!C14 -> 266239 | K17: ='CAM-Jan`24'!G14 -> 90900.663 | L17: ='CAM-Jan`24'!H14 -> 175338.34 | M17: ='CAM-Feb`24'!C14 -> 113524.21 | N17: ='CAM-Feb`24'!G14 -> 38760.008 | O17: ='CAM-Feb`24'!H14 -> 74764.201 | P17: ='CAM-Mar`24'!C15 -> 162762.8 | Q17: ='CAM-Mar`24'!G15 -> 55571.298 | R17: ='CAM-Mar`24'!H15 -> 107191.51 | S17: ='CAM-Apr`24'!C15 -> 33504.107 | T17: ='CAM-Apr`24'!G15 -> 11439.141 | U17: ='CAM-Apr`24'!H15 -> 22064.965 | V17: ='CAM-May`24'!C15 -> 148083.11 | W17: ='CAM-May`24'!G15 -> 50559.284 | X17: ='CAM-May`24'!H15 -> 97523.83 | Y17: ='CAM-Jun`24'!C15 -> 143709.15 | Z17: ='CAM-Jun`24'!G15 -> 49065.904 | AA17: ='CAM-Jun`24'!H15 -> 94643.248 | AB17: ='CAM-Jul`24'!C15 -> 52054.886 | AC17: ='CAM-Jul`24'!G15 -> 17772.842 | AD17: ='CAM-Jul`24'!H15 -> 34282.044 | AE17: ='CAM-Aug`24'!C15 -> 34080.308 | AF17: ='CAM-Aug`24'!G15 -> 11635.871 | AG17: ='CAM-Aug`24'!H15 -> 22444.438 | AH17: ='CAM-Sep`24'!C15 -> 61593.64 | AI17: ='CAM-Sep`24'!G15 -> 21029.612 | AJ17: ='CAM-Sep`24'!H15 -> 40564.029 | AK17: ='CAM-Oct`24'!C15 -> 68044.61 | AL17: ='CAM-Oct`24'!G15 -> 23232.134 | AM17: ='CAM-Oct`24'!H15 -> 44812.476 | AN17: ='CAM-Nov`24'!C15 -> 0 | AO17: ='CAM-Nov`24'!G15 -> 0 | AP17: ='CAM-Nov`24'!H15 -> 0 | AQ17: ='CAM-Dec2024'!C15 -> 34200 | AR17: ='CAM-Dec2024'!G15 -> 11676.737 | AS17: ='CAM-Dec2024'!H15 -> 22523.263 | AT17: ='CAM-Jan2025'!C15 -> 34200 | AU17: ='CAM-Jan2025'!G15 -> 11676.737 | AV17: ='CAM-Jan2025'!H15 -> 22523.263 | AW17: ='CAM-Feb2025'!C15 -> 154331.45 | AX17: ='CAM-Feb2025'!G15 -> 52692.622 | AY17: ='CAM-Feb2025'!H15 -> 101638.83 | AZ17: ='CAM-Mar2025'!C15 -> 188077.27 | BA17: ='CAM-Mar2025'!G15 -> 64214.291 | BB17: ='CAM-Mar2025'!H15 -> 123862.98 | BC17: ='CAM-Apr2025'!C15 -> 312510.88 | BD17: ='CAM-Apr2025'!G15 -> 106699.04 | BE17: ='CAM-Apr2025'!H15 -> 205811.84 | BF17: ='CAM-May2025'!C15 -> 343334.06 | BG17: ='CAM-May2025'!G15 -> 117222.85 | BH17: ='CAM-May2025'!H15 -> 226111.21 | BI17: ='CAM-Jun2025'!C15 -> 263062.96 | BJ17: ='CAM-Jun2025'!G15 -> 89816.285 | BK17: ='CAM-Jun2025'!H15 -> 173246.68 | BL17: ='CAM-Jul2025'!C15 -> 241906.6 | BM17: ='CAM-Jul2025'!G15 -> 82592.972 | BN17: ='CAM-Jul2025'!H15 -> 159313.63 | BO17: ='CAM-Aug2025'!C15 -> 176530.46 | BP17: ='CAM-Aug2025'!G15 -> 60271.92 | BQ17: ='CAM-Aug2025'!H15 -> 116258.54 | BR17: ='CAM-Sep2025'!C15 -> 202787.55 | BS17: ='CAM-Sep2025'!G15 -> 69236.748 | BT17: ='CAM-Sep2025'!H15 -> 133550.8 | BU17: ='CAM-Oct2025'!C15 -> 175440.28 | BV17: ='CAM-Oct2025'!G15 -> 59899.707 | BW17: ='CAM-Oct2025'!H15 -> 115540.58 | BX17: ='CAM-Nov2025'!C15 -> 43988.83 | BY17: ='CAM-Nov2025'!G15 -> 15018.888 | BZ17: ='CAM-Nov2025'!H15 -> 28969.942
A18: 11 | B18: Cooling Tower water charges | C18: 0 | D18: 0 | E18: 0 | F18: 0 | G18: ='CAM-Oct`23'!C14 -> 0 | H18: 0 | I18: ='CAM-Dec`23'!C14 -> 0 | J18: ='CAM-Jan`24'!C15 -> 0 | K18: ='CAM-Jan`24'!G15 -> 0 | L18: ='CAM-Jan`24'!H15 -> 0 | M18: ='CAM-Feb`24'!C15 -> 67711.797 | N18: ='CAM-Feb`24'!G15 -> 0 | O18: ='CAM-Feb`24'!H15 -> 67711.797 | P18: ='CAM-Mar`24'!C16 -> 74116.594 | Q18: ='CAM-Mar`24'!G16 -> 0 | R18: ='CAM-Mar`24'!H16 -> 74116.594 | S18: ='CAM-Apr`24'!C16 -> 88436.076 | T18: ='CAM-Apr`24'!G16 -> 0 | U18: ='CAM-Apr`24'!H16 -> 88436.076 | V18: ='CAM-May`24'!C16 -> 75471.353 | W18: ='CAM-May`24'!G16 -> 0 | X18: ='CAM-May`24'!H16 -> 75471.353 | Y18: ='CAM-Jun`24'!C16 -> 58457.53 | Z18: ='CAM-Jun`24'!G16 -> 0 | AA18: ='CAM-Jun`24'!H16 -> 58457.53 | AB18: ='CAM-Jul`24'!C16 -> 55572.864 | AC18: ='CAM-Jul`24'!G16 -> 0 | AD18: ='CAM-Jul`24'!H16 -> 55572.864 | AE18: ='CAM-Aug`24'!C16 -> 64304.065 | AF18: ='CAM-Aug`24'!G16 -> 0 | AG18: ='CAM-Aug`24'!H16 -> 64304.065 | AH18: ='CAM-Sep`24'!C16 -> 58043.79 | AI18: ='CAM-Sep`24'!G16 -> 0 | AJ18: ='CAM-Sep`24'!H16 -> 58043.79 | AK18: ='CAM-Oct`24'!C16 -> 61158.9 | AL18: ='CAM-Oct`24'!G16 -> 0 | AM18: ='CAM-Oct`24'!H16 -> 61158.9 | AN18: ='CAM-Nov`24'!C16 -> 84261.115 | AO18: ='CAM-Nov`24'!G16 -> 0 | AP18: ='CAM-Nov`24'!H16 -> 84261.115 | AQ18: ='CAM-Dec2024'!C16 -> 30788.55 | AR18: ='CAM-Dec2024'!G16 -> 0 | AS18: ='CAM-Dec2024'!H16 -> 30788.55 | AT18: ='CAM-Jan2025'!C16 -> 23946.65 | AU18: ='CAM-Jan2025'!G16 -> 0 | AV18: ='CAM-Jan2025'!H16 -> 23946.65 | AW18: ='CAM-Feb2025'!C16 -> 23946.65 | AX18: ='CAM-Feb2025'!G16 -> 0 | AY18: ='CAM-Feb2025'!H16 -> 23946.65 | AZ18: ='CAM-Mar2025'!C16 -> 23946.65 | BA18: ='CAM-Mar2025'!G16 -> 0 | BB18: ='CAM-Mar2025'!H16 -> 23946.65 | BC18: ='CAM-Apr2025'!C16 -> 103528.75 | BD18: ='CAM-Apr2025'!G16 -> 0 | BE18: ='CAM-Apr2025'!H16 -> 103528.75 | BF18: ='CAM-May2025'!C16 -> 73820.5 | BG18: ='CAM-May2025'!G16 -> 0 | BH18: ='CAM-May2025'!H16 -> 73820.5 | BI18: ='CAM-Jun2025'!C16 -> 92365.65 | BJ18: ='CAM-Jun2025'!G16 -> 0 | BK18: ='CAM-Jun2025'!H16 -> 92365.65 | BL18: ='CAM-Jul2025'!C16 -> 86784.1 | BM18: ='CAM-Jul2025'!G16 -> 0 | BN18: ='CAM-Jul2025'!H16 -> 86784.1 | BO18: ='CAM-Aug2025'!C16 -> 83183.1 | BP18: ='CAM-Aug2025'!G16 -> 0 | BQ18: ='CAM-Aug2025'!H16 -> 83183.1 | BR18: ='CAM-Sep2025'!C16 -> 82823 | BS18: ='CAM-Sep2025'!G16 -> 0 | BT18: ='CAM-Sep2025'!H16 -> 82823 | BU18: ='CAM-Oct2025'!C16 -> 78861.9 | BV18: ='CAM-Oct2025'!G16 -> 0 | BW18: ='CAM-Oct2025'!H16 -> 78861.9 | BX18: ='CAM-Nov2025'!C16 -> 85163.65 | BY18: ='CAM-Nov2025'!G16 -> 0 | BZ18: ='CAM-Nov2025'!H16 -> 85163.65
A19: 12 | B19: FMS Cost (By Area) | C19: ='CAM-Jun`23'!C15 -> 297146 | D19: ='CAM-Jul`23'!C15 -> 297146 | E19: ='CAM-Aug`23'!C15 -> 297146 | F19: ='CAM-Sep`23'!C15 -> 297146 | G19: ='CAM-Oct`23'!C15 -> 297146 | H19: ='CAM-Nov`23'!C15 -> 63596 | I19: ='CAM-Dec`23'!C15 -> 79603 | J19: ='CAM-Jan`24'!C16 -> 15769 | K19: ='CAM-Jan`24'!G16 -> 5383.9316 | L19: ='CAM-Jan`24'!H16 -> 10385.068 | M19: ='CAM-Feb`24'!C16 -> 115790 | N19: ='CAM-Feb`24'!G16 -> 39533.606 | O19: ='CAM-Feb`24'!H16 -> 76256.394 | P19: ='CAM-Mar`24'!C17 -> 0 | Q19: ='CAM-Mar`24'!G17 -> 0 | R19: ='CAM-Mar`24'!H17 -> 0 | S19: ='CAM-Apr`24'!C17 -> 12545 | T19: ='CAM-Apr`24'!G17 -> 4283.1772 | U19: ='CAM-Apr`24'!H17 -> 8261.8228 | V19: ='CAM-May`24'!C17 -> 118711.7 | W19: ='CAM-May`24'!G17 -> 40531.148 | X19: ='CAM-May`24'!H17 -> 78180.552 | Y19: ='CAM-Jun`24'!C17 -> 117371.7 | Z19: ='CAM-Jun`24'!G17 -> 40073.638 | AA19: ='CAM-Jun`24'!H17 -> 77298.062 | AB19: ='CAM-Jul`24'!C17 -> 127471.7 | AC19: ='CAM-Jul`24'!G17 -> 43522.031 | AD19: ='CAM-Jul`24'!H17 -> 83949.669 | AE19: ='CAM-Aug`24'!C17 -> 32117 | AF19: ='CAM-Aug`24'!G17 -> 10965.548 | AG19: ='CAM-Aug`24'!H17 -> 21151.452 | AH19: ='CAM-Sep`24'!C17 -> 135962 | AI19: ='CAM-Sep`24'!G17 -> 46420.832 | AJ19: ='CAM-Sep`24'!H17 -> 89541.168 | AK19: ='CAM-Oct`24'!C17 -> 270711 | AL19: ='CAM-Oct`24'!G17 -> 92427.516 | AM19: ='CAM-Oct`24'!H17 -> 178283.48 | AN19: ='CAM-Nov`24'!C17 -> 171429 | AO19: ='CAM-Nov`24'!G17 -> 58530.154 | AP19: ='CAM-Nov`24'!H17 -> 112898.85 | AQ19: ='CAM-Dec2024'!C17 -> 101190 | AR19: ='CAM-Dec2024'!G17 -> 34548.8 | AS19: ='CAM-Dec2024'!H17 -> 66641.2 | AT19: ='CAM-Jan2025'!C17 -> 88012 | AU19: ='CAM-Jan2025'!G17 -> 0 | AV19: ='CAM-Jan2025'!H17 -> 88012 | AW19: ='CAM-Feb2025'!C17 -> 28236.32 | AX19: ='CAM-Feb2025'!G17 -> 0 | AY19: ='CAM-Feb2025'!H17 -> 28236.32 | AZ19: ='CAM-Mar2025'!C17 -> 237547.97 | BA19: ='CAM-Mar2025'!G17 -> 0 | BB19: ='CAM-Mar2025'!H17 -> 237547.97 | BC19: ='CAM-Apr2025'!C17 -> 414446 | BD19: ='CAM-Apr2025'!G17 -> 0 | BE19: ='CAM-Apr2025'!H17 -> 414446 | BF19: ='CAM-May2025'!C17 -> 264208 | BG19: ='CAM-May2025'!G17 -> 0 | BH19: ='CAM-May2025'!H17 -> 264208 | BI19: ='CAM-Jun2025'!C17 -> 263190 | BJ19: ='CAM-Jun2025'!G17 -> 0 | BK19: ='CAM-Jun2025'!H17 -> 263190 | BL19: ='CAM-Jul2025'!C17 -> 268739 | BM19: ='CAM-Jul2025'!G17 -> 0 | BN19: ='CAM-Jul2025'!H17 -> 268739 | BO19: ='CAM-Aug2025'!C17 -> 405875 | BP19: ='CAM-Aug2025'!G17 -> 0 | BQ19: ='CAM-Aug2025'!H17 -> 405875 | BR19: ='CAM-Sep2025'!C17 -> 349551.41 | BS19: ='CAM-Sep2025'!G17 -> 0 | BT19: ='CAM-Sep2025'!H17 -> 349551.41 | BU19: ='CAM-Oct2025'!C17 -> 437030 | BV19: ='CAM-Oct2025'!G17 -> 0 | BW19: ='CAM-Oct2025'!H17 -> 437030 | BX19: ='CAM-Nov2025'!C17 -> 140585 | BY19: ='CAM-Nov2025'!G17 -> 0 | BZ19: ='CAM-Nov2025'!H17 -> 140585
A20: 13 | B20: Liosaning & Licenses (By Area) (Building Insurance, Fire audit, Electrical Inspections, PCB, etc). | C20: ='CAM-Jun`23'!C16 -> 794231 | D20: ='CAM-Jul`23'!C16 -> 25000 | E20: ='CAM-Aug`23'!C16 -> 25000 | F20: ='CAM-Sep`23'!C16 -> 25000 | G20: ='CAM-Oct`23'!C16 -> 25000 | H20: ='CAM-Nov`23'!C16 -> 51250 | I20: ='CAM-Dec`23'!C16 -> 77500 | J20: ='CAM-Jan`24'!C17 -> 0 | K20: ='CAM-Jan`24'!G17 -> 0 | L20: ='CAM-Jan`24'!H17 -> 0 | M20: ='CAM-Feb`24'!C17 -> 0 | N20: ='CAM-Feb`24'!G17 -> 0 | O20: ='CAM-Feb`24'!H17 -> 0 | P20: ='CAM-Mar`24'!C18 -> 350000 | Q20: ='CAM-Mar`24'!G18 -> 119498.77 | R20: ='CAM-Mar`24'!H18 -> 230501.23 | S20: ='CAM-Apr`24'!C18 -> 0 | T20: ='CAM-Apr`24'!G18 -> 0 | U20: ='CAM-Apr`24'!H18 -> 0 | V20: ='CAM-May`24'!C18 -> 0 | W20: ='CAM-May`24'!G18 -> 0 | X20: ='CAM-May`24'!H18 -> 0 | Y20: ='CAM-Jun`24'!C18 -> 356248.67 | Z20: ='CAM-Jun`24'!G18 -> 121632.22 | AA20: ='CAM-Jun`24'!H18 -> 234616.45 | AB20: ='CAM-Jul`24'!C18 -> 356248.67 | AC20: ='CAM-Jul`24'!G18 -> 121632.22 | AD20: ='CAM-Jul`24'!H18 -> 234616.45 | AE20: ='CAM-Aug`24'!C18 -> 656248.67 | AF20: ='CAM-Aug`24'!G18 -> 224059.73 | AG20: ='CAM-Aug`24'!H18 -> 432188.94 | AH20: ='CAM-Sep`24'!C18 -> 300000 | AI20: ='CAM-Sep`24'!G18 -> 102427.51 | AJ20: ='CAM-Sep`24'!H18 -> 197572.49 | AK20: ='CAM-Oct`24'!C18 -> 300000 | AL20: ='CAM-Oct`24'!G18 -> 102427.51 | AM20: ='CAM-Oct`24'!H18 -> 197572.49 | AN20: ='CAM-Nov`24'!C18 -> 55000 | AO20: ='CAM-Nov`24'!G18 -> 18778.378 | AP20: ='CAM-Nov`24'!H18 -> 36221.622 | AQ20: ='CAM-Dec2024'!C18 -> 55000 | AR20: ='CAM-Dec2024'!G18 -> 18778.378 | AS20: ='CAM-Dec2024'!H18 -> 36221.622 | AT20: ='CAM-Jan2025'!C18 -> 55000 | AU20: ='CAM-Jan2025'!G18 -> 18778.378 | AV20: ='CAM-Jan2025'!H18 -> 36221.622 | AW20: ='CAM-Feb2025'!C18 -> 55000 | AX20: ='CAM-Feb2025'!G18 -> 18778.378 | AY20: ='CAM-Feb2025'!H18 -> 36221.622 | AZ20: ='CAM-Mar2025'!C18 -> 55000 | BA20: ='CAM-Mar2025'!G18 -> 18778.378 | BB20: ='CAM-Mar2025'!H18 -> 36221.622 | BC20: ='CAM-Apr2025'!C18 -> 143294.17 | BD20: ='CAM-Apr2025'!G18 -> 48924.219 | BE20: ='CAM-Apr2025'!H18 -> 94369.951 | BF20: ='CAM-May2025'!C18 -> 143294.17 | BG20: ='CAM-May2025'!G18 -> 48924.219 | BH20: ='CAM-May2025'!H18 -> 94369.951 | BI20: ='CAM-Jun2025'!C18 -> 143294.17 | BJ20: ='CAM-Jun2025'!G18 -> 48924.219 | BK20: ='CAM-Jun2025'!H18 -> 94369.951 | BL20: ='CAM-Jul2025'!C18 -> 143294.17 | BM20: ='CAM-Jul2025'!G18 -> 48924.219 | BN20: ='CAM-Jul2025'!H18 -> 94369.951 | BO20: ='CAM-Aug2025'!C18 -> 143294.17 | BP20: ='CAM-Aug2025'!G18 -> 48924.219 | BQ20: ='CAM-Aug2025'!H18 -> 94369.951 | BR20: ='CAM-Sep2025'!C18 -> 143294.17 | BS20: ='CAM-Sep2025'!G18 -> 48924.219 | BT20: ='CAM-Sep2025'!H18 -> 94369.951 | BU20: ='CAM-Oct2025'!C18 -> 143294.17 | BV20: ='CAM-Oct2025'!G18 -> 48924.219 | BW20: ='CAM-Oct2025'!H18 -> 94369.951 | BX20: ='CAM-Nov2025'!C18 -> 143294.17 | BY20: ='CAM-Nov2025'!G18 -> 48924.219 | BZ20: ='CAM-Nov2025'!H18 -> 94369.951
B21: Total CAM Charges | C21: ='CAM-Jun`23'!C17 -> 1658281.1 | D21: =SUM(D8:D20) -> 1795539.5 | E21: =SUM(E8:E20) -> 1912244.3 | F21: =SUM(F8:F20) -> 2495923.2 | G21: =SUM(G8:G20) -> 2628602.9 | H21: =SUM(H8:H20) -> 2725938 | I21: =SUM(I8:I20) -> 2838346.7 | J21: =SUM(J8:J20) -> 3094603.1 | K21: =SUM(K8:K20) -> 703505.5 | ... BZ21: =SUM(BZ8:BZ20) -> 3287931.1
A22: 14 | B22: Contingency, Sinking Fund @2% (Applicable till formation of Association) | C22: =C21*2% -> 33165.622 | D22: =D21*2% -> 35910.79 | E22: =E21*2% -> 38244.885 | F22: =F21*2% -> 49918.463 | G22: =G21*2% -> 52572.057 | H22: =H21*2% -> 54518.761 | I22: =I21*2% -> 56766.935 | J22: =J21*2% -> 61892.062 | ... X22: =X21*2% -> 54721.359 | Y22: 0 | Z22: 0 | AA22: 0 | AB22: 0 | AC22: 0 | AD22: 0 | AE22: 0 | AF22: 0 | AG22: 0 | AH22: 0 | AI22: 0 | AJ22: 0 | AK22: 0 | AL22: 0 | AM22: 0 | AN22: 0 | AO22: 0 | AP22: 0 | AQ22: 0 | AR22: 0 | AS22: 0 | AT22: 0 | AU22: 0 | AV22: 0 | AW22: 0 | AX22: 0 | AY22: 0 | AZ22: 0 | BA22: 0 | BB22: 0 | BC22: 0 | BD22: 0 | BE22: 0 | BF22: 0 | BG22: 0 | BH22: 0 | BI22: 0 | BJ22: 0 | BK22: 0 | BL22: 0 | BM22: 0 | BN22: 0 | BO22: 0 | BP22: 0 | BQ22: 0 | BR22: 0 | BS22: 0 | BT22: 0 | BU22: 0 | BV22: 0 | BW22: 0 | BX22: 0 | BY22: 0 | BZ22: 0
A23: 15 | B23: Fixed Management Fees | C23: 490749 | D23: 490749 | E23: 490749 | F23: 490749 | G23: 490749 | H23: 490749 | I23: 490749 | J23: 490749 | K23: =K7*1 -> 167554 | L23: =L7*1 -> 323195 | M23: 490749 | N23: =N7*1 -> 167554 | O23: =O7*1 -> 323195 | P23: 490749 | Q23: =Q7*1 -> 167554 | R23: =R7*1 -> 323195 | S23: 490749 | T23: =T7*1 -> 167554 | U23: =U7*1 -> 323195 | V23: 490749 | W23: =W7*1 -> 167554 | X23: =X7*1 -> 323195 | Y23: 490749 | Z23: =Z7*1 -> 167554 | AA23: =AA7*1 -> 323195 | AB23: 490749 | AC23: =AC7*1 -> 167554 | AD23: =AD7*1 -> 323195 | AE23: 490749 | AF23: =AF7*1 -> 167554 | AG23: =AG7*1 -> 323195 | AH23: 490749 | AI23: =AI7*1 -> 167554 | AJ23: =AJ7*1 -> 323195 | AK23: 490749 | AL23: =AL7*1 -> 167554 | AM23: =AM7*1 -> 323195 | AN23: 490749 | AO23: =AO7*1 -> 167554 | AP23: =AP7*1 -> 323195 | AQ23: 490749 | AR23: =AR7*1 -> 167554 | AS23: =AS7*1 -> 323195 | AT23: 490749 | AU23: =AU7*1 -> 167554 | AV23: =AV7*1 -> 323195 | AW23: 490749 | AX23: =AX7*1 -> 167554 | AY23: =AY7*1 -> 323195 | AZ23: 490749 | BA23: =BA7*1 -> 167554 | BB23: =BB7*1 -> 323195 | BC23: 490749 | BD23: =BD7*1 -> 167554 | BE23: =BE7*1 -> 323195 | BF23: 490749 | BG23: =BG7*1 -> 167554 | BH23: =BH7*1 -> 323195 | BI23: 490749 | BJ23: =BJ7*1 -> 167554 | BK23: =BK7*1 -> 323195 | BL23: 490749 | BM23: =BM7*1 -> 167554 | BN23: =BN7*1 -> 323195 | BO23: 490749 | BP23: =BP7*1 -> 167554 | BQ23: =BQ7*1 -> 323195 | BR23: 490749 | BS23: =BS7*1 -> 167554 | BT23: =BT7*1 -> 323195 | BU23: 490749 | BV23: =BV7*1 -> 167554 | BW23: =BW7*1 -> 323195 | BX23: 490749 | BY23: =BY7*1 -> 167554 | BZ23: =BZ7*1 -> 323195
B24: Grand Total | C24: =SUM(C21:C23) -> 2182195.7 | D24: =SUM(D21:D23) -> 2322199.3 | E24: =SUM(E21:E23) -> 2441238.2 | F24: =SUM(F21:F23) -> 3036590.6 | G24: =SUM(G21:G23) -> 3171923.9 | H24: =SUM(H21:H23) -> 3271205.8 | I24: =SUM(I21:I23) -> 3385862.7 | J24: =SUM(J21:J23) -> 3647244.2 | ... BZ24: =SUM(BZ21:BZ23) -> 3611126.1
B25: Including Contingency & Sinking fund Per Sft CAM Charges | C25: =(C22+C23+C21)/$C$4 -> 4.4466637 | D25: =(D22+D23+D21)/$C$4 -> 4.7319491 | E25: =(E22+E23+E21)/$C$4 -> 4.9745148 | F25: =(F22+F23+F21)/$C$4 -> 6.1876655 | G25: =(G22+G23+G21)/$C$4 -> 6.4634343 | H25: =(H22+H23+H21)/$C$4 -> 6.6657411 | I25: =(I22+I23+I21)/$C$4 -> 6.8993776 | J25: =(J22+J23+J21)/$C$4 -> 7.4319951 | K25: =K24/K7 -> 5.2826528 | L25: =L24/L7 -> 8.5462788 | M25: =(M22+M23+M21)/$C$4 -> 7.0158194 | N25: =N24/N7 -> 5.1102732 | O25: =O24/O7 -> 8.0037118 | P25: =P24/P7 -> 7.5832883 | Q25: =Q24/Q7 -> 5.5710204 | R25: =R24/R7 -> 8.6265084 | S25: =S24/S7 -> 7.2209139 | T25: =T24/T7 -> 5.0055258 | U25: =U24/U7 -> 8.3694377 | ... BZ25: =BZ24/BZ7 -> 11.173212
B26: Collected per SFT | T26: 5 | U26: 10 | W26: 5 | X26: 10 | Z26: 5 | AA26: 10 | AC26: 5 | AD26: 10 | AF26: 5 | AG26: 10 | AI26: 5 | AJ26: 10 | AL26: 5 | AM26: 10 | AO26: 5 | AP26: 10 | AR26: 5 | AS26: 10 | AU26: 6 | AV26: 10 | AX26: 6 | AY26: 10 | BA26: 6 | BB26: 10 | BD26: 6 | BE26: 10 | BG26: 6 | BH26: 10 | BJ26: 6 | BK26: 10 | BM26: 6 | BN26: 10 | BP26: 6 | BQ26: 12 | BS26: 6 | BT26: 12 | BV26: 6 | BW26: 12 | BY26: 6 | BZ26: 12
B27: Variance Per SFT | I27: MCP | J27: OGM | T27: =T26-T25 -> -0.0055257935 | U27: =U26-U25 -> 1.6305623 | W27: =W26-W25 -> -0.95916142 | X27: =X26-X25 -> 0.36499854 | Z27: =Z26-Z25 -> -1.1557284 | AA27: =AA26-AA25 -> 0.33693317 | AC27: =AC26-AC25 -> -0.86831994 | AD27: =AD26-AD25 -> 0.72151846 | AF27: =AF26-AF25 -> -1.3343474 | AG27: =AG26-AG25 -> 0.88203685 | AI27: =AI26-AI25 -> -0.90268089 | AJ27: =AJ26-AJ25 -> 1.1714963 | AL27: =AL26-AL25 -> -1.2396784 | AM27: =AM26-AM25 -> 0.65631696 | AO27: =AO26-AO25 -> -0.88147641 | AP27: =AP26-AP25 -> -0.16724778 | AR27: =AR26-AR25 -> -0.73699433 | AS27: =AS26-AS25 -> 0.57399186 | AU27: =AU26-AU25 -> 0.306115 | AV27: =AV26-AV25 -> 0.85801546 | AX27: =AX26-AX25 -> 0.28771643 | AY27: =AY26-AY25 -> 0.92864389 | BA27: =BA26-BA25 -> -0.0028257043 | BB27: =BB26-BB25 -> -0.048875855 | BD27: =BD26-BD25 -> -0.39546971 | BE27: =BE26-BE25 -> -1.7846484 | BG27: =BG26-BG25 -> -1.0339878 | BH27: =BH26-BH25 -> -2.5594576 | BJ27: =BJ26-BJ25 -> -0.30775806 | BK27: =BK26-BK25 -> -1.1734221 | BL27: =BJ27+BG27+BD27+BA27+AX27+AU27 -> -1.1462098 | BM27: =BM26-BM25 -> -0.8957828 | BN27: =BN26-BN25 -> -2.2573654 | BP27: =BP26-BP25 -> -0.62704248 | BQ27: =BQ26-BQ25 -> -0.27806091 | BS27: =BS26-BS25 -> -0.37722349 | BT27: =BT26-BT25 -> 0.43217105 | BV27: =BV26-BV25 -> -0.25978696 | BW27: =BW26-BW25 -> 0.3264176 | BY27: =BY26-BY25 -> -0.20020083 | BZ27: =BZ26-BZ25 -> 0.8267884
B28: Variance Amount on total SFT | G28: Jun-23 to Dec-23 | H28: average | I28: 5.77 | J28: 5.77 | T28: =T7*T27 -> -925.86881 | U28: =U7*U27 -> 526989.58 | W28: =W7*W27 -> -160711.33 | X28: =X7*X27 -> 117965.7 | Z28: =Z7*Z27 -> -193646.92 | AA28: =AA7*AA27 -> 108895.11 | AC28: =AC7*AC27 -> -145490.48 | AD28: =AD7*AD27 -> 233191.16 | AF28: =AF7*AF27 -> -223575.24 | AG28: =AG7*AG27 -> 285069.9 | AI28: =AI7*AI27 -> -151247.79 | AJ28: =AJ7*AJ27 -> 378621.75 | AL28: =AL7*AL27 -> -207713.07 | AM28: =AM7*AM27 -> 212118.36 | AO28: =AO7*AO27 -> -147694.9 | AP28: =AP7*AP27 -> -54053.647 | AR28: =AR7*AR27 -> -123486.35 | AS28: =AS7*AS27 -> 185511.3 | AU28: =AU7*AU27 -> 51290.793 | AV28: =AV7*AV27 -> 277306.31 | AX28: =AX7*AX27 -> 48208.038 | AY28: =AY7*AY27 -> 300133.06 | BA28: =BA7*BA27 -> -473.45806 | BB28: =BB7*BB27 -> -15796.432 | BD28: =BD7*BD27 -> -66262.532 | BE28: =BE7*BE27 -> -576789.42 | BG28: =BG7*BG27 -> -173248.78 | BH28: =BH7*BH27 -> -827203.89 | BJ28: =BJ7*BJ27 -> -51566.094 | BK28: =BK7*BK27 -> -379244.17 | BM28: =BM7*BM27 -> -150091.99 | BN28: =BN7*BN27 -> -729569.22 | BP28: =BP7*BP27 -> -105063.47 | BQ28: =BQ7*BQ27 -> -89867.895 | BS28: =BS7*BS27 -> -63205.304 | BT28: =BT7*BT27 -> 139675.52 | BV28: =BV7*BV27 -> -43528.344 | BW28: =BW7*BW27 -> 105496.54 | BY28: =BY7*BY27 -> -33544.449 | BZ28: =BZ7*BZ27 -> 267213.88
G29: Jan-24 to May-24 | H29: average | I29: 5.39 | BD29: 6.22 | BE29: 11.6 | BG29: 6.86 | BH29: 12.38 | BJ29: 6.4 | BK29: 10.92 | BM29: 6.71 | BN29: 12.97 | BP29: 6.91 | BQ29: 13.15 | BS29: 6.31 | BT29: 11.3 | BV29: 6.08 | BW29: 11.49 | BY29: 5.92 | BZ29: 10.99
H30: average | I30: 5.578 | K30: 6 | BD30: =BD25-BD29 -> 0.17546971 | BE30: =BE25-BE29 -> 0.18464835 | BG30: =BG25-BG29 -> 0.17398775 | BH30: =BH25-BH29 -> 0.17945758 | BJ30: =BJ25-BJ29 -> -0.092241942 | BK30: =BK25-BK29 -> 0.25342213 | BM30: =BM25-BM29 -> 0.1857828 | BN30: =BN25-BN29 -> -0.71263456 | BP30: =BP25-BP29 -> -0.28295752 | BQ30: =BQ25-BQ29 -> -0.87193909 | BS30: =BS25-BS29 -> 0.067223489 | BT30: =BT25-BT29 -> 0.26782895 | BV30: =BV25-BV29 -> 0.17978696 | BW30: =BW25-BW29 -> 0.1835824 | BY30: =BY25-BY29 -> 0.28020083 | BZ30: =BZ25-BZ29 -> 0.1832116
I31: =0.58*167554*12 -> 1166175.8 | K31: =AVERAGE(K25,N25,Q25,T25,W25,Z25,AC25,AF25,AI25) -> 5.6877456 | L31: jan to Mar average
K32: =K30-K31 -> 0.31225441

Sheet FM Cost-incl Utility
A1: Facility Management Expenses as on 31st Oct 2023
A2: S.No | B2: Name of the Contractor/Vendor | C2: Fee | D2: GST | E2: Amount Spent | F2: Remarks
A3: 1 | B3: Wakeon Innovative - Computers Purchase | C3: 126271 | D3: =C3*18% -> 22728.78 | E3: =C3+D3 -> 148999.78
A4: 2 | B4: RKS Technologies - Walkie Talkies Purchase | C4: 274500 | D4: =C4*18% -> 49410 | E4: =C4+D4 -> 323910 | F4: Purchase 15No's WALKIE TALKIE - MOTOROLA XIR P3688 MOTOROLA
A5: 3 | B5: Emerzhent - FM Services | C5: 5704969 | D5: =C5*18% -> 1026894.4 | E5: =C5+D5 -> 6731863.4
A6: 4 | B6: Lord Ganapathi Pooja Expenses. Diwali Sweets | C6: 49121 | D6: 0 | E6: =C6+D6 -> 49121
A7: 5 | B7: TSSPDCL - FMS Cost - MCP - From July 23 onwards | C7: 6474617 | D7: 0 | E7: =C7+D7 -> 6474617
A8: 6 | B8: Jubilee Hills Filling Station - Diesel Cost | C8: 2038031 | D8: 0 | E8: =C8+D8 -> 2038031
A9: 7 | B9: OM SRI SAI WATER METERS | C9: 72400 | D9: =C9*18% -> 13032 | E9: =C9+D9 -> 85432 | F9: purchase Water Meters and Accessasries
A10: 8 | B10: DELIGHT ENTERPRISES | C10: 173812 | D10: =C10*18% -> 31286.16 | E10: =C10+D10 -> 205098.16 | F10: purchase Water Meters and Accessasries
A11: 9 | B11: Emerald Tools Corporation | C11: 13500 | D11: =C11*18% -> 2430 | E11: =C11+D11 -> 15930 | F11: Hardware Items purchase
A12: 10 | B12: Shaikh Taher | C12: 132568 | D12: =C12*18% -> 23862.24 | E12: =C12+D12 -> 156430.24 | F12: Metal Lockers Purchase
A13: 11 | B13: Sharpedge - Signage Materials | C13: 49578 | D13: =C13*18% -> 8924.04 | E13: =C13+D13 -> 58502.04 | F13: Signage Material
A14: 12 | B14: SRI VENKATESWARA HOSPITALITY SERVICES | C14: 130100 | D14: =C14*5% -> 6505 | E14: =C14+D14 -> 136605 | F14: Lunch Expenses for Lord Ganesh Festival and Projects Opening Day and Dussera Festival Expenses
A15: 13 | B15: SVR ENTERPRISES | C15: 93220 | D15: =C15*18% -> 16779.6 | E15: =C15+D15 -> 109999.6 | F15: Kent RO Water Plant
A16: 14 | B16: Ashok Agencies | C16: 19200 | D16: 0 | E16: =C16+D16 -> 19200 | F16: Tea & Coffee Mix Packs
A17: 15 | B17: Independence Day Celebrations Bill | C17: 5460 | D17: 0 | E17: =C17+D17 -> 5460
A18: 16 | B18: Lifeline Enterprises - Eye Bolts Purchase | C18: 260000 | D18: =C18*18% -> 46800 | E18: =C18+D18 -> 306800 | F18: Purchase Eye Bolts Purchase for Facade cleaning
A19: 17 | B19: HMWS Water Bills | C19: 486150 | D19: 0 | E19: =C19+D19 -> 486150
A20: 18 | B20: Water Tanker Expenses - R Balraj | C20: 140200 | D20: 0 | E20: =C20+D20 -> 140200
A21: 19 | B21: Septic Tank Cleaning Expenses - Laxman | C21: 86000 | D21: 0 | E21: =C21+D21 -> 86000
A22: Total | C22: =SUM(C3:C21) -> 16329697 | D22: =SUM(D3:D21) -> 1248652.2 | E22: =SUM(E3:E21) -> 17578349

Sheet FM Cost-excl Utility
A1: Facility Management Expenses as on 31st Oct 2023
A2: S.No | B2: Name of the Contractor/Vendor | C2: Project Expenses | D2: Operation Expenses | E2: GST | F2: Amount Spent | G2: Remarks
A3: 1 | B3: Wakeon Innovative - Computers Purchase | D3: 126271 | E3: =D3*18% -> 22728.78 | F3: =C3+D3+E3 -> 148999.78
A4: 2 | B4: RKS Technologies - Walkie Talkies Purchase | D4: 274500 | E4: =D4*18% -> 49410 | F4: =C4+D4+E4 -> 323910 | G4: Purchase 15No's WALKIE TALKIE - MOTOROLA XIR P3688 MOTOROLA
A5: 3 | B5: Emerzhent - FM Services | F5: =C5+D5+E5 -> 0
A6: 4 | B6: Lord Ganapathi Pooja Expenses | D6: 49121 | E6: 0 | F6: =C6+D6+E6 -> 49121
A7: 5 | B7: TSSPDCL - FMS Cost - MCP - From July 23 onwards | F7: =C7+D7+E7 -> 0
A8: 6 | B8: Jubilee Hills Filling Station - Diesel Cost | F8: =C8+D8+E8 -> 0
A9: 7 | B9: OM SRI SAI WATER METERS | D9: 72400 | E9: =D9*18% -> 13032 | F9: =C9+D9+E9 -> 85432 | G9: Purchase Water Meters and Accessories
A10: 8 | B10: DELIGHT ENTERPRISES | D10: 173812 | E10: =D10*18% -> 31286.16 | F10: =C10+D10+E10 -> 205098.16 | G10: Purchase Water Meters and Accessories
A11: 9 | B11: Emerald Tools Corporation | D11: 13500 | E11: =D11*18% -> 2430 | F11: =C11+D11+E11 -> 15930 | G11: Hardware Items purchase
A12: 10 | B12: Sheikh Taher | D12: 132568 | E12: =D12*18% -> 23862.24 | F12: =C12+D12+E12 -> 156430.24 | G12: Metal Lockers Purchase
A13: 11 | B13: Sharp edge - Signage Materials | D13: 49578 | E13: =D13*18% -> 8924.04 | F13: =C13+D13+E13 -> 58502.04 | G13: Signage Material
A14: 12 | B14: SRI VENKATESWARA HOSPITALITY SERVICES | D14: 130100 | E14: =D14*5% -> 6505 | F14: =C14+D14+E14 -> 136605 | G14: Lunch Expenses for Lord Ganesh Festival and Projects Opening Day and Dussera Festival Expenses
A15: 13 | B15: SVR ENTERPRISES | D15: 93220 | E15: =D15*18% -> 16779.6 | F15: =C15+D15+E15 -> 109999.6 | G15: Kent RO Water Plant
A16: 14 | B16: Ashok Agencies | D16: 19200 | E16: 0 | F16: =C16+D16+E16 -> 19200 | G16: Tea & Coffee Mix Packs
A17: 15 | B17: Independence Day Celebrations Bill | D17: 5460 | E17: 0 | F17: =C17+D17+E17 -> 5460
A18: 16 | B18: Lifeline Enterprises - Eye Bolts Purchase | D18: 260000 | E18: =C18*18% -> 0 | F18: =C18+D18+E18 -> 260000 | G18: Purchase Eye Bolts Purchase for Facade cleaning
A19: 17 | B19: HMWS Water Bills | F19: =C19+D19+E19 -> 0
A20: 18 | B20: Water Tanker Expenses - R Balraj | E20: 0 | F20: =C20+D20+E20 -> 0
A21: 19 | B21: Septic Tank Cleaning Expenses - Laxman | D21: 86000 | E21: 0 | F21: =C21+D21+E21 -> 86000
A22: Total | C22: =SUM(C3:C21) -> 0 | D22: =SUM(D3:D21) -> 1485730 | E22: =SUM(E3:E21) -> 174957.82 | F22: =SUM(F3:F21) -> 1660687.8
B23: No of months(Jun`23 to Oct`23) | D23: 5
B24: Cost/month | D24: =D22/D23 -> 297146

Sheet CAM-Jun`23
A2: CAM CHARGES CALCULATION SUMMARY - OGM-Jun`23
B3: Total Building Saleable area | C3: Area sft | D3: 490749
A4: CAM Charges INR/ Per sq ft / Month | C4: per sq. ft cost | D4: =SUM(D6:D16) -> 3.379082
A5: Sl no | B5: Description | C5: Per month | D5: Per sft
A6: 1 | B6: Management staff | C6: 53038 | D6: =C6/D3 -> 0.10807562
A7: 2 | B7: Technical manpower | C7: 214572.12 | D7: =C7/D3 -> 0.43723394
A8: 3 | B8: HK Manpower | C8: 83898 | D8: =C8/D3 -> 0.17095908
A9: 4 | B9: LP Manpower -Security Services | C9: 158096 | D9: =C9/D3 -> 0.32215246
A10: 5 | B10: AMC | C10: 0 | D10: =C10/D3 -> 0
A11: 6 | B11: Consumables | C11: 0 | D11: =C11/D3 -> 0
A12: 7 | B12: Common area Electrical & DG Charges | C12: 0 | D12: =C12/D3 -> 0
A13: 8 | B13: Common area Water charges | C13: 39300 | D13: =C13/D3 -> 0.080081671
A14: 9 | B14: Sewerage Tanker | C14: =2000*9 -> 18000 | D14: =C14/D3 -> 0.036678628
A15: 10 | B15: FMS Cost | C15: 297146 | D15: =C15/D3 -> 0.60549487
A16: 11 | B16: Additonal Expenditure | C16: =769231+25000 -> 794231 | D16: =C16/D3 -> 1.6184057
A17: A | B17: Total CAM Charges | C17: =SUM(C6:C16) -> 1658281.1
A18: 12 | B18: Contingency, Sinking Fund @2% | C18: =C17*2% -> 33165.622 | D18: =C18/D3 -> 0.06758164
A19: 13 | B19: Fixed Management Fees | C19: 490749 | D19: =C19/D3 -> 1
A20: B | B20: Including Contingency & Sinking fund Per Sft CAM Charges | C20: =(C18+C19+C17)/D3 -> 4.4466637

Sheet Tenant CAM-Jun`23
A1: Tenant CAM details-OGM-Jun`23
A2: Floor | E2: CAM cost per Sft | F2: ='CAM-Jun`23'!C20 -> 4.4466637
A3: Ground Floor
A4: S.NO | B4: Description | C4: SBUA | D4: Ownership | E4: Tenants | F4: CAM Cost | G4: Carpet Area | H4: Cost/Sft
A5: 1 | B5: Retail 01 | C5: =3311 -> 3311 | D5: Amar Chowdhary | E5: HDFC Bank Ltd | F5: =(C5)*F2 -> 14722.903 | G5: =C5*65% -> 2152.15 | H5: =F5/G5 -> 6.841021
A6: 2 | B6: Retail 02 | C6: =3816 -> 3816 | D6: UDS Landowners | E6: Milu Foods (Vacs Bakery) | F6: =C6*F2 -> 16968.469
A7: 3 | B7: Retail 03 | C7: 3814 | D7: KSR Group | E7: Chicken Wild Wings Pvt Ltd | F7: =C7*F2 -> 16959.575
A8: 4 | B8: Retail 04 | C8: =3648 -> 3648 | D8: Aashish Bansal and Mona Bansal | E8: Fatcity Hospitality LLP | F8: =C8*F2 -> 16221.429
A9: 5 | B9: Retail 05 | C9: =3436 -> 3436 | D9: Vazir Singh Pilania and Thota Raghu Buchanna | E9: Fatcity Hospitality LLP | F9: =C9*F2 -> 15278.736
A10: 6 | B10: Retail 06 | C10: =2723 -> 2723 | D10: TanujaNayani and Ratna/Gouri Reddy | E10: Fatcity Hospitality LLP | F10: =C10*F2 -> 12108.265
A11: 7 | B11: Retail 07 | C11: =1381 -> 1381 | D11: TanujaNayani | E11: ICICI Bank Ltd | F11: =C11*F2 -> 6140.8425
A12: 8 | B12: Retail 08 | C12: =755 -> 755 | D12: K Sudhakar Reddy | E12: ICICI Bank Ltd | F12: =C12*F2 -> 3357.2311
C13: =SUM(C5:C12) -> 22884
A14: First Floor | G14: Collected CAM | H14: Actual CAM
A15: S.NO | B15: Description | C15: SBUA | D15: Ownership
A16: 1 | B16: Retail 01 | C16: =6725 -> 6725 | D16: Developer | F16: =C16*F2 -> 29903.813 | G16: =C16*10 -> 67250 | H16: =C16*9.48 -> 63753 | I16: =G16-H16 -> 3497
A17: 2 | B17: Retail 02 | C17: =7686 -> 7686 | D17: Developer | F17: =C17*F2 -> 34177.057
A18: 3 | B18: Retail 03 | C18: =9714 -> 9714 | D18: Developer and Landowners | F18: =C18*F2 -> 43194.891
A19: 4 | B19: Retail 04 | C19: =9514 -> 9514 | D19: UDS Landowners | F19: =C19*F2 -> 42305.558
A20: Total | C20: =C16+C17+C18+C19 -> 33639
A22: Second Floor to Sixth Floor
A23: S.NO | B23: Description | C23: SBUA | D23: Ownership
A24: 1 | B24: All Offices | C24: 167554 | D24: Microchip Technology India Pvt Ltd | F24: =C24*F2 -> 745056.28
A27: Seventh Floor
A28: S.NO | B28: Description | C28: SBUA | D28: Ownership
A29: 1 | B29: Office 01 | C29: 5637 | D29: Developer
B30: 1A.1 | C30: 2000 | D30: Pamara Venkata Ramana Devi and Pamera Ram Gopal Rao | F30: =C30*F2 -> 8893.3273
B31: 1B.2 | C31: =587 -> 587 | D31: Developer | F31: =C31*F2 -> 2610.1916
B32: 1B | C32: =3050 -> 3050 | D32: Nirmal + Dileep (DEV) | F32: =C32*F2 -> 13562.324
B33: Sub-total | C33: =SUM(C30:C32) -> 5637
A34: 2 | B34: Office 02 | C34: 11425 | D34: Avinash Kotagiri (DEV) | F34: =C34*F2 -> 50803.132
A35: 3 | B35: Office 03 | C35: =8457 -> 8457 | D35: Ananth+Dileep+Anoop (DEV)
B36: 3A.1 | C36: 2156 | D36: Ananth(DEV) | F36: =C36*F2 -> 9587.0068
B37: 3A.2 | C37: =2073 -> 2073 | D37: Bhavya Reddy 2,500 Sq.Ft | F37: =C37*F2 -> 9217.9338
B38: 3B.1 | C38: =2927 -> 2927 | D38: Sasya Reddy 2,500 Sq.Ft | F38: =C38*F2 -> 13015.385
B39: 3B.2 | C39: =1301 -> 1301 | D39: Anoop (DEV) | F39: =C39*F2 -> 5785.1094
B40: Sub-total | C40: =SUM(C36:C39) -> 8457
A41: 4 | B41: Office 04 | C41: 8699 | D41: Anoop (DEV) | F41: =C41*F2 -> 38681.527
A42: Total | C42: =SUM(C29,C34,C35,C41) -> 34218
A44: Eighth Floor
A45: S.NO | B45: Description | C45: SBUA | D45: Ownership
A46: 1 | B46: Office 01 | C46: =2101 -> 2101 | D46: Tachyon IT Solutions Pvt Ltd (DEV) | F46: =C46*F2 -> 9342.4403
A47: 2 | B47: Office 02 | C47: 11425 | D47: Tachyon IT Solutions Pvt Ltd (DEV) | F47: =C47*F2 -> 50803.132
A48: 3 | B48: Office 03 | C48: =8457 -> 8457 | D48: Tachyon IT Solutions Pvt Ltd (DEV) | F48: =C48*F2 -> 37605.435
A49: 4 | B49: Office 04 | C49: 8699 | D49: Tachyon IT Solutions Pvt Ltd (DEV) | F49: =C49*F2 -> 38681.527
A50: Total | C50: =SUM(C46:C49) -> 30682
A52: Ninth Floor
A53: S.NO | B53: Description | C53: SBUA | D53: Ownership
A54: 1 | B54: Office 01 | C54: 5637 | D54: Pulluri Mining and Logistics Pvt Ltd (DEV) | F54: =C54*F2 -> 25065.843
A55: 2 | B55: Office 02 | C55: 11425 | D55: Pulluri Mining and Logistics Pvt Ltd (DEV) | F55: =C55*F2 -> 50803.132
A56: 3 | B56: Office 03 | C56: =8457 -> 8457 | D56: UDS Developer Arjun Rao Group
B57: 3.1 | C57: =3957 -> 3957 | D57: Arjun Rao (DEV) | F57: =C57*F2 -> 17595.448
B58: 3.2 | C58: =1500 -> 1500 | D58: Karabee Kailash (Ohja) (DEV) | F58: =C58*F2 -> 6669.9955
B59: 3.3 | C59: =1500 -> 1500 | D59: Jakka Deepa (DEV) | F59: =C59*F2 -> 6669.9955
B60: 3.4 | C60: =1500 -> 1500 | D60: Indu Priya (DEV) | F60: =C60*F2 -> 6669.9955
B61: Sub-total | C61: =SUM(C57:C60) -> 8457
A62: 4 | B62: Office 04 | C62: 8699 | D62: AGA Infra Projects Pvt Ltd (DEV) | F62: =C62*F2 -> 38681.527
A63: Total | C63: =SUM(C54:C56,C62) -> 34218
A65: Tenth Floor
A66: S.NO | B66: Description | C66: SBUA | D66: Ownership
A67: 1 | B67: Office 01 | C67: 5637 | D67: Raj Kumar Maganti & Pradeep Kumar Maganti /Siri Sampada | E67: Siri Sampada Real Estate | F67: =C67*F2 -> 25065.843
A68: 2 | B68: Office 02 | C68: 11425 | D68: Developer
B69: 2.1 | C69: 3000 | D69: Srinivas Reddy Challa (DEV) | F69: =C69*F2 -> 13339.991
B70: 2.2 | C70: 1000 | D70: Shruti Gummadi (DEV) | F70: =C70*F2 -> 4446.6637
B71: 2.3 | C71: =3925-1000+500 -> 3425 | D71: Deepthi Kesireddy (DEV) | F71: =C71*F2 -> 15229.823
B72: 2.4 | C72: 1000 | D72: Chandralekha Kesireddy (DEV) | F72: =C72*F2 -> 4446.6637
B73: 2.5 | C73: 2000 | D73: Manohar SP (DEV) | F73: =C73*F2 -> 8893.3273
B74: 2.6 | C74: 1000 | D74: Shwetha Reddy | F74: =C74*F2 -> 4446.6637
B75: Sub-total | C75: =SUM(C69:C74) -> 11425
A76: 3 | B76: Office 03 | C76: =8457 -> 8457 | D76: Sukender Reddy Pulusani, Vijay Kumar & Others.
B77: 3.1 | C77: 2300 | D77: Kadiyala Venkateshwar Rao | F77: =C77*F2 -> 10227.326
B78: 3.2 | C78: 1000 | D78: Sunkara Vijaya Durga & Sunkara Jishna Sathwik | F78: =C78*F2 -> 4446.6637
B79: 3.3 | C79: 1153 | D79: Sukender Reddy Pulusani | F79: =C79*F2 -> 5127.0032
B80: 3.4 | C80: 1152 | D80: Neetha Pulusani | F80: =C80*F2 -> 5122.5565
B81: 3.5 | C81: 1152 | D81: Kireet Reddy Pulusani | F81: =C81*F2 -> 5122.5565
B82: 3.6 | C82: 850 | D82: Krishna Kumar Vempati | F82: =C82*F2 -> 3779.6641
B83: 3.7 | C83: 850 | D83: J Vijay Kumar & Laxmi | F83: =C83*F2 -> 3779.6641
B84: Sub-total | C84: =SUM(C77:C83) -> 8457
A85: 4 | B85: Office 04 | C85: 8699 | D85: Rohan Mandala & Sridhar Anisha (DEV) | F85: =C85*F2 -> 38681.527
A86: Total | C86: =SUM(C67,C75,C76,C85) -> 34218
A88: Eleventh Floor
A89: S.NO | B89: Description | C89: SBUA | D89: Ownership
A90: 1 | B90: Office 01 | C90: 5637 | D90: Developer
B91: 1A | C91: =2587 -> 2587 | D91: Madhusudhan Reddy Kypa(Dileep kurnool) | F91: =C91*F2 -> 11503.519
B92: 1B | C92: 3050 | D92: Pavan Kumar Mummasani & Manasa Priyadharshini (DEV) | F92: =C92*F2 -> 13562.324
B93: Sub-total | C93: =SUM(C91:C92) -> 5637
A94: 2 | B94: Office 02 | C94: 11425 | D94: UDS Landowners (KDR Family)
B95: 2.1 | C95: 3028 | D95: K. Rajesh Reddy (LO) | F95: =C95*F2 -> 13464.498
B96: 2.2 | C96: =4004-1320 -> 2684 | D96: K Saritha(LO) | F96: =C96*F2 -> 11934.845
B97: 2.3 | C97: 3028 | D97: K Ramachandra Reddy (LO) | F97: =C97*F2 -> 13464.498
B98: 2.4 | C98: =1365+1320 -> 2685 | D98: K Spandana(LO) | F98: =C98*F2 -> 11939.292
B99: Sub-total | C99: =SUM(C95:C98) -> 11425
A100: 3 | B100: Office 03 | C100: 8457 | D100: Arundathi(LO) | F100: =C100*F2 -> 37605.435
A101: 4 | B101: Office 04 | C101: 8699 | D101: Manjula(LO) | F101: =C101*F2 -> 38681.527
A102: Total | C102: =SUM(C90+C99+C100+C101) -> 34218
A104: Twelfth Floor
A105: S.NO | B105: Description | C105: SBUA | D105: Ownership
A106: 1 | B106: Office 01 | C106: =2101 -> 2101 | D106: K. Tanuja (DEV) | F106: =C106*F2 -> 9342.4403
A107: 2 | B107: Office 02 | C107: 11425 | D107: UDS (Developer + Landowner)
B108: 2.1 | C108: =11166 -> 11166 | D108: Madhukar Reddy (LO) | F108: =C108*F2 -> 49651.446
...

Sheet CAM-Jul`23
A2: CAM CHARGES CALCULATION SUMMARY - OGM-Jul`23
B3: Total Building Saleable area | C3: Area sft | D3: 490749
A4: CAM Charges INR/ Per sq ft / Month | C4: per sq. ft cost | D4: =SUM(D6:D16) -> 3.6587736
A5: Sl no | B5: Description | C5: Per month | D5: Per sft
A6: 1 | B6: Management staff | C6: 148967 | D6: =C6/D3 -> 0.30355029
A7: 2 | B7: Technical manpower | C7: 319159.81 | D7: =C7/D3 -> 0.65035244
A8: 3 | B8: HK Manpower | C8: 202650 | D8: =C8/D3 -> 0.41294022
A9: 4 | B9: LP Manpower -Security Services | C9: 581771.08 | D9: =C9/D3 -> 1.1854758
A10: 5 | B10: AMC | C10: 5000 | D10: =C10/D3 -> 0.010188508
A11: 6 | B11: Consumables | C11: 0 | D11: =C11/D3 -> 0
A12: 7 | B12: Common area Electrical & DG Charges | C12: 178245.6 | D12: =C12/D3 -> 0.36321134
A13: 8 | B13: Common area Water charges | C13: 17600 | D13: =C13/D3 -> 0.035863547
A14: 9 | B14: Sewerage Tanker/Water Tanker | C14: =2000*10 -> 20000 | D14: =C14/D3 -> 0.040754031
A15: 10 | B15: FMS Cost | C15: 297146 | D15: =C15/D3 -> 0.60549487
A16: 11 | B16: Liosaning & Licenses | C16: 25000 | D16: =C16/D3 -> 0.050942539
A17: A | B17: Total CAM Charges | C17: =SUM(C6:C16) -> 1795539.5
A18: 12 | B18: Contingency, Sinking Fund @2% | C18: =C17*2% -> 35910.79 | D18: =C18/D3 -> 0.073175472
A19: 13 | B19: Fixed Management Fees | C19: 490749 | D19: =C19/D3 -> 1
A20: B | B20: Including Contingency & Sinking fund Per Sft CAM Charges | C20: =(C18+C19+C17)/D3 -> 4.7319491

Sheet Tenant CAM-Jul`23
A1: Tenant CAM details-OGM-Jul`23
A2: Floor | E2: CAM cost per Sft | F2: ='CAM-Jul`23'!C20 -> 4.7319491
A3: Ground Floor
A4: S.NO | B4: Description | C4: SBUA | D4: Ownership | E4: Tenants | F4: CAM Cost | G4: Carpet Area | H4: Cost/Sft
A5: 1 | B5: Retail 01 | C5: =3311 -> 3311 | D5: Amar Chowdhary | E5: HDFC Bank Ltd | F5: =(C5)*F2 -> 15667.483 | G5: =C5*65% -> 2152.15 | H5: =F5/G5 -> 7.2799217
A6: 2 | B6: Retail 02 | C6: =3816 -> 3816 | D6: UDS Landowners | E6: Milu Foods (Vacs Bakery) | F6: =C6*F2 -> 18057.118
A7: 3 | B7: Retail 03 | C7: 3814 | D7: KSR Group | E7: Chicken Wild Wings Pvt Ltd | F7: =C7*F2 -> 18047.654
A8: 4 | B8: Retail 04 | C8: =3648 -> 3648 | D8: Aashish Bansal and Mona Bansal | E8: Fatcity Hospitality LLP | F8: =C8*F2 -> 17262.15
A9: 5 | B9: Retail 05 | C9: =3436 -> 3436 | D9: Vazir Singh Pilania and Thota Raghu Buchanna | E9: Fatcity Hospitality LLP | F9: =C9*F2 -> 16258.977
A10: 6 | B10: Retail 06 | C10: =2723 -> 2723 | D10: TanujaNayani and Ratna/Gouri Reddy | E10: Fatcity Hospitality LLP | F10: =C10*F2 -> 12885.097
A11: 7 | B11: Retail 07 | C11: =1381 -> 1381 | D11: TanujaNayani | E11: ICICI Bank Ltd | F11: =C11*F2 -> 6534.8217
A12: 8 | B12: Retail 08 | C12: =755 -> 755 | D12: K Sudhakar Reddy | E12: ICICI Bank Ltd | F12: =C12*F2 -> 3572.6216
C13: =SUM(C5:C12) -> 22884
A14: First Floor
A15: S.NO | B15: Description | C15: SBUA | D15: Ownership
A16: 1 | B16: Retail 01 | C16: =6725 -> 6725 | D16: Developer | F16: =C16*F2 -> 31822.358
A17: 2 | B17: Retail 02 | C17: =7686 -> 7686 | D17: Developer | F17: =C17*F2 -> 36369.761
A18: 3 | B18: Retail 03 | C18: =9714 -> 9714 | D18: Developer and Landowners | F18: =C18*F2 -> 45966.153
A19: 4 | B19: Retail 04 | C19: =9514 -> 9514 | D19: UDS Landowners | F19: =C19*F2 -> 45019.764
A20: Total | C20: =C16+C17+C18+C19 -> 33639
A22: Second Floor to Sixth Floor
A23: S.NO | B23: Description | C23: SBUA | D23: Ownership
A24: 1 | B24: All Offices | C24: 167554 | D24: Microchip Technology India Pvt Ltd | F24: =C24*F2 -> 792857
A27: Seventh Floor
A28: S.NO | B28: Description | C28: SBUA | D28: Ownership
A29: 1 | B29: Office 01 | C29: 5637 | D29: Developer
B30: 1A.1 | C30: 2000 | D30: Pamara Venkata Ramana Devi and Pamera Ram Gopal Rao | F30: =C30*F2 -> 9463.8982
B31: 1B.2 | C31: =587 -> 587 | D31: Developer | F31: =C31*F2 -> 2777.6541
B32: 1B | C32: =3050 -> 3050 | D32: Nirmal + Dileep (DEV) | F32: =C32*F2 -> 14432.445
B33: Sub-total | C33: =SUM(C30:C32) -> 5637
A34: 2 | B34: Office 02 | C34: 11425 | D34: Avinash Kotagiri (DEV) | F34: =C34*F2 -> 54062.518
A35: 3 | B35: Office 03 | C35: =8457 -> 8457 | D35: Ananth+Dileep+Anoop (DEV)
B36: 3A.1 | C36: 2156 | D36: Ananth(DEV) | F36: =C36*F2 -> 10202.082
B37: 3A.2 | C37: =2073 -> 2073 | D37: Bhavya Reddy 2,500 Sq.Ft | F37: =C37*F2 -> 9809.3305
B38: 3B.1 | C38: =2927 -> 2927 | D38: Sasya Reddy 2,500 Sq.Ft | F38: =C38*F2 -> 13850.415
B39: 3B.2 | C39: =1301 -> 1301 | D39: Anoop (DEV) | F39: =C39*F2 -> 6156.2658
B40: Sub-total | C40: =SUM(C36:C39) -> 8457
A41: 4 | B41: Office 04 | C41: 8699 | D41: Anoop (DEV) | F41: =C41*F2 -> 41163.225
A42: Total | C42: =SUM(C29,C34,C35,C41) -> 34218
A44: Eighth Floor
A45: S.NO | B45: Description | C45: SBUA | D45: Ownership
A46: 1 | B46: Office 01 | C46: =2101 -> 2101 | D46: Tachyon IT Solutions Pvt Ltd (DEV) | F46: =C46*F2 -> 9941.825
A47: 2 | B47: Office 02 | C47: 11425 | D47: Tachyon IT Solutions Pvt Ltd (DEV) | F47: =C47*F2 -> 54062.518
A48: 3 | B48: Office 03 | C48: =8457 -> 8457 | D48: Tachyon IT Solutions Pvt Ltd (DEV) | F48: =C48*F2 -> 40018.093
A49: 4 | B49: Office 04 | C49: 8699 | D49: Tachyon IT Solutions Pvt Ltd (DEV) | F49: =C49*F2 -> 41163.225
A50: Total | C50: =SUM(C46:C49) -> 30682
A52: Ninth Floor
A53: S.NO | B53: Description | C53: SBUA | D53: Ownership
A54: 1 | B54: Office 01 | C54: 5637 | D54: Pulluri Mining and Logistics Pvt Ltd (DEV) | F54: =C54*F2 -> 26673.997
A55: 2 | B55: Office 02 | C55: 11425 | D55: Pulluri Mining and Logistics Pvt Ltd (DEV) | F55: =C55*F2 -> 54062.518
A56: 3 | B56: Office 03 | C56: =8457 -> 8457 | D56: UDS Developer Arjun Rao Group
B57: 3.1 | C57: =3957 -> 3957 | D57: Arjun Rao (DEV) | F57: =C57*F2 -> 18724.323
B58: 3.2 | C58: =1500 -> 1500 | D58: Karabee Kailash (Ohja) (DEV) | F58: =C58*F2 -> 7097.9236
B59: 3.3 | C59: =1500 -> 1500 | D59: Jakka Deepa (DEV) | F59: =C59*F2 -> 7097.9236
B60: 3.4 | C60: =1500 -> 1500 | D60: Indu Priya (DEV) | F60: =C60*F2 -> 7097.9236
B61: Sub-total | C61: =SUM(C57:C60) -> 8457
A62: 4 | B62: Office 04 | C62: 8699 | D62: AGA Infra Projects Pvt Ltd (DEV) | F62: =C62*F2 -> 41163.225
A63: Total | C63: =SUM(C54:C56,C62) -> 34218
A65: Tenth Floor
A66: S.NO | B66: Description | C66: SBUA | D66: Ownership
A67: 1 | B67: Office 01 | C67: 5637 | D67: Raj Kumar Maganti & Pradeep Kumar Maganti /Siri Sampada | E67: Siri Sampada Real Estate | F67: =C67*F2 -> 26673.997
A68: 2 | B68: Office 02 | C68: 11425 | D68: Developer
B69: 2.1 | C69: 3000 | D69: Srinivas Reddy Challa (DEV) | F69: =C69*F2 -> 14195.847
B70: 2.2 | C70: 1000 | D70: Shruti Gummadi (DEV) | F70: =C70*F2 -> 4731.9491
B71: 2.3 | C71: =3925-1000+500 -> 3425 | D71: Deepthi Kesireddy (DEV) | F71: =C71*F2 -> 16206.926
B72: 2.4 | C72: 1000 | D72: Chandralekha Kesireddy (DEV) | F72: =C72*F2 -> 4731.9491
B73: 2.5 | C73: 2000 | D73: Manohar SP (DEV) | F73: =C73*F2 -> 9463.8982
B74: 2.6 | C74: 1000 | D74: Shwetha Reddy | F74: =C74*F2 -> 4731.9491
B75: Sub-total | C75: =SUM(C69:C74) -> 11425
A76: 3 | B76: Office 03 | C76: =8457 -> 8457 | D76: Sukender Reddy Pulusani, Vijay Kumar & Others.
B77: 3.1 | C77: 2300 | D77: Kadiyala Venkateshwar Rao | F77: =C77*F2 -> 10883.483
B78: 3.2 | C78: 1000 | D78: Sunkara Vijaya Durga & Sunkara Jishna Sathwik | F78: =C78*F2 -> 4731.9491
B79: 3.3 | C79: 1153 | D79: Sukender Reddy Pulusani | F79: =C79*F2 -> 5455.9373
B80: 3.4 | C80: 1152 | D80: Neetha Pulusani | F80: =C80*F2 -> 5451.2053
B81: 3.5 | C81: 1152 | D81: Kireet Reddy Pulusani | F81: =C81*F2 -> 5451.2053
B82: 3.6 | C82: 850 | D82: Krishna Kumar Vempati | F82: =C82*F2 -> 4022.1567
B83: 3.7 | C83: 850 | D83: J Vijay Kumar & Laxmi | F83: =C83*F2 -> 4022.1567
B84: Sub-total | C84: =SUM(C77:C83) -> 8457
A85: 4 | B85: Office 04 | C85: 8699 | D85: Rohan Mandala & Sridhar Anisha (DEV) | F85: =C85*F2 -> 41163.225
A86: Total | C86: =SUM(C67,C75,C76,C85) -> 34218
A88: Eleventh Floor
A89: S.NO | B89: Description | C89: SBUA | D89: Ownership
A90: 1 | B90: Office 01 | C90: 5637 | D90: Developer
B91: 1A | C91: =2587 -> 2587 | D91: Madhusudhan Reddy Kypa(Dileep kurnool) | F91: =C91*F2 -> 12241.552
B92: 1B | C92: 3050 | D92: Pavan Kumar Mummasani & Manasa Priyadharshini (DEV) | F92: =C92*F2 -> 14432.445
B93: Sub-total | C93: =SUM(C91:C92) -> 5637
A94: 2 | B94: Office 02 | C94: 11425 | D94: UDS Landowners (KDR Family)
B95: 2.1 | C95: 3028 | D95: K. Rajesh Reddy (LO) | F95: =C95*F2 -> 14328.342
B96: 2.2 | C96: =4004-1320 -> 2684 | D96: K Saritha(LO) | F96: =C96*F2 -> 12700.551
B97: 2.3 | C97: 3028 | D97: K Ramachandra Reddy (LO) | F97: =C97*F2 -> 14328.342
B98: 2.4 | C98: =1365+1320 -> 2685 | D98: K Spandana(LO) | F98: =C98*F2 -> 12705.283
B99: Sub-total | C99: =SUM(C95:C98) -> 11425
A100: 3 | B100: Office 03 | C100: 8457 | D100: Arundathi(LO) | F100: =C100*F2 -> 40018.093
A101: 4 | B101: Office 04 | C101: 8699 | D101: Manjula(LO) | F101: =C101*F2 -> 41163.225
A102: Total | C102: =SUM(C90+C99+C100+C101) -> 34218
A104: Twelfth Floor
A105: S.NO | B105: Description | C105: SBUA | D105: Ownership
A106: 1 | B106: Office 01 | C106: =2101 -> 2101 | D106: K. Tanuja (DEV) | F106: =C106*F2 -> 9941.825
A107: 2 | B107: Office 02 | C107: 11425 | D107: UDS (Developer + Landowner)
B108: 2.1 | C108: =11166 -> 11166 | D108: Madhukar Reddy (LO) | F108: =C108*F2 -> 52836.943
...

Sheet CAM-Aug`23
A2: CAM CHARGES CALCULATION SUMMARY - OGM-Aug`23
B3: Total Building Saleable area | C3: Area sft | D3: 490749
A4: CAM Charges INR/ Per sq ft / Month | C4: per sq. ft cost | D4: =SUM(D6:D16) -> 3.8965831
A5: Sl no | B5: Description | C5: Per month | D5: Per sft
A6: 1 | B6: Management staff | C6: 140000 | D6: =C6/D3 -> 0.28527822
A7: 2 | B7: Technical manpower | C7: 336939.16 | D7: =C7/D3 -> 0.68658145
A8: 3 | B8: HK Manpower | C8: 232689 | D8: =C8/D3 -> 0.47415074
A9: 4 | B9: LP Manpower -Security Services | C9: 605821.08 | D9: =C9/D3 -> 1.2344826
A10: 5 | B10: AMC | C10: =45000+5000 -> 50000 | D10: =C10/D3 -> 0.10188508
A11: 6 | B11: Consumables | C11: 10917 | D11: =C11/D3 -> 0.022245588
A12: 7 | B12: Common area Electrical & DG Charges | C12: 168132.03 | D12: =C12/D3 -> 0.3426029
A13: 8 | B13: Common area Water charges | C13: 9600 | D13: =C13/D3 -> 0.019561935
A14: 9 | B14: Sewerage Tanker/Water Tanker | C14: =2000*18 -> 36000 | D14: =C14/D3 -> 0.073357256
A15: 10 | B15: FMS Cost | C15: 297146 | D15: =C15/D3 -> 0.60549487
A16: 11 | B16: Liosaning & Licenses | C16: 25000 | D16: =C16/D3 -> 0.050942539
A17: A | B17: Total CAM Charges | C17: =SUM(C6:C16) -> 1912244.3
A18: 12 | B18: Contingency, Sinking Fund @2% | C18: =C17*2% -> 38244.885 | D18: =C18/D3 -> 0.077931662
A19: 13 | B19: Fixed Management Fees | C19: 490749 | D19: =C19/D3 -> 1
A20: B | B20: Including Contingency & Sinking fund Per Sft CAM Charges | C20: =(C18+C19+C17)/D3 -> 4.9745148

Sheet Tenant CAM-Aug`23
A1: Tenant CAM details-OGM-Aug`23
A2: Floor | E2: CAM cost per Sft | F2: ='CAM-Aug`23'!C20 -> 4.9745148
A3: Ground Floor
A4: S.NO | B4: Description | C4: SBUA | D4: Ownership | E4: Tenants | F4: CAM Cost | G4: Carpet Area | H4: Cost/Sft
A5: 1 | B5: Retail 01 | C5: =3311 -> 3311 | D5: Amar Chowdhary | E5: HDFC Bank Ltd | F5: =(C5)*F2 -> 16470.618 | G5: =C5*65% -> 2152.15 | H5: =F5/G5 -> 7.6530997
A6: 2 | B6: Retail 02 | C6: =3816 -> 3816 | D6: UDS Landowners | E6: Milu Foods (Vacs Bakery) | F6: =C6*F2 -> 18982.748
A7: 3 | B7: Retail 03 | C7: 3814 | D7: KSR Group | E7: Chicken Wild Wings Pvt Ltd | F7: =C7*F2 -> 18972.799
A8: 4 | B8: Retail 04 | C8: =3648 -> 3648 | D8: Aashish Bansal and Mona Bansal | E8: Fatcity Hospitality LLP | F8: =C8*F2 -> 18147.03
A9: 5 | B9: Retail 05 | C9: =3436 -> 3436 | D9: Vazir Singh Pilania and Thota Raghu Buchanna | E9: Fatcity Hospitality LLP | F9: =C9*F2 -> 17092.433
A10: 6 | B10: Retail 06 | C10: =2723 -> 2723 | D10: TanujaNayani and Ratna/Gouri Reddy | E10: Fatcity Hospitality LLP | F10: =C10*F2 -> 13545.604
A11: 7 | B11: Retail 07 | C11: =1381 -> 1381 | D11: TanujaNayani | E11: ICICI Bank Ltd | F11: =C11*F2 -> 6869.8049
A12: 8 | B12: Retail 08 | C12: =755 -> 755 | D12: K Sudhakar Reddy | E12: ICICI Bank Ltd | F12: =C12*F2 -> 3755.7587
C13: =SUM(C5:C12) -> 22884
A14: First Floor
A15: S.NO | B15: Description | C15: SBUA | D15: Ownership
A16: 1 | B16: Retail 01 | C16: =6725 -> 6725 | D16: Developer | F16: =C16*F2 -> 33453.612
A17: 2 | B17: Retail 02 | C17: =7686 -> 7686 | D17: Developer | F17: =C17*F2 -> 38234.121
A18: 3 | B18: Retail 03 | C18: =9714 -> 9714 | D18: Developer and Landowners | F18: =C18*F2 -> 48322.437
A19: 4 | B19: Retail 04 | C19: =9514 -> 9514 | D19: UDS Landowners | F19: =C19*F2 -> 47327.534
A20: Total | C20: =C16+C17+C18+C19 -> 33639
A22: Second Floor to Sixth Floor
A23: S.NO | B23: Description | C23: SBUA | D23: Ownership
A24: 1 | B24: All Offices | C24: 167554 | D24: Microchip Technology India Pvt Ltd | F24: =C24*F2 -> 833499.85
A27: Seventh Floor
A28: S.NO | B28: Description | C28: SBUA | D28: Ownership
A29: 1 | B29: Office 01 | C29: 5637 | D29: Developer
B30: 1A.1 | C30: 2000 | D30: Pamara Venkata Ramana Devi and Pamera Ram Gopal Rao | F30: =C30*F2 -> 9949.0296
B31: 1B.2 | C31: =587 -> 587 | D31: Developer | F31: =C31*F2 -> 2920.0402
B32: 1B | C32: =3050 -> 3050 | D32: Nirmal + Dileep (DEV) | F32: =C32*F2 -> 15172.27
B33: Sub-total | C33: =SUM(C30:C32) -> 5637
A34: 2 | B34: Office 02 | C34: 11425 | D34: Avinash Kotagiri (DEV) | F34: =C34*F2 -> 56833.831
A35: 3 | B35: Office 03 | C35: =8457 -> 8457 | D35: Ananth+Dileep+Anoop (DEV)
B36: 3A.1 | C36: 2156 | D36: Ananth(DEV) | F36: =C36*F2 -> 10725.054
B37: 3A.2 | C37: =2073 -> 2073 | D37: Bhavya Reddy 2,500 Sq.Ft | F37: =C37*F2 -> 10312.169
B38: 3B.1 | C38: =2927 -> 2927 | D38: Sasya Reddy 2,500 Sq.Ft | F38: =C38*F2 -> 14560.405
B39: 3B.2 | C39: =1301 -> 1301 | D39: Anoop (DEV) | F39: =C39*F2 -> 6471.8437
B40: Sub-total | C40: =SUM(C36:C39) -> 8457
A41: 4 | B41: Office 04 | C41: 8699 | D41: Anoop (DEV) | F41: =C41*F2 -> 43273.304
A42: Total | C42: =SUM(C29,C34,C35,C41) -> 34218
A44: Eighth Floor
A45: S.NO | B45: Description | C45: SBUA | D45: Ownership
A46: 1 | B46: Office 01 | C46: =2101 -> 2101 | D46: Tachyon IT Solutions Pvt Ltd (DEV) | F46: =C46*F2 -> 10451.456
A47: 2 | B47: Office 02 | C47: 11425 | D47: Tachyon IT Solutions Pvt Ltd (DEV) | F47: =C47*F2 -> 56833.831
A48: 3 | B48: Office 03 | C48: =8457 -> 8457 | D48: Tachyon IT Solutions Pvt Ltd (DEV) | F48: =C48*F2 -> 42069.472
A49: 4 | B49: Office 04 | C49: 8699 | D49: Tachyon IT Solutions Pvt Ltd (DEV) | F49: =C49*F2 -> 43273.304
A50: Total | C50: =SUM(C46:C49) -> 30682
A52: Ninth Floor
A53: S.NO | B53: Description | C53: SBUA | D53: Ownership
A54: 1 | B54: Office 01 | C54: 5637 | D54: Pulluri Mining and Logistics Pvt Ltd (DEV) | F54: =C54*F2 -> 28041.34
A55: 2 | B55: Office 02 | C55: 11425 | D55: Pulluri Mining and Logistics Pvt Ltd (DEV) | F55: =C55*F2 -> 56833.831
A56: 3 | B56: Office 03 | C56: =8457 -> 8457 | D56: UDS Developer Arjun Rao Group
B57: 3.1 | C57: =3957 -> 3957 | D57: Arjun Rao (DEV) | F57: =C57*F2 -> 19684.155
B58: 3.2 | C58: =1500 -> 1500 | D58: Karabee Kailash (Ohja) (DEV) | F58: =C58*F2 -> 7461.7722
B59: 3.3 | C59: =1500 -> 1500 | D59: Jakka Deepa (DEV) | F59: =C59*F2 -> 7461.7722
B60: 3.4 | C60: =1500 -> 1500 | D60: Indu Priya (DEV) | F60: =C60*F2 -> 7461.7722
B61: Sub-total | C61: =SUM(C57:C60) -> 8457
A62: 4 | B62: Office 04 | C62: 8699 | D62: AGA Infra Projects Pvt Ltd (DEV) | F62: =C62*F2 -> 43273.304
A63: Total | C63: =SUM(C54:C56,C62) -> 34218
A65: Tenth Floor
A66: S.NO | B66: Description | C66: SBUA | D66: Ownership
A67: 1 | B67: Office 01 | C67: 5637 | D67: Raj Kumar Maganti & Pradeep Kumar Maganti /Siri Sampada | E67: Siri Sampada Real Estate | F67: =C67*F2 -> 28041.34
A68: 2 | B68: Office 02 | C68: 11425 | D68: Developer
B69: 2.1 | C69: 3000 | D69: Srinivas Reddy Challa (DEV) | F69: =C69*F2 -> 14923.544
B70: 2.2 | C70: 1000 | D70: Shruti Gummadi (DEV) | F70: =C70*F2 -> 4974.5148
B71: 2.3 | C71: =3925-1000+500 -> 3425 | D71: Deepthi Kesireddy (DEV) | F71: =C71*F2 -> 17037.713
B72: 2.4 | C72: 1000 | D72: Chandralekha Kesireddy (DEV) | F72: =C72*F2 -> 4974.5148
B73: 2.5 | C73: 2000 | D73: Manohar SP (DEV) | F73: =C73*F2 -> 9949.0296
B74: 2.6 | C74: 1000 | D74: Shwetha Reddy | F74: =C74*F2 -> 4974.5148
B75: Sub-total | C75: =SUM(C69:C74) -> 11425
A76: 3 | B76: Office 03 | C76: =8457 -> 8457 | D76: Sukender Reddy Pulusani, Vijay Kumar & Others.
B77: 3.1 | C77: 2300 | D77: Kadiyala Venkateshwar Rao | F77: =C77*F2 -> 11441.384
B78: 3.2 | C78: 1000 | D78: Sunkara Vijaya Durga & Sunkara Jishna Sathwik | F78: =C78*F2 -> 4974.5148
B79: 3.3 | C79: 1153 | D79: Sukender Reddy Pulusani | F79: =C79*F2 -> 5735.6155
B80: 3.4 | C80: 1152 | D80: Neetha Pulusani | F80: =C80*F2 -> 5730.641
B81: 3.5 | C81: 1152 | D81: Kireet Reddy Pulusani | F81: =C81*F2 -> 5730.641
B82: 3.6 | C82: 850 | D82: Krishna Kumar Vempati | F82: =C82*F2 -> 4228.3376
B83: 3.7 | C83: 850 | D83: J Vijay Kumar & Laxmi | F83: =C83*F2 -> 4228.3376
B84: Sub-total | C84: =SUM(C77:C83) -> 8457
A85: 4 | B85: Office 04 | C85: 8699 | D85: Rohan Mandala & Sridhar Anisha (DEV) | F85: =C85*F2 -> 43273.304
A86: Total | C86: =SUM(C67,C75,C76,C85) -> 34218
A88: Eleventh Floor
A89: S.NO | B89: Description | C89: SBUA | D89: Ownership
A90: 1 | B90: Office 01 | C90: 5637 | D90: Developer
B91: 1A | C91: =2587 -> 2587 | D91: Madhusudhan Reddy Kypa(Dileep kurnool) | F91: =C91*F2 -> 12869.07
B92: 1B | C92: 3050 | D92: Pavan Kumar Mummasani & Manasa Priyadharshini (DEV) | F92: =C92*F2 -> 15172.27
B93: Sub-total | C93: =SUM(C91:C92) -> 5637
A94: 2 | B94: Office 02 | C94: 11425 | D94: UDS Landowners (KDR Family)
B95: 2.1 | C95: 3028 | D95: K. Rajesh Reddy (LO) | F95: =C95*F2 -> 15062.831
B96: 2.2 | C96: =4004-1320 -> 2684 | D96: K Saritha(LO) | F96: =C96*F2 -> 13351.598
B97: 2.3 | C97: 3028 | D97: K Ramachandra Reddy (LO) | F97: =C97*F2 -> 15062.831
B98: 2.4 | C98: =1365+1320 -> 2685 | D98: K Spandana(LO) | F98: =C98*F2 -> 13356.572
B99: Sub-total | C99: =SUM(C95:C98) -> 11425
A100: 3 | B100: Office 03 | C100: 8457 | D100: Arundathi(LO) | F100: =C100*F2 -> 42069.472
A101: 4 | B101: Office 04 | C101: 8699 | D101: Manjula(LO) | F101: =C101*F2 -> 43273.304
A102: Total | C102: =SUM(C90+C99+C100+C101) -> 34218
A104: Twelfth Floor
A105: S.NO | B105: Description | C105: SBUA | D105: Ownership
A106: 1 | B106: Office 01 | C106: =2101 -> 2101 | D106: K. Tanuja (DEV) | F106: =C106*F2 -> 10451.456
A107: 2 | B107: Office 02 | C107: 11425 | D107: UDS (Developer + Landowner)
B108: 2.1 | C108: =11166 -> 11166 | D108: Madhukar Reddy (LO) | F108: =C108*F2 -> 55545.432
...

Sheet CAM-Sep`23
A2: CAM CHARGES CALCULATION SUMMARY - OGM-Sep`23
B3: Total Building Saleable area | C3: Area sft | D3: 490749
A4: CAM Charges INR/ Per sq ft / Month | C4: per sq. ft cost | D4: =SUM(D6:D16) -> 5.0859465
A5: Sl no | B5: Description | C5: Per month | D5: Per sft
A6: 1 | B6: Management staff | C6: 140000 | D6: =C6/D3 -> 0.28527822
A7: 2 | B7: Technical manpower | C7: 303890.86 | D7: =C7/D3 -> 0.61923888
A8: 3 | B8: HK Manpower | C8: 200251 | D8: =C8/D3 -> 0.40805177
A9: 4 | B9: LP Manpower -Security Services | C9: 674625.17 | D9: =C9/D3 -> 1.3746848
A10: 5 | B10: AMC | C10: =45000+5000 -> 50000 | D10: =C10/D3 -> 0.10188508
A11: 6 | B11: Consumables | C11: 0 | D11: =C11/D3 -> 0
A12: 7 | B12: Common area Electrical & DG Charges | C12: 284860.14 | D12: =C12/D3 -> 0.58045995
A13: 8 | B13: Common area Water charges | C13: 486150 | D13: =C13/D3 -> 0.99062861
A14: 9 | B14: Sewerage Tanker/Water Tanker | C14: 34000 | D14: =C14/D3 -> 0.069281853
A15: 10 | B15: FMS Cost | C15: 297146 | D15: =C15/D3 -> 0.60549487
A16: 11 | B16: Liosaning & Licenses | C16: 25000 | D16: =C16/D3 -> 0.050942539
A17: A | B17: Total CAM Charges | C17: =SUM(C6:C16) -> 2495923.2
A18: 12 | B18: Contingency, Sinking Fund @2% | C18: =C17*2% -> 49918.463 | D18: =C18/D3 -> 0.10171893
A19: 13 | B19: Fixed Management Fees | C19: 490749 | D19: =C19/D3 -> 1
A20: B | B20: Including Contingency & Sinking fund Per Sft CAM Charges | C20: =(C18+C19+C17)/D3 -> 6.1876655

Sheet Tenant CAM-Sep`23
A1: Tenant CAM details-OGM-Oct`23
A2: Floor | E2: CAM cost per Sft | F2: ='CAM-Sep`23'!C20 -> 6.1876655
A3: Ground Floor
A4: S.NO | B4: Description | C4: SBUA | D4: Ownership | E4: Tenants | F4: CAM Cost | G4: Carpet Area | H4: Cost/Sft
A5: 1 | B5: Retail 01 | C5: =3311 -> 3311 | D5: Amar Chowdhary | E5: HDFC Bank Ltd | F5: =(C5)*F2 -> 20487.36 | G5: =C5*65% -> 2152.15 | H5: =F5/G5 -> 9.5194853
A6: 2 | B6: Retail 02 | C6: =3816 -> 3816 | D6: UDS Landowners | E6: Milu Foods (Vacs Bakery) | F6: =C6*F2 -> 23612.131
A7: 3 | B7: Retail 03 | C7: 3814 | D7: KSR Group | E7: Chicken Wild Wings Pvt Ltd | F7: =C7*F2 -> 23599.756
A8: 4 | B8: Retail 04 | C8: =3648 -> 3648 | D8: Aashish Bansal and Mona Bansal | E8: Fatcity Hospitality LLP | F8: =C8*F2 -> 22572.604
A9: 5 | B9: Retail 05 | C9: =3436 -> 3436 | D9: Vazir Singh Pilania and Thota Raghu Buchanna | E9: Fatcity Hospitality LLP | F9: =C9*F2 -> 21260.818
A10: 6 | B10: Retail 06 | C10: =2723 -> 2723 | D10: TanujaNayani and Ratna/Gouri Reddy | E10: Fatcity Hospitality LLP | F10: =C10*F2 -> 16849.013
A11: 7 | B11: Retail 07 | C11: =1381 -> 1381 | D11: TanujaNayani | E11: ICICI Bank Ltd | F11: =C11*F2 -> 8545.166
A12: 8 | B12: Retail 08 | C12: =755 -> 755 | D12: K Sudhakar Reddy | E12: ICICI Bank Ltd | F12: =C12*F2 -> 4671.6874
C13: =SUM(C5:C12) -> 22884
A14: First Floor
A15: S.NO | B15: Description | C15: SBUA | D15: Ownership
A16: 1 | B16: Retail 01 | C16: =6725 -> 6725 | D16: Developer | F16: =C16*F2 -> 41612.05
A17: 2 | B17: Retail 02 | C17: =7686 -> 7686 | D17: Developer | F17: =C17*F2 -> 47558.397
A18: 3 | B18: Retail 03 | C18: =9714 -> 9714 | D18: Developer and Landowners | F18: =C18*F2 -> 60106.982
A19: 4 | B19: Retail 04 | C19: =9514 -> 9514 | D19: UDS Landowners | F19: =C19*F2 -> 58869.449
A20: Total | C20: =C16+C17+C18+C19 -> 33639
A22: Second Floor to Sixth Floor
A23: S.NO | B23: Description | C23: SBUA | D23: Ownership
A24: 1 | B24: All Offices | C24: 167554 | D24: Microchip Technology India Pvt Ltd | F24: =C24*F2 -> 1036768.1
A27: Seventh Floor
A28: S.NO | B28: Description | C28: SBUA | D28: Ownership
A29: 1 | B29: Office 01 | C29: 5637 | D29: Developer
B30: 1A.1 | C30: 2000 | D30: Pamara Venkata Ramana Devi and Pamera Ram Gopal Rao | F30: =C30*F2 -> 12375.331
B31: 1B.2 | C31: =587 -> 587 | D31: Developer | F31: =C31*F2 -> 3632.1596
B32: 1B | C32: =3050 -> 3050 | D32: Nirmal + Dileep (DEV) | F32: =C32*F2 -> 18872.38
B33: Sub-total | C33: =SUM(C30:C32) -> 5637
A34: 2 | B34: Office 02 | C34: 11425 | D34: Avinash Kotagiri (DEV) | F34: =C34*F2 -> 70694.078
A35: 3 | B35: Office 03 | C35: =8457 -> 8457 | D35: Ananth+Dileep+Anoop (DEV)
B36: 3A.1 | C36: 2156 | D36: Ananth(DEV) | F36: =C36*F2 -> 13340.607
B37: 3A.2 | C37: =2073 -> 2073 | D37: Bhavya Reddy 2,500 Sq.Ft | F37: =C37*F2 -> 12827.03
B38: 3B.1 | C38: =2927 -> 2927 | D38: Sasya Reddy 2,500 Sq.Ft | F38: =C38*F2 -> 18111.297
B39: 3B.2 | C39: =1301 -> 1301 | D39: Anoop (DEV) | F39: =C39*F2 -> 8050.1528
B40: Sub-total | C40: =SUM(C36:C39) -> 8457
A41: 4 | B41: Office 04 | C41: 8699 | D41: Anoop (DEV) | F41: =C41*F2 -> 53826.502
A42: Total | C42: =SUM(C29,C34,C35,C41) -> 34218
A44: Eighth Floor
A45: S.NO | B45: Description | C45: SBUA | D45: Ownership
A46: 1 | B46: Office 01 | C46: =2101 -> 2101 | D46: Tachyon IT Solutions Pvt Ltd (DEV) | F46: =C46*F2 -> 13000.285
A47: 2 | B47: Office 02 | C47: 11425 | D47: Tachyon IT Solutions Pvt Ltd (DEV) | F47: =C47*F2 -> 70694.078
A48: 3 | B48: Office 03 | C48: =8457 -> 8457 | D48: Tachyon IT Solutions Pvt Ltd (DEV) | F48: =C48*F2 -> 52329.087
A49: 4 | B49: Office 04 | C49: 8699 | D49: Tachyon IT Solutions Pvt Ltd (DEV) | F49: =C49*F2 -> 53826.502
A50: Total | C50: =SUM(C46:C49) -> 30682
A52: Ninth Floor
A53: S.NO | B53: Description | C53: SBUA | D53: Ownership
A54: 1 | B54: Office 01 | C54: 5637 | D54: Pulluri Mining and Logistics Pvt Ltd (DEV) | F54: =C54*F2 -> 34879.87
A55: 2 | B55: Office 02 | C55: 11425 | D55: Pulluri Mining and Logistics Pvt Ltd (DEV) | F55: =C55*F2 -> 70694.078
A56: 3 | B56: Office 03 | C56: =8457 -> 8457 | D56: UDS Developer Arjun Rao Group
B57: 3.1 | C57: =3957 -> 3957 | D57: Arjun Rao (DEV) | F57: =C57*F2 -> 24484.592
B58: 3.2 | C58: =1500 -> 1500 | D58: Karabee Kailash (Ohja) (DEV) | F58: =C58*F2 -> 9281.4982
B59: 3.3 | C59: =1500 -> 1500 | D59: Jakka Deepa (DEV) | F59: =C59*F2 -> 9281.4982
B60: 3.4 | C60: =1500 -> 1500 | D60: Indu Priya (DEV) | F60: =C60*F2 -> 9281.4982
B61: Sub-total | C61: =SUM(C57:C60) -> 8457
A62: 4 | B62: Office 04 | C62: 8699 | D62: AGA Infra Projects Pvt Ltd (DEV) | F62: =C62*F2 -> 53826.502
A63: Total | C63: =SUM(C54:C56,C62) -> 34218
A65: Tenth Floor
A66: S.NO | B66: Description | C66: SBUA | D66: Ownership
A67: 1 | B67: Office 01 | C67: 5637 | D67: Raj Kumar Maganti & Pradeep Kumar Maganti /Siri Sampada | E67: Siri Sampada Real Estate | F67: =C67*F2 -> 34879.87
A68: 2 | B68: Office 02 | C68: 11425 | D68: Developer
B69: 2.1 | C69: 3000 | D69: Srinivas Reddy Challa (DEV) | F69: =C69*F2 -> 18562.996
B70: 2.2 | C70: 1000 | D70: Shruti Gummadi (DEV) | F70: =C70*F2 -> 6187.6655
B71: 2.3 | C71: =3925-1000+500 -> 3425 | D71: Deepthi Kesireddy (DEV) | F71: =C71*F2 -> 21192.754
B72: 2.4 | C72: 1000 | D72: Chandralekha Kesireddy (DEV) | F72: =C72*F2 -> 6187.6655
B73: 2.5 | C73: 2000 | D73: Manohar SP (DEV) | F73: =C73*F2 -> 12375.331
B74: 2.6 | C74: 1000 | D74: Shwetha Reddy | F74: =C74*F2 -> 6187.6655
B75: Sub-total | C75: =SUM(C69:C74) -> 11425
A76: 3 | B76: Office 03 | C76: =8457 -> 8457 | D76: Sukender Reddy Pulusani, Vijay Kumar & Others.
B77: 3.1 | C77: 2300 | D77: Kadiyala Venkateshwar Rao | F77: =C77*F2 -> 14231.631
B78: 3.2 | C78: 1000 | D78: Sunkara Vijaya Durga & Sunkara Jishna Sathwik | F78: =C78*F2 -> 6187.6655
B79: 3.3 | C79: 1153 | D79: Sukender Reddy Pulusani | F79: =C79*F2 -> 7134.3783
B80: 3.4 | C80: 1152 | D80: Neetha Pulusani | F80: =C80*F2 -> 7128.1906
B81: 3.5 | C81: 1152 | D81: Kireet Reddy Pulusani | F81: =C81*F2 -> 7128.1906
B82: 3.6 | C82: 850 | D82: Krishna Kumar Vempati | F82: =C82*F2 -> 5259.5156
B83: 3.7 | C83: 850 | D83: J Vijay Kumar & Laxmi | F83: =C83*F2 -> 5259.5156
B84: Sub-total | C84: =SUM(C77:C83) -> 8457
A85: 4 | B85: Office 04 | C85: 8699 | D85: Rohan Mandala & Sridhar Anisha (DEV) | F85: =C85*F2 -> 53826.502
A86: Total | C86: =SUM(C67,C75,C76,C85) -> 34218
A88: Eleventh Floor
A89: S.NO | B89: Description | C89: SBUA | D89: Ownership
A90: 1 | B90: Office 01 | C90: 5637 | D90: Developer
B91: 1A | C91: =2587 -> 2587 | D91: Madhusudhan Reddy Kypa(Dileep kurnool) | F91: =C91*F2 -> 16007.491
B92: 1B | C92: 3050 | D92: Pavan Kumar Mummasani & Manasa Priyadharshini (DEV) | F92: =C92*F2 -> 18872.38
B93: Sub-total | C93: =SUM(C91:C92) -> 5637
A94: 2 | B94: Office 02 | C94: 11425 | D94: UDS Landowners (KDR Family)
B95: 2.1 | C95: 3028 | D95: K. Rajesh Reddy (LO) | F95: =C95*F2 -> 18736.251
B96: 2.2 | C96: =4004-1320 -> 2684 | D96: K Saritha(LO) | F96: =C96*F2 -> 16607.694
B97: 2.3 | C97: 3028 | D97: K Ramachandra Reddy (LO) | F97: =C97*F2 -> 18736.251
B98: 2.4 | C98: =1365+1320 -> 2685 | D98: K Spandana(LO) | F98: =C98*F2 -> 16613.882
B99: Sub-total | C99: =SUM(C95:C98) -> 11425
A100: 3 | B100: Office 03 | C100: 8457 | D100: Arundathi(LO) | F100: =C100*F2 -> 52329.087
A101: 4 | B101: Office 04 | C101: 8699 | D101: Manjula(LO) | F101: =C101*F2 -> 53826.502
A102: Total | C102: =SUM(C90+C99+C100+C101) -> 34218
A104: Twelfth Floor
A105: S.NO | B105: Description | C105: SBUA | D105: Ownership
A106: 1 | B106: Office 01 | C106: =2101 -> 2101 | D106: K. Tanuja (DEV) | F106: =C106*F2 -> 13000.285
A107: 2 | B107: Office 02 | C107: 11425 | D107: UDS (Developer + Landowner)
B108: 2.1 | C108: =11166 -> 11166 | D108: Madhukar Reddy (LO) | F108: =C108*F2 -> 69091.472
...

Sheet CAM-Oct`23
A2: CAM CHARGES CALCULATION SUMMARY - OGM-Oct`23
B3: Total Building Saleable area | C3: Area sft | D3: 490749
A4: CAM Charges INR/ Per sq ft / Month | C4: per sq. ft cost | D4: =SUM(D6:D16) -> 5.3563081
A5: Sl no | B5: Description | C5: Per month | D5: Per sft
A6: 1 | B6: Management staff | C6: 197561 | D6: =C6/D3 -> 0.40257036
A7: 2 | B7: Technical manpower | C7: 313903.64 | D7: =C7/D3 -> 0.63964194
A8: 3 | B8: HK Manpower | C8: 209224 | D8: =C8/D3 -> 0.42633607
A9: 4 | B9: LP Manpower -Security Services | C9: 660344.45 | D9: =C9/D3 -> 1.3455849
A10: 5 | B10: AMC | C10: =45000+5000+6000 -> 56000 | D10: =C10/D3 -> 0.11411129
A11: 6 | B11: Consumables | C11: 12164 | D11: =C11/D3 -> 0.024786602
A12: 7 | B12: Common area Electrical & DG Charges | C12: 526913.85 | D12: =C12/D3 -> 1.0736932
A13: 8 | B13: Common area Water charges | C13: 330345.92 | D13: =C13/D3 -> 0.67314639
A14: 9 | B14: Sewerage Tanker/Water Tanker | D14: =C14/D3 -> 0
A15: 10 | B15: FMS Cost | C15: 297146 | D15: =C15/D3 -> 0.60549487
A16: 11 | B16: Liosaning & Licenses | C16: 25000 | D16: =C16/D3 -> 0.050942539
A17: A | B17: Total CAM Charges | C17: =SUM(C6:C16) -> 2628602.9
A18: 12 | B18: Contingency, Sinking Fund @2% | C18: =C17*2% -> 52572.057 | D18: =C18/D3 -> 0.10712616
A19: 13 | B19: Fixed Management Fees | C19: 490749 | D19: =C19/D3 -> 1
A20: B | B20: Including Contingency & Sinking fund Per Sft CAM Charges | C20: =(C18+C19+C17)/D3 -> 6.4634343

Sheet Tenant CAM-Oct`23
A1: Tenant CAM details-OGM-Oct`23
A2: Floor | E2: CAM cost per Sft | F2: ='CAM-Oct`23'!C20 -> 6.4634343
A3: Ground Floor
A4: S.NO | B4: Description | C4: SBUA | D4: Ownership | E4: Tenants | F4: CAM Cost | G4: Carpet Area | H4: Cost/Sft
A5: 1 | B5: Retail 01 | C5: =3311 -> 3311 | D5: Amar Chowdhary | E5: HDFC Bank Ltd | F5: =(C5)*F2 -> 21400.431 | G5: =C5*65% -> 2152.15 | H5: =F5/G5 -> 9.9437451
A6: 2 | B6: Retail 02 | C6: =3816 -> 3816 | D6: UDS Landowners | E6: Milu Foods (Vacs Bakery) | F6: =C6*F2 -> 24664.465
A7: 3 | B7: Retail 03 | C7: 3814 | D7: KSR Group | E7: Chicken Wild Wings Pvt Ltd | F7: =C7*F2 -> 24651.538
A8: 4 | B8: Retail 04 | C8: =3648 -> 3648 | D8: Aashish Bansal and Mona Bansal | E8: Fatcity Hospitality LLP | F8: =C8*F2 -> 23578.608
A9: 5 | B9: Retail 05 | C9: =3436 -> 3436 | D9: Vazir Singh Pilania and Thota Raghu Buchanna | E9: Fatcity Hospitality LLP | F9: =C9*F2 -> 22208.36
A10: 6 | B10: Retail 06 | C10: =2723 -> 2723 | D10: TanujaNayani and Ratna/Gouri Reddy | E10: Fatcity Hospitality LLP | F10: =C10*F2 -> 17599.932
A11: 7 | B11: Retail 07 | C11: =1381 -> 1381 | D11: TanujaNayani | E11: ICICI Bank Ltd | F11: =C11*F2 -> 8926.0028
A12: 8 | B12: Retail 08 | C12: =755 -> 755 | D12: K Sudhakar Reddy | E12: ICICI Bank Ltd | F12: =C12*F2 -> 4879.8929
C13: =SUM(C5:C12) -> 22884
A14: First Floor
A15: S.NO | B15: Description | C15: SBUA | D15: Ownership
A16: 1 | B16: Retail 01 | C16: =6725 -> 6725 | D16: Developer | F16: =C16*F2 -> 43466.596
A17: 2 | B17: Retail 02 | C17: =7686 -> 7686 | D17: Developer | F17: =C17*F2 -> 49677.956
A18: 3 | B18: Retail 03 | C18: =9714 -> 9714 | D18: Developer and Landowners | F18: =C18*F2 -> 62785.801
A19: 4 | B19: Retail 04 | C19: =9514 -> 9514 | D19: UDS Landowners | F19: =C19*F2 -> 61493.114
A20: Total | C20: =C16+C17+C18+C19 -> 33639
A22: Second Floor to Sixth Floor
A23: S.NO | B23: Description | C23: SBUA | D23: Ownership
A24: 1 | B24: All Offices | C24: 167554 | D24: Microchip Technology India Pvt Ltd | F24: =C24*F2 -> 1082974.3
A27: Seventh Floor
A28: S.NO | B28: Description | C28: SBUA | D28: Ownership
A29: 1 | B29: Office 01 | C29: 5637 | D29: Developer
B30: 1A.1 | C30: 2000 | D30: Pamara Venkata Ramana Devi and Pamera Ram Gopal Rao | F30: =C30*F2 -> 12926.869
B31: 1B.2 | C31: =587 -> 587 | D31: Developer | F31: =C31*F2 -> 3794.0359
B32: 1B | C32: =3050 -> 3050 | D32: Nirmal + Dileep (DEV) | F32: =C32*F2 -> 19713.475
B33: Sub-total | C33: =SUM(C30:C32) -> 5637
A34: 2 | B34: Office 02 | C34: 11425 | D34: Avinash Kotagiri (DEV) | F34: =C34*F2 -> 73844.737
A35: 3 | B35: Office 03 | C35: =8457 -> 8457 | D35: Ananth+Dileep+Anoop (DEV)
B36: 3A.1 | C36: 2156 | D36: Ananth(DEV) | F36: =C36*F2 -> 13935.164
B37: 3A.2 | C37: =2073 -> 2073 | D37: Bhavya Reddy 2,500 Sq.Ft | F37: =C37*F2 -> 13398.699
B38: 3B.1 | C38: =2927 -> 2927 | D38: Sasya Reddy 2,500 Sq.Ft | F38: =C38*F2 -> 18918.472
B39: 3B.2 | C39: =1301 -> 1301 | D39: Anoop (DEV) | F39: =C39*F2 -> 8408.928
B40: Sub-total | C40: =SUM(C36:C39) -> 8457
A41: 4 | B41: Office 04 | C41: 8699 | D41: Anoop (DEV) | F41: =C41*F2 -> 56225.415
A42: Total | C42: =SUM(C29,C34,C35,C41) -> 34218
A44: Eighth Floor
A45: S.NO | B45: Description | C45: SBUA | D45: Ownership
A46: 1 | B46: Office 01 | C46: =2101 -> 2101 | D46: Tachyon IT Solutions Pvt Ltd (DEV) | F46: =C46*F2 -> 13579.675
A47: 2 | B47: Office 02 | C47: 11425 | D47: Tachyon IT Solutions Pvt Ltd (DEV) | F47: =C47*F2 -> 73844.737
A48: 3 | B48: Office 03 | C48: =8457 -> 8457 | D48: Tachyon IT Solutions Pvt Ltd (DEV) | F48: =C48*F2 -> 54661.264
A49: 4 | B49: Office 04 | C49: 8699 | D49: Tachyon IT Solutions Pvt Ltd (DEV) | F49: =C49*F2 -> 56225.415
A50: Total | C50: =SUM(C46:C49) -> 30682
A52: Ninth Floor
A53: S.NO | B53: Description | C53: SBUA | D53: Ownership
A54: 1 | B54: Office 01 | C54: 5637 | D54: Pulluri Mining and Logistics Pvt Ltd (DEV) | F54: =C54*F2 -> 36434.379
A55: 2 | B55: Office 02 | C55: 11425 | D55: Pulluri Mining and Logistics Pvt Ltd (DEV) | F55: =C55*F2 -> 73844.737
A56: 3 | B56: Office 03 | C56: =8457 -> 8457 | D56: UDS Developer Arjun Rao Group
B57: 3.1 | C57: =3957 -> 3957 | D57: Arjun Rao (DEV) | F57: =C57*F2 -> 25575.809
B58: 3.2 | C58: =1500 -> 1500 | D58: Karabee Kailash (Ohja) (DEV) | F58: =C58*F2 -> 9695.1514
B59: 3.3 | C59: =1500 -> 1500 | D59: Jakka Deepa (DEV) | F59: =C59*F2 -> 9695.1514
B60: 3.4 | C60: =1500 -> 1500 | D60: Indu Priya (DEV) | F60: =C60*F2 -> 9695.1514
B61: Sub-total | C61: =SUM(C57:C60) -> 8457
A62: 4 | B62: Office 04 | C62: 8699 | D62: AGA Infra Projects Pvt Ltd (DEV) | F62: =C62*F2 -> 56225.415
A63: Total | C63: =SUM(C54:C56,C62) -> 34218
A65: Tenth Floor
A66: S.NO | B66: Description | C66: SBUA | D66: Ownership
A67: 1 | B67: Office 01 | C67: 5637 | D67: Raj Kumar Maganti & Pradeep Kumar Maganti /Siri Sampada | E67: Siri Sampada Real Estate | F67: =C67*F2 -> 36434.379
A68: 2 | B68: Office 02 | C68: 11425 | D68: Developer
B69: 2.1 | C69: 3000 | D69: Srinivas Reddy Challa (DEV) | F69: =C69*F2 -> 19390.303
B70: 2.2 | C70: 1000 | D70: Shruti Gummadi (DEV) | F70: =C70*F2 -> 6463.4343
B71: 2.3 | C71: =3925-1000+500 -> 3425 | D71: Deepthi Kesireddy (DEV) | F71: =C71*F2 -> 22137.262
B72: 2.4 | C72: 1000 | D72: Chandralekha Kesireddy (DEV) | F72: =C72*F2 -> 6463.4343
B73: 2.5 | C73: 2000 | D73: Manohar SP (DEV) | F73: =C73*F2 -> 12926.869
B74: 2.6 | C74: 1000 | D74: Shwetha Reddy | F74: =C74*F2 -> 6463.4343
B75: Sub-total | C75: =SUM(C69:C74) -> 11425
A76: 3 | B76: Office 03 | C76: =8457 -> 8457 | D76: Sukender Reddy Pulusani, Vijay Kumar & Others.
B77: 3.1 | C77: 2300 | D77: Kadiyala Venkateshwar Rao | F77: =C77*F2 -> 14865.899
B78: 3.2 | C78: 1000 | D78: Sunkara Vijaya Durga & Sunkara Jishna Sathwik | F78: =C78*F2 -> 6463.4343
B79: 3.3 | C79: 1153 | D79: Sukender Reddy Pulusani | F79: =C79*F2 -> 7452.3397
B80: 3.4 | C80: 1152 | D80: Neetha Pulusani | F80: =C80*F2 -> 7445.8763
B81: 3.5 | C81: 1152 | D81: Kireet Reddy Pulusani | F81: =C81*F2 -> 7445.8763
B82: 3.6 | C82: 850 | D82: Krishna Kumar Vempati | F82: =C82*F2 -> 5493.9191
B83: 3.7 | C83: 850 | D83: J Vijay Kumar & Laxmi | F83: =C83*F2 -> 5493.9191
B84: Sub-total | C84: =SUM(C77:C83) -> 8457
A85: 4 | B85: Office 04 | C85: 8699 | D85: Rohan Mandala & Sridhar Anisha (DEV) | F85: =C85*F2 -> 56225.415
A86: Total | C86: =SUM(C67,C75,C76,C85) -> 34218
A88: Eleventh Floor
A89: S.NO | B89: Description | C89: SBUA | D89: Ownership
A90: 1 | B90: Office 01 | C90: 5637 | D90: Developer
B91: 1A | C91: =2587 -> 2587 | D91: Madhusudhan Reddy Kypa(Dileep kurnool) | F91: =C91*F2 -> 16720.905
B92: 1B | C92: 3050 | D92: Pavan Kumar Mummasani & Manasa Priyadharshini (DEV) | F92: =C92*F2 -> 19713.475
B93: Sub-total | C93: =SUM(C91:C92) -> 5637
A94: 2 | B94: Office 02 | C94: 11425 | D94: UDS Landowners (KDR Family)
B95: 2.1 | C95: 3028 | D95: K. Rajesh Reddy (LO) | F95: =C95*F2 -> 19571.279
B96: 2.2 | C96: =4004-1320 -> 2684 | D96: K Saritha(LO) | F96: =C96*F2 -> 17347.858
B97: 2.3 | C97: 3028 | D97: K Ramachandra Reddy (LO) | F97: =C97*F2 -> 19571.279
B98: 2.4 | C98: =1365+1320 -> 2685 | D98: K Spandana(LO) | F98: =C98*F2 -> 17354.321
B99: Sub-total | C99: =SUM(C95:C98) -> 11425
A100: 3 | B100: Office 03 | C100: 8457 | D100: Arundathi(LO) | F100: =C100*F2 -> 54661.264
A101: 4 | B101: Office 04 | C101: 8699 | D101: Manjula(LO) | F101: =C101*F2 -> 56225.415
A102: Total | C102: =SUM(C90+C99+C100+C101) -> 34218
A104: Twelfth Floor
A105: S.NO | B105: Description | C105: SBUA | D105: Ownership
A106: 1 | B106: Office 01 | C106: =2101 -> 2101 | D106: K. Tanuja (DEV) | F106: =C106*F2 -> 13579.675
A107: 2 | B107: Office 02 | C107: 11425 | D107: UDS (Developer + Landowner)
B108: 2.1 | C108: =11166 -> 11166 | D108: Madhukar Reddy (LO) | F108: =C108*F2 -> 72170.707
...

Sheet CAM-Nov`23
E1: .
A2: CAM CHARGES CALCULATION SUMMARY - OGM-Nov`23
B3: Total Building Saleable area | C3: Area sft | D3: 490749
A4: CAM Charges INR/ Per sq ft / Month | C4: per sq. ft cost | D4: =SUM(D6:D16) -> 5.5546482
A5: Sl no | B5: Description | C5: Per month | D5: Per sft
A6: 1 | B6: Management staff | C6: 234758 | D6: =C6/D3 -> 0.47836674
A7: 2 | B7: Technical manpower | C7: 315254.99 | D7: =C7/D3 -> 0.64239558
A8: 3 | B8: HK Manpower | C8: 223858 | D8: =C8/D3 -> 0.45615579
A9: 4 | B9: LP Manpower -Security Services | C9: 637994.44 | D9: =C9/D3 -> 1.3000423
A10: 5 | B10: AMC | C10: =45000+5000+6000 -> 56000 | D10: =C10/D3 -> 0.11411129
A11: 6 | B11: Consumables | C11: 24951 | D11: =C11/D3 -> 0.050842691 | E11: Stationary-9-Nov`23
A12: 7 | B12: Common area Electrical & DG Charges | C12: 789696.42 | D12: =C12/D3 -> 1.6091656
A13: 8 | B13: Common area Water charges | C13: 284579.18 | D13: =C13/D3 -> 0.57988743
A14: 9 | B14: Sewerage Tanker/Water Tanker | C14: 44000 | D14: =C14/D3 -> 0.089658868
A15: 10 | B15: FMS Cost | C15: =16666+46930 -> 63596 | D15: =C15/D3 -> 0.12958967 | E15: TSSPDCL-Dairy-16666, Diwali sweets-46930
A16: 11 | B16: Liosaning & Licenses | C16: =26250+25000 -> 51250 | D16: =C16/D3 -> 0.1044322
A17: A | B17: Total CAM Charges | C17: =SUM(C6:C16) -> 2725938
A18: 12 | B18: Contingency, Sinking Fund @2% | C18: =C17*2% -> 54518.761 | D18: =C18/D3 -> 0.11109296
A19: 13 | B19: Fixed Management Fees | C19: 490749 | D19: =C19/D3 -> 1
A20: B | B20: Including Contingency & Sinking fund Per Sft CAM Charges | C20: =(C18+C19+C17)/D3 -> 6.6657411

Sheet Tenant CAM-Nov`23
A1: Tenant CAM details-OGM-Nov`23
A2: Floor | E2: CAM cost per Sft | F2: ='CAM-Nov`23'!C20 -> 6.6657411
A3: Ground Floor
A4: S.NO | B4: Description | C4: SBUA | D4: Ownership | E4: Tenants | F4: CAM Cost | G4: Carpet Area | H4: Cost/Sft
A5: 1 | B5: Retail 01 | C5: =3311 -> 3311 | D5: Amar Chowdhary | E5: HDFC Bank Ltd | F5: =(C5)*F2 -> 22070.269 | G5: =C5*65% -> 2152.15 | H5: =F5/G5 -> 10.254986
A6: 2 | B6: Retail 02 | C6: =3816 -> 3816 | D6: UDS Landowners | E6: Milu Foods (Vacs Bakery) | F6: =C6*F2 -> 25436.468
A7: 3 | B7: Retail 03 | C7: 3814 | D7: KSR Group | E7: Chicken Wild Wings Pvt Ltd | F7: =C7*F2 -> 25423.137
A8: 4 | B8: Retail 04 | C8: =3648 -> 3648 | D8: Aashish Bansal and Mona Bansal | E8: Fatcity Hospitality LLP | F8: =C8*F2 -> 24316.624
A9: 5 | B9: Retail 05 | C9: =3436 -> 3436 | D9: Vazir Singh Pilania and Thota Raghu Buchanna | E9: Fatcity Hospitality LLP | F9: =C9*F2 -> 22903.487
A10: 6 | B10: Retail 06 | C10: =2723 -> 2723 | D10: TanujaNayani and Ratna/Gouri Reddy | E10: Fatcity Hospitality LLP | F10: =C10*F2 -> 18150.813
A11: 7 | B11: Retail 07 | C11: =1381 -> 1381 | D11: TanujaNayani | E11: ICICI Bank Ltd | F11: =C11*F2 -> 9205.3885
A12: 8 | B12: Retail 08 | C12: =755 -> 755 | D12: K Sudhakar Reddy | E12: ICICI Bank Ltd | F12: =C12*F2 -> 5032.6346
C13: =SUM(C5:C12) -> 22884
A14: First Floor
A15: S.NO | B15: Description | C15: SBUA | D15: Ownership
A16: 1 | B16: Retail 01 | C16: =6725 -> 6725 | D16: Developer | F16: =C16*F2 -> 44827.109
A17: 2 | B17: Retail 02 | C17: =7686 -> 7686 | D17: Developer | F17: =C17*F2 -> 51232.886
A18: 3 | B18: Retail 03 | C18: =9714 -> 9714 | D18: Developer and Landowners | F18: =C18*F2 -> 64751.009
A19: 4 | B19: Retail 04 | C19: =9514 -> 9514 | D19: UDS Landowners | F19: =C19*F2 -> 63417.861
A20: Total | C20: =C16+C17+C18+C19 -> 33639
A22: Second Floor to Sixth Floor
A23: S.NO | B23: Description | C23: SBUA | D23: Ownership
A24: 1 | B24: All Offices | C24: 167554 | D24: Microchip Technology India Pvt Ltd | F24: =C24*F2 -> 1116871.6
A27: Seventh Floor
A28: S.NO | B28: Description | C28: SBUA | D28: Ownership
A29: 1 | B29: Office 01 | C29: 5637 | D29: Developer
B30: 1A.1 | C30: 2000 | D30: Pamara Venkata Ramana Devi and Pamera Ram Gopal Rao | F30: =C30*F2 -> 13331.482
B31: 1B.2 | C31: =587 -> 587 | D31: Developer | F31: =C31*F2 -> 3912.79
B32: 1B | C32: =3050 -> 3050 | D32: Nirmal + Dileep (DEV) | F32: =C32*F2 -> 20330.51
B33: Sub-total | C33: =SUM(C30:C32) -> 5637
A34: 2 | B34: Office 02 | C34: 11425 | D34: Avinash Kotagiri (DEV) | F34: =C34*F2 -> 76156.092
A35: 3 | B35: Office 03 | C35: =8457 -> 8457 | D35: Ananth+Dileep+Anoop (DEV)
B36: 3A.1 | C36: 2156 | D36: Ananth(DEV) | F36: =C36*F2 -> 14371.338
B37: 3A.2 | C37: =2073 -> 2073 | D37: Bhavya Reddy 2,500 Sq.Ft | F37: =C37*F2 -> 13818.081
B38: 3B.1 | C38: =2927 -> 2927 | D38: Sasya Reddy 2,500 Sq.Ft | F38: =C38*F2 -> 19510.624
B39: 3B.2 | C39: =1301 -> 1301 | D39: Anoop (DEV) | F39: =C39*F2 -> 8672.1292
B40: Sub-total | C40: =SUM(C36:C39) -> 8457
A41: 4 | B41: Office 04 | C41: 8699 | D41: Anoop (DEV) | F41: =C41*F2 -> 57985.282
A42: Total | C42: =SUM(C29,C34,C35,C41) -> 34218
A44: Eighth Floor
A45: S.NO | B45: Description | C45: SBUA | D45: Ownership
A46: 1 | B46: Office 01 | C46: =2101 -> 2101 | D46: Tachyon IT Solutions Pvt Ltd (DEV) | F46: =C46*F2 -> 14004.722
A47: 2 | B47: Office 02 | C47: 11425 | D47: Tachyon IT Solutions Pvt Ltd (DEV) | F47: =C47*F2 -> 76156.092
A48: 3 | B48: Office 03 | C48: =8457 -> 8457 | D48: Tachyon IT Solutions Pvt Ltd (DEV) | F48: =C48*F2 -> 56372.173
A49: 4 | B49: Office 04 | C49: 8699 | D49: Tachyon IT Solutions Pvt Ltd (DEV) | F49: =C49*F2 -> 57985.282
A50: Total | C50: =SUM(C46:C49) -> 30682
A52: Ninth Floor
A53: S.NO | B53: Description | C53: SBUA | D53: Ownership
A54: 1 | B54: Office 01 | C54: 5637 | D54: Pulluri Mining and Logistics Pvt Ltd (DEV) | F54: =C54*F2 -> 37574.783
A55: 2 | B55: Office 02 | C55: 11425 | D55: Pulluri Mining and Logistics Pvt Ltd (DEV) | F55: =C55*F2 -> 76156.092
A56: 3 | B56: Office 03 | C56: =8457 -> 8457 | D56: UDS Developer Arjun Rao Group
B57: 3.1 | C57: =3957 -> 3957 | D57: Arjun Rao (DEV) | F57: =C57*F2 -> 26376.338
B58: 3.2 | C58: =1500 -> 1500 | D58: Karabee Kailash (Ohja) (DEV) | F58: =C58*F2 -> 9998.6117
B59: 3.3 | C59: =1500 -> 1500 | D59: Jakka Deepa (DEV) | F59: =C59*F2 -> 9998.6117
B60: 3.4 | C60: =1500 -> 1500 | D60: Indu Priya (DEV) | F60: =C60*F2 -> 9998.6117
B61: Sub-total | C61: =SUM(C57:C60) -> 8457
A62: 4 | B62: Office 04 | C62: 8699 | D62: AGA Infra Projects Pvt Ltd (DEV) | F62: =C62*F2 -> 57985.282
A63: Total | C63: =SUM(C54:C56,C62) -> 34218
A65: Tenth Floor
A66: S.NO | B66: Description | C66: SBUA | D66: Ownership
A67: 1 | B67: Office 01 | C67: 5637 | D67: Raj Kumar Maganti & Pradeep Kumar Maganti /Siri Sampada | E67: Siri Sampada Real Estate | F67: =C67*F2 -> 37574.783
A68: 2 | B68: Office 02 | C68: 11425 | D68: Developer
B69: 2.1 | C69: 3000 | D69: Srinivas Reddy Challa (DEV) | F69: =C69*F2 -> 19997.223
B70: 2.2 | C70: 1000 | D70: Shruti Gummadi (DEV) | F70: =C70*F2 -> 6665.7411
B71: 2.3 | C71: =3925-1000+500 -> 3425 | D71: Deepthi Kesireddy (DEV) | F71: =C71*F2 -> 22830.163
B72: 2.4 | C72: 1000 | D72: Chandralekha Kesireddy (DEV) | F72: =C72*F2 -> 6665.7411
B73: 2.5 | C73: 2000 | D73: Manohar SP (DEV) | F73: =C73*F2 -> 13331.482
B74: 2.6 | C74: 1000 | D74: Shwetha Reddy | F74: =C74*F2 -> 6665.7411
B75: Sub-total | C75: =SUM(C69:C74) -> 11425
A76: 3 | B76: Office 03 | C76: =8457 -> 8457 | D76: Sukender Reddy Pulusani, Vijay Kumar & Others.
B77: 3.1 | C77: 2300 | D77: Kadiyala Venkateshwar Rao | F77: =C77*F2 -> 15331.205
B78: 3.2 | C78: 1000 | D78: Sunkara Vijaya Durga & Sunkara Jishna Sathwik | F78: =C78*F2 -> 6665.7411
B79: 3.3 | C79: 1153 | D79: Sukender Reddy Pulusani | F79: =C79*F2 -> 7685.5995
B80: 3.4 | C80: 1152 | D80: Neetha Pulusani | F80: =C80*F2 -> 7678.9338
B81: 3.5 | C81: 1152 | D81: Kireet Reddy Pulusani | F81: =C81*F2 -> 7678.9338
B82: 3.6 | C82: 850 | D82: Krishna Kumar Vempati | F82: =C82*F2 -> 5665.88
B83: 3.7 | C83: 850 | D83: J Vijay Kumar & Laxmi | F83: =C83*F2 -> 5665.88
B84: Sub-total | C84: =SUM(C77:C83) -> 8457
A85: 4 | B85: Office 04 | C85: 8699 | D85: Rohan Mandala & Sridhar Anisha (DEV) | F85: =C85*F2 -> 57985.282
A86: Total | C86: =SUM(C67,C75,C76,C85) -> 34218
A88: Eleventh Floor
A89: S.NO | B89: Description | C89: SBUA | D89: Ownership
A90: 1 | B90: Office 01 | C90: 5637 | D90: Developer
B91: 1A | C91: =2587 -> 2587 | D91: Madhusudhan Reddy Kypa(Dileep kurnool) | F91: =C91*F2 -> 17244.272
B92: 1B | C92: 3050 | D92: Pavan Kumar Mummasani & Manasa Priyadharshini (DEV) | F92: =C92*F2 -> 20330.51
B93: Sub-total | C93: =SUM(C91:C92) -> 5637
A94: 2 | B94: Office 02 | C94: 11425 | D94: UDS Landowners (KDR Family)
B95: 2.1 | C95: 3028 | D95: K. Rajesh Reddy (LO) | F95: =C95*F2 -> 20183.864
B96: 2.2 | C96: =4004-1320 -> 2684 | D96: K Saritha(LO) | F96: =C96*F2 -> 17890.849
B97: 2.3 | C97: 3028 | D97: K Ramachandra Reddy (LO) | F97: =C97*F2 -> 20183.864
B98: 2.4 | C98: =1365+1320 -> 2685 | D98: K Spandana(LO) | F98: =C98*F2 -> 17897.515
B99: Sub-total | C99: =SUM(C95:C98) -> 11425
A100: 3 | B100: Office 03 | C100: 8457 | D100: Arundathi(LO) | F100: =C100*F2 -> 56372.173
A101: 4 | B101: Office 04 | C101: 8699 | D101: Manjula(LO) | F101: =C101*F2 -> 57985.282
A102: Total | C102: =SUM(C90+C99+C100+C101) -> 34218
A104: Twelfth Floor
A105: S.NO | B105: Description | C105: SBUA | D105: Ownership
A106: 1 | B106: Office 01 | C106: =2101 -> 2101 | D106: K. Tanuja (DEV) | F106: =C106*F2 -> 14004.722
A107: 2 | B107: Office 02 | C107: 11425 | D107: UDS (Developer + Landowner)
B108: 2.1 | C108: =11166 -> 11166 | D108: Madhukar Reddy (LO) | F108: =C108*F2 -> 74429.665
...

Sheet CAM-Dec`23
E1: .
A2: CAM CHARGES CALCULATION SUMMARY - OGM-Dec`23
B3: Total Building Saleable area | C3: Area sft | D3: 490749
A4: CAM Charges INR/ Per sq ft / Month | C4: per sq. ft cost | D4: =SUM(D6:D16) -> 5.7837036
A5: Sl no | B5: Description | C5: Per month | D5: Per sft
A6: 1 | B6: Management staff | C6: 262200 | D6: =C6/D3 -> 0.53428535
A7: 2 | B7: Technical manpower | C7: 315466 | D7: =C7/D3 -> 0.64282556
A8: 3 | B8: HK Manpower | C8: 214010 | D8: =C8/D3 -> 0.43608851
A9: 4 | B9: LP Manpower -Security Services | C9: 660344 | D9: =C9/D3 -> 1.345584
A10: 5 | B10: AMC | C10: =45000+5000+6000 -> 56000 | D10: =C10/D3 -> 0.11411129
A11: 6 | B11: Consumables | C11: 52361 | D11: =C11/D3 -> 0.10669609
A12: 7 | B12: Common area Electrical & DG Charges | C12: 861105.07 | D12: =C12/D3 -> 1.7546751
A13: 8 | B13: Common area Water charges | C13: 259757.67 | D13: =C13/D3 -> 0.52930861
A14: 9 | B14: Sewerage Tanker/Water Tanker | C14: 0 | D14: =C14/D3 -> 0
A15: 10 | B15: FMS Cost | C15: 79603 | D15: =C15/D3 -> 0.16220716
A16: 11 | B16: Liosaning & Licenses | C16: =52500+25000 -> 77500 | D16: =C16/D3 -> 0.15792187
A17: A | B17: Total CAM Charges | C17: =SUM(C6:C16) -> 2838346.7
A18: 12 | B18: Contingency, Sinking Fund @2% | C18: =C17*2% -> 56766.935 | D18: =C18/D3 -> 0.11567407
A19: 13 | B19: Fixed Management Fees | C19: 490749 | D19: =C19/D3 -> 1
A20: B | B20: Including Contingency & Sinking fund Per Sft CAM Charges | C20: =(C18+C19+C17)/D3 -> 6.8993776

Sheet Tenant CAM-Dec`23
A1: Tenant CAM details-OGM-Dec`23
A2: Floor | E2: CAM cost per Sft | F2: ='CAM-Dec`23'!C20 -> 6.8993776
A3: Ground Floor
A4: S.NO | B4: Description | C4: SBUA | D4: Ownership | E4: Tenants | F4: CAM Cost | G4: Carpet Area | H4: Cost/Sft
A5: 1 | B5: Retail 01 | C5: =3311 -> 3311 | D5: Amar Chowdhary | E5: HDFC Bank Ltd | F5: =(C5)*F2 -> 22843.839 | G5: =C5*65% -> 2152.15 | H5: =F5/G5 -> 10.614427
A6: 2 | B6: Retail 02 | C6: =3816 -> 3816 | D6: UDS Landowners | E6: Milu Foods (Vacs Bakery) | F6: =C6*F2 -> 26328.025
A7: 3 | B7: Retail 03 | C7: 3814 | D7: KSR Group | E7: Chicken Wild Wings Pvt Ltd | F7: =C7*F2 -> 26314.226
A8: 4 | B8: Retail 04 | C8: =3648 -> 3648 | D8: Aashish Bansal and Mona Bansal | E8: Fatcity Hospitality LLP | F8: =C8*F2 -> 25168.93
A9: 5 | B9: Retail 05 | C9: =3436 -> 3436 | D9: Vazir Singh Pilania and Thota Raghu Buchanna | E9: Fatcity Hospitality LLP | F9: =C9*F2 -> 23706.262
A10: 6 | B10: Retail 06 | C10: =2723 -> 2723 | D10: TanujaNayani and Ratna/Gouri Reddy | E10: Fatcity Hospitality LLP | F10: =C10*F2 -> 18787.005
A11: 7 | B11: Retail 07 | C11: =1381 -> 1381 | D11: TanujaNayani | E11: ICICI Bank Ltd | F11: =C11*F2 -> 9528.0405
A12: 8 | B12: Retail 08 | C12: =755 -> 755 | D12: K Sudhakar Reddy | E12: ICICI Bank Ltd | F12: =C12*F2 -> 5209.0301
C13: =SUM(C5:C12) -> 22884
A14: First Floor
A15: S.NO | B15: Description | C15: SBUA | D15: Ownership
A16: 1 | B16: Retail 01 | C16: =6725 -> 6725 | D16: Developer | F16: =C16*F2 -> 46398.315
A17: 2 | B17: Retail 02 | C17: =7686 -> 7686 | D17: Developer | F17: =C17*F2 -> 53028.616
A18: 3 | B18: Retail 03 | C18: =9714 -> 9714 | D18: Developer and Landowners | F18: =C18*F2 -> 67020.554
A19: 4 | B19: Retail 04 | C19: =9514 -> 9514 | D19: UDS Landowners | F19: =C19*F2 -> 65640.679
A20: Total | C20: =C16+C17+C18+C19 -> 33639
A22: Second Floor to Sixth Floor
A23: S.NO | B23: Description | C23: SBUA | D23: Ownership
A24: 1 | B24: All Offices | C24: 167554 | D24: Microchip Technology India Pvt Ltd | F24: =C24*F2 -> 1156018.3
A27: Seventh Floor
A28: S.NO | B28: Description | C28: SBUA | D28: Ownership
A29: 1 | B29: Office 01 | C29: 5637 | D29: Developer
B30: 1A.1 | C30: 2000 | D30: Pamara Venkata Ramana Devi and Pamera Ram Gopal Rao | F30: =C30*F2 -> 13798.755
B31: 1B.2 | C31: =587 -> 587 | D31: Developer | F31: =C31*F2 -> 4049.9347
B32: 1B | C32: =3050 -> 3050 | D32: Nirmal + Dileep (DEV) | F32: =C32*F2 -> 21043.102
B33: Sub-total | C33: =SUM(C30:C32) -> 5637
A34: 2 | B34: Office 02 | C34: 11425 | D34: Avinash Kotagiri (DEV) | F34: =C34*F2 -> 78825.389
A35: 3 | B35: Office 03 | C35: =8457 -> 8457 | D35: Ananth+Dileep+Anoop (DEV)
B36: 3A.1 | C36: 2156 | D36: Ananth(DEV) | F36: =C36*F2 -> 14875.058
B37: 3A.2 | C37: =2073 -> 2073 | D37: Bhavya Reddy 2,500 Sq.Ft | F37: =C37*F2 -> 14302.41
B38: 3B.1 | C38: =2927 -> 2927 | D38: Sasya Reddy 2,500 Sq.Ft | F38: =C38*F2 -> 20194.478
B39: 3B.2 | C39: =1301 -> 1301 | D39: Anoop (DEV) | F39: =C39*F2 -> 8976.0903
B40: Sub-total | C40: =SUM(C36:C39) -> 8457
A41: 4 | B41: Office 04 | C41: 8699 | D41: Anoop (DEV) | F41: =C41*F2 -> 60017.686
A42: Total | C42: =SUM(C29,C34,C35,C41) -> 34218
A44: Eighth Floor
A45: S.NO | B45: Description | C45: SBUA | D45: Ownership
A46: 1 | B46: Office 01 | C46: =2101 -> 2101 | D46: Tachyon IT Solutions Pvt Ltd (DEV) | F46: =C46*F2 -> 14495.592
A47: 2 | B47: Office 02 | C47: 11425 | D47: Tachyon IT Solutions Pvt Ltd (DEV) | F47: =C47*F2 -> 78825.389
A48: 3 | B48: Office 03 | C48: =8457 -> 8457 | D48: Tachyon IT Solutions Pvt Ltd (DEV) | F48: =C48*F2 -> 58348.037
A49: 4 | B49: Office 04 | C49: 8699 | D49: Tachyon IT Solutions Pvt Ltd (DEV) | F49: =C49*F2 -> 60017.686
A50: Total | C50: =SUM(C46:C49) -> 30682
A52: Ninth Floor
A53: S.NO | B53: Description | C53: SBUA | D53: Ownership
A54: 1 | B54: Office 01 | C54: 5637 | D54: Pulluri Mining and Logistics Pvt Ltd (DEV) | F54: =C54*F2 -> 38891.792
A55: 2 | B55: Office 02 | C55: 11425 | D55: Pulluri Mining and Logistics Pvt Ltd (DEV) | F55: =C55*F2 -> 78825.389
A56: 3 | B56: Office 03 | C56: =8457 -> 8457 | D56: UDS Developer Arjun Rao Group
B57: 3.1 | C57: =3957 -> 3957 | D57: Arjun Rao (DEV) | F57: =C57*F2 -> 27300.837
B58: 3.2 | C58: =1500 -> 1500 | D58: Karabee Kailash (Ohja) (DEV) | F58: =C58*F2 -> 10349.066
B59: 3.3 | C59: =1500 -> 1500 | D59: Jakka Deepa (DEV) | F59: =C59*F2 -> 10349.066
B60: 3.4 | C60: =1500 -> 1500 | D60: Indu Priya (DEV) | F60: =C60*F2 -> 10349.066
B61: Sub-total | C61: =SUM(C57:C60) -> 8457
A62: 4 | B62: Office 04 | C62: 8699 | D62: AGA Infra Projects Pvt Ltd (DEV) | F62: =C62*F2 -> 60017.686
A63: Total | C63: =SUM(C54:C56,C62) -> 34218
A65: Tenth Floor
A66: S.NO | B66: Description | C66: SBUA | D66: Ownership
A67: 1 | B67: Office 01 | C67: 5637 | D67: Raj Kumar Maganti & Pradeep Kumar Maganti /Siri Sampada | E67: Siri Sampada Real Estate | F67: =C67*F2 -> 38891.792
A68: 2 | B68: Office 02 | C68: 11425 | D68: Developer
B69: 2.1 | C69: 3000 | D69: Srinivas Reddy Challa (DEV) | F69: =C69*F2 -> 20698.133
B70: 2.2 | C70: 1000 | D70: Shruti Gummadi (DEV) | F70: =C70*F2 -> 6899.3776
B71: 2.3 | C71: =3925-1000+500 -> 3425 | D71: Deepthi Kesireddy (DEV) | F71: =C71*F2 -> 23630.368
B72: 2.4 | C72: 1000 | D72: Chandralekha Kesireddy (DEV) | F72: =C72*F2 -> 6899.3776
B73: 2.5 | C73: 2000 | D73: Manohar SP (DEV) | F73: =C73*F2 -> 13798.755
B74: 2.6 | C74: 1000 | D74: Shwetha Reddy | F74: =C74*F2 -> 6899.3776
B75: Sub-total | C75: =SUM(C69:C74) -> 11425
A76: 3 | B76: Office 03 | C76: =8457 -> 8457 | D76: Sukender Reddy Pulusani, Vijay Kumar & Others.
B77: 3.1 | C77: 2300 | D77: Kadiyala Venkateshwar Rao | F77: =C77*F2 -> 15868.569
B78: 3.2 | C78: 1000 | D78: Sunkara Vijaya Durga & Sunkara Jishna Sathwik | F78: =C78*F2 -> 6899.3776
B79: 3.3 | C79: 1153 | D79: Sukender Reddy Pulusani | F79: =C79*F2 -> 7954.9824
B80: 3.4 | C80: 1152 | D80: Neetha Pulusani | F80: =C80*F2 -> 7948.083
B81: 3.5 | C81: 1152 | D81: Kireet Reddy Pulusani | F81: =C81*F2 -> 7948.083
B82: 3.6 | C82: 850 | D82: Krishna Kumar Vempati | F82: =C82*F2 -> 5864.471
B83: 3.7 | C83: 850 | D83: J Vijay Kumar & Laxmi | F83: =C83*F2 -> 5864.471
B84: Sub-total | C84: =SUM(C77:C83) -> 8457
A85: 4 | B85: Office 04 | C85: 8699 | D85: Rohan Mandala & Sridhar Anisha (DEV) | F85: =C85*F2 -> 60017.686
A86: Total | C86: =SUM(C67,C75,C76,C85) -> 34218
A88: Eleventh Floor
A89: S.NO | B89: Description | C89: SBUA | D89: Ownership
A90: 1 | B90: Office 01 | C90: 5637 | D90: Developer
B91: 1A | C91: =2587 -> 2587 | D91: Madhusudhan Reddy Kypa(Dileep kurnool) | F91: =C91*F2 -> 17848.69
B92: 1B | C92: 3050 | D92: Pavan Kumar Mummasani & Manasa Priyadharshini (DEV) | F92: =C92*F2 -> 21043.102
B93: Sub-total | C93: =SUM(C91:C92) -> 5637
A94: 2 | B94: Office 02 | C94: 11425 | D94: UDS Landowners (KDR Family)
B95: 2.1 | C95: 3028 | D95: K. Rajesh Reddy (LO) | F95: =C95*F2 -> 20891.315
B96: 2.2 | C96: =4004-1320 -> 2684 | D96: K Saritha(LO) | F96: =C96*F2 -> 18517.93
B97: 2.3 | C97: 3028 | D97: K Ramachandra Reddy (LO) | F97: =C97*F2 -> 20891.315
B98: 2.4 | C98: =1365+1320 -> 2685 | D98: K Spandana(LO) | F98: =C98*F2 -> 18524.829
B99: Sub-total | C99: =SUM(C95:C98) -> 11425
A100: 3 | B100: Office 03 | C100: 8457 | D100: Arundathi(LO) | F100: =C100*F2 -> 58348.037
A101: 4 | B101: Office 04 | C101: 8699 | D101: Manjula(LO) | F101: =C101*F2 -> 60017.686
A102: Total | C102: =SUM(C90+C99+C100+C101) -> 34218
A104: Twelfth Floor
A105: S.NO | B105: Description | C105: SBUA | D105: Ownership
A106: 1 | B106: Office 01 | C106: =2101 -> 2101 | D106: K. Tanuja (DEV) | F106: =C106*F2 -> 14495.592
A107: 2 | B107: Office 02 | C107: 11425 | D107: UDS (Developer + Landowner)
B108: 2.1 | C108: =11166 -> 11166 | D108: Madhukar Reddy (LO) | F108: =C108*F2 -> 77038.451
...

Sheet CAM-Jan`24
A1: CAM CHARGES CALCULATION SUMMARY - OGM-Jan`24
B2: Total Building Saleable Area | C2: Area sft | D2: 490749 | E2: MCP Occupied area | H2: OGM Area
A3: CAM Charges INR/ Per sq ft / Month | C3: per sq. ft cost | D3: =SUM(D5:D17) -> 6.3058776 | E3: MCP | F3: Per Sft | G3: 167554 | H3: =D2-G3 -> 323195
A4: Sl no | B4: Description | C4: Per month | D4: Per sft
A5: 1 | B5: Management staff (By Area) | C5: =262200+77500 -> 339700 | D5: =C5/D2 -> 0.69220722 | G5: =G3*D5 -> 115982.09 | H5: =H3*D5 -> 223717.91
A6: 2 | B6: Technical manpower | C6: 354076 | D6: =C6/D2 -> 0.72150122 | E6: =C6*D28 -> 114786.34 | F6: =E6/D2 -> 0.23390031 | G6: =F6*G3 -> 39190.932 | H6: =C6-G6 -> 314885.07
A7: 3 | B7: HK Manpower | C7: 253952 | D7: =C7/D2 -> 0.51747839 | E7: =C7*D27 -> 173672.13 | F7: =E7/D2 -> 0.35389197 | G7: =F7*G3 -> 59296.015 | H7: =C7-G7 -> 194655.99
A8: 4 | B8: LP Manpower -Security Services | C8: 751571 | D8: =C8/D2 -> 1.5314774 | G8: =G3*D8 -> 256605.16 | H8: =H3*D8 -> 494965.84
A9: 5 | B9: AMC | C9: =45000+5000+6000 -> 56000 | D9: =C9/D2 -> 0.11411129 | G9: =D9*G3 -> 19119.803 | H9: =D9*H3 -> 36880.197
A10: 6 | B10: AMC Excl. MCP | C10: 0 | D10: 0 | G10: 0
A11: 7 | B11: Consumables | C11: 0 | D11: =C11/D2 -> 0 | E11: =C11*D27 -> 0 | F11: =E11/D2 -> 0 | G11: =F11*G3 -> 0 | H11: =C11-G11 -> 0
A12: 8 | B12: Consumables Excl MCP | C12: 0 | D12: 0 | G12: 0
A13: 9 | B13: Common area Electrical & DG Charges (Tech %Share) | C13: 1057296.1 | D13: =C13/D2 -> 2.1544539 | E13: =+C13*D28 -> 342760.18 | F13: =E13/D2 -> 0.69844295 | G13: =F13*G3 -> 117026.91 | H13: =C13-G13 -> 940269.21
A14: 10 | B14: Common area Water charges (By Area) | C14: =266239-C15 -> 266239 | D14: =C14/D2 -> 0.54251562 | G14: =G3*D14 -> 90900.663 | H14: =H3*D14 -> 175338.34
A15: 11 | B15: Cooling Tower water charges | C15: =E32 -> 0 | H15: =C15 -> 0
A16: 12 | B16: FMS Cost (By Area) | C16: 15769 | D16: =C16/D2 -> 0.032132516 | G16: =D16*G3 -> 5383.9316 | H16: =H3*D16 -> 10385.068
A17: 13 | B17: Liosaning & Licenses | C17: 0 | D17: =C17/D2 -> 0 | G17: =D17*G4 -> 0 | H17: =C17-G17 -> 0
A18: A | B18: Total CAM Charges | C18: =SUM(C5:C17) -> 3094603.1 | G18: =SUM(G5:G17) -> 703505.5 | H18: =SUM(H5:H17) -> 2391097.6
A19: 14 | B19: Contingency, Sinking Fund @2% | C19: =C18*2% -> 61892.062 | G19: =G18*2% -> 14070.11 | H19: =C19-G19 -> 47821.952
A20: 15 | B20: Fixed Management Fees | C20: 490749 | D20: =C20/D2 -> 1 | G20: =D20*G3 -> 167554 | H20: =C20-G20 -> 323195
B21: Grand Total | C21: =C18+C19+C20 -> 3647244.2 | G21: =G18+G19+G20 -> 885129.61 | H21: =H18+H19+H20 -> 2762114.6
A22: B | B22: Including Contingency & Sinking fund Per Sft CAM Charges | C22: =(C19+C20+C18)/D2 -> 7.4319951 | G22: =(G18+G19+G20)/G3 -> 5.2826528 | H22: =(H19+H20+H18)/H3 -> 8.5462788
A25: S No | B25: Description | C25: Total Area in SFT | D25: % on Total area | E25: Remarks
A26: 1 | B26: Total building common area | C26: 381481.87
A27: 2 | B27: MCP Utilization common area | C27: 260886.97 | D27: =C27/C26 -> 0.68387778 | E27: Housekeeping
A28: 3 | B28: MCP Utilization common area | C28: 123670.93 | D28: =C28/C26 -> 0.3241856 | E28: Technical
A29: 4 | B29: B4 parking
A31: S No | B31: January`24 | C31: Consumed KL | D31: Rate/KL | E31: Amount
A32: 1 | B32: MCP cooling tower water consumption | C32: 0 | D32: 332.68 | E32: =C32*D32 -> 0 | F32: Water meter not fixed.

Sheet Tenant CAM-Jan`24
A1: Tenant CAM details-OGM-Jan`24
A2: Floor | E2: CAM cost per Sft | F2: ='CAM-Jan`24'!H22 -> 8.5462788
A3: Ground Floor
A4: S.NO | B4: Description | C4: SBUA | D4: Ownership | E4: Tenants | F4: CAM Cost | G4: Carpet Area | H4: Cost/Sft
A5: 1 | B5: Retail 01 | C5: =3311 -> 3311 | D5: Amar Chowdhary | E5: HDFC Bank Ltd | F5: =(C5)*F2 -> 28296.729 | G5: =C5*65% -> 2152.15 | H5: =F5/G5 -> 13.148121
A6: 2 | B6: Retail 02 | C6: =3816 -> 3816 | D6: UDS Landowners | E6: Milu Foods (Vacs Bakery) | F6: =C6*F2 -> 32612.6
A7: 3 | B7: Retail 03 | C7: 3814 | D7: KSR Group | E7: Chicken Wild Wings Pvt Ltd | F7: =C7*F2 -> 32595.507
A8: 4 | B8: Retail 04 | C8: =3648 -> 3648 | D8: Aashish Bansal and Mona Bansal | E8: Fatcity Hospitality LLP | F8: =C8*F2 -> 31176.825
A9: 5 | B9: Retail 05 | C9: =3436 -> 3436 | D9: Vazir Singh Pilania and Thota Raghu Buchanna | E9: Fatcity Hospitality LLP | F9: =C9*F2 -> 29365.014
A10: 6 | B10: Retail 06 | C10: =2723 -> 2723 | D10: TanujaNayani and Ratna/Gouri Reddy | E10: Fatcity Hospitality LLP | F10: =C10*F2 -> 23271.517
A11: 7 | B11: Retail 07 | C11: =1381 -> 1381 | D11: TanujaNayani | E11: ICICI Bank Ltd | F11: =C11*F2 -> 11802.411
A12: 8 | B12: Retail 08 | C12: =755 -> 755 | D12: K Sudhakar Reddy | E12: ICICI Bank Ltd | F12: =C12*F2 -> 6452.4405
C13: =SUM(C5:C12) -> 22884
A14: First Floor
A15: S.NO | B15: Description | C15: SBUA | D15: Ownership
A16: 1 | B16: Retail 01 | C16: =6725 -> 6725 | D16: Developer | F16: =C16*F2 -> 57473.725
A17: 2 | B17: Retail 02 | C17: =7686 -> 7686 | D17: Developer | F17: =C17*F2 -> 65686.699
A18: 3 | B18: Retail 03 | C18: =9714 -> 9714 | D18: Developer and Landowners | F18: =C18*F2 -> 83018.552
A19: 4 | B19: Retail 04 | C19: =9514 -> 9514 | D19: UDS Landowners | F19: =C19*F2 -> 81309.296
A20: Total | C20: =C16+C17+C18+C19 -> 33639
A22: Second Floor to Sixth Floor
A23: S.NO | B23: Description | C23: SBUA | D23: Ownership
A24: 1 | B24: All Offices | C24: 167554 | D24: Microchip Technology India Pvt Ltd | F24: =C24*'CAM-Jan`24'!G22 -> 885129.61
A27: Seventh Floor
A28: S.NO | B28: Description | C28: SBUA | D28: Ownership
A29: 1 | B29: Office 01 | C29: 5637 | D29: Developer
B30: 1A.1 | C30: 2000 | D30: Pamara Venkata Ramana Devi and Pamera Ram Gopal Rao | F30: =C30*F2 -> 17092.558
B31: 1B.2 | C31: =587 -> 587 | D31: Developer | F31: =C31*F2 -> 5016.6656
B32: 1B | C32: =3050 -> 3050 | D32: Nirmal + Dileep (DEV) | F32: =C32*F2 -> 26066.15
B33: Sub-total | C33: =SUM(C30:C32) -> 5637
A34: 2 | B34: Office 02 | C34: 11425 | D34: Avinash Kotagiri (DEV) | F34: =C34*F2 -> 97641.235
A35: 3 | B35: Office 03 | C35: =8457 -> 8457 | D35: Ananth+Dileep+Anoop (DEV)
B36: 3A.1 | C36: 2156 | D36: Ananth(DEV) | F36: =C36*F2 -> 18425.777
B37: 3A.2 | C37: =2073 -> 2073 | D37: Bhavya Reddy 2,500 Sq.Ft | F37: =C37*F2 -> 17716.436
B38: 3B.1 | C38: =2927 -> 2927 | D38: Sasya Reddy 2,500 Sq.Ft | F38: =C38*F2 -> 25014.958
B39: 3B.2 | C39: =1301 -> 1301 | D39: Anoop (DEV) | F39: =C39*F2 -> 11118.709
B40: Sub-total | C40: =SUM(C36:C39) -> 8457
A41: 4 | B41: Office 04 | C41: 8699 | D41: Anoop (DEV) | F41: =C41*F2 -> 74344.079
A42: Total | C42: =SUM(C29,C34,C35,C41) -> 34218
A44: Eighth Floor
A45: S.NO | B45: Description | C45: SBUA | D45: Ownership
A46: 1 | B46: Office 01 | C46: =2101 -> 2101 | D46: Tachyon IT Solutions Pvt Ltd (DEV) | F46: =C46*F2 -> 17955.732
A47: 2 | B47: Office 02 | C47: 11425 | D47: Tachyon IT Solutions Pvt Ltd (DEV) | F47: =C47*F2 -> 97641.235
A48: 3 | B48: Office 03 | C48: =8457 -> 8457 | D48: Tachyon IT Solutions Pvt Ltd (DEV) | F48: =C48*F2 -> 72275.879
A49: 4 | B49: Office 04 | C49: 8699 | D49: Tachyon IT Solutions Pvt Ltd (DEV) | F49: =C49*F2 -> 74344.079
A50: Total | C50: =SUM(C46:C49) -> 30682
A52: Ninth Floor
A53: S.NO | B53: Description | C53: SBUA | D53: Ownership
A54: 1 | B54: Office 01 | C54: 5637 | D54: Pulluri Mining and Logistics Pvt Ltd (DEV) | F54: =C54*F2 -> 48175.373
A55: 2 | B55: Office 02 | C55: 11425 | D55: Pulluri Mining and Logistics Pvt Ltd (DEV) | F55: =C55*F2 -> 97641.235
A56: 3 | B56: Office 03 | C56: =8457 -> 8457 | D56: UDS Developer Arjun Rao Group
B57: 3.1 | C57: =3957 -> 3957 | D57: Arjun Rao (DEV) | F57: =C57*F2 -> 33817.625
B58: 3.2 | C58: =1500 -> 1500 | D58: Karabee Kailash (Ohja) (DEV) | F58: =C58*F2 -> 12819.418
B59: 3.3 | C59: =1500 -> 1500 | D59: Jakka Deepa (DEV) | F59: =C59*F2 -> 12819.418
B60: 3.4 | C60: =1500 -> 1500 | D60: Indu Priya (DEV) | F60: =C60*F2 -> 12819.418
B61: Sub-total | C61: =SUM(C57:C60) -> 8457
A62: 4 | B62: Office 04 | C62: 8699 | D62: AGA Infra Projects Pvt Ltd (DEV) | F62: =C62*F2 -> 74344.079
A63: Total | C63: =SUM(C54:C56,C62) -> 34218
A65: Tenth Floor
A66: S.NO | B66: Description | C66: SBUA | D66: Ownership
A67: 1 | B67: Office 01 | C67: 5637 | D67: Raj Kumar Maganti & Pradeep Kumar Maganti /Siri Sampada | E67: Siri Sampada Real Estate | F67: =C67*F2 -> 48175.373
A68: 2 | B68: Office 02 | C68: 11425 | D68: Developer
B69: 2.1 | C69: 3000 | D69: Srinivas Reddy Challa (DEV) | F69: =C69*F2 -> 25638.836
B70: 2.2 | C70: 1000 | D70: Shruti Gummadi (DEV) | F70: =C70*F2 -> 8546.2788
B71: 2.3 | C71: =3925-1000+500 -> 3425 | D71: Deepthi Kesireddy (DEV) | F71: =C71*F2 -> 29271.005
B72: 2.4 | C72: 1000 | D72: Chandralekha Kesireddy (DEV) | F72: =C72*F2 -> 8546.2788
B73: 2.5 | C73: 2000 | D73: Manohar SP (DEV) | F73: =C73*F2 -> 17092.558
B74: 2.6 | C74: 1000 | D74: Shwetha Reddy | F74: =C74*F2 -> 8546.2788
B75: Sub-total | C75: =SUM(C69:C74) -> 11425
A76: 3 | B76: Office 03 | C76: =8457 -> 8457 | D76: Sukender Reddy Pulusani, Vijay Kumar & Others.
B77: 3.1 | C77: 2300 | D77: Kadiyala Venkateshwar Rao | F77: =C77*F2 -> 19656.441
B78: 3.2 | C78: 1000 | D78: Sunkara Vijaya Durga & Sunkara Jishna Sathwik | F78: =C78*F2 -> 8546.2788
B79: 3.3 | C79: 1153 | D79: Sukender Reddy Pulusani | F79: =C79*F2 -> 9853.8594
B80: 3.4 | C80: 1152 | D80: Neetha Pulusani | F80: =C80*F2 -> 9845.3131
B81: 3.5 | C81: 1152 | D81: Kireet Reddy Pulusani | F81: =C81*F2 -> 9845.3131
B82: 3.6 | C82: 850 | D82: Krishna Kumar Vempati | F82: =C82*F2 -> 7264.3369
B83: 3.7 | C83: 850 | D83: J Vijay Kumar & Laxmi | F83: =C83*F2 -> 7264.3369
B84: Sub-total | C84: =SUM(C77:C83) -> 8457
A85: 4 | B85: Office 04 | C85: 8699 | D85: Rohan Mandala & Sridhar Anisha (DEV) | F85: =C85*F2 -> 74344.079
A86: Total | C86: =SUM(C67,C75,C76,C85) -> 34218
A88: Eleventh Floor
A89: S.NO | B89: Description | C89: SBUA | D89: Ownership
A90: 1 | B90: Office 01 | C90: 5637 | D90: Developer
B91: 1A | C91: =2587 -> 2587 | D91: Madhusudhan Reddy Kypa(Dileep kurnool) | F91: =C91*F2 -> 22109.223
B92: 1B | C92: 3050 | D92: Pavan Kumar Mummasani & Manasa Priyadharshini (DEV) | F92: =C92*F2 -> 26066.15
B93: Sub-total | C93: =SUM(C91:C92) -> 5637
A94: 2 | B94: Office 02 | C94: 11425 | D94: UDS Landowners (KDR Family)
B95: 2.1 | C95: 3028 | D95: K. Rajesh Reddy (LO) | F95: =C95*F2 -> 25878.132
B96: 2.2 | C96: =4004-1320 -> 2684 | D96: K Saritha(LO) | F96: =C96*F2 -> 22938.212
B97: 2.3 | C97: 3028 | D97: K Ramachandra Reddy (LO) | F97: =C97*F2 -> 25878.132
B98: 2.4 | C98: =1365+1320 -> 2685 | D98: K Spandana(LO) | F98: =C98*F2 -> 22946.758
B99: Sub-total | C99: =SUM(C95:C98) -> 11425
A100: 3 | B100: Office 03 | C100: 8457 | D100: Arundathi(LO) | F100: =C100*F2 -> 72275.879
A101: 4 | B101: Office 04 | C101: 8699 | D101: Manjula(LO) | F101: =C101*F2 -> 74344.079
A102: Total | C102: =SUM(C90+C99+C100+C101) -> 34218
A104: Twelfth Floor
A105: S.NO | B105: Description | C105: SBUA | D105: Ownership
A106: 1 | B106: Office 01 | C106: =2101 -> 2101 | D106: K. Tanuja (DEV) | F106: =C106*F2 -> 17955.732
A107: 2 | B107: Office 02 | C107: 11425 | D107: UDS (Developer + Landowner)
B108: 2.1 | C108: =11166 -> 11166 | D108: Madhukar Reddy (LO) | F108: =C108*F2 -> 95427.749
...

Sheet CAM-Feb`24
A1: CAM CHARGES CALCULATION SUMMARY - OGM-Feb`24
B2: Total Building Saleable area | C2: Area sft | D2: 490749 | E2: MCP Occupied area | H2: OGM Area
A3: CAM Charges INR/ Per sq ft / Month | C3: per sq. ft cost | D3: =SUM(D5:D17) -> 5.7598857 | E3: MCP | F3: Per Sft | G3: 167554 | H3: =D2-G3 -> 323195
A4: Sl no | B4: Description | C4: Per month | D4: Per sft
A5: 1 | B5: Management staff (By Area) | C5: =262200+77500 -> 339700 | D5: =C5/D2 -> 0.69220722 | G5: =G3*D5 -> 115982.09 | H5: =H3*D5 -> 223717.91
A6: 2 | B6: Technical manpower (% Share) | C6: 396050.84 | D6: =C6/D2 -> 0.80703341 | E6: =C6*D28 -> 128393.98 | F6: =E6/D2 -> 0.26162861 | G6: =F6*G3 -> 43836.92 | H6: =C6-G6 -> 352213.92
A7: 3 | B7: Technical manpower | C7: 295625 | D7: =C7/D2 -> 0.60239552 | E7: =C7*D27 -> 202171.37 | F7: =E7/D2 -> 0.41196491 | G7: =F7*G3 -> 69026.368 | H7: =C7-G7 -> 226598.63
A8: 4 | B8: HK Manpower | C8: 776020.71 | D8: =C8/D2 -> 1.5812986 | G8: =G3*D8 -> 264952.91 | H8: =H3*D8 -> 511067.8
A9: 5 | B9: LP Manpower -Security Services | C9: =45000+5000+6000 -> 56000 | D9: =C9/D2 -> 0.11411129 | G9: =D9*G3 -> 19119.803 | H9: =C9-G9 -> 36880.197
A10: 6 | B10: AMC | C10: 0 | D10: 0 | G10: 0
A11: 7 | B11: Consumables | C11: 22313 | D11: =C11/D2 -> 0.045467235 | E11: =C11*D27 -> 15259.365 | F11: =E11/D2 -> 0.031094031 | G11: =F11*G3 -> 5209.9293 | H11: =C11-G11 -> 17103.071
A12: 8 | B12: Consumables Excl MCP | C12: 0 | D12: 0 | G12: 0
A13: 9 | B13: Common area Electrical & DG Charges (Tech %Share) | C13: 711634.4 | D13: =C13/D2 -> 1.4500985 | E13: =+C13*D28 -> 230701.63 | F13: =+E13/D2 -> 0.47010106 | G13: =+F13*G3 -> 78767.313 | H13: =C13-G13 -> 632867.09
A14: 10 | B14: Common area Water charges (By Area) | C14: =181236.00569273-C15 -> 113524.21 | D14: =C14/D2 -> 0.23132846 | G14: =G3*D14 -> 38760.008 | H14: =C14-G14 -> 74764.201
A15: 11 | B15: Cooling Tower water charges | C15: =E32 -> 67711.797 | H15: =C15 -> 67711.797
A16: 12 | B16: Liosaning & Licenses | C16: =2000+74250+3100+36440 -> 115790 | D16: =C16/D2 -> 0.23594546 | G16: =D16*G3 -> 39533.606 | H16: =C16-G16 -> 76256.394
A17: 13 | B17: Liosaning & Licenses (By Area) | C17: 0 | D17: =C17/D2 -> 0
A18: A | B18: Total CAM Charges | C18: =SUM(C5:C17) -> 2894370 | G18: =SUM(G5:G17) -> 675188.94 | H18: =SUM(H5:H17) -> 2219181
A19: 14 | B19: Contingency, Sinking Fund @2% | C19: =C18*2% -> 57887.399 | G19: =G18*2% -> 13503.779 | H19: =C19-G19 -> 44383.62
A20: 15 | B20: Fixed Management Fees | C20: 490749 | D20: =C20/D2 -> 1 | G20: =D20*G3 -> 167554 | H20: =C20-G20 -> 323195
B21: Grand Total | C21: =C18+C19+C20 -> 3443006.4 | G21: =G18+G19+G20 -> 856246.72 | H21: =H18+H19+H20 -> 2586759.6
A22: B | B22: Including Contingency & Sinking fund Per Sft CAM Charges | C22: =(C19+C20+C18)/D2 -> 7.0158194 | G22: =(G18+G19+G20)/G3 -> 5.1102732 | H22: =(H19+H20+H18)/H3 -> 8.0037118
A25: S No | B25: Description | C25: Total Area in SFT | D25: % on Total area | E25: Remarks
A26: 1 | B26: Total Building common area | C26: 381481.87
A27: 2 | B27: MCP Utilization common area | C27: 260886.97 | D27: =C27/C26 -> 0.68387778 | E27: Housekeeping
A28: 3 | B28: MCP Utilization common area | C28: 123670.93 | D28: =C28/C26 -> 0.3241856 | E28: Technical
A29: 4 | B29: B4 parking
A31: S No | B31: February`24 | C31: Consumed KL | D31: Rate/KL | E31: Amount
A32: 1 | B32: MCP cooling tower consumption | C32: 302 | D32: 224.21125 | E32: =C32*D32 -> 67711.797

Sheet Tenant CAM-Feb`24
A1: Tenant CAM details-OGM-Feb`24
A2: Floor | E2: CAM cost per Sft | F2: ='CAM-Feb`24'!H22 -> 8.0037118
A3: Ground Floor
A4: S.NO | B4: Description | C4: SBUA | D4: Ownership | E4: Tenants | F4: CAM Cost | G4: Carpet Area | H4: Cost/Sft
A5: 1 | B5: Retail 01 | C5: =3311 -> 3311 | D5: Amar Chowdhary | E5: HDFC Bank Ltd | F5: =(C5)*F2 -> 26500.29 | G5: =C5*65% -> 2152.15 | H5: =F5/G5 -> 12.313403
A6: 2 | B6: Retail 02 | C6: =3816 -> 3816 | D6: UDS Landowners | E6: Milu Foods (Vacs Bakery) | F6: =C6*F2 -> 30542.164
A7: 3 | B7: Retail 03 | C7: 3814 | D7: KSR Group | E7: Chicken Wild Wings Pvt Ltd | F7: =C7*F2 -> 30526.157
A8: 4 | B8: Retail 04 | C8: =3648 -> 3648 | D8: Aashish Bansal and Mona Bansal | E8: Fatcity Hospitality LLP | F8: =C8*F2 -> 29197.541
A9: 5 | B9: Retail 05 | C9: =3436 -> 3436 | D9: Vazir Singh Pilania and Thota Raghu Buchanna | E9: Fatcity Hospitality LLP | F9: =C9*F2 -> 27500.754
A10: 6 | B10: Retail 06 | C10: =2723 -> 2723 | D10: TanujaNayani and Ratna/Gouri Reddy | E10: Fatcity Hospitality LLP | F10: =C10*F2 -> 21794.107
A11: 7 | B11: Retail 07 | C11: =1381 -> 1381 | D11: TanujaNayani | E11: ICICI Bank Ltd | F11: =C11*F2 -> 11053.126
A12: 8 | B12: Retail 08 | C12: =755 -> 755 | D12: K Sudhakar Reddy | E12: ICICI Bank Ltd | F12: =C12*F2 -> 6042.8024
C13: =SUM(C5:C12) -> 22884
A14: First Floor
A15: S.NO | B15: Description | C15: SBUA | D15: Ownership
A16: 1 | B16: Retail 01 | C16: =6725 -> 6725 | D16: Developer | F16: =C16*F2 -> 53824.962
A17: 2 | B17: Retail 02 | C17: =7686 -> 7686 | D17: Developer | F17: =C17*F2 -> 61516.529
A18: 3 | B18: Retail 03 | C18: =9714 -> 9714 | D18: Developer and Landowners | F18: =C18*F2 -> 77748.056
A19: 4 | B19: Retail 04 | C19: =9514 -> 9514 | D19: UDS Landowners | F19: =C19*F2 -> 76147.314
A20: Total | C20: =C16+C17+C18+C19 -> 33639
A22: Second Floor to Sixth Floor
A23: S.NO | B23: Description | C23: SBUA | D23: Ownership
A24: 1 | B24: All Offices | C24: 167554 | D24: Microchip Technology India Pvt Ltd | F24: =C24*'CAM-Feb`24'!G22 -> 856246.72
A27: Seventh Floor
A28: S.NO | B28: Description | C28: SBUA | D28: Ownership
A29: 1 | B29: Office 01 | C29: 5637 | D29: Developer
B30: 1A.1 | C30: 2000 | D30: Pamara Venkata Ramana Devi and Pamera Ram Gopal Rao | F30: =C30*F2 -> 16007.424
B31: 1B.2 | C31: =587 -> 587 | D31: Developer | F31: =C31*F2 -> 4698.1788
B32: 1B | C32: =3050 -> 3050 | D32: Nirmal + Dileep (DEV) | F32: =C32*F2 -> 24411.321
B33: Sub-total | C33: =SUM(C30:C32) -> 5637
A34: 2 | B34: Office 02 | C34: 11425 | D34: Avinash Kotagiri (DEV) | F34: =C34*F2 -> 91442.407
A35: 3 | B35: Office 03 | C35: =8457 -> 8457 | D35: Ananth+Dileep+Anoop (DEV)
B36: 3A.1 | C36: 2156 | D36: Ananth(DEV) | F36: =C36*F2 -> 17256.003
B37: 3A.2 | C37: =2073 -> 2073 | D37: Bhavya Reddy 2,500 Sq.Ft | F37: =C37*F2 -> 16591.695
B38: 3B.1 | C38: =2927 -> 2927 | D38: Sasya Reddy 2,500 Sq.Ft | F38: =C38*F2 -> 23426.864
B39: 3B.2 | C39: =1301 -> 1301 | D39: Anoop (DEV) | F39: =C39*F2 -> 10412.829
B40: Sub-total | C40: =SUM(C36:C39) -> 8457
A41: 4 | B41: Office 04 | C41: 8699 | D41: Anoop (DEV) | F41: =C41*F2 -> 69624.289
A42: Total | C42: =SUM(C29,C34,C35,C41) -> 34218
A44: Eighth Floor
A45: S.NO | B45: Description | C45: SBUA | D45: Ownership
A46: 1 | B46: Office 01 | C46: =2101 -> 2101 | D46: Tachyon IT Solutions Pvt Ltd (DEV) | F46: =C46*F2 -> 16815.798
A47: 2 | B47: Office 02 | C47: 11425 | D47: Tachyon IT Solutions Pvt Ltd (DEV) | F47: =C47*F2 -> 91442.407
A48: 3 | B48: Office 03 | C48: =8457 -> 8457 | D48: Tachyon IT Solutions Pvt Ltd (DEV) | F48: =C48*F2 -> 67687.391
A49: 4 | B49: Office 04 | C49: 8699 | D49: Tachyon IT Solutions Pvt Ltd (DEV) | F49: =C49*F2 -> 69624.289
A50: Total | C50: =SUM(C46:C49) -> 30682
A52: Ninth Floor
A53: S.NO | B53: Description | C53: SBUA | D53: Ownership
A54: 1 | B54: Office 01 | C54: 5637 | D54: Pulluri Mining and Logistics Pvt Ltd (DEV) | F54: =C54*F2 -> 45116.923
A55: 2 | B55: Office 02 | C55: 11425 | D55: Pulluri Mining and Logistics Pvt Ltd (DEV) | F55: =C55*F2 -> 91442.407
A56: 3 | B56: Office 03 | C56: =8457 -> 8457 | D56: UDS Developer Arjun Rao Group
B57: 3.1 | C57: =3957 -> 3957 | D57: Arjun Rao (DEV) | F57: =C57*F2 -> 31670.688
B58: 3.2 | C58: =1500 -> 1500 | D58: Karabee Kailash (Ohja) (DEV) | F58: =C58*F2 -> 12005.568
B59: 3.3 | C59: =1500 -> 1500 | D59: Jakka Deepa (DEV) | F59: =C59*F2 -> 12005.568
B60: 3.4 | C60: =1500 -> 1500 | D60: Indu Priya (DEV) | F60: =C60*F2 -> 12005.568
B61: Sub-total | C61: =SUM(C57:C60) -> 8457
A62: 4 | B62: Office 04 | C62: 8699 | D62: AGA Infra Projects Pvt Ltd (DEV) | F62: =C62*F2 -> 69624.289
A63: Total | C63: =SUM(C54:C56,C62) -> 34218
A65: Tenth Floor
A66: S.NO | B66: Description | C66: SBUA | D66: Ownership
A67: 1 | B67: Office 01 | C67: 5637 | D67: Raj Kumar Maganti & Pradeep Kumar Maganti /Siri Sampada | E67: Siri Sampada Real Estate | F67: =C67*F2 -> 45116.923
A68: 2 | B68: Office 02 | C68: 11425 | D68: Developer
B69: 2.1 | C69: 3000 | D69: Srinivas Reddy Challa (DEV) | F69: =C69*F2 -> 24011.135
B70: 2.2 | C70: 1000 | D70: Shruti Gummadi (DEV) | F70: =C70*F2 -> 8003.7118
B71: 2.3 | C71: =3925-1000+500 -> 3425 | D71: Deepthi Kesireddy (DEV) | F71: =C71*F2 -> 27412.713
B72: 2.4 | C72: 1000 | D72: Chandralekha Kesireddy (DEV) | F72: =C72*F2 -> 8003.7118
B73: 2.5 | C73: 2000 | D73: Manohar SP (DEV) | F73: =C73*F2 -> 16007.424
B74: 2.6 | C74: 1000 | D74: Shwetha Reddy | F74: =C74*F2 -> 8003.7118
B75: Sub-total | C75: =SUM(C69:C74) -> 11425
A76: 3 | B76: Office 03 | C76: =8457 -> 8457 | D76: Sukender Reddy Pulusani, Vijay Kumar & Others.
B77: 3.1 | C77: 2300 | D77: Kadiyala Venkateshwar Rao | F77: =C77*F2 -> 18408.537
B78: 3.2 | C78: 1000 | D78: Sunkara Vijaya Durga & Sunkara Jishna Sathwik | F78: =C78*F2 -> 8003.7118
B79: 3.3 | C79: 1153 | D79: Sukender Reddy Pulusani | F79: =C79*F2 -> 9228.2797
B80: 3.4 | C80: 1152 | D80: Neetha Pulusani | F80: =C80*F2 -> 9220.276
B81: 3.5 | C81: 1152 | D81: Kireet Reddy Pulusani | F81: =C81*F2 -> 9220.276
B82: 3.6 | C82: 850 | D82: Krishna Kumar Vempati | F82: =C82*F2 -> 6803.155
B83: 3.7 | C83: 850 | D83: J Vijay Kumar & Laxmi | F83: =C83*F2 -> 6803.155
B84: Sub-total | C84: =SUM(C77:C83) -> 8457
A85: 4 | B85: Office 04 | C85: 8699 | D85: Rohan Mandala & Sridhar Anisha (DEV) | F85: =C85*F2 -> 69624.289
A86: Total | C86: =SUM(C67,C75,C76,C85) -> 34218
A88: Eleventh Floor
A89: S.NO | B89: Description | C89: SBUA | D89: Ownership
A90: 1 | B90: Office 01 | C90: 5637 | D90: Developer
B91: 1A | C91: =2587 -> 2587 | D91: Madhusudhan Reddy Kypa(Dileep kurnool) | F91: =C91*F2 -> 20705.602
B92: 1B | C92: 3050 | D92: Pavan Kumar Mummasani & Manasa Priyadharshini (DEV) | F92: =C92*F2 -> 24411.321
B93: Sub-total | C93: =SUM(C91:C92) -> 5637
A94: 2 | B94: Office 02 | C94: 11425 | D94: UDS Landowners (KDR Family)
B95: 2.1 | C95: 3028 | D95: K. Rajesh Reddy (LO) | F95: =C95*F2 -> 24235.239
B96: 2.2 | C96: =4004-1320 -> 2684 | D96: K Saritha(LO) | F96: =C96*F2 -> 21481.962
B97: 2.3 | C97: 3028 | D97: K Ramachandra Reddy (LO) | F97: =C97*F2 -> 24235.239
B98: 2.4 | C98: =1365+1320 -> 2685 | D98: K Spandana(LO) | F98: =C98*F2 -> 21489.966
B99: Sub-total | C99: =SUM(C95:C98) -> 11425
A100: 3 | B100: Office 03 | C100: 8457 | D100: Arundathi(LO) | F100: =C100*F2 -> 67687.391
A101: 4 | B101: Office 04 | C101: 8699 | D101: Manjula(LO) | F101: =C101*F2 -> 69624.289
A102: Total | C102: =SUM(C90+C99+C100+C101) -> 34218
A104: Twelfth Floor
A105: S.NO | B105: Description | C105: SBUA | D105: Ownership
A106: 1 | B106: Office 01 | C106: =2101 -> 2101 | D106: K. Tanuja (DEV) | F106: =C106*F2 -> 16815.798
A107: 2 | B107: Office 02 | C107: 11425 | D107: UDS (Developer + Landowner)
B108: 2.1 | C108: =11166 -> 11166 | D108: Madhukar Reddy (LO) | F108: =C108*F2 -> 89369.446
...

Sheet CAM-Mar`24
E1: .
A2: CAM CHARGES CALCULATION SUMMARY - OGM-Mar`24
B3: Total Building Saleable area | C3: Area sft | D3: 490749 | E3: MCP Occupied area | H3: OGM Area
A4: CAM Charges INR/ Per sq ft / Month | C4: per sq. ft cost | D4: =SUM(D6:D18) -> 6.3031767 | E4: MCP | F4: Per Sft | G4: 167554 | H4: =D3-G4 -> 323195
A5: Sl no | B5: Description | C5: Per month | D5: Per sft
A6: 1 | B6: Management staff (By Area) | C6: =262200+77500 -> 339700 | D6: =C6/D3 -> 0.69220722 | G6: =G4*D6 -> 115982.09 | H6: =H4*D6 -> 223717.91
A7: 2 | B7: Technical manpower | C7: 445788.92 | D7: =C7/D3 -> 0.90838478 | E7: =C7*(D29) -> 144518.35 | F7: =E7/D3 -> 0.29448526 | G7: =F7*G4 -> 49342.184 | H7: =C7-G7 -> 396446.74
A8: 3 | B8: HK Manpower | C8: 340210 | D8: =C8/D3 -> 0.69324645 | E8: =C8*D28 -> 232662.06 | F8: =E8/D3 -> 0.47409584 | G8: =F8*G4 -> 79436.654 | H8: =C8-G8 -> 260773.35
A9: 4 | B9: LP Manpower -Security Services | C9: 680837.4 | D9: =C9/D3 -> 1.3873434 | G9: =G4*D9 -> 232454.94 | H9: =H4*D9 -> 448382.46
A10: 5 | B10: AMC | C10: =45000+5000+6000 -> 56000 | D10: =C10/D3 -> 0.11411129 | G10: =D10*G4 -> 19119.803 | H10: =C10-G10 -> 36880.197
A11: 6 | B11: Consumables | C11: 0 | D11: 0 | G11: 0
A12: 7 | B12: Consumables (HK %Share) | C12: 0 | D12: =C12/D3 -> 0 | E12: =C12*D28 -> 0 | F12: =E12/D3 -> 0 | G12: =F12*G4 -> 0 | H12: =C12-G12 -> 0
A13: 8 | B13: Consumables Excl MCP | C13: 0 | D13: 0 | G13: 0
A14: 9 | B14: Common area Electrical & DG Charges (Tech %Share) | C14: 717978.53 | D14: =C14/D3 -> 1.463026 | E14: =C14*(D29) -> 232758.3 | F14: =E14/D3 -> 0.47429195 | G14: =F14*G4 -> 79469.514 | H14: =C14-G14 -> 638509.02
A15: 10 | B15: Common area Water charges (By Area) | C15: =236879.396710526-C16 -> 162762.8 | D15: =C15/D3 -> 0.33166202 | G15: =G4*D15 -> 55571.298 | H15: =C15-G15 -> 107191.51
A16: 11 | B16: Liosaning & Licenses | C16: =E33 -> 74116.594 | H16: =C16 -> 74116.594
A17: 12 | B17: FMS Cost (By Area) | D17: =C17/D3 -> 0 | G17: =D17*G4 -> 0 | H17: =C17-G17 -> 0
A18: 13 | B18: Liosaning & Licenses (By Area) | C18: 350000 | D18: =C18/D3 -> 0.71319554 | G18: =D18*G4 -> 119498.77 | H18: =C18-G18 -> 230501.23
A19: A | B19: Total CAM Charges | C19: =SUM(C6:C18) -> 3167394.2 | G19: =SUM(G6:G18) -> 750875.25 | H19: =SUM(H6:H18) -> 2416519
A20: 14 | B20: Contingency, Sinking Fund @2% | C20: =C19*2% -> 63347.885 | D20: =C20/D3 -> 0.12908408 | G20: =G19*2% -> 15017.505 | H20: =C20-G20 -> 48330.38
A21: 15 | B21: Fixed Management Fees | C21: 490749 | D21: =C21/D3 -> 1 | G21: =D21*G4 -> 167554 | H21: =C21-G21 -> 323195
B22: Grand Total | C22: =C19+C20+C21 -> 3721491.1 | G22: =G19+G20+G21 -> 933446.75 | H22: =H19+H20+H21 -> 2788044.4
A23: B | B23: Including Contingency & Sinking fund Per Sft CAM Charges | C23: =(C20+C21+C19)/D3 -> 7.5832883 | G23: =(G19+G20+G21)/G4 -> 5.5710204 | H23: =(H20+H21+H19)/H4 -> 8.6265084
A26: S No | B26: Description | C26: Total Area in SFT | D26: % on Total area | E26: Remarks
A27: 1 | B27: Total building common area | C27: 381481.87
A28: 2 | B28: MCP Utilization common area | C28: 260886.97 | D28: =C28/C27 -> 0.68387778 | E28: Housekeeping
A29: 3 | B29: MCP Utilization common area excluding B4 parking | C29: 123670.93 | D29: =C29/C27 -> 0.3241856 | E29: Technical
A30: 4 | B30: B4 parking
A32: S No | B32: March`24 | C32: Consumed KL | D32: Rate/KL | E32: Amount
A33: 1 | B33: MCP cooling tower water consumption | C33: 295 | D33: 251.24269 | E33: =C33*D33 -> 74116.594

Sheet Tenant CAM-Mar`24
A1: Tenant CAM details-OGM-Mar`24
A2: Floor | E2: CAM cost per Sft | F2: ='CAM-Mar`24'!H23 -> 8.6265084
A3: Ground Floor
A4: S.NO | B4: Description | C4: SBUA | D4: Ownership | E4: Tenants | F4: CAM Cost | G4: Carpet Area | H4: Cost/Sft
A5: 1 | B5: Retail 01 | C5: =3311 -> 3311 | D5: Amar Chowdhary | E5: HDFC Bank Ltd | F5: =(C5)*F2 -> 28562.369 | G5: =C5*65% -> 2152.15 | H5: =F5/G5 -> 13.271551
A6: 2 | B6: Retail 02 | C6: =3816 -> 3816 | D6: UDS Landowners | E6: Milu Foods (Vacs Bakery) | F6: =C6*F2 -> 32918.756
A7: 3 | B7: Retail 03 | C7: 3814 | D7: KSR Group | E7: Chicken Wild Wings Pvt Ltd | F7: =C7*F2 -> 32901.503
A8: 4 | B8: Retail 04 | C8: =3648 -> 3648 | D8: Aashish Bansal and Mona Bansal | E8: Fatcity Hospitality LLP | F8: =C8*F2 -> 31469.503
A9: 5 | B9: Retail 05 | C9: =3436 -> 3436 | D9: Vazir Singh Pilania and Thota Raghu Buchanna | E9: Fatcity Hospitality LLP | F9: =C9*F2 -> 29640.683
A10: 6 | B10: Retail 06 | C10: =2723 -> 2723 | D10: TanujaNayani and Ratna/Gouri Reddy | E10: Fatcity Hospitality LLP | F10: =C10*F2 -> 23489.982
A11: 7 | B11: Retail 07 | C11: =1381 -> 1381 | D11: TanujaNayani | E11: ICICI Bank Ltd | F11: =C11*F2 -> 11913.208
A12: 8 | B12: Retail 08 | C12: =755 -> 755 | D12: K Sudhakar Reddy | E12: ICICI Bank Ltd | F12: =C12*F2 -> 6513.0138
C13: =SUM(C5:C12) -> 22884
A14: First Floor
A15: S.NO | B15: Description | C15: SBUA | D15: Ownership
A16: 1 | B16: Retail 01 | C16: =6725 -> 6725 | D16: Developer | F16: =C16*F2 -> 58013.269
A17: 2 | B17: Retail 02 | C17: =7686 -> 7686 | D17: Developer | F17: =C17*F2 -> 66303.344
A18: 3 | B18: Retail 03 | C18: =9714 -> 9714 | D18: Developer and Landowners | F18: =C18*F2 -> 83797.903
A19: 4 | B19: Retail 04 | C19: =9514 -> 9514 | D19: UDS Landowners | F19: =C19*F2 -> 82072.601
A20: Total | C20: =C16+C17+C18+C19 -> 33639
A22: Second Floor to Sixth Floor
A23: S.NO | B23: Description | C23: SBUA | D23: Ownership
A24: 1 | B24: All Offices | C24: 167554 | D24: Microchip Technology India Pvt Ltd | F24: =C24*'CAM-Mar`24'!G23 -> 933446.75
A27: Seventh Floor
A28: S.NO | B28: Description | C28: SBUA | D28: Ownership
A29: 1 | B29: Office 01 | C29: 5637 | D29: Developer
B30: 1A.1 | C30: 2000 | D30: Pamara Venkata Ramana Devi and Pamera Ram Gopal Rao | F30: =C30*F2 -> 17253.017
B31: 1B.2 | C31: =587 -> 587 | D31: Developer | F31: =C31*F2 -> 5063.7604
B32: 1B | C32: =3050 -> 3050 | D32: Nirmal + Dileep (DEV) | F32: =C32*F2 -> 26310.851
B33: Sub-total | C33: =SUM(C30:C32) -> 5637
A34: 2 | B34: Office 02 | C34: 11425 | D34: Avinash Kotagiri (DEV) | F34: =C34*F2 -> 98557.858
A35: 3 | B35: Office 03 | C35: =8457 -> 8457 | D35: Ananth+Dileep+Anoop (DEV)
B36: 3A.1 | C36: 2156 | D36: Ananth(DEV) | F36: =C36*F2 -> 18598.752
B37: 3A.2 | C37: =2073 -> 2073 | D37: Bhavya Reddy 2,500 Sq.Ft | F37: =C37*F2 -> 17882.752
B38: 3B.1 | C38: =2927 -> 2927 | D38: Sasya Reddy 2,500 Sq.Ft | F38: =C38*F2 -> 25249.79
B39: 3B.2 | C39: =1301 -> 1301 | D39: Anoop (DEV) | F39: =C39*F2 -> 11223.087
B40: Sub-total | C40: =SUM(C36:C39) -> 8457
A41: 4 | B41: Office 04 | C41: 8699 | D41: Anoop (DEV) | F41: =C41*F2 -> 75041.997
A42: Total | C42: =SUM(C29,C34,C35,C41) -> 34218
A44: Eighth Floor
A45: S.NO | B45: Description | C45: SBUA | D45: Ownership
A46: 1 | B46: Office 01 | C46: =2101 -> 2101 | D46: Tachyon IT Solutions Pvt Ltd (DEV) | F46: =C46*F2 -> 18124.294
A47: 2 | B47: Office 02 | C47: 11425 | D47: Tachyon IT Solutions Pvt Ltd (DEV) | F47: =C47*F2 -> 98557.858
A48: 3 | B48: Office 03 | C48: =8457 -> 8457 | D48: Tachyon IT Solutions Pvt Ltd (DEV) | F48: =C48*F2 -> 72954.382
A49: 4 | B49: Office 04 | C49: 8699 | D49: Tachyon IT Solutions Pvt Ltd (DEV) | F49: =C49*F2 -> 75041.997
A50: Total | C50: =SUM(C46:C49) -> 30682
A52: Ninth Floor
A53: S.NO | B53: Description | C53: SBUA | D53: Ownership
A54: 1 | B54: Office 01 | C54: 5637 | D54: Pulluri Mining and Logistics Pvt Ltd (DEV) | F54: =C54*F2 -> 48627.628
A55: 2 | B55: Office 02 | C55: 11425 | D55: Pulluri Mining and Logistics Pvt Ltd (DEV) | F55: =C55*F2 -> 98557.858
A56: 3 | B56: Office 03 | C56: =8457 -> 8457 | D56: UDS Developer Arjun Rao Group
B57: 3.1 | C57: =3957 -> 3957 | D57: Arjun Rao (DEV) | F57: =C57*F2 -> 34135.094
B58: 3.2 | C58: =1500 -> 1500 | D58: Karabee Kailash (Ohja) (DEV) | F58: =C58*F2 -> 12939.763
B59: 3.3 | C59: =1500 -> 1500 | D59: Jakka Deepa (DEV) | F59: =C59*F2 -> 12939.763
B60: 3.4 | C60: =1500 -> 1500 | D60: Indu Priya (DEV) | F60: =C60*F2 -> 12939.763
B61: Sub-total | C61: =SUM(C57:C60) -> 8457
A62: 4 | B62: Office 04 | C62: 8699 | D62: AGA Infra Projects Pvt Ltd (DEV) | F62: =C62*F2 -> 75041.997
A63: Total | C63: =SUM(C54:C56,C62) -> 34218
A65: Tenth Floor
A66: S.NO | B66: Description | C66: SBUA | D66: Ownership
A67: 1 | B67: Office 01 | C67: 5637 | D67: Raj Kumar Maganti & Pradeep Kumar Maganti /Siri Sampada | E67: Siri Sampada Real Estate | F67: =C67*F2 -> 48627.628
A68: 2 | B68: Office 02 | C68: 11425 | D68: Developer
B69: 2.1 | C69: 3000 | D69: Srinivas Reddy Challa (DEV) | F69: =C69*F2 -> 25879.525
B70: 2.2 | C70: 1000 | D70: Shruti Gummadi (DEV) | F70: =C70*F2 -> 8626.5084
B71: 2.3 | C71: =3925-1000+500 -> 3425 | D71: Deepthi Kesireddy (DEV) | F71: =C71*F2 -> 29545.791
B72: 2.4 | C72: 1000 | D72: Chandralekha Kesireddy (DEV) | F72: =C72*F2 -> 8626.5084
B73: 2.5 | C73: 2000 | D73: Manohar SP (DEV) | F73: =C73*F2 -> 17253.017
B74: 2.6 | C74: 1000 | D74: Shwetha Reddy | F74: =C74*F2 -> 8626.5084
B75: Sub-total | C75: =SUM(C69:C74) -> 11425
A76: 3 | B76: Office 03 | C76: =8457 -> 8457 | D76: Sukender Reddy Pulusani, Vijay Kumar & Others.
B77: 3.1 | C77: 2300 | D77: Kadiyala Venkateshwar Rao | F77: =C77*F2 -> 19840.969
B78: 3.2 | C78: 1000 | D78: Sunkara Vijaya Durga & Sunkara Jishna Sathwik | F78: =C78*F2 -> 8626.5084
B79: 3.3 | C79: 1153 | D79: Sukender Reddy Pulusani | F79: =C79*F2 -> 9946.3642
B80: 3.4 | C80: 1152 | D80: Neetha Pulusani | F80: =C80*F2 -> 9937.7377
B81: 3.5 | C81: 1152 | D81: Kireet Reddy Pulusani | F81: =C81*F2 -> 9937.7377
B82: 3.6 | C82: 850 | D82: Krishna Kumar Vempati | F82: =C82*F2 -> 7332.5321
B83: 3.7 | C83: 850 | D83: J Vijay Kumar & Laxmi | F83: =C83*F2 -> 7332.5321
B84: Sub-total | C84: =SUM(C77:C83) -> 8457
A85: 4 | B85: Office 04 | C85: 8699 | D85: Rohan Mandala & Sridhar Anisha (DEV) | F85: =C85*F2 -> 75041.997
A86: Total | C86: =SUM(C67,C75,C76,C85) -> 34218
A88: Eleventh Floor
A89: S.NO | B89: Description | C89: SBUA | D89: Ownership
A90: 1 | B90: Office 01 | C90: 5637 | D90: Developer
B91: 1A | C91: =2587 -> 2587 | D91: Madhusudhan Reddy Kypa(Dileep kurnool) | F91: =C91*F2 -> 22316.777
B92: 1B | C92: 3050 | D92: Pavan Kumar Mummasani & Manasa Priyadharshini (DEV) | F92: =C92*F2 -> 26310.851
B93: Sub-total | C93: =SUM(C91:C92) -> 5637
A94: 2 | B94: Office 02 | C94: 11425 | D94: UDS Landowners (KDR Family)
B95: 2.1 | C95: 3028 | D95: K. Rajesh Reddy (LO) | F95: =C95*F2 -> 26121.067
B96: 2.2 | C96: =4004-1320 -> 2684 | D96: K Saritha(LO) | F96: =C96*F2 -> 23153.549
B97: 2.3 | C97: 3028 | D97: K Ramachandra Reddy (LO) | F97: =C97*F2 -> 26121.067
B98: 2.4 | C98: =1365+1320 -> 2685 | D98: K Spandana(LO) | F98: =C98*F2 -> 23162.175
B99: Sub-total | C99: =SUM(C95:C98) -> 11425
A100: 3 | B100: Office 03 | C100: 8457 | D100: Arundathi(LO) | F100: =C100*F2 -> 72954.382
A101: 4 | B101: Office 04 | C101: 8699 | D101: Manjula(LO) | F101: =C101*F2 -> 75041.997
A102: Total | C102: =SUM(C90+C99+C100+C101) -> 34218
A104: Twelfth Floor
A105: S.NO | B105: Description | C105: SBUA | D105: Ownership
A106: 1 | B106: Office 01 | C106: =2101 -> 2101 | D106: K. Tanuja (DEV) | F106: =C106*F2 -> 18124.294
A107: 2 | B107: Office 02 | C107: 11425 | D107: UDS (Developer + Landowner)
B108: 2.1 | C108: =11166 -> 11166 | D108: Madhukar Reddy (LO) | F108: =C108*F2 -> 96323.593
...

Sheet CAM-Apr`24
E1: .
A2: CAM CHARGES CALCULATION SUMMARY - OGM-Apr`24
B3: Total Building Saleable area | C3: Area sft | D3: 490749 | E3: MCP Occupied area | H3: OGM Area
A4: CAM Charges INR/ Per sq ft / Month | C4: per sq. ft cost | D4: =SUM(D6:D18) -> 5.9187289 | E4: MCP | F4: Per Sft | G4: 167554 | H4: =D3-G4 -> 323195
A5: Sl no | B5: Description | C5: Per month | D5: Per sft
A6: 1 | B6: Management staff (By Area) | C6: =255533+77500+50000 -> 383033 | D6: =C6/D3 -> 0.78050694 | G6: =G4*D6 -> 130777.06 | H6: =H4*D6 -> 252255.94
A7: 2 | B7: Technical manpower | C7: 449526 | D7: =C7/D3 -> 0.91599983 | E7: =C7*(D29) -> 145729.86 | F7: =E7/D3 -> 0.29695396 | G7: =F7*G4 -> 49755.823 | H7: =C7-G7 -> 399770.18
A8: 3 | B8: HK Manpower | C8: 310200 | D8: =C8/D3 -> 0.63209502 | E8: =C8*D28 -> 212138.89 | F8: =E8/D3 -> 0.43227574 | G8: =F8*G4 -> 72429.529 | H8: =C8-G8 -> 237770.47
A9: 4 | B9: LP Manpower -Security Services | C9: 656106 | D9: =C9/D3 -> 1.3369482 | G9: =G4*D9 -> 224011.02 | H9: =H4*D9 -> 432094.98
A10: 5 | B10: AMC | C10: =45000+5000+6000+152000 -> 208000 | D10: =C10/D3 -> 0.42384192 | G10: =D10*G4 -> 71016.41 | H10: =C10-G10 -> 136983.59
A11: 6 | B11: Consumables | C11: 0 | D11: 0 | G11: 0
A12: 7 | B12: Consumables (HK %Share) | C12: 0 | D12: =C12/D3 -> 0 | E12: =C12*D28 -> 0 | F12: =E12/D3 -> 0 | G12: =F12*G4 -> 0 | H12: =C12-G12 -> 0
A13: 8 | B13: Consumables Excl MCP | C13: 0 | D13: 0 | G13: 0
A14: 9 | B14: Common area Electrical & DG Charges (Tech %Share) | C14: =459489.49749356+392206.685019915 -> 851696.18 | D14: =C14/D3 -> 1.7355026 | E14: =C14*(D29) -> 276107.64 | F14: =E14/D3 -> 0.56262496 | G14: =F14*G4 -> 94270.063 | H14: =C14-G14 -> 757426.12
A15: 10 | B15: Common area Water charges (By Area) | C15: =121940.182243229-C16 -> 33504.107 | D15: =C15/D3 -> 0.06827137 | G15: =G4*D15 -> 11439.141 | H15: =C15-G15 -> 22064.965
A16: 11 | B16: Liosaning & Licenses | C16: =E33 -> 88436.076 | H16: =C16 -> 88436.076
A17: 12 | B17: FMS Cost (By Area) | C17: =8000+3500+1045 -> 12545 | D17: =C17/D3 -> 0.025562966 | G17: =D17*G4 -> 4283.1772 | H17: =C17-G17 -> 8261.8228
A18: 13 | B18: Liosaning & Licenses (By Area) | C18: 0 | D18: =C18/D3 -> 0 | G18: =D18*G4 -> 0 | H18: =C18-G18 -> 0
A19: A | B19: Total CAM Charges | C19: =SUM(C6:C18) -> 2993046.4 | G19: =SUM(G6:G18) -> 657982.22 | H19: =SUM(H6:H18) -> 2335064.1
A20: 14 | B20: Contingency, Sinking Fund @2% | C20: =C19*2% -> 59860.927 | D20: =C20/D3 -> 0.1219787 | G20: =G19*2% -> 13159.644 | H20: =C20-G20 -> 46701.283
A21: 15 | B21: Fixed Management Fees | C21: 490749 | D21: =C21/D3 -> 1 | G21: =D21*G4 -> 167554 | H21: =C21-G21 -> 323195
B22: Grand Total | C22: =C19+C20+C21 -> 3543656.3 | G22: =G19+G20+G21 -> 838695.87 | H22: =H19+H20+H21 -> 2704960.4
A23: B | B23: Including Contingency & Sinking fund Per Sft CAM Charges | C23: =(C20+C21+C19)/D3 -> 7.2209139 | G23: =(G19+G20+G21)/G4 -> 5.0055258 | H23: =(H20+H21+H19)/H4 -> 8.3694377
A26: S No | B26: Description | C26: Total Area in SFT | D26: % on Total area | E26: Remarks
A27: 1 | B27: Total building common area | C27: 381481.87
A28: 2 | B28: MCP Utilization common area | C28: 260886.97 | D28: =C28/C27 -> 0.68387778 | E28: Housekeeping
A29: 3 | B29: MCP Utilization common area excluding B4 parking | C29: 123670.93 | D29: =C29/C27 -> 0.3241856 | E29: Technical
A30: 4 | B30: B4 parking
A32: S No | B32: April`24 | C32: Consumed KL | D32: Rate/KL | E32: Amount
A33: 1 | B33: MCP cooling tower water consumption | C33: 356 | D33: 248.41594 | E33: =C33*D33 -> 88436.076
A35: S No | B35: AMCs | C35: Amount
A36: 1 | B36: Pest control | C36: 45000
A37: 2 | B37: Garbage pick-up | C37: 5000
A38: 3 | B38: HMWSS charges | C38: 6000
A39: 4 | B39: STP operations- Feb`24 & Mar`24 | C39: 152000
B40: Total | C40: =SUM(C36:C39) -> 208000
A42: S No | B42: FMS Cost | C42: Amount
A43: 1 | B43: B3 temporary sintex tank cleaning | C43: 8000
A44: 2 | B44: Ground floor BMS room AC unit repairing charges | C44: 3500
A45: 3 | B45: OGM office printer cartridge and domestic line highrise plumbing items | C45: 1045
B46: Total | C46: =SUM(C43:C45) -> 12545
A48: S No | B48: Common area Electrical & DG Charges (Tech %Share) | C48: Amount
A49: 1 | B49: Common area EB & DG charges for the month of May`24 | C49: 459489.5
A50: 2 | B50: ACD common area share for the month of May`24 | C50: 392206.69
B51: Total | C51: =SUM(C49:C50) -> 851696.18

Sheet Tenant CAM-Apr`24
A1: Tenant CAM details-OGM-Apr`24
A2: Floor | E2: CAM cost per Sft | F2: ='CAM-Apr`24'!H23 -> 8.3694377
A3: Ground Floor
A4: S.NO | B4: Description | C4: SBUA | D4: Ownership | E4: Tenants | F4: CAM Cost | G4: Carpet Area | H4: Cost/Sft
A5: 1 | B5: Retail 01 | C5: =3311 -> 3311 | D5: Amar Chowdhary | E5: HDFC Bank Ltd | F5: =(C5)*F2 -> 27711.208 | G5: =C5*65% -> 2152.15 | H5: =F5/G5 -> 12.876058
A6: 2 | B6: Retail 02 | C6: =3816 -> 3816 | D6: UDS Landowners | E6: Milu Foods (Vacs Bakery) | F6: =C6*F2 -> 31937.774
A7: 3 | B7: Retail 03 | C7: 3814 | D7: KSR Group | E7: Chicken Wild Wings Pvt Ltd | F7: =C7*F2 -> 31921.035
A8: 4 | B8: Retail 04 | C8: =3648 -> 3648 | D8: Aashish Bansal and Mona Bansal | E8: Fatcity Hospitality LLP | F8: =C8*F2 -> 30531.709
A9: 5 | B9: Retail 05 | C9: =3436 -> 3436 | D9: Vazir Singh Pilania and Thota Raghu Buchanna | E9: Fatcity Hospitality LLP | F9: =C9*F2 -> 28757.388
A10: 6 | B10: Retail 06 | C10: =2723 -> 2723 | D10: TanujaNayani and Ratna/Gouri Reddy | E10: Fatcity Hospitality LLP | F10: =C10*F2 -> 22789.979
A11: 7 | B11: Retail 07 | C11: =1381 -> 1381 | D11: TanujaNayani | E11: ICICI Bank Ltd | F11: =C11*F2 -> 11558.193
A12: 8 | B12: Retail 08 | C12: =755 -> 755 | D12: K Sudhakar Reddy | E12: ICICI Bank Ltd | F12: =C12*F2 -> 6318.9255
C13: =SUM(C5:C12) -> 22884
A14: First Floor
A15: S.NO | B15: Description | C15: SBUA | D15: Ownership
A16: 1 | B16: Retail 01 | C16: =6725 -> 6725 | D16: Developer | F16: =C16*F2 -> 56284.469
A17: 2 | B17: Retail 02 | C17: =7686 -> 7686 | D17: Developer | F17: =C17*F2 -> 64327.498
A18: 3 | B18: Retail 03 | C18: =9714 -> 9714 | D18: Developer and Landowners | F18: =C18*F2 -> 81300.718
A19: 4 | B19: Retail 04 | C19: =9514 -> 9514 | D19: UDS Landowners | F19: =C19*F2 -> 79626.83
A20: Total | C20: =C16+C17+C18+C19 -> 33639
A22: Second Floor to Sixth Floor
A23: S.NO | B23: Description | C23: SBUA | D23: Ownership
A24: 1 | B24: All Offices | C24: 167554 | D24: Microchip Technology India Pvt Ltd | F24: =C24*'CAM-Apr`24'!G23 -> 838695.87
A27: Seventh Floor
A28: S.NO | B28: Description | C28: SBUA | D28: Ownership
A29: 1 | B29: Office 01 | C29: 5637 | D29: Developer
B30: 1A.1 | C30: 2000 | D30: Pamara Venkata Ramana Devi and Pamera Ram Gopal Rao | F30: =C30*F2 -> 16738.875
B31: 1B.2 | C31: =587 -> 587 | D31: Developer | F31: =C31*F2 -> 4912.8599
B32: 1B | C32: =3050 -> 3050 | D32: Nirmal + Dileep (DEV) | F32: =C32*F2 -> 25526.785
B33: Sub-total | C33: =SUM(C30:C32) -> 5637
A34: 2 | B34: Office 02 | C34: 11425 | D34: Avinash Kotagiri (DEV) | F34: =C34*F2 -> 95620.826
A35: 3 | B35: Office 03 | C35: =8457 -> 8457 | D35: Ananth+Dileep+Anoop (DEV)
B36: 3A.1 | C36: 2156 | D36: Ananth(DEV) | F36: =C36*F2 -> 18044.508
B37: 3A.2 | C37: =2073 -> 2073 | D37: Bhavya Reddy 2,500 Sq.Ft | F37: =C37*F2 -> 17349.844
B38: 3B.1 | C38: =2927 -> 2927 | D38: Sasya Reddy 2,500 Sq.Ft | F38: =C38*F2 -> 24497.344
B39: 3B.2 | C39: =1301 -> 1301 | D39: Anoop (DEV) | F39: =C39*F2 -> 10888.638
B40: Sub-total | C40: =SUM(C36:C39) -> 8457
A41: 4 | B41: Office 04 | C41: 8699 | D41: Anoop (DEV) | F41: =C41*F2 -> 72805.739
A42: Total | C42: =SUM(C29,C34,C35,C41) -> 34218
A44: Eighth Floor
A45: S.NO | B45: Description | C45: SBUA | D45: Ownership
A46: 1 | B46: Office 01 | C46: =2101 -> 2101 | D46: Tachyon IT Solutions Pvt Ltd (DEV) | F46: =C46*F2 -> 17584.189
A47: 2 | B47: Office 02 | C47: 11425 | D47: Tachyon IT Solutions Pvt Ltd (DEV) | F47: =C47*F2 -> 95620.826
A48: 3 | B48: Office 03 | C48: =8457 -> 8457 | D48: Tachyon IT Solutions Pvt Ltd (DEV) | F48: =C48*F2 -> 70780.335
A49: 4 | B49: Office 04 | C49: 8699 | D49: Tachyon IT Solutions Pvt Ltd (DEV) | F49: =C49*F2 -> 72805.739
A50: Total | C50: =SUM(C46:C49) -> 30682
A52: Ninth Floor
A53: S.NO | B53: Description | C53: SBUA | D53: Ownership
A54: 1 | B54: Office 01 | C54: 5637 | D54: Pulluri Mining and Logistics Pvt Ltd (DEV) | F54: =C54*F2 -> 47178.52
A55: 2 | B55: Office 02 | C55: 11425 | D55: Pulluri Mining and Logistics Pvt Ltd (DEV) | F55: =C55*F2 -> 95620.826
A56: 3 | B56: Office 03 | C56: =8457 -> 8457 | D56: UDS Developer Arjun Rao Group
B57: 3.1 | C57: =3957 -> 3957 | D57: Arjun Rao (DEV) | F57: =C57*F2 -> 33117.865
B58: 3.2 | C58: =1500 -> 1500 | D58: Karabee Kailash (Ohja) (DEV) | F58: =C58*F2 -> 12554.157
B59: 3.3 | C59: =1500 -> 1500 | D59: Jakka Deepa (DEV) | F59: =C59*F2 -> 12554.157
B60: 3.4 | C60: =1500 -> 1500 | D60: Indu Priya (DEV) | F60: =C60*F2 -> 12554.157
B61: Sub-total | C61: =SUM(C57:C60) -> 8457
A62: 4 | B62: Office 04 | C62: 8699 | D62: AGA Infra Projects Pvt Ltd (DEV) | F62: =C62*F2 -> 72805.739
A63: Total | C63: =SUM(C54:C56,C62) -> 34218
A65: Tenth Floor
A66: S.NO | B66: Description | C66: SBUA | D66: Ownership
A67: 1 | B67: Office 01 | C67: 5637 | D67: Raj Kumar Maganti & Pradeep Kumar Maganti /Siri Sampada | E67: Siri Sampada Real Estate | F67: =C67*F2 -> 47178.52
A68: 2 | B68: Office 02 | C68: 11425 | D68: Developer
B69: 2.1 | C69: 3000 | D69: Srinivas Reddy Challa (DEV) | F69: =C69*F2 -> 25108.313
B70: 2.2 | C70: 1000 | D70: Shruti Gummadi (DEV) | F70: =C70*F2 -> 8369.4377
B71: 2.3 | C71: =3925-1000+500 -> 3425 | D71: Deepthi Kesireddy (DEV) | F71: =C71*F2 -> 28665.324
B72: 2.4 | C72: 1000 | D72: Chandralekha Kesireddy (DEV) | F72: =C72*F2 -> 8369.4377
B73: 2.5 | C73: 2000 | D73: Manohar SP (DEV) | F73: =C73*F2 -> 16738.875
B74: 2.6 | C74: 1000 | D74: Shwetha Reddy | F74: =C74*F2 -> 8369.4377
B75: Sub-total | C75: =SUM(C69:C74) -> 11425
A76: 3 | B76: Office 03 | C76: =8457 -> 8457 | D76: Sukender Reddy Pulusani, Vijay Kumar & Others.
B77: 3.1 | C77: 2300 | D77: Kadiyala Venkateshwar Rao | F77: =C77*F2 -> 19249.707
B78: 3.2 | C78: 1000 | D78: Sunkara Vijaya Durga & Sunkara Jishna Sathwik | F78: =C78*F2 -> 8369.4377
B79: 3.3 | C79: 1153 | D79: Sukender Reddy Pulusani | F79: =C79*F2 -> 9649.9617
B80: 3.4 | C80: 1152 | D80: Neetha Pulusani | F80: =C80*F2 -> 9641.5923
B81: 3.5 | C81: 1152 | D81: Kireet Reddy Pulusani | F81: =C81*F2 -> 9641.5923
B82: 3.6 | C82: 850 | D82: Krishna Kumar Vempati | F82: =C82*F2 -> 7114.0221
B83: 3.7 | C83: 850 | D83: J Vijay Kumar & Laxmi | F83: =C83*F2 -> 7114.0221
B84: Sub-total | C84: =SUM(C77:C83) -> 8457
A85: 4 | B85: Office 04 | C85: 8699 | D85: Rohan Mandala & Sridhar Anisha (DEV) | F85: =C85*F2 -> 72805.739
A86: Total | C86: =SUM(C67,C75,C76,C85) -> 34218
A88: Eleventh Floor
A89: S.NO | B89: Description | C89: SBUA | D89: Ownership
A90: 1 | B90: Office 01 | C90: 5637 | D90: Developer
B91: 1A | C91: =2587 -> 2587 | D91: Madhusudhan Reddy Kypa(Dileep kurnool) | F91: =C91*F2 -> 21651.735
B92: 1B | C92: 3050 | D92: Pavan Kumar Mummasani & Manasa Priyadharshini (DEV) | F92: =C92*F2 -> 25526.785
B93: Sub-total | C93: =SUM(C91:C92) -> 5637
A94: 2 | B94: Office 02 | C94: 11425 | D94: UDS Landowners (KDR Family)
B95: 2.1 | C95: 3028 | D95: K. Rajesh Reddy (LO) | F95: =C95*F2 -> 25342.657
B96: 2.2 | C96: =4004-1320 -> 2684 | D96: K Saritha(LO) | F96: =C96*F2 -> 22463.571
B97: 2.3 | C97: 3028 | D97: K Ramachandra Reddy (LO) | F97: =C97*F2 -> 25342.657
B98: 2.4 | C98: =1365+1320 -> 2685 | D98: K Spandana(LO) | F98: =C98*F2 -> 22471.94
B99: Sub-total | C99: =SUM(C95:C98) -> 11425
A100: 3 | B100: Office 03 | C100: 8457 | D100: Arundathi(LO) | F100: =C100*F2 -> 70780.335
A101: 4 | B101: Office 04 | C101: 8699 | D101: Manjula(LO) | F101: =C101*F2 -> 72805.739
A102: Total | C102: =SUM(C90+C99+C100+C101) -> 34218
A104: Twelfth Floor
A105: S.NO | B105: Description | C105: SBUA | D105: Ownership
A106: 1 | B106: Office 01 | C106: =2101 -> 2101 | D106: K. Tanuja (DEV) | F106: =C106*F2 -> 17584.189
A107: 2 | B107: Office 02 | C107: 11425 | D107: UDS (Developer + Landowner)
B108: 2.1 | C108: =11166 -> 11166 | D108: Madhukar Reddy (LO) | F108: =C108*F2 -> 93453.142
...

Sheet CAM-May`24
E1: .
A2: CAM CHARGES CALCULATION SUMMARY - OGM-May`24
B3: Total Building Saleable area | C3: Area sft | D3: 490749 | E3: MCP Occupied area | H3: OGM Area
A4: CAM Charges INR/ Per sq ft / Month | C4: per sq. ft cost | D4: =SUM(D6:D18) -> 7.0814841 | E4: MCP | F4: Per Sft | G4: 167554 | H4: =D3-G4 -> 323195
A5: Sl no | B5: Description | C5: Per month | D5: Per sft
A6: 1 | B6: Management staff (By Area) | C6: =262200+77500+50000 -> 389700 | D6: =C6/D3 -> 0.7940923 | G6: =G4*D6 -> 133053.34 | H6: =H4*D6 -> 256646.66
A7: 2 | B7: Technical manpower (% Share) | C7: 442335.19 | D7: =C7/D3 -> 0.9013471 | E7: =C7*(D29) -> 143398.7 | F7: =E7/D3 -> 0.29220375 | G7: =F7*G4 -> 48959.908 | H7: =C7-G7 -> 393375.28
A8: 3 | B8: HK Manpower (% Share) | C8: 354052 | D8: =C8/D3 -> 0.72145231 | E8: =C8*D28 -> 242128.29 | F8: =E8/D3 -> 0.4933852 | G8: =F8*G4 -> 82668.664 | H8: =C8-G8 -> 271383.34
A9: 4 | B9: LP Manpower -Security Services (By Area) | C9: 802542.26 | D9: =C9/D3 -> 1.6353416 | G9: =G4*D9 -> 274008.03 | H9: =H4*D9 -> 528534.23
A10: 5 | B10: AMC (By Area) | C10: =45000+5000+6000+160000 -> 216000 | D10: =C10/D3 -> 0.44014354 | G10: =D10*G4 -> 73747.81 | H10: =C10-G10 -> 142252.19
A11: 6 | B11: AMC Excl. MCP | C11: 0 | D11: 0 | G11: 0
A12: 7 | B12: Consumables (HK %Share) | C12: 0 | D12: =C12/D3 -> 0 | E12: =C12*D28 -> 0 | F12: =E12/D3 -> 0 | G12: =F12*G4 -> 0 | H12: =C12-G12 -> 0
A13: 8 | B13: Consumables Excl MCP | C13: 0 | D13: 0 | G13: 0
A14: 9 | B14: Common area Electrical & DG Charges (Tech %Share) | C14: =611600.275183983+392206.685019915 -> 1003807 | D14: =C14/D3 -> 2.045459 | E14: =C14*(D29) -> 325419.76 | F14: =E14/D3 -> 0.66310836 | G14: =F14*G4 -> 111106.46 | H14: =C14-G14 -> 892700.5
A15: 10 | B15: Common area Water charges (By Area) | C15: =223554.465851735-C16 -> 148083.11 | D15: =C15/D3 -> 0.30174919 | G15: =G4*D15 -> 50559.284 | H15: =C15-G15 -> 97523.83
A16: 11 | B16: Cooling Tower water charges | C16: =E33 -> 75471.353 | H16: =C16 -> 75471.353
A17: 12 | B17: FMS Cost (By Area) | C17: =C48 -> 118711.7 | D17: =C17/D3 -> 0.24189902 | G17: =D17*G4 -> 40531.148 | H17: =C17-G17 -> 78180.552
A18: 13 | B18: Liosaning & Licenses (By Area) | C18: 0 | D18: =C18/D3 -> 0 | G18: =D18*G4 -> 0 | H18: =C18-G18 -> 0
A19: A | B19: Total CAM Charges | C19: =SUM(C6:C18) -> 3550702.6 | G19: =SUM(G6:G18) -> 814634.64 | H19: =SUM(H6:H18) -> 2736067.9
A20: 14 | B20: Contingency, Sinking Fund @2% | C20: =C19*2% -> 71014.052 | D20: =C20/D3 -> 0.14470544 | G20: =G19*2% -> 16292.693 | H20: =C20-G20 -> 54721.359
A21: 15 | B21: Fixed Management Fees | C21: 490749 | D21: =C21/D3 -> 1 | G21: =D21*G4 -> 167554 | H21: =C21-G21 -> 323195
B22: Grand Total | C22: =C19+C20+C21 -> 4112465.6 | G22: =G19+G20+G21 -> 998481.33 | H22: =H19+H20+H21 -> 3113984.3
A23: B | B23: Including Contingency & Sinking fund Per Sft CAM Charges | C23: =(C20+C21+C19)/D3 -> 8.3799776 | G23: =(G19+G20+G21)/G4 -> 5.9591614 | H23: =(H20+H21+H19)/H4 -> 9.6350015
A26: S No | B26: Description | C26: Total Area in SFT | D26: % on Total area | E26: Remarks
A27: 1 | B27: Total building common area | C27: 381481.87
A28: 2 | B28: MCP Utilization common area | C28: 260886.97 | D28: =C28/C27 -> 0.68387778 | E28: Housekeeping
A29: 3 | B29: MCP Utilization common area excluding B4 parking | C29: 123670.93 | D29: =C29/C27 -> 0.3241856 | E29: Technical
A30: 4 | B30: B4 parking
A32: S No | B32: May`24 | C32: Consumed KL | D32: Rate/KL | E32: Amount
A33: 1 | B33: MCP cooling tower water consumption | C33: 381 | D33: 198.08754 | E33: =C33*D33 -> 75471.353
A35: S No | B35: AMCs | C35: Amount
A36: 1 | B36: Pest control | C36: 45000
A37: 2 | B37: Garbage pick-up | C37: 5000
A38: 3 | B38: HMWSS charges | C38: 6000
A39: 4 | B39: STP operations- Feb`24 & Mar`24 | C39: 160000
B40: Total | C40: =SUM(C36:C39) -> 216000
A42: S No | B42: FMS Cost | C42: Amount
A43: 1 | B43: Computer service and AutoCAD installation | C43: 1325
A44: 2 | B44: Button cell for water TDS & PH meters | C44: 320
A45: 3 | B45: Electrical CEIG drawings printout for CEIG inspection | C45: 260
A46: 4 | B46: TS Fire expenses ( 3.5 Lacs / 3 Months) | C46: 116666.7 | D46: Need to reconfirm with the data share to microchip
A47: 5 | B47: Water bottles case for CEIG inspection | C47: 140
B48: Total | C48: =SUM(C43:C47) -> 118711.7
A50: S No | B50: Common area Electrical & DG Charges (Tech %Share) | C50: Amount
A51: 1 | B51: Common area EB & DG charges for the month of May`24 | C51: 611600.28
A52: 2 | B52: ACD common area share for the month of May`24 | C52: 392206.69
B53: Total | C53: =SUM(C51:C52) -> 1003807

Sheet Tenant CAM-May`24
A1: Tenant CAM details-OGM-May`24
A2: Floor | E2: CAM cost per Sft | F2: ='CAM-May`24'!H23 -> 9.6350015
A3: Ground Floor
A4: S.NO | B4: Description | C4: SBUA | D4: Ownership | E4: Tenants | F4: CAM Cost | G4: Carpet Area | H4: Cost/Sft
A5: 1 | B5: Retail 01 | C5: =3311 -> 3311 | D5: Amar Chowdhary | E5: HDFC Bank Ltd | F5: =(C5)*F2 -> 31901.49 | G5: =C5*65% -> 2152.15 | H5: =F5/G5 -> 14.823079
A6: 2 | B6: Retail 02 | C6: =3816 -> 3816 | D6: UDS Landowners | E6: Milu Foods (Vacs Bakery) | F6: =C6*F2 -> 36767.166
A7: 3 | B7: Retail 03 | C7: 3814 | D7: KSR Group | E7: Chicken Wild Wings Pvt Ltd | F7: =C7*F2 -> 36747.896
A8: 4 | B8: Retail 04 | C8: =3648 -> 3648 | D8: Aashish Bansal and Mona Bansal | E8: Fatcity Hospitality LLP | F8: =C8*F2 -> 35148.485
A9: 5 | B9: Retail 05 | C9: =3436 -> 3436 | D9: Vazir Singh Pilania and Thota Raghu Buchanna | E9: Fatcity Hospitality LLP | F9: =C9*F2 -> 33105.865
A10: 6 | B10: Retail 06 | C10: =2723 -> 2723 | D10: TanujaNayani and Ratna/Gouri Reddy | E10: Fatcity Hospitality LLP | F10: =C10*F2 -> 26236.109
A11: 7 | B11: Retail 07 | C11: =1381 -> 1381 | D11: TanujaNayani | E11: ICICI Bank Ltd | F11: =C11*F2 -> 13305.937
A12: 8 | B12: Retail 08 | C12: =755 -> 755 | D12: K Sudhakar Reddy | E12: ICICI Bank Ltd | F12: =C12*F2 -> 7274.4261
C13: =SUM(C5:C12) -> 22884
A14: First Floor
A15: S.NO | B15: Description | C15: SBUA | D15: Ownership
A16: 1 | B16: Retail 01 | C16: =6725 -> 6725 | D16: Developer | F16: =C16*F2 -> 64795.385
A17: 2 | B17: Retail 02 | C17: =7686 -> 7686 | D17: Developer | F17: =C17*F2 -> 74054.621
A18: 3 | B18: Retail 03 | C18: =9714 -> 9714 | D18: Developer and Landowners | F18: =C18*F2 -> 93594.404
A19: 4 | B19: Retail 04 | C19: =9514 -> 9514 | D19: UDS Landowners | F19: =C19*F2 -> 91667.404
A20: Total | C20: =C16+C17+C18+C19 -> 33639
A22: Second Floor to Sixth Floor
A23: S.NO | B23: Description | C23: SBUA | D23: Ownership
A24: 1 | B24: All Offices | C24: 167554 | D24: Microchip Technology India Pvt Ltd | F24: =C24*'CAM-May`24'!G23 -> 998481.33
A27: Seventh Floor
A28: S.NO | B28: Description | C28: SBUA | D28: Ownership
A29: 1 | B29: Office 01 | C29: 5637 | D29: Developer
B30: 1A.1 | C30: 2000 | D30: Pamara Venkata Ramana Devi and Pamera Ram Gopal Rao | F30: =C30*F2 -> 19270.003
B31: 1B.2 | C31: =587 -> 587 | D31: Developer | F31: =C31*F2 -> 5655.7459
B32: 1B | C32: =3050 -> 3050 | D32: Nirmal + Dileep (DEV) | F32: =C32*F2 -> 29386.754
B33: Sub-total | C33: =SUM(C30:C32) -> 5637
A34: 2 | B34: Office 02 | C34: 11425 | D34: Avinash Kotagiri (DEV) | F34: =C34*F2 -> 110079.89
A35: 3 | B35: Office 03 | C35: =8457 -> 8457 | D35: Ananth+Dileep+Anoop (DEV)
B36: 3A.1 | C36: 2156 | D36: Ananth(DEV) | F36: =C36*F2 -> 20773.063
B37: 3A.2 | C37: =2073 -> 2073 | D37: Bhavya Reddy 2,500 Sq.Ft | F37: =C37*F2 -> 19973.358
B38: 3B.1 | C38: =2927 -> 2927 | D38: Sasya Reddy 2,500 Sq.Ft | F38: =C38*F2 -> 28201.649
B39: 3B.2 | C39: =1301 -> 1301 | D39: Anoop (DEV) | F39: =C39*F2 -> 12535.137
B40: Sub-total | C40: =SUM(C36:C39) -> 8457
A41: 4 | B41: Office 04 | C41: 8699 | D41: Anoop (DEV) | F41: =C41*F2 -> 83814.878
A42: Total | C42: =SUM(C29,C34,C35,C41) -> 34218
A44: Eighth Floor
A45: S.NO | B45: Description | C45: SBUA | D45: Ownership
A46: 1 | B46: Office 01 | C46: =2101 -> 2101 | D46: Tachyon IT Solutions Pvt Ltd (DEV) | F46: =C46*F2 -> 20243.138
A47: 2 | B47: Office 02 | C47: 11425 | D47: Tachyon IT Solutions Pvt Ltd (DEV) | F47: =C47*F2 -> 110079.89
A48: 3 | B48: Office 03 | C48: =8457 -> 8457 | D48: Tachyon IT Solutions Pvt Ltd (DEV) | F48: =C48*F2 -> 81483.207
A49: 4 | B49: Office 04 | C49: 8699 | D49: Tachyon IT Solutions Pvt Ltd (DEV) | F49: =C49*F2 -> 83814.878
A50: Total | C50: =SUM(C46:C49) -> 30682
A52: Ninth Floor
A53: S.NO | B53: Description | C53: SBUA | D53: Ownership
A54: 1 | B54: Office 01 | C54: 5637 | D54: Pulluri Mining and Logistics Pvt Ltd (DEV) | F54: =C54*F2 -> 54312.503
A55: 2 | B55: Office 02 | C55: 11425 | D55: Pulluri Mining and Logistics Pvt Ltd (DEV) | F55: =C55*F2 -> 110079.89
A56: 3 | B56: Office 03 | C56: =8457 -> 8457 | D56: UDS Developer Arjun Rao Group
B57: 3.1 | C57: =3957 -> 3957 | D57: Arjun Rao (DEV) | F57: =C57*F2 -> 38125.701
B58: 3.2 | C58: =1500 -> 1500 | D58: Karabee Kailash (Ohja) (DEV) | F58: =C58*F2 -> 14452.502
B59: 3.3 | C59: =1500 -> 1500 | D59: Jakka Deepa (DEV) | F59: =C59*F2 -> 14452.502
B60: 3.4 | C60: =1500 -> 1500 | D60: Indu Priya (DEV) | F60: =C60*F2 -> 14452.502
B61: Sub-total | C61: =SUM(C57:C60) -> 8457
A62: 4 | B62: Office 04 | C62: 8699 | D62: AGA Infra Projects Pvt Ltd (DEV) | F62: =C62*F2 -> 83814.878
A63: Total | C63: =SUM(C54:C56,C62) -> 34218
A65: Tenth Floor
A66: S.NO | B66: Description | C66: SBUA | D66: Ownership
A67: 1 | B67: Office 01 | C67: 5637 | D67: Raj Kumar Maganti & Pradeep Kumar Maganti /Siri Sampada | E67: Siri Sampada Real Estate | F67: =C67*F2 -> 54312.503
A68: 2 | B68: Office 02 | C68: 11425 | D68: Developer
B69: 2.1 | C69: 3000 | D69: Srinivas Reddy Challa (DEV) | F69: =C69*F2 -> 28905.004
B70: 2.2 | C70: 1000 | D70: Shruti Gummadi (DEV) | F70: =C70*F2 -> 9635.0015
B71: 2.3 | C71: =3925-1000+500 -> 3425 | D71: Deepthi Kesireddy (DEV) | F71: =C71*F2 -> 32999.88
B72: 2.4 | C72: 1000 | D72: Chandralekha Kesireddy (DEV) | F72: =C72*F2 -> 9635.0015
B73: 2.5 | C73: 2000 | D73: Manohar SP (DEV) | F73: =C73*F2 -> 19270.003
B74: 2.6 | C74: 1000 | D74: Shwetha Reddy | F74: =C74*F2 -> 9635.0015
B75: Sub-total | C75: =SUM(C69:C74) -> 11425
A76: 3 | B76: Office 03 | C76: =8457 -> 8457 | D76: Sukender Reddy Pulusani, Vijay Kumar & Others.
B77: 3.1 | C77: 2300 | D77: Kadiyala Venkateshwar Rao | F77: =C77*F2 -> 22160.503
B78: 3.2 | C78: 1000 | D78: Sunkara Vijaya Durga & Sunkara Jishna Sathwik | F78: =C78*F2 -> 9635.0015
B79: 3.3 | C79: 1153 | D79: Sukender Reddy Pulusani | F79: =C79*F2 -> 11109.157
B80: 3.4 | C80: 1152 | D80: Neetha Pulusani | F80: =C80*F2 -> 11099.522
B81: 3.5 | C81: 1152 | D81: Kireet Reddy Pulusani | F81: =C81*F2 -> 11099.522
B82: 3.6 | C82: 850 | D82: Krishna Kumar Vempati | F82: =C82*F2 -> 8189.7512
B83: 3.7 | C83: 850 | D83: J Vijay Kumar & Laxmi | F83: =C83*F2 -> 8189.7512
B84: Sub-total | C84: =SUM(C77:C83) -> 8457
A85: 4 | B85: Office 04 | C85: 8699 | D85: Rohan Mandala & Sridhar Anisha (DEV) | F85: =C85*F2 -> 83814.878
A86: Total | C86: =SUM(C67,C75,C76,C85) -> 34218
A88: Eleventh Floor
A89: S.NO | B89: Description | C89: SBUA | D89: Ownership
A90: 1 | B90: Office 01 | C90: 5637 | D90: Developer
B91: 1A | C91: =2587 -> 2587 | D91: Madhusudhan Reddy Kypa(Dileep kurnool) | F91: =C91*F2 -> 24925.749
B92: 1B | C92: 3050 | D92: Pavan Kumar Mummasani & Manasa Priyadharshini (DEV) | F92: =C92*F2 -> 29386.754
B93: Sub-total | C93: =SUM(C91:C92) -> 5637
A94: 2 | B94: Office 02 | C94: 11425 | D94: UDS Landowners (KDR Family)
B95: 2.1 | C95: 3028 | D95: K. Rajesh Reddy (LO) | F95: =C95*F2 -> 29174.784
B96: 2.2 | C96: =4004-1320 -> 2684 | D96: K Saritha(LO) | F96: =C96*F2 -> 25860.344
B97: 2.3 | C97: 3028 | D97: K Ramachandra Reddy (LO) | F97: =C97*F2 -> 29174.784
B98: 2.4 | C98: =1365+1320 -> 2685 | D98: K Spandana(LO) | F98: =C98*F2 -> 25869.979
B99: Sub-total | C99: =SUM(C95:C98) -> 11425
A100: 3 | B100: Office 03 | C100: 8457 | D100: Arundathi(LO) | F100: =C100*F2 -> 81483.207
A101: 4 | B101: Office 04 | C101: 8699 | D101: Manjula(LO) | F101: =C101*F2 -> 83814.878
A102: Total | C102: =SUM(C90+C99+C100+C101) -> 34218
A104: Twelfth Floor
A105: S.NO | B105: Description | C105: SBUA | D105: Ownership
A106: 1 | B106: Office 01 | C106: =2101 -> 2101 | D106: K. Tanuja (DEV) | F106: =C106*F2 -> 20243.138
A107: 2 | B107: Office 02 | C107: 11425 | D107: UDS (Developer + Landowner)
B108: 2.1 | C108: =11166 -> 11166 | D108: Madhukar Reddy (LO) | F108: =C108*F2 -> 107584.43
...

Sheet CAM-Jun`24
E1: .
A2: CAM CHARGES CALCULATION SUMMARY - OGM-Jun`24
B3: Total Building Saleable area | C3: Area sft | D3: 490749 | E3: MCP Occupied area | H3: OGM Area
A4: CAM Charges INR/ Per sq ft / Month | C4: per sq. ft cost | D4: =SUM(D6:D18) -> 7.3464546 | E4: MCP | F4: Per Sft | G4: 167554 | H4: =D3-G4 -> 323195
A5: Sl no | B5: Description | C5: Per month | D5: Per sft
A6: 1 | B6: Management staff (By Area) | C6: =262200+77500+50000 -> 389700 | D6: =C6/D3 -> 0.7940923 | G6: =G4*D6 -> 133053.34 | H6: =H4*D6 -> 256646.66
A7: 2 | B7: Technical manpower (% Share) | C7: 448502.68 | D7: =C7/D3 -> 0.91391461 | E7: =C7*(D29) -> 145398.11 | F7: =E7/D3 -> 0.29627796 | G7: =F7*G4 -> 49642.557 | H7: =C7-G7 -> 398860.12
A8: 3 | B8: HK Manpower (% Share) | C8: 414000 | D8: =C8/D3 -> 0.84360844 | E8: =C8*D28 -> 283125.4 | F8: =E8/D3 -> 0.57692507 | G8: =F8*G4 -> 96666.102 | H8: =C8-G8 -> 317333.9
A9: 4 | B9: LP Manpower -Security Services (By Area) | C9: 675091 | D9: =C9/D3 -> 1.375634 | G9: =G4*D9 -> 230492.98 | H9: =H4*D9 -> 444598.02
A10: 5 | B10: AMC (By Area) | C10: =C42-C11 -> 136000 | D10: =C10/D3 -> 0.27712741 | G10: =D10*G4 -> 46433.806 | H10: =C10-G10 -> 89566.194
A11: 6 | B11: AMC Excl. MCP | C11: 51573 | D11: =C11/D3 -> 0.10509038 | G11: 0 | H11: =C11-G11 -> 51573
A12: 7 | B12: Consumables (HK %Share) | C12: 1357 | D12: =C12/D3 -> 0.002765161 | E12: =C12*D28 -> 928.02214 | F12: =E12/D3 -> 0.0018910322 | G12: =F12*G4 -> 316.85 | H12: =C12-G12 -> 1040.15
A13: 8 | B13: Consumables Excl MCP | C13: 0 | D13: 0 | G13: 0
A14: 9 | B14: Common area Electrical & DG Charges (Tech %Share) | C14: =C58 -> 871712.07 | D14: =C14/D3 -> 1.776289 | E14: =C14*(D29) -> 282596.5 | F14: =E14/D3 -> 0.57584733 | G14: =F14*G4 -> 96485.524 | H14: =C14-G14 -> 775226.55
A15: 10 | B15: Common area Water charges (By Area) | C15: =202166.682135997-C16 -> 143709.15 | D15: =C15/D3 -> 0.29283636 | G15: =G4*D15 -> 49065.904 | H15: =C15-G15 -> 94643.248
A16: 11 | B16: Cooling Tower water charges | C16: =E33 -> 58457.53 | H16: =C16 -> 58457.53
A17: 12 | B17: FMS Cost (By Area) | C17: =C45+C50+C51 -> 117371.7 | D17: =C17/D3 -> 0.2391685 | G17: =D17*G4 -> 40073.638 | H17: =C17-G17 -> 77298.062
A18: 13 | B18: Liosaning & Licenses (By Area) | C18: 356248.67 | D18: =C18/D3 -> 0.72592846 | G18: =D18*G4 -> 121632.22 | H18: =C18-G18 -> 234616.45
A19: A | B19: Total CAM Charges | C19: =SUM(C6:C18) -> 3663722.8 | G19: =SUM(G6:G18) -> 863862.92 | H19: =SUM(H6:H18) -> 2799859.9
A20: 14 | B20: Contingency, Sinking Fund @2% | C20: 0 | D20: =C20/D3 -> 0 | G20: 0 | H20: =C20-G20 -> 0
A21: 15 | B21: Fixed Management Fees | C21: 490749 | D21: =C21/D3 -> 1 | G21: =D21*G4 -> 167554 | H21: =C21-G21 -> 323195
B22: Grand Total | C22: =C19+C20+C21 -> 4154471.8 | G22: =G19+G20+G21 -> 1031416.9 | H22: =H19+H20+H21 -> 3123054.9
A23: B | B23: Including Contingency & Sinking fund Per Sft CAM Charges | C23: =(C20+C21+C19)/D3 -> 8.4655736 | G23: =(G19+G20+G21)/G4 -> 6.1557284 | H23: =(H20+H21+H19)/H4 -> 9.6630668
A26: S No | B26: Description | C26: Total Area in SFT | D26: % on Total area | E26: Remarks
A27: 1 | B27: Total building common area | C27: 381481.87
A28: 2 | B28: MCP Utilization common area | C28: 260886.97 | D28: =C28/C27 -> 0.68387778 | E28: Housekeeping
A29: 3 | B29: MCP Utilization common area excluding B4 parking | C29: 123670.93 | D29: =C29/C27 -> 0.3241856 | E29: Technical
A30: 4 | B30: B4 parking
A32: S No | B32: Jun`24 | C32: Consumed KL | D32: Rate/KL | E32: Amount
A33: 1 | B33: MCP cooling tower water consumption | C33: 313 | D33: 186.76527 | E33: =C33*D33 -> 58457.53
A35: S No | B35: AMCs | C35: Amount
A36: 1 | B36: Pest control | C36: 45000
A37: 2 | B37: Garbage pick-up | C37: 5000
A38: 3 | B38: HMWSS charges | C38: 6000
A39: 4 | B39: STP operations- Jun`24 | C39: 80000
A40: 5 | B40: Cooling Tower Chemicals- | C40: 51573 | D40: Excl. MCP
A41: 6
B42: Total | C42: =SUM(C36:C40) -> 187573
A44: S No | B44: FMS Cost | C44: Amount
A45: 1 | B45: Carpentry material | C45: 520
A46: 2 | B46: Brooms-10 no`s | C46: 500 | D46: HK
A47: 3 | B47: Water bottle and room freshner | C47: 300 | D47: HK
A48: 4 | B48: Handwash and bleaching powder | C48: 350 | D48: HK
A49: 5 | B49: Toilet cleaner | C49: 207 | D49: HK
A50: 6 | B50: Fire extinguishers covers and tags | C50: 185
A51: 7 | B51: TS Fire expenses ( 3.5 Lacs / 3 Months) | C51: 116666.7 | D51: Need to reconfirm with the data share to microchip
A52: 8
B53: Total | C53: =SUM(C45:C52) -> 118728.7
A55: S No | B55: Common area Electrical & DG Charges (Tech %Share) | C55: Amount
A56: 1 | B56: Common area EB & DG charges for the month of Jun`24 | C56: 479505.39
A57: 2 | B57: ACD common area share for the month of Jun`24 Amortization 3/3 | C57: 392206.69
B58: Total | C58: =SUM(C56:C57) -> 871712.07
A60: S No | B60: Liosaning & Licenses | C60: Amount
A61: 1 | B61: Building Insurance-TATA AIG-Total | C61: 1068746
B62: Building Insurance- Amortization-1/3 | C62: =C61/3 -> 356248.67

Sheet Tenant CAM-Jun`24
A1: Tenant CAM details-OGM-Jun`24
A2: Floor | E2: CAM cost per Sft | F2: ='CAM-Jun`24'!H23 -> 9.6630668
A3: Ground Floor
A4: S.NO | B4: Description | C4: SBUA | D4: Ownership | E4: Tenants | F4: CAM Cost | G4: Carpet Area | H4: Cost/Sft
A5: 1 | B5: Retail 01 | C5: =3311 -> 3311 | D5: Amar Chowdhary | E5: HDFC Bank Ltd | F5: =(C5)*F2 -> 31994.414 | G5: =C5*65% -> 2152.15 | H5: =F5/G5 -> 14.866257
A6: 2 | B6: Retail 02 | C6: =3816 -> 3816 | D6: UDS Landowners | E6: Milu Foods (Vacs Bakery) | F6: =C6*F2 -> 36874.263
A7: 3 | B7: Retail 03 | C7: 3814 | D7: KSR Group | E7: Chicken Wild Wings Pvt Ltd | F7: =C7*F2 -> 36854.937
A8: 4 | B8: Retail 04 | C8: =3648 -> 3648 | D8: Aashish Bansal and Mona Bansal | E8: Fatcity Hospitality LLP | F8: =C8*F2 -> 35250.868
A9: 5 | B9: Retail 05 | C9: =3436 -> 3436 | D9: Vazir Singh Pilania and Thota Raghu Buchanna | E9: Fatcity Hospitality LLP | F9: =C9*F2 -> 33202.298
A10: 6 | B10: Retail 06 | C10: =2723 -> 2723 | D10: TanujaNayani and Ratna/Gouri Reddy | E10: Fatcity Hospitality LLP | F10: =C10*F2 -> 26312.531
A11: 7 | B11: Retail 07 | C11: =1381 -> 1381 | D11: TanujaNayani | E11: ICICI Bank Ltd | F11: =C11*F2 -> 13344.695
A12: 8 | B12: Retail 08 | C12: =755 -> 755 | D12: K Sudhakar Reddy | E12: ICICI Bank Ltd | F12: =C12*F2 -> 7295.6155
C13: =SUM(C5:C12) -> 22884
A14: First Floor
A15: S.NO | B15: Description | C15: SBUA | D15: Ownership
A16: 1 | B16: Retail 01 | C16: =6725 -> 6725 | D16: Developer | F16: =C16*F2 -> 64984.124
A17: 2 | B17: Retail 02 | C17: =7686 -> 7686 | D17: Developer | F17: =C17*F2 -> 74270.332
A18: 3 | B18: Retail 03 | C18: =9714 -> 9714 | D18: Developer and Landowners | F18: =C18*F2 -> 93867.031
A19: 4 | B19: Retail 04 | C19: =9514 -> 9514 | D19: UDS Landowners | F19: =C19*F2 -> 91934.418
A20: Total | C20: =C16+C17+C18+C19 -> 33639
A22: Second Floor to Sixth Floor
A23: S.NO | B23: Description | C23: SBUA | D23: Ownership
A24: 1 | B24: All Offices | C24: 167554 | D24: Microchip Technology India Pvt Ltd | F24: =C24*'CAM-Jun`24'!G23 -> 1031416.9
A27: Seventh Floor
A28: S.NO | B28: Description | C28: SBUA | D28: Ownership
A29: 1 | B29: Office 01 | C29: 5637 | D29: Developer
B30: 1A.1 | C30: 2000 | D30: Pamara Venkata Ramana Devi and Pamera Ram Gopal Rao | F30: =C30*F2 -> 19326.134
B31: 1B.2 | C31: =587 -> 587 | D31: Developer | F31: =C31*F2 -> 5672.2202
B32: 1B | C32: =3050 -> 3050 | D32: Nirmal + Dileep (DEV) | F32: =C32*F2 -> 29472.354
B33: Sub-total | C33: =SUM(C30:C32) -> 5637
A34: 2 | B34: Office 02 | C34: 11425 | D34: Avinash Kotagiri (DEV) | F34: =C34*F2 -> 110400.54
A35: 3 | B35: Office 03 | C35: =8457 -> 8457 | D35: Ananth+Dileep+Anoop (DEV)
B36: 3A.1 | C36: 2156 | D36: Ananth(DEV) | F36: =C36*F2 -> 20833.572
B37: 3A.2 | C37: =2073 -> 2073 | D37: Bhavya Reddy 2,500 Sq.Ft | F37: =C37*F2 -> 20031.538
B38: 3B.1 | C38: =2927 -> 2927 | D38: Sasya Reddy 2,500 Sq.Ft | F38: =C38*F2 -> 28283.797
B39: 3B.2 | C39: =1301 -> 1301 | D39: Anoop (DEV) | F39: =C39*F2 -> 12571.65
B40: Sub-total | C40: =SUM(C36:C39) -> 8457
A41: 4 | B41: Office 04 | C41: 8699 | D41: Anoop (DEV) | F41: =C41*F2 -> 84059.018
A42: Total | C42: =SUM(C29,C34,C35,C41) -> 34218
A44: Eighth Floor
A45: S.NO | B45: Description | C45: SBUA | D45: Ownership
A46: 1 | B46: Office 01 | C46: =2101 -> 2101 | D46: Tachyon IT Solutions Pvt Ltd (DEV) | F46: =C46*F2 -> 20302.103
A47: 2 | B47: Office 02 | C47: 11425 | D47: Tachyon IT Solutions Pvt Ltd (DEV) | F47: =C47*F2 -> 110400.54
A48: 3 | B48: Office 03 | C48: =8457 -> 8457 | D48: Tachyon IT Solutions Pvt Ltd (DEV) | F48: =C48*F2 -> 81720.556
A49: 4 | B49: Office 04 | C49: 8699 | D49: Tachyon IT Solutions Pvt Ltd (DEV) | F49: =C49*F2 -> 84059.018
A50: Total | C50: =SUM(C46:C49) -> 30682
A52: Ninth Floor
A53: S.NO | B53: Description | C53: SBUA | D53: Ownership
A54: 1 | B54: Office 01 | C54: 5637 | D54: Pulluri Mining and Logistics Pvt Ltd (DEV) | F54: =C54*F2 -> 54470.708
A55: 2 | B55: Office 02 | C55: 11425 | D55: Pulluri Mining and Logistics Pvt Ltd (DEV) | F55: =C55*F2 -> 110400.54
A56: 3 | B56: Office 03 | C56: =8457 -> 8457 | D56: UDS Developer Arjun Rao Group
B57: 3.1 | C57: =3957 -> 3957 | D57: Arjun Rao (DEV) | F57: =C57*F2 -> 38236.755
B58: 3.2 | C58: =1500 -> 1500 | D58: Karabee Kailash (Ohja) (DEV) | F58: =C58*F2 -> 14494.6
B59: 3.3 | C59: =1500 -> 1500 | D59: Jakka Deepa (DEV) | F59: =C59*F2 -> 14494.6
B60: 3.4 | C60: =1500 -> 1500 | D60: Indu Priya (DEV) | F60: =C60*F2 -> 14494.6
B61: Sub-total | C61: =SUM(C57:C60) -> 8457
A62: 4 | B62: Office 04 | C62: 8699 | D62: AGA Infra Projects Pvt Ltd (DEV) | F62: =C62*F2 -> 84059.018
A63: Total | C63: =SUM(C54:C56,C62) -> 34218
A65: Tenth Floor
A66: S.NO | B66: Description | C66: SBUA | D66: Ownership
A67: 1 | B67: Office 01 | C67: 5637 | D67: Raj Kumar Maganti & Pradeep Kumar Maganti /Siri Sampada | E67: Siri Sampada Real Estate | F67: =C67*F2 -> 54470.708
A68: 2 | B68: Office 02 | C68: 11425 | D68: Developer
B69: 2.1 | C69: 3000 | D69: Srinivas Reddy Challa (DEV) | F69: =C69*F2 -> 28989.2
B70: 2.2 | C70: 1000 | D70: Shruti Gummadi (DEV) | F70: =C70*F2 -> 9663.0668
B71: 2.3 | C71: =3925-1000+500 -> 3425 | D71: Deepthi Kesireddy (DEV) | F71: =C71*F2 -> 33096.004
B72: 2.4 | C72: 1000 | D72: Chandralekha Kesireddy (DEV) | F72: =C72*F2 -> 9663.0668
B73: 2.5 | C73: 2000 | D73: Manohar SP (DEV) | F73: =C73*F2 -> 19326.134
B74: 2.6 | C74: 1000 | D74: Shwetha Reddy | F74: =C74*F2 -> 9663.0668
B75: Sub-total | C75: =SUM(C69:C74) -> 11425
A76: 3 | B76: Office 03 | C76: =8457 -> 8457 | D76: Sukender Reddy Pulusani, Vijay Kumar & Others.
B77: 3.1 | C77: 2300 | D77: Kadiyala Venkateshwar Rao | F77: =C77*F2 -> 22225.054
B78: 3.2 | C78: 1000 | D78: Sunkara Vijaya Durga & Sunkara Jishna Sathwik | F78: =C78*F2 -> 9663.0668
B79: 3.3 | C79: 1153 | D79: Sukender Reddy Pulusani | F79: =C79*F2 -> 11141.516
B80: 3.4 | C80: 1152 | D80: Neetha Pulusani | F80: =C80*F2 -> 11131.853
B81: 3.5 | C81: 1152 | D81: Kireet Reddy Pulusani | F81: =C81*F2 -> 11131.853
B82: 3.6 | C82: 850 | D82: Krishna Kumar Vempati | F82: =C82*F2 -> 8213.6068
B83: 3.7 | C83: 850 | D83: J Vijay Kumar & Laxmi | F83: =C83*F2 -> 8213.6068
B84: Sub-total | C84: =SUM(C77:C83) -> 8457
A85: 4 | B85: Office 04 | C85: 8699 | D85: Rohan Mandala & Sridhar Anisha (DEV) | F85: =C85*F2 -> 84059.018
A86: Total | C86: =SUM(C67,C75,C76,C85) -> 34218
A88: Eleventh Floor
A89: S.NO | B89: Description | C89: SBUA | D89: Ownership
A90: 1 | B90: Office 01 | C90: 5637 | D90: Developer
B91: 1A | C91: =2587 -> 2587 | D91: Madhusudhan Reddy Kypa(Dileep kurnool) | F91: =C91*F2 -> 24998.354
B92: 1B | C92: 3050 | D92: Pavan Kumar Mummasani & Manasa Priyadharshini (DEV) | F92: =C92*F2 -> 29472.354
B93: Sub-total | C93: =SUM(C91:C92) -> 5637
A94: 2 | B94: Office 02 | C94: 11425 | D94: UDS Landowners (KDR Family)
B95: 2.1 | C95: 3028 | D95: K. Rajesh Reddy (LO) | F95: =C95*F2 -> 29259.766
B96: 2.2 | C96: =4004-1320 -> 2684 | D96: K Saritha(LO) | F96: =C96*F2 -> 25935.671
B97: 2.3 | C97: 3028 | D97: K Ramachandra Reddy (LO) | F97: =C97*F2 -> 29259.766
B98: 2.4 | C98: =1365+1320 -> 2685 | D98: K Spandana(LO) | F98: =C98*F2 -> 25945.334
B99: Sub-total | C99: =SUM(C95:C98) -> 11425
A100: 3 | B100: Office 03 | C100: 8457 | D100: Arundathi(LO) | F100: =C100*F2 -> 81720.556
A101: 4 | B101: Office 04 | C101: 8699 | D101: Manjula(LO) | F101: =C101*F2 -> 84059.018
A102: Total | C102: =SUM(C90+C99+C100+C101) -> 34218
A104: Twelfth Floor
A105: S.NO | B105: Description | C105: SBUA | D105: Ownership
A106: 1 | B106: Office 01 | C106: =2101 -> 2101 | D106: K. Tanuja (DEV) | F106: =C106*F2 -> 20302.103
A107: 2 | B107: Office 02 | C107: 11425 | D107: UDS (Developer + Landowner)
B108: 2.1 | C108: =11166 -> 11166 | D108: Madhukar Reddy (LO) | F108: =C108*F2 -> 107897.8
...

Sheet CAM-Jul`24
E1: .
A2: CAM CHARGES CALCULATION SUMMARY - OGM-Jul`24
B3: Total Building Saleable area | C3: Area sft | D3: 490749 | E3: MCP Occupied area | H3: OGM Area
A4: CAM Charges INR/ Per sq ft / Month | C4: per sq. ft cost | D4: =SUM(D6:D18) -> 7.000926 | E4: MCP | F4: Per Sft | G4: 167554 | H4: =D3-G4 -> 323195
A5: Sl no | B5: Description | C5: Per month | D5: Per sft
A6: 1 | B6: Management staff (By Area) | C6: =262200+77500+50000 -> 389700 | D6: =C6/D3 -> 0.7940923 | G6: =G4*D6 -> 133053.34 | H6: =H4*D6 -> 256646.66
A7: 2 | B7: Technical manpower (% Share) | C7: 434075 | D7: =C7/D3 -> 0.8845153 | E7: =C7*(D29) -> 140720.86 | F7: =E7/D3 -> 0.28674712 | G7: =F7*G4 -> 48045.628 | H7: =C7-G7 -> 386029.37
A8: 3 | B8: HK Manpower (% Share) | C8: 389390 | D8: =C8/D3 -> 0.79346061 | E8: =C8*D28 -> 266295.17 | F8: =E8/D3 -> 0.54263008 | G8: =F8*G4 -> 90919.84 | H8: =C8-G8 -> 298470.16
A9: 4 | B9: LP Manpower -Security Services (By Area) | C9: 677635 | D9: =C9/D3 -> 1.3808179 | G9: =G4*D9 -> 231361.56 | H9: =H4*D9 -> 446273.44
A10: 5 | B10: AMC (By Area) | C10: =C45-(C11+C13) -> 212462 | D10: =C10/D3 -> 0.43293415 | G10: =D10*G4 -> 72539.848 | H10: =C10-G10 -> 139922.15
A11: 6 | B11: AMC Excl. MCP | C11: =C40+C44 -> 55573 | D11: =C11/D3 -> 0.11324119 | G11: 0 | H11: =C11-G11 -> 55573
A12: 7 | B12: Consumables (HK %Share) | C12: 0 | D12: =C12/D3 -> 0 | E12: =C12*D28 -> 0 | F12: =E12/D3 -> 0 | G12: =F12*G4 -> 0 | H12: =C12-G12 -> 0
A13: 8 | B13: Consumables Excl MCP | C13: =C43 -> 227385 | D13: =C13/D3 -> 0.46334277 | G13: 0 | H13: =C13-G13 -> 227385
A14: 9 | B14: Common area Electrical & DG Charges (Tech %Share) | C14: =C61 -> 513702.2 | D14: =C14/D3 -> 1.0467718 | E14: =C14*(D29) -> 166534.86 | F14: =E14/D3 -> 0.33934834 | G14: =F14*G4 -> 56859.172 | H14: =C14-G14 -> 456843.03
A15: 10 | B15: Common area Water charges (By Area) | C15: =107627.750189487-C16 -> 52054.886 | D15: =C15/D3 -> 0.10607232 | G15: =G4*D15 -> 17772.842 | H15: =C15-G15 -> 34282.044
A16: 11 | B16: Cooling Tower water charges | C16: =E33 -> 55572.864 | H16: =C16 -> 55572.864
A17: 12 | B17: FMS Cost (By Area) | C17: =C56 -> 127471.7 | D17: =C17/D3 -> 0.25974928 | G17: =D17*G4 -> 43522.031 | H17: =C17-G17 -> 83949.669
A18: 13 | B18: Liosaning & Licenses (By Area) | C18: =C65 -> 356248.67 | D18: =C18/D3 -> 0.72592846 | G18: =D18*G4 -> 121632.22 | H18: =C18-G18 -> 234616.45
A19: A | B19: Total CAM Charges | C19: =SUM(C6:C18) -> 3491270.3 | G19: =SUM(G6:G18) -> 815706.48 | H19: =SUM(H6:H18) -> 2675563.8
A20: 14 | B20: Contingency, Sinking Fund @2% | C20: 0 | D20: =C20/D3 -> 0 | G20: 0 | H20: =C20-G20 -> 0
A21: 15 | B21: Fixed Management Fees | C21: 490749 | D21: =C21/D3 -> 1 | G21: =D21*G4 -> 167554 | H21: =C21-G21 -> 323195
B22: Grand Total | C22: =C19+C20+C21 -> 3982019.3 | G22: =G19+G20+G21 -> 983260.48 | H22: =H19+H20+H21 -> 2998758.8
A23: B | B23: Including Contingency & Sinking fund Per Sft CAM Charges | C23: =(C20+C21+C19)/D3 -> 8.114167 | G23: =(G19+G20+G21)/G4 -> 5.8683199 | H23: =(H20+H21+H19)/H4 -> 9.2784815
A26: S No | B26: Description | C26: Total Area in SFT | D26: % on Total area | E26: Remarks
A27: 1 | B27: Total building common area | C27: 381481.87
A28: 2 | B28: MCP Utilization common area | C28: 260886.97 | D28: =C28/C27 -> 0.68387778 | E28: Housekeeping
A29: 3 | B29: MCP Utilization common area excluding B4 parking | C29: 123670.93 | D29: =C29/C27 -> 0.3241856 | E29: Technical
A30: 4 | B30: B4 parking
A32: S No | B32: Jul`24 | C32: Consumed KL | D32: Rate/KL | E32: Amount
A33: 1 | B33: MCP cooling tower water consumption | C33: 181 | D33: 307.0324 | E33: =C33*D33 -> 55572.864
A35: S No | B35: AMCs | C35: Amount
A36: 1 | B36: Pest control | C36: 45000
A37: 2 | B37: Garbage pick-up | C37: 5000
A38: 3 | B38: HMWSS charges | C38: 6000
A39: 4 | B39: STP operations- Jul`24 | C39: 80000
A40: 5 | B40: Cooling Tower Chemicals- | C40: 51573 | D40: Excl. MCP
A41: 6 | B41: Crystal Salt for WTP regeneration | C41: 12412
A42: 7 | B42: Apex, Façade glass cleaning | C42: 64050
A43: 8 | B43: DG set B-check maintenance | C43: 227385 | D43: Excl. MCP | E43: Consumables
A44: 9 | B44: Kitchen grease trap | C44: 4000 | D44: Excl. MCP
B45: Total | C45: =SUM(C36:C44) -> 495420
A47: S No | B47: FMS Cost | C47: Amount
A48: 1 | B48: Fire pump- Airvent | C48: 1250
A49: 2 | B49: B4-Sump pump capacitor | C49: 200
A50: 3 | B50: SLD color print out for CEIG inspection | C50: 160
A51: 4 | B51: Registers | C51: 1360
A52: 5 | B52: First Aid medicine | C52: 428
A53: 6 | B53: 15th August-decorations | C53: 7407
A54: 7 | B54: TS Fire expenses ( 3.5 Lacs / 3 Months) | C54: 116666.7 | D54: Need to reconfirm with the data share to microchip
A55: 8
B56: Total | C56: =SUM(C48:C55) -> 127471.7
A58: S No | B58: Common area Electrical & DG Charges (Tech %Share) | C58: Amount
A59: 1 | B59: Common area EB & DG charges for the month of Jul`24 | C59: 513702.2
A60: 2
B61: Total | C61: =SUM(C59:C60) -> 513702.2
A63: S No | B63: Liosaning & Licenses | C63: Amount
A64: 1 | B64: Building Insurance-TATA AIG-Total | C64: 1068746
B65: Building Insurance- Amortization-2/3 | C65: =C64/3 -> 356248.67

Sheet Tenant CAM-Jul`24
A1: Tenant CAM details-OGM-Jun`24
A2: Floor | E2: CAM cost per Sft | F2: ='CAM-Jul`24'!H23 -> 9.2784815
A3: Ground Floor
A4: S.NO | B4: Description | C4: SBUA | D4: Ownership | E4: Tenants | F4: CAM Cost | G4: Carpet Area | H4: Cost/Sft
A5: 1 | B5: Retail 01 | C5: =3311 -> 3311 | D5: Amar Chowdhary | E5: HDFC Bank Ltd | F5: =(C5)*F2 -> 30721.052 | G5: =C5*65% -> 2152.15 | H5: =F5/G5 -> 14.274587
A6: 2 | B6: Retail 02 | C6: =3816 -> 3816 | D6: UDS Landowners | E6: Milu Foods (Vacs Bakery) | F6: =C6*F2 -> 35406.686
A7: 3 | B7: Retail 03 | C7: 3814 | D7: KSR Group | E7: Chicken Wild Wings Pvt Ltd | F7: =C7*F2 -> 35388.129
A8: 4 | B8: Retail 04 | C8: =3648 -> 3648 | D8: Aashish Bansal and Mona Bansal | E8: Fatcity Hospitality LLP | F8: =C8*F2 -> 33847.901
A9: 5 | B9: Retail 05 | C9: =3436 -> 3436 | D9: Vazir Singh Pilania and Thota Raghu Buchanna | E9: Fatcity Hospitality LLP | F9: =C9*F2 -> 31880.863
A10: 6 | B10: Retail 06 | C10: =2723 -> 2723 | D10: TanujaNayani and Ratna/Gouri Reddy | E10: Fatcity Hospitality LLP | F10: =C10*F2 -> 25265.305
A11: 7 | B11: Retail 07 | C11: =1381 -> 1381 | D11: TanujaNayani | E11: ICICI Bank Ltd | F11: =C11*F2 -> 12813.583
A12: 8 | B12: Retail 08 | C12: =755 -> 755 | D12: K Sudhakar Reddy | E12: ICICI Bank Ltd | F12: =C12*F2 -> 7005.2536
C13: =SUM(C5:C12) -> 22884
A14: First Floor
A15: S.NO | B15: Description | C15: SBUA | D15: Ownership
A16: 1 | B16: Retail 01 | C16: =6725 -> 6725 | D16: Developer | F16: =C16*F2 -> 62397.788
A17: 2 | B17: Retail 02 | C17: =7686 -> 7686 | D17: Developer | F17: =C17*F2 -> 71314.409
A18: 3 | B18: Retail 03 | C18: =9714 -> 9714 | D18: Developer and Landowners | F18: =C18*F2 -> 90131.17
A19: 4 | B19: Retail 04 | C19: =9514 -> 9514 | D19: UDS Landowners | F19: =C19*F2 -> 88275.473
A20: Total | C20: =C16+C17+C18+C19 -> 33639
A22: Second Floor to Sixth Floor
A23: S.NO | B23: Description | C23: SBUA | D23: Ownership
A24: 1 | B24: All Offices | C24: 167554 | D24: Microchip Technology India Pvt Ltd | F24: =C24*'CAM-Jul`24'!G23 -> 983260.48
A27: Seventh Floor
A28: S.NO | B28: Description | C28: SBUA | D28: Ownership
A29: 1 | B29: Office 01 | C29: 5637 | D29: Developer
B30: 1A.1 | C30: 2000 | D30: Pamara Venkata Ramana Devi and Pamera Ram Gopal Rao | F30: =C30*F2 -> 18556.963
B31: 1B.2 | C31: =587 -> 587 | D31: Developer | F31: =C31*F2 -> 5446.4687
B32: 1B | C32: =3050 -> 3050 | D32: Nirmal + Dileep (DEV) | F32: =C32*F2 -> 28299.369
B33: Sub-total | C33: =SUM(C30:C32) -> 5637
A34: 2 | B34: Office 02 | C34: 11425 | D34: Avinash Kotagiri (DEV) | F34: =C34*F2 -> 106006.65
A35: 3 | B35: Office 03 | C35: =8457 -> 8457 | D35: Ananth+Dileep+Anoop (DEV)
B36: 3A.1 | C36: 2156 | D36: Ananth(DEV) | F36: =C36*F2 -> 20004.406
B37: 3A.2 | C37: =2073 -> 2073 | D37: Bhavya Reddy 2,500 Sq.Ft | F37: =C37*F2 -> 19234.292
B38: 3B.1 | C38: =2927 -> 2927 | D38: Sasya Reddy 2,500 Sq.Ft | F38: =C38*F2 -> 27158.115
B39: 3B.2 | C39: =1301 -> 1301 | D39: Anoop (DEV) | F39: =C39*F2 -> 12071.304
B40: Sub-total | C40: =SUM(C36:C39) -> 8457
A41: 4 | B41: Office 04 | C41: 8699 | D41: Anoop (DEV) | F41: =C41*F2 -> 80713.511
A42: Total | C42: =SUM(C29,C34,C35,C41) -> 34218
A44: Eighth Floor
A45: S.NO | B45: Description | C45: SBUA | D45: Ownership
A46: 1 | B46: Office 01 | C46: =2101 -> 2101 | D46: Tachyon IT Solutions Pvt Ltd (DEV) | F46: =C46*F2 -> 19494.09
A47: 2 | B47: Office 02 | C47: 11425 | D47: Tachyon IT Solutions Pvt Ltd (DEV) | F47: =C47*F2 -> 106006.65
A48: 3 | B48: Office 03 | C48: =8457 -> 8457 | D48: Tachyon IT Solutions Pvt Ltd (DEV) | F48: =C48*F2 -> 78468.118
A49: 4 | B49: Office 04 | C49: 8699 | D49: Tachyon IT Solutions Pvt Ltd (DEV) | F49: =C49*F2 -> 80713.511
A50: Total | C50: =SUM(C46:C49) -> 30682
A52: Ninth Floor
A53: S.NO | B53: Description | C53: SBUA | D53: Ownership
A54: 1 | B54: Office 01 | C54: 5637 | D54: Pulluri Mining and Logistics Pvt Ltd (DEV) | F54: =C54*F2 -> 52302.8
A55: 2 | B55: Office 02 | C55: 11425 | D55: Pulluri Mining and Logistics Pvt Ltd (DEV) | F55: =C55*F2 -> 106006.65
A56: 3 | B56: Office 03 | C56: =8457 -> 8457 | D56: UDS Developer Arjun Rao Group
B57: 3.1 | C57: =3957 -> 3957 | D57: Arjun Rao (DEV) | F57: =C57*F2 -> 36714.951
B58: 3.2 | C58: =1500 -> 1500 | D58: Karabee Kailash (Ohja) (DEV) | F58: =C58*F2 -> 13917.722
B59: 3.3 | C59: =1500 -> 1500 | D59: Jakka Deepa (DEV) | F59: =C59*F2 -> 13917.722
B60: 3.4 | C60: =1500 -> 1500 | D60: Indu Priya (DEV) | F60: =C60*F2 -> 13917.722
B61: Sub-total | C61: =SUM(C57:C60) -> 8457
A62: 4 | B62: Office 04 | C62: 8699 | D62: AGA Infra Projects Pvt Ltd (DEV) | F62: =C62*F2 -> 80713.511
A63: Total | C63: =SUM(C54:C56,C62) -> 34218
A65: Tenth Floor
A66: S.NO | B66: Description | C66: SBUA | D66: Ownership
A67: 1 | B67: Office 01 | C67: 5637 | D67: Raj Kumar Maganti & Pradeep Kumar Maganti /Siri Sampada | E67: Siri Sampada Real Estate | F67: =C67*F2 -> 52302.8
A68: 2 | B68: Office 02 | C68: 11425 | D68: Developer
B69: 2.1 | C69: 3000 | D69: Srinivas Reddy Challa (DEV) | F69: =C69*F2 -> 27835.445
B70: 2.2 | C70: 1000 | D70: Shruti Gummadi (DEV) | F70: =C70*F2 -> 9278.4815
B71: 2.3 | C71: =3925-1000+500 -> 3425 | D71: Deepthi Kesireddy (DEV) | F71: =C71*F2 -> 31778.799
B72: 2.4 | C72: 1000 | D72: Chandralekha Kesireddy (DEV) | F72: =C72*F2 -> 9278.4815
B73: 2.5 | C73: 2000 | D73: Manohar SP (DEV) | F73: =C73*F2 -> 18556.963
B74: 2.6 | C74: 1000 | D74: Shwetha Reddy | F74: =C74*F2 -> 9278.4815
B75: Sub-total | C75: =SUM(C69:C74) -> 11425
A76: 3 | B76: Office 03 | C76: =8457 -> 8457 | D76: Sukender Reddy Pulusani, Vijay Kumar & Others.
B77: 3.1 | C77: 2300 | D77: Kadiyala Venkateshwar Rao | F77: =C77*F2 -> 21340.508
B78: 3.2 | C78: 1000 | D78: Sunkara Vijaya Durga & Sunkara Jishna Sathwik | F78: =C78*F2 -> 9278.4815
B79: 3.3 | C79: 1153 | D79: Sukender Reddy Pulusani | F79: =C79*F2 -> 10698.089
B80: 3.4 | C80: 1152 | D80: Neetha Pulusani | F80: =C80*F2 -> 10688.811
B81: 3.5 | C81: 1152 | D81: Kireet Reddy Pulusani | F81: =C81*F2 -> 10688.811
B82: 3.6 | C82: 850 | D82: Krishna Kumar Vempati | F82: =C82*F2 -> 7886.7093
B83: 3.7 | C83: 850 | D83: J Vijay Kumar & Laxmi | F83: =C83*F2 -> 7886.7093
B84: Sub-total | C84: =SUM(C77:C83) -> 8457
A85: 4 | B85: Office 04 | C85: 8699 | D85: Rohan Mandala & Sridhar Anisha (DEV) | F85: =C85*F2 -> 80713.511
A86: Total | C86: =SUM(C67,C75,C76,C85) -> 34218
A88: Eleventh Floor
A89: S.NO | B89: Description | C89: SBUA | D89: Ownership
A90: 1 | B90: Office 01 | C90: 5637 | D90: Developer
B91: 1A | C91: =2587 -> 2587 | D91: Madhusudhan Reddy Kypa(Dileep kurnool) | F91: =C91*F2 -> 24003.432
B92: 1B | C92: 3050 | D92: Pavan Kumar Mummasani & Manasa Priyadharshini (DEV) | F92: =C92*F2 -> 28299.369
B93: Sub-total | C93: =SUM(C91:C92) -> 5637
A94: 2 | B94: Office 02 | C94: 11425 | D94: UDS Landowners (KDR Family)
B95: 2.1 | C95: 3028 | D95: K. Rajesh Reddy (LO) | F95: =C95*F2 -> 28095.242
B96: 2.2 | C96: =4004-1320 -> 2684 | D96: K Saritha(LO) | F96: =C96*F2 -> 24903.444
B97: 2.3 | C97: 3028 | D97: K Ramachandra Reddy (LO) | F97: =C97*F2 -> 28095.242
B98: 2.4 | C98: =1365+1320 -> 2685 | D98: K Spandana(LO) | F98: =C98*F2 -> 24912.723
B99: Sub-total | C99: =SUM(C95:C98) -> 11425
A100: 3 | B100: Office 03 | C100: 8457 | D100: Arundathi(LO) | F100: =C100*F2 -> 78468.118
A101: 4 | B101: Office 04 | C101: 8699 | D101: Manjula(LO) | F101: =C101*F2 -> 80713.511
A102: Total | C102: =SUM(C90+C99+C100+C101) -> 34218
A104: Twelfth Floor
A105: S.NO | B105: Description | C105: SBUA | D105: Ownership
A106: 1 | B106: Office 01 | C106: =2101 -> 2101 | D106: K. Tanuja (DEV) | F106: =C106*F2 -> 19494.09
A107: 2 | B107: Office 02 | C107: 11425 | D107: UDS (Developer + Landowner)
B108: 2.1 | C108: =11166 -> 11166 | D108: Madhukar Reddy (LO) | F108: =C108*F2 -> 103603.52
...

Sheet CAM-Aug`24
E1: .
A2: CAM CHARGES CALCULATION SUMMARY - OGM-Aug`24
