Workbook

Sheet Consolidated
A2: CAM CHARGES CALCULATION SUMMARY - OGM
B3: Total Building Saleable area | C3: Area sft | D3: ='Area Deatils'!E20 -> 490749
A4: CAM Charges INR/ Per sq ft / Month | C4: Per sq. ft cost | D4: =SUM(D6:D14) -> 12.056266
A5: Sl no | B5: Description | C5: Per month | D5: Per sft
A6: 1 | B6: Management staff | C6: ='Emerzhent Manpower'!C14 -> 475000 | D6: =C6/D3 -> 0.96790824
A7: 2 | B7: Technical manpower | C7: ='Manpower - Technical'!J16 -> 588436 | D7: =C7/D3 -> 1.199057
A8: 3 | B8: HK Manpower | C8: ='HK Manpower'!I11 -> 904000 | D8: =C8/D3 -> 1.8420822
A9: 4 | B9: LP Manpower -Security Services | C9: ='LP Manpower'!G15 -> 1142500 | D9: =C9/D3 -> 2.328074
A10: 5 | B10: AMC | C10: ='AMC Charges'!D23 -> 1012166.7 | D10: =C10/D3 -> 2.0624936
A11: 6 | B11: Consumables | C11: =Consumables!C39 -> 360000 | D11: =C11/D3 -> 0.73357256
A12: 7 | B12: Common area Electrical Charges | C12: =490749*2 -> 981498 | D12: =C12/D3 -> 2
A13: 8 | B13: Common area Water charges | C13: 300000 | D13: =C13/D3 -> 0.61131047
A14: 9 | B14: Liosaning & Licenses | C14: ='Liosaning & Licenses'!C12 -> 152999.67 | D14: =C14/D3 -> 0.31176766
A15: A | B15: Total CAM budget | C15: =SUM(C6:C14) -> 5916600.3
A16: 10 | B16: Contingency, Sinking Fund @2% | C16: =C15*2% -> 118332.01 | D16: =C16/D3 -> 0.24112531
A17: 11 | B17: Fixed Management Fees for Property Management Agency | C17: 0 | D17: =C17/D3 -> 0
A18: B | B18: Including Contingency & Sinking fund Per Sft CAM Charges | C18: =(C16+C17+C15)/D3 -> 12.297391
A20: Note: | B20: Contingency,Sinking fund would be retained in the association account in FD
B21: Common area water charges may vary depends up on CAM agrement with client & After HMWSSB Connection. Considered tanker price and per day consumption would be - 100 KL
B22: Above HK manpower was considered 100% Occupancy
B23: Common area Electrical charges will vary as per site condition

Sheet Area Deatils
D4: Floor | E4: Leaseble Area In sft
D5: Ground Floor | E5: 22884
D6: First floor | E6: 33639
D7: 2nd Floor | E7: 34218
D8: 3rd Floor | E8: 34218
D9: 4th Floor | E9: 30682
D10: 5th Floor | E10: 34218
D11: 6th Floor | E11: 34218
D12: 7th Floor | E12: 34218
D13: 8th Floor | E13: 30682
D14: 9th Floor | E14: 34218
D15: 10th Floor | E15: 34218
D16: 11th Floor | E16: 34218
... D19: 14th Floor | E19: 34218
E20: =SUM(E5:E19) -> 490749

Sheet Emerzhent Manpower
A1: MANAGMENT STAFF DEPLOYMENT PLAN
A2: Designation | B2: Total Budgeted
A4: Property manager | B4: 1 | C4: 100000
A5: Facility Executive | B5: 2 | C5: =50000*2 -> 100000
A6: HK Executive | B6: 1 | C6: 40000
A7: Fire & Saftey executive | B7: 1 | C7: 40000
A8: Asst Finance Manager | B8: 1 | C8: 50000
A9: Security Manager | B9: 1 | C9: 50000
A10: FOE - Front office executive | B10: 1 | C10: 30000
A11: Employee Insurance | B11: LS | C11: 10000
A12: HR Benifits (Bonus) | C12: =SUM(C4:C11)/12 -> 35000 | D12: =SUM(C4:C9) -> 380000
A13: Employee welfare | B13: LS | C13: 20000
A14: Total Emerzhent | C14: =SUM(C4:C13) -> 475000

Sheet Manpower - Technical
A1: Sl no | B1: Description | C1: A-Shift | D1: B-Shift | E1: C- Shift | F1: Reiliver | G1: G- Shift | H1: Total | I1: Costing | J1: Total Costing | K1: Job Description
B2: Operation | C2: 0 | D2: 0 | E2: 0 | F2: 0 | K2: Responsible for overall facility and PM
A3: 1 | B3: Shift Supervisor | C3: 1 | D3: 1 | E3: 1 | F3: 1 | H3: =SUM(C3:G3) -> 4 | I3: 34344 | J3: =H3*I3 -> 137376 | K3: Responsible for overall facility and PM, and operations
A4: 2 | B4: MST | C4: 1 | D4: 1 | E4: 1 | F4: 1 | H4: =SUM(C4:G4) -> 4 | I4: 31000 | J4: =H4*I4 -> 124000 | K4: Take care of the general complaints & Take care of LT room,Transformer room & DG Room.Should be placed in plant room.
A5: 3 | B5: Plumber | C5: 1 | D5: 1 | E5: 1 | F5: 1 | H5: =SUM(C5:G5) -> 4 | I5: 27794 | J5: =H5*I5 -> 111176 | K5: Taking care of WTP,Water system & Fire fightting system and plumbing system.
A6: 4 | B6: BMS | C6: 1 | D6: 1 | E6: 1 | F6: 0 | H6: =SUM(C6:G6) -> 3 | I6: 27794 | J6: =H6*I6 -> 83382 | K6: BMS Operations
B7: Preventive maintainence
A8: 5 | B8: Plumber | G8: 1 | H8: 0 | I8: 27794 | J8: =H8*I8 -> 0 | K8: PM for total building Equipments
A9: 6 | B9: HVAC Technician | G9: 1 | H9: 1 | I9: 27794 | J9: =H9*I9 -> 27794
A10: 7 | B10: Electrician | G10: 2 | H10: 2 | I10: 27794 | J10: =H10*I10 -> 55588
A11: 8 | B11: Technical Helper | G11: 1 | H11: 1 | I11: 23000 | J11: =H11*I11 -> 23000 | K11: Trainees
B12: Product up keep
A13: 9 | B13: Carpenter | G13: 1 | H13: =SUM(C13:G13) -> 1 | I13: 26120 | J13: =H13*I13 -> 26120
A14: 10 | B14: Painter | G14: 0 | H14: =SUM(C14:G14) -> 0 | I14: 26109 | J14: =H14*I14 -> 0
A15: 11 | B15: Masion | G15: 0 | H15: 0 | I15: 26120 | J15: =H15*I15 -> 0
B16: Grand Total | C16: =SUM(C2:C14) -> 4 | D16: =SUM(D2:D14) -> 4 | E16: =SUM(E2:E14) -> 4 | F16: =SUM(F2:F14) -> 3 | G16: =SUM(G2:G15) -> 6 | H16: =SUM(C16:G16) -> 21 | J16: =SUM(J3:J15) -> 588436

Sheet AMC Charges
A1: Sl no | B1: Description | C1: Qty | D1: Cost per month | E1: Cost per annum | F1: Remarks
A2: 1 | B2: STP | C2: 1 | D2: 75000 | E2: =D2*12 -> 900000 | F2: Operational Expenses
A3: 2 | B3: Elevators | C3: 10 | D3: =E3/10 -> 175000 | E3: =175000*10 -> 1750000 | F3: DLP
A4: 3 | B4: Escalators | C4: 2 | D4: =E4/12 -> 25000 | E4: =150000*2 -> 300000 | F4: DLP
A5: 4 | B5: Façade cleaning | C5: LS | D5: 70000 | E5: =D5*12 -> 840000 | F5: Operational Expenses
A6: 5 | B6: Chillers | C6: 3 | D6: =E6/12 -> 118750 | E6: =3*500*950 -> 1425000 | F6: DLP
A7: 6 | B7: Secondary system VFD | C7: LS | D7: 40000 | E7: =D7*12 -> 480000 | F7: DLP
A8: 7 | B8: Water test reports | D8: 8000 | E8: =D8*12 -> 96000 | F8: Operational Expenses
A9: 8 | B9: PCB Test reports | D9: 8000 | E9: =D9*12 -> 96000 | F9: Operational Expenses
A10: 9 | B10: Generator B-check | C10: 2 | D10: =E10/12 -> 16666.667 | E10: =100000*2 -> 200000 | F10: Operational Expenses
A11: 10 | B11: Generator AMC | D11: 18000 | E11: =D11*12 -> 216000 | F11: DLP
A12: 11 | B12: Gardening | D12: 35000 | E12: =D12*12 -> 420000 | F12: Operational Expenses
A13: 12 | B13: FA System | D13: 50000 | E13: =D13*12 -> 600000 | F13: DLP
A14: 13 | B14: Water tanks & Sumps cleaning | D14: =E14/12 -> 16666.667 | E14: 200000 | F14: Operational Expenses
A15: 14 | B15: UPS | C15: 3 | D15: =E15/12 -> 6250 | E15: 75000 | F15: DLP
A16: 15 | B16: BMS | D16: 10000 | E16: =D16*12 -> 120000 | F16: DLP
A17: 16 | B17: Pest control | C17: 1 | D17: 45000 | E17: =D17*12 -> 540000 | F17: Operational Expenses
A18: 17 | B18: eFacility - MMS,Help desk | D18: =E18/12 -> 66500 | E18: =198000+150000+450000 -> 798000 | F18: Operational Expenses
A19: 18 | B19: Transformers & Breaker testing | C19: 2 | D19: =E19/12 -> 16666.667 | E19: 200000 | F19: Operational Expenses
A20: 19 | B20: Valets for stack parking | C20: 6 | D20: =25000*C20 -> 150000 | E20: =D20*12 -> 1800000 | F20: Operational Expenses
A21: 20 | B21: Stack Parking | C21: 140 | D21: =E21/12 -> 46666.667 | E21: =C21*4000 -> 560000 | F21: DLP
A22: 21 | B22: Security Equipments (Boom barrier,DFMD) | C22: 3 | D22: 15000 | E22: =D22*12 -> 180000 | F22: Operational Expenses
D23: =SUM(D2:D22) -> 1012166.7 | E23: =SUM(E2:E22) -> 11796000

Sheet HK Manpower
A1: Sl no | B1: Description | C1: A-Shift | D1: B-Shift | E1: C-shift | F1: G-Shift | G1: Total | H1: Cost per person | I1: Total Costing
A2: 1 | B2: Supervisors | C2: 1 | D2: 1 | E2: 1 | G2: =SUM(C2:F2) -> 3 | H2: 30000 | I2: =H2*G2 -> 90000
A3: 2 | B3: HK- Boy/ Maid ( Stair cases ) | C3: 1 | D3: 1 | E3: 0 | F3: 0 | G3: =SUM(C3:F3) -> 2 | H3: 22000 | I3: =H3*G3 -> 44000
A4: 3 | B4: HK- Boy/ Maid All basements | C4: 4 | D4: 4 | E4: 0 | F4: 0 | G4: =SUM(C4:F4) -> 8 | H4: 22000 | I4: =H4*G4 -> 176000
A5: 4 | B5: HK- Boy/ Maid Ground Floor | C5: 1 | D5: 1 | E5: 0 | F5: 0 | G5: =SUM(C5:F5) -> 2 | H5: 22000 | I5: =H5*G5 -> 44000
A6: 5 | B6: HK- Boy/ Maid First Floor | C6: 1 | D6: 1 | E6: 0 | F6: 0 | G6: =SUM(C6:F6) -> 2 | H6: 22000 | I6: =H6*G6 -> 44000
A7: 6 | B7: HK- Boy/ Maid 7th floor to 14 th floor | C7: 8 | D7: 8 | E7: 4 | F7: 0 | G7: =SUM(C7:F7) -> 20 | H7: 22000 | I7: =H7*G7 -> 440000
A8: 7 | B8: HK- Boy/ Maid Roof top | C8: 0 | D8: 1 | E8: 0 | F8: 0 | G8: =SUM(C8:F8) -> 1 | H8: 22000 | I8: =H8*G8 -> 22000
A9: 8 | B9: HK- Boy/ Maid Office boy | C9: 0 | D9: 0 | E9: 0 | F9: 1 | G9: =SUM(C9:F9) -> 1 | H9: 22000 | I9: =H9*G9 -> 22000
A10: 9 | B10: HK- Boy/ Maid Gardner | C10: 0 | D10: 0 | E10: 0 | F10: 1 | G10: =SUM(C10:F10) -> 1 | H10: 22000 | I10: =H10*G10 -> 22000
B11: Total | C11: =SUM(C2:C10) -> 16 | D11: =SUM(D2:D10) -> 17 | E11: =SUM(E2:E10) -> 5 | F11: =SUM(F2:F10) -> 2 | G11: =SUM(C11:F11) -> 40 | I11: =SUM(I2:I10) -> 904000

Sheet Consumables
A1: Sl no | B1: Description | C1: Cost per month
A2: 1 | B2: Electrical & Mechanical | C2: 50000
A3: i | B3: Light & Bulbs
A4: ii | B4: Cables,Wires
A5: iii | B5: MCB's,Contactors
A6: iv | B6: Breaker spare parts
A7: v | B7: Switches,sockets,modular boxes,insulation tapes
A8: vi | B8: Pumps Re-winding,Repairing
A9: vii | B9: Air con-ditioning insulation
A10: viii | B10: battery's
A11: 2 | B11: Plumbing and Hardware spares | C11: 30000
A12: i | B12: CP & Sanitery spare parts
A13: ii | B13: PVC,CPVC parts
A14: iii | B14: Solvents,dipseal,teflon tape,GI Dummys
A15: iv | B15: GI Fittings
A16: v | B16: Butterfly valves,flanges,Nut &Bolts
A17: vi | B17: Salt for regeneration (WTP)
A18: 3 | B18: Fire & Saftey Material | C18: 200000
A19: i | B19: Detectors
A20: ii | B20: fire extinguishers refilling
A21: iii | B21: CCTV and PA System
A22: 4 | B22: Carpentery Material | C22: 15000
A23: i | B23: Screws
A24: ii | B24: Wood material
A25: iii | B25: Hinges,Door closers,Door handels,Push bars etc...
A26: 5 | B26: Civil & Masonary | C26: 20000
A27: i | B27: Sand,Cement etc...
A28: 6 | B28: General Building | C28: 25000
A29: i | B29: Facade glass
A30: ii | B30: Facade Tiles
A31: iii | B31: Marble,granite and tile work
A32: 7 | B32: House Keeping Equipments | C32: 10000
A33: 8 | B33: Paint material | C33: 15000
A34: 9 | B34: Printing & Stationery | C34: 25000
A35: 10 | B35: Security | C35: 15000
A36: i | B36: House Keeping
A37: 11 | B37: HK Chemicals costing | C37: 75000
A38: 12 | B38: House keeping general Items | C38: 60000
C39: 360000

Sheet LP Manpower
B1: SECURITY MANPOWER REQUIREMENT
A2: S no | B2: Location | C2: A-shift | D2: B-Shift | E2: Total | F2: Cost per person | G2: Total Costing
A3: 1 | B3: SO | E3: 1 | F3: 40000 | G3: =F3*E3 -> 40000
A4: 2 | B4: Supervisor | C4: 1 | D4: 1 | E4: =D4+C4 -> 2 | F4: 35000 | G4: =F4*E4 -> 70000
A5: 3 | B5: SG-Basement -4 | C5: 1 | D5: 1 | E5: =D5+C5 -> 2 | F5: 29500 | G5: =F5*E5 -> 59000
A6: 4 | B6: SG-Basement - 3 | C6: 1 | D6: 1 | E6: =D6+C6 -> 2 | F6: 29500 | G6: =F6*E6 -> 59000
A7: 5 | B7: SG_Basement - 2 | C7: 1 | D7: 1 | E7: =D7+C7 -> 2 | F7: 29500 | G7: =F7*E7 -> 59000
A8: 6 | B8: SG_Basement - 1 | C8: 2 | D8: 2 | E8: =D8+C8 -> 4 | F8: 29500 | G8: =F8*E8 -> 118000
A9: 7 | B9: SG-Relieving | C9: 2 | D9: 2 | E9: =D9+C9 -> 4 | F9: 29500 | G9: =F9*E9 -> 118000
A10: 8 | B10: SG_ Lobby & GF,FF | C10: 2 | D10: 2 | E10: 4 | F10: 29500 | G10: =F10*E10 -> 118000
A11: 9 | B11: SG-Gates - Entry & Exit | C11: 7 | D11: 7 | E11: =D11+C11 -> 14 | F11: 29500 | G11: =F11*E11 -> 413000
A12: 10 | B12: SG_Terrace | C12: 0 | D12: 0 | E12: =D12+C12 -> 0 | F12: 29500 | G12: =F12*E12 -> 0
A13: 11 | B13: SG-7 th to 14 th floor | C13: 1 | D13: 1 | E13: =D13+C13 -> 2 | F13: 29500 | G13: =F13*E13 -> 59000
A14: 12 | B14: SG-CCTV | C14: 0 | D14: 1 | E14: =D14+C14 -> 1 | F14: 29500 | G14: =F14*E14 -> 29500
B15: Total for 12 Hrs | C15: =SUM(C3:C14) -> 18 | D15: =SUM(D4:D14) -> 19 | E15: =SUM(E3:E14) -> 38 | G15: =SUM(G3:G14) -> 1142500

Sheet Liosaning & Licenses
B1: Liosaning & Licenses Cost | C1: Monthly
A2: 1 | B2: Electrical and DG License renewal | C2: 8333
A3: 2 | B3: Dasara Expenses | C3: 6000
A4: 3 | B4: Fire NOC Third party audit charges | C4: 5000
A5: 4 | B5: CTO /CFO | C5: 45000
A6: 5 | B6: Labour license and registration | C6: 5000
A7: 6 | B7: Environmental and Pollution Control Inspections | C7: 0
A8: 7 | B8: Health & Saftey audit | C8: 5000
A9: 8 | B9: Fire & Peril Insurance | C9: =800000/12 -> 66666.667
A10: 9 | B10: Audit fees | C10: 6000
A11: 10 | B11: Consultancy charges - PF &HR | C11: 6000
B12: Total | C12: =SUM(C2:C11) -> 152999.67
